Workbook

Sheet CFP
B2: OWL | K2: =B2 -> OWL | T2: =B2 -> OWL
B4: BALANCE | C4: =BALANCES!B1 -> 46073 | K4: FLOWS | L4: =C4 -> 46073 | M4: <---> | N4: =U4 -> 46081 | T4: BALANCE | U4: 46081
B6: BANK | C6: USD | D6: EUR | E6: CNY | F6: AED | G6: RUB | H6: OMR | I6: TOTAL USD | K6: BANK | L6: =C6 -> USD | M6: =D6 -> EUR | N6: =E6 -> CNY | O6: =F6 -> AED | P6: =G6 -> RUB | Q6: =H6 -> OMR | R6: TOTAL USD | T6: BANK | U6: =C6 -> USD | V6: =D6 -> EUR | W6: =E6 -> CNY | X6: =F6 -> AED | Y6: =G6 -> RUB | Z6: =H6 -> OMR | AA6: TOTAL USD | AC6: CHECK
B7: EMLAK | C7: {=SUMIFS(BALANCES!$C:$C,BALANCES!$A:$A,$B$2,BALANCES!$B:$B,$B7,BALANCES!$D:$D,C$6)+SUMIFS(FLOWS!$C:$C,FLOWS!$A:$A,$B$2,FLOWS!$E:$E,$B7,FLOWS!$D:$D,C$6,FLOWS!$H:$H,"<"&$C$4)+SUM(SUMIFS(DEALS!$J:$J,DEALS!$A:$A,{"*REFUND*","*EXECUTED*"},DEALS!$G:$G,$B$2,DEALS!$E:$E,"<"&$C$4,DEALS!$K:$K,C$6,DEALS!$M:$M,$B7,DEALS!$N:$N,"<>*RECEIVED*",DEALS!$N:$N,"<>*EXECUTED*"))+SUM(SUMIFS(DEALS!$R:$R,DEALS!$A:$A,{"*REFUND*","*EXECUTED*"},DEALS!$O:$O,$B$2,DEALS!$E:$E,"<"&$C$4,DEALS!$S:$S,C$6,DEALS!$U:$U,$B7,DEALS!$V:$V,"<>*RECEIVED*",DEALS!$V:$V,"<>*EXECUTED*"))} -> 2197.03 | D7: {=SUMIFS(BALANCES!$C:$C,BALANCES!$A:$A,$B$2,BALANCES!$B:$B,$B7,BALANCES!$D:$D,D$6)+SUMIFS(FLOWS!$C:$C,FLOWS!$A:$A,$B$2,FLOWS!$E:$E,$B7,FLOWS!$D:$D,D$6,FLOWS!$H:$H,"<"&$C$4)+SUM(SUMIFS(DEALS!$J:$J,DEALS!$A:$A,{"*REFUND*","*EXECUTED*"},DEALS!$G:$G,$B$2,DEALS!$E:$E,"<"&$C$4,DEALS!$K:$K,D$6,DEALS!$M:$M,$B7,DEALS!$N:$N,"<>*RECEIVED*",DEALS!$N:$N,"<>*EXECUTED*"))+SUM(SUMIFS(DEALS!$R:$R,DEALS!$A:$A,{"*REFUND*","*EXECUTED*"},DEALS!$O:$O,$B$2,DEALS!$E:$E,"<"&$C$4,DEALS!$S:$S,D$6,DEALS!$U:$U,$B7,DEALS!$V:$V,"<>*RECEIVED*",DEALS!$V:$V,"<>*EXECUTED*"))} -> 44.88 | E7: {=SUMIFS(BALANCES!$C:$C,BALANCES!$A:$A,$B$2,BALANCES!$B:$B,$B7,BALANCES!$D:$D,E$6)+SUMIFS(FLOWS!$C:$C,FLOWS!$A:$A,$B$2,FLOWS!$E:$E,$B7,FLOWS!$D:$D,E$6,FLOWS!$H:$H,"<"&$C$4)+SUM(SUMIFS(DEALS!$J:$J,DEALS!$A:$A,{"*REFUND*","*EXECUTED*"},DEALS!$G:$G,$B$2,DEALS!$E:$E,"<"&$C$4,DEALS!$K:$K,E$6,DEALS!$M:$M,$B7,DEALS!$N:$N,"<>*RECEIVED*",DEALS!$N:$N,"<>*EXECUTED*"))+SUM(SUMIFS(DEALS!$R:$R,DEALS!$A:$A,{"*REFUND*","*EXECUTED*"},DEALS!$O:$O,$B$2,DEALS!$E:$E,"<"&$C$4,DEALS!$S:$S,E$6,DEALS!$U:$U,$B7,DEALS!$V:$V,"<>*RECEIVED*",DEALS!$V:$V,"<>*EXECUTED*"))} -> 54.77 | F7: {=SUMIFS(BALANCES!$C:$C,BALANCES!$A:$A,$B$2,BALANCES!$B:$B,$B7,BALANCES!$D:$D,F$6)+SUMIFS(FLOWS!$C:$C,FLOWS!$A:$A,$B$2,FLOWS!$E:$E,$B7,FLOWS!$D:$D,F$6,FLOWS!$H:$H,"<"&$C$4)+SUM(SUMIFS(DEALS!$J:$J,DEALS!$A:$A,{"*REFUND*","*EXECUTED*"},DEALS!$G:$G,$B$2,DEALS!$E:$E,"<"&$C$4,DEALS!$K:$K,F$6,DEALS!$M:$M,$B7,DEALS!$N:$N,"<>*RECEIVED*",DEALS!$N:$N,"<>*EXECUTED*"))+SUM(SUMIFS(DEALS!$R:$R,DEALS!$A:$A,{"*REFUND*","*EXECUTED*"},DEALS!$O:$O,$B$2,DEALS!$E:$E,"<"&$C$4,DEALS!$S:$S,F$6,DEALS!$U:$U,$B7,DEALS!$V:$V,"<>*RECEIVED*",DEALS!$V:$V,"<>*EXECUTED*"))} -> 6221.49 | G7: {=SUMIFS(BALANCES!$C:$C,BALANCES!$A:$A,$B$2,BALANCES!$B:$B,$B7,BALANCES!$D:$D,G$6)+SUMIFS(FLOWS!$C:$C,FLOWS!$A:$A,$B$2,FLOWS!$E:$E,$B7,FLOWS!$D:$D,G$6,FLOWS!$H:$H,"<"&$C$4)+SUM(SUMIFS(DEALS!$J:$J,DEALS!$A:$A,{"*REFUND*","*EXECUTED*"},DEALS!$G:$G,$B$2,DEALS!$E:$E,"<"&$C$4,DEALS!$K:$K,G$6,DEALS!$M:$M,$B7,DEALS!$N:$N,"<>*RECEIVED*",DEALS!$N:$N,"<>*EXECUTED*"))+SUM(SUMIFS(DEALS!$R:$R,DEALS!$A:$A,{"*REFUND*","*EXECUTED*"},DEALS!$O:$O,$B$2,DEALS!$E:$E,"<"&$C$4,DEALS!$S:$S,G$6,DEALS!$U:$U,$B7,DEALS!$V:$V,"<>*RECEIVED*",DEALS!$V:$V,"<>*EXECUTED*"))} -> 0 | H7: {=SUMIFS(BALANCES!$C:$C,BALANCES!$A:$A,$B$2,BALANCES!$B:$B,$B7,BALANCES!$D:$D,H$6)+SUMIFS(FLOWS!$C:$C,FLOWS!$A:$A,$B$2,FLOWS!$E:$E,$B7,FLOWS!$D:$D,H$6,FLOWS!$H:$H,"<"&$C$4)+SUM(SUMIFS(DEALS!$J:$J,DEALS!$A:$A,{"*REFUND*","*EXECUTED*"},DEALS!$G:$G,$B$2,DEALS!$E:$E,"<"&$C$4,DEALS!$K:$K,H$6,DEALS!$M:$M,$B7,DEALS!$N:$N,"<>*RECEIVED*",DEALS!$N:$N,"<>*EXECUTED*"))+SUM(SUMIFS(DEALS!$R:$R,DEALS!$A:$A,{"*REFUND*","*EXECUTED*"},DEALS!$O:$O,$B$2,DEALS!$E:$E,"<"&$C$4,DEALS!$S:$S,H$6,DEALS!$U:$U,$B7,DEALS!$V:$V,"<>*RECEIVED*",DEALS!$V:$V,"<>*EXECUTED*"))} -> 0 | I7: =C7*VLOOKUP(C$6,'FX RATES'!$E$1:$F$50,2,FALSE)+D7*VLOOKUP(D$6,'FX RATES'!$E$1:$F$50,2,FALSE)+E7*VLOOKUP(E$6,'FX RATES'!$E$1:$F$50,2,FALSE)+F7*VLOOKUP(F$6,'FX RATES'!$E$1:$F$50,2,FALSE)+G7*VLOOKUP(G$6,'FX RATES'!$E$1:$F$50,2,FALSE)+H7*VLOOKUP(H$6,'FX RATES'!$E$1:$F$50,2,FALSE) -> 3951.8559 | K7: =B7 -> EMLAK | L7: {=SUMIFS(FLOWS!$C:$C,FLOWS!$A:$A,$B$2,FLOWS!$E:$E,$K7,FLOWS!$D:$D,L$6,FLOWS!$H:$H,">="&$C$4,FLOWS!$H:$H,"<="&$U$4)+SUM(SUMIFS(DEALS!$J:$J,DEALS!$A:$A,{"*REFUND*","*EXECUTED*"},DEALS!$G:$G,$B$2,DEALS!$E:$E,">="&$C$4,DEALS!$E:$E,"<="&$U$4,DEALS!$K:$K,L$6,DEALS!$M:$M,$K7,DEALS!$N:$N,"<>*RECEIVED*",DEALS!$N:$N,"<>*EXECUTED*"))+SUM(SUMIFS(DEALS!$R:$R,DEALS!$A:$A,{"*REFUND*","*EXECUTED*"},DEALS!$O:$O,$B$2,DEALS!$E:$E,">="&$C$4,DEALS!$E:$E,"<="&$U$4,DEALS!$S:$S,L$6,DEALS!$U:$U,$K7,DEALS!$V:$V,"<>*RECEIVED*",DEALS!$V:$V,"<>*EXECUTED*"))} -> 0 | M7: {=SUMIFS(FLOWS!$C:$C,FLOWS!$A:$A,$B$2,FLOWS!$E:$E,$K7,FLOWS!$D:$D,M$6,FLOWS!$H:$H,">="&$C$4,FLOWS!$H:$H,"<="&$U$4)+SUM(SUMIFS(DEALS!$J:$J,DEALS!$A:$A,{"*REFUND*","*EXECUTED*"},DEALS!$G:$G,$B$2,DEALS!$E:$E,">="&$C$4,DEALS!$E:$E,"<="&$U$4,DEALS!$K:$K,M$6,DEALS!$M:$M,$K7,DEALS!$N:$N,"<>*RECEIVED*",DEALS!$N:$N,"<>*EXECUTED*"))+SUM(SUMIFS(DEALS!$R:$R,DEALS!$A:$A,{"*REFUND*","*EXECUTED*"},DEALS!$O:$O,$B$2,DEALS!$E:$E,">="&$C$4,DEALS!$E:$E,"<="&$U$4,DEALS!$S:$S,M$6,DEALS!$U:$U,$K7,DEALS!$V:$V,"<>*RECEIVED*",DEALS!$V:$V,"<>*EXECUTED*"))} -> 0 | N7: {=SUMIFS(FLOWS!$C:$C,FLOWS!$A:$A,$B$2,FLOWS!$E:$E,$K7,FLOWS!$D:$D,N$6,FLOWS!$H:$H,">="&$C$4,FLOWS!$H:$H,"<="&$U$4)+SUM(SUMIFS(DEALS!$J:$J,DEALS!$A:$A,{"*REFUND*","*EXECUTED*"},DEALS!$G:$G,$B$2,DEALS!$E:$E,">="&$C$4,DEALS!$E:$E,"<="&$U$4,DEALS!$K:$K,N$6,DEALS!$M:$M,$K7,DEALS!$N:$N,"<>*RECEIVED*",DEALS!$N:$N,"<>*EXECUTED*"))+SUM(SUMIFS(DEALS!$R:$R,DEALS!$A:$A,{"*REFUND*","*EXECUTED*"},DEALS!$O:$O,$B$2,DEALS!$E:$E,">="&$C$4,DEALS!$E:$E,"<="&$U$4,DEALS!$S:$S,N$6,DEALS!$U:$U,$K7,DEALS!$V:$V,"<>*RECEIVED*",DEALS!$V:$V,"<>*EXECUTED*"))} -> 0 | O7: {=SUMIFS(FLOWS!$C:$C,FLOWS!$A:$A,$B$2,FLOWS!$E:$E,$K7,FLOWS!$D:$D,O$6,FLOWS!$H:$H,">="&$C$4,FLOWS!$H:$H,"<="&$U$4)+SUM(SUMIFS(DEALS!$J:$J,DEALS!$A:$A,{"*REFUND*","*EXECUTED*"},DEALS!$G:$G,$B$2,DEALS!$E:$E,">="&$C$4,DEALS!$E:$E,"<="&$U$4,DEALS!$K:$K,O$6,DEALS!$M:$M,$K7,DEALS!$N:$N,"<>*RECEIVED*",DEALS!$N:$N,"<>*EXECUTED*"))+SUM(SUMIFS(DEALS!$R:$R,DEALS!$A:$A,{"*REFUND*","*EXECUTED*"},DEALS!$O:$O,$B$2,DEALS!$E:$E,">="&$C$4,DEALS!$E:$E,"<="&$U$4,DEALS!$S:$S,O$6,DEALS!$U:$U,$K7,DEALS!$V:$V,"<>*RECEIVED*",DEALS!$V:$V,"<>*EXECUTED*"))} -> 0 | P7: {=SUMIFS(FLOWS!$C:$C,FLOWS!$A:$A,$B$2,FLOWS!$E:$E,$K7,FLOWS!$D:$D,P$6,FLOWS!$H:$H,">="&$C$4,FLOWS!$H:$H,"<="&$U$4)+SUM(SUMIFS(DEALS!$J:$J,DEALS!$A:$A,{"*REFUND*","*EXECUTED*"},DEALS!$G:$G,$B$2,DEALS!$E:$E,">="&$C$4,DEALS!$E:$E,"<="&$U$4,DEALS!$K:$K,P$6,DEALS!$M:$M,$K7,DEALS!$N:$N,"<>*RECEIVED*",DEALS!$N:$N,"<>*EXECUTED*"))+SUM(SUMIFS(DEALS!$R:$R,DEALS!$A:$A,{"*REFUND*","*EXECUTED*"},DEALS!$O:$O,$B$2,DEALS!$E:$E,">="&$C$4,DEALS!$E:$E,"<="&$U$4,DEALS!$S:$S,P$6,DEALS!$U:$U,$K7,DEALS!$V:$V,"<>*RECEIVED*",DEALS!$V:$V,"<>*EXECUTED*"))} -> 0 | Q7: {=SUMIFS(FLOWS!$C:$C,FLOWS!$A:$A,$B$2,FLOWS!$E:$E,$K7,FLOWS!$D:$D,Q$6,FLOWS!$H:$H,">="&$C$4,FLOWS!$H:$H,"<="&$U$4)+SUM(SUMIFS(DEALS!$J:$J,DEALS!$A:$A,{"*REFUND*","*EXECUTED*"},DEALS!$G:$G,$B$2,DEALS!$E:$E,">="&$C$4,DEALS!$E:$E,"<="&$U$4,DEALS!$K:$K,Q$6,DEALS!$M:$M,$K7,DEALS!$N:$N,"<>*RECEIVED*",DEALS!$N:$N,"<>*EXECUTED*"))+SUM(SUMIFS(DEALS!$R:$R,DEALS!$A:$A,{"*REFUND*","*EXECUTED*"},DEALS!$O:$O,$B$2,DEALS!$E:$E,">="&$C$4,DEALS!$E:$E,"<="&$U$4,DEALS!$S:$S,Q$6,DEALS!$U:$U,$K7,DEALS!$V:$V,"<>*RECEIVED*",DEALS!$V:$V,"<>*EXECUTED*"))} -> 0 | R7: =L7*VLOOKUP(L$6,'FX RATES'!$E$1:$F$50,2,FALSE)+M7*VLOOKUP(M$6,'FX RATES'!$E$1:$F$50,2,FALSE)+N7*VLOOKUP(N$6,'FX RATES'!$E$1:$F$50,2,FALSE)+O7*VLOOKUP(O$6,'FX RATES'!$E$1:$F$50,2,FALSE)+P7*VLOOKUP(P$6,'FX RATES'!$E$1:$F$50,2,FALSE)+Q7*VLOOKUP(Q$6,'FX RATES'!$E$1:$F$50,2,FALSE) -> 0 | T7: =B7 -> EMLAK | U7: {=SUMIFS(BALANCES!$C:$C,BALANCES!$A:$A,$B$2,BALANCES!$B:$B,$T7,BALANCES!$D:$D,U$6)+SUMIFS(FLOWS!$C:$C,FLOWS!$A:$A,$B$2,FLOWS!$E:$E,$T7,FLOWS!$D:$D,U$6,FLOWS!$H:$H,"<="&$U$4)+SUM(SUMIFS(DEALS!$J:$J,DEALS!$A:$A,{"*REFUND*","*EXECUTED*"},DEALS!$G:$G,$B$2,DEALS!$E:$E,"<="&$U$4,DEALS!$K:$K,U$6,DEALS!$M:$M,$T7,DEALS!$N:$N,"<>*RECEIVED*",DEALS!$N:$N,"<>*EXECUTED*"))+SUM(SUMIFS(DEALS!$R:$R,DEALS!$A:$A,{"*REFUND*","*EXECUTED*"},DEALS!$O:$O,$B$2,DEALS!$E:$E,"<="&$U$4,DEALS!$S:$S,U$6,DEALS!$U:$U,$T7,DEALS!$V:$V,"<>*RECEIVED*",DEALS!$V:$V,"<>*EXECUTED*"))} -> 2197.03 | V7: {=SUMIFS(BALANCES!$C:$C,BALANCES!$A:$A,$B$2,BALANCES!$B:$B,$T7,BALANCES!$D:$D,V$6)+SUMIFS(FLOWS!$C:$C,FLOWS!$A:$A,$B$2,FLOWS!$E:$E,$T7,FLOWS!$D:$D,V$6,FLOWS!$H:$H,"<="&$U$4)+SUM(SUMIFS(DEALS!$J:$J,DEALS!$A:$A,{"*REFUND*","*EXECUTED*"},DEALS!$G:$G,$B$2,DEALS!$E:$E,"<="&$U$4,DEALS!$K:$K,V$6,DEALS!$M:$M,$T7,DEALS!$N:$N,"<>*RECEIVED*",DEALS!$N:$N,"<>*EXECUTED*"))+SUM(SUMIFS(DEALS!$R:$R,DEALS!$A:$A,{"*REFUND*","*EXECUTED*"},DEALS!$O:$O,$B$2,DEALS!$E:$E,"<="&$U$4,DEALS!$S:$S,V$6,DEALS!$U:$U,$T7,DEALS!$V:$V,"<>*RECEIVED*",DEALS!$V:$V,"<>*EXECUTED*"))} -> 44.88 | W7: {=SUMIFS(BALANCES!$C:$C,BALANCES!$A:$A,$B$2,BALANCES!$B:$B,$T7,BALANCES!$D:$D,W$6)+SUMIFS(FLOWS!$C:$C,FLOWS!$A:$A,$B$2,FLOWS!$E:$E,$T7,FLOWS!$D:$D,W$6,FLOWS!$H:$H,"<="&$U$4)+SUM(SUMIFS(DEALS!$J:$J,DEALS!$A:$A,{"*REFUND*","*EXECUTED*"},DEALS!$G:$G,$B$2,DEALS!$E:$E,"<="&$U$4,DEALS!$K:$K,W$6,DEALS!$M:$M,$T7,DEALS!$N:$N,"<>*RECEIVED*",DEALS!$N:$N,"<>*EXECUTED*"))+SUM(SUMIFS(DEALS!$R:$R,DEALS!$A:$A,{"*REFUND*","*EXECUTED*"},DEALS!$O:$O,$B$2,DEALS!$E:$E,"<="&$U$4,DEALS!$S:$S,W$6,DEALS!$U:$U,$T7,DEALS!$V:$V,"<>*RECEIVED*",DEALS!$V:$V,"<>*EXECUTED*"))} -> 54.77 | X7: {=SUMIFS(BALANCES!$C:$C,BALANCES!$A:$A,$B$2,BALANCES!$B:$B,$T7,BALANCES!$D:$D,X$6)+SUMIFS(FLOWS!$C:$C,FLOWS!$A:$A,$B$2,FLOWS!$E:$E,$T7,FLOWS!$D:$D,X$6,FLOWS!$H:$H,"<="&$U$4)+SUM(SUMIFS(DEALS!$J:$J,DEALS!$A:$A,{"*REFUND*","*EXECUTED*"},DEALS!$G:$G,$B$2,DEALS!$E:$E,"<="&$U$4,DEALS!$K:$K,X$6,DEALS!$M:$M,$T7,DEALS!$N:$N,"<>*RECEIVED*",DEALS!$N:$N,"<>*EXECUTED*"))+SUM(SUMIFS(DEALS!$R:$R,DEALS!$A:$A,{"*REFUND*","*EXECUTED*"},DEALS!$O:$O,$B$2,DEALS!$E:$E,"<="&$U$4,DEALS!$S:$S,X$6,DEALS!$U:$U,$T7,DEALS!$V:$V,"<>*RECEIVED*",DEALS!$V:$V,"<>*EXECUTED*"))} -> 6221.49 | Y7: {=SUMIFS(BALANCES!$C:$C,BALANCES!$A:$A,$B$2,BALANCES!$B:$B,$T7,BALANCES!$D:$D,Y$6)+SUMIFS(FLOWS!$C:$C,FLOWS!$A:$A,$B$2,FLOWS!$E:$E,$T7,FLOWS!$D:$D,Y$6,FLOWS!$H:$H,"<="&$U$4)+SUM(SUMIFS(DEALS!$J:$J,DEALS!$A:$A,{"*REFUND*","*EXECUTED*"},DEALS!$G:$G,$B$2,DEALS!$E:$E,"<="&$U$4,DEALS!$K:$K,Y$6,DEALS!$M:$M,$T7,DEALS!$N:$N,"<>*RECEIVED*",DEALS!$N:$N,"<>*EXECUTED*"))+SUM(SUMIFS(DEALS!$R:$R,DEALS!$A:$A,{"*REFUND*","*EXECUTED*"},DEALS!$O:$O,$B$2,DEALS!$E:$E,"<="&$U$4,DEALS!$S:$S,Y$6,DEALS!$U:$U,$T7,DEALS!$V:$V,"<>*RECEIVED*",DEALS!$V:$V,"<>*EXECUTED*"))} -> 0 | Z7: {=SUMIFS(BALANCES!$C:$C,BALANCES!$A:$A,$B$2,BALANCES!$B:$B,$T7,BALANCES!$D:$D,Z$6)+SUMIFS(FLOWS!$C:$C,FLOWS!$A:$A,$B$2,FLOWS!$E:$E,$T7,FLOWS!$D:$D,Z$6,FLOWS!$H:$H,"<="&$U$4)+SUM(SUMIFS(DEALS!$J:$J,DEALS!$A:$A,{"*REFUND*","*EXECUTED*"},DEALS!$G:$G,$B$2,DEALS!$E:$E,"<="&$U$4,DEALS!$K:$K,Z$6,DEALS!$M:$M,$T7,DEALS!$N:$N,"<>*RECEIVED*",DEALS!$N:$N,"<>*EXECUTED*"))+SUM(SUMIFS(DEALS!$R:$R,DEALS!$A:$A,{"*REFUND*","*EXECUTED*"},DEALS!$O:$O,$B$2,DEALS!$E:$E,"<="&$U$4,DEALS!$S:$S,Z$6,DEALS!$U:$U,$T7,DEALS!$V:$V,"<>*RECEIVED*",DEALS!$V:$V,"<>*EXECUTED*"))} -> 0 | AA7: =U7*VLOOKUP(U$6,'FX RATES'!$E$1:$F$50,2,FALSE)+V7*VLOOKUP(V$6,'FX RATES'!$E$1:$F$50,2,FALSE)+W7*VLOOKUP(W$6,'FX RATES'!$E$1:$F$50,2,FALSE)+X7*VLOOKUP(X$6,'FX RATES'!$E$1:$F$50,2,FALSE)+Y7*VLOOKUP(Y$6,'FX RATES'!$E$1:$F$50,2,FALSE)+Z7*VLOOKUP(Z$6,'FX RATES'!$E$1:$F$50,2,FALSE) -> 3951.8559 | AC7: =I7+R7-AA7 -> 0
B8: CBD | C8: {=SUMIFS(BALANCES!$C:$C,BALANCES!$A:$A,$B$2,BALANCES!$B:$B,$B8,BALANCES!$D:$D,C$6)+SUMIFS(FLOWS!$C:$C,FLOWS!$A:$A,$B$2,FLOWS!$E:$E,$B8,FLOWS!$D:$D,C$6,FLOWS!$H:$H,"<"&$C$4)+SUM(SUMIFS(DEALS!$J:$J,DEALS!$A:$A,{"*REFUND*","*EXECUTED*"},DEALS!$G:$G,$B$2,DEALS!$E:$E,"<"&$C$4,DEALS!$K:$K,C$6,DEALS!$M:$M,$B8,DEALS!$N:$N,"<>*RECEIVED*",DEALS!$N:$N,"<>*EXECUTED*"))+SUM(SUMIFS(DEALS!$R:$R,DEALS!$A:$A,{"*REFUND*","*EXECUTED*"},DEALS!$O:$O,$B$2,DEALS!$E:$E,"<"&$C$4,DEALS!$S:$S,C$6,DEALS!$U:$U,$B8,DEALS!$V:$V,"<>*RECEIVED*",DEALS!$V:$V,"<>*EXECUTED*"))} -> 93787.7 | D8: {=SUMIFS(BALANCES!$C:$C,BALANCES!$A:$A,$B$2,BALANCES!$B:$B,$B8,BALANCES!$D:$D,D$6)+SUMIFS(FLOWS!$C:$C,FLOWS!$A:$A,$B$2,FLOWS!$E:$E,$B8,FLOWS!$D:$D,D$6,FLOWS!$H:$H,"<"&$C$4)+SUM(SUMIFS(DEALS!$J:$J,DEALS!$A:$A,{"*REFUND*","*EXECUTED*"},DEALS!$G:$G,$B$2,DEALS!$E:$E,"<"&$C$4,DEALS!$K:$K,D$6,DEALS!$M:$M,$B8,DEALS!$N:$N,"<>*RECEIVED*",DEALS!$N:$N,"<>*EXECUTED*"))+SUM(SUMIFS(DEALS!$R:$R,DEALS!$A:$A,{"*REFUND*","*EXECUTED*"},DEALS!$O:$O,$B$2,DEALS!$E:$E,"<"&$C$4,DEALS!$S:$S,D$6,DEALS!$U:$U,$B8,DEALS!$V:$V,"<>*RECEIVED*",DEALS!$V:$V,"<>*EXECUTED*"))} -> 893.77 | E8: {=SUMIFS(BALANCES!$C:$C,BALANCES!$A:$A,$B$2,BALANCES!$B:$B,$B8,BALANCES!$D:$D,E$6)+SUMIFS(FLOWS!$C:$C,FLOWS!$A:$A,$B$2,FLOWS!$E:$E,$B8,FLOWS!$D:$D,E$6,FLOWS!$H:$H,"<"&$C$4)+SUM(SUMIFS(DEALS!$J:$J,DEALS!$A:$A,{"*REFUND*","*EXECUTED*"},DEALS!$G:$G,$B$2,DEALS!$E:$E,"<"&$C$4,DEALS!$K:$K,E$6,DEALS!$M:$M,$B8,DEALS!$N:$N,"<>*RECEIVED*",DEALS!$N:$N,"<>*EXECUTED*"))+SUM(SUMIFS(DEALS!$R:$R,DEALS!$A:$A,{"*REFUND*","*EXECUTED*"},DEALS!$O:$O,$B$2,DEALS!$E:$E,"<"&$C$4,DEALS!$S:$S,E$6,DEALS!$U:$U,$B8,DEALS!$V:$V,"<>*RECEIVED*",DEALS!$V:$V,"<>*EXECUTED*"))} -> 6100.28 | F8: {=SUMIFS(BALANCES!$C:$C,BALANCES!$A:$A,$B$2,BALANCES!$B:$B,$B8,BALANCES!$D:$D,F$6)+SUMIFS(FLOWS!$C:$C,FLOWS!$A:$A,$B$2,FLOWS!$E:$E,$B8,FLOWS!$D:$D,F$6,FLOWS!$H:$H,"<"&$C$4)+SUM(SUMIFS(DEALS!$J:$J,DEALS!$A:$A,{"*REFUND*","*EXECUTED*"},DEALS!$G:$G,$B$2,DEALS!$E:$E,"<"&$C$4,DEALS!$K:$K,F$6,DEALS!$M:$M,$B8,DEALS!$N:$N,"<>*RECEIVED*",DEALS!$N:$N,"<>*EXECUTED*"))+SUM(SUMIFS(DEALS!$R:$R,DEALS!$A:$A,{"*REFUND*","*EXECUTED*"},DEALS!$O:$O,$B$2,DEALS!$E:$E,"<"&$C$4,DEALS!$S:$S,F$6,DEALS!$U:$U,$B8,DEALS!$V:$V,"<>*RECEIVED*",DEALS!$V:$V,"<>*EXECUTED*"))} -> 1577693.5 | G8: {=SUMIFS(BALANCES!$C:$C,BALANCES!$A:$A,$B$2,BALANCES!$B:$B,$B8,BALANCES!$D:$D,G$6)+SUMIFS(FLOWS!$C:$C,FLOWS!$A:$A,$B$2,FLOWS!$E:$E,$B8,FLOWS!$D:$D,G$6,FLOWS!$H:$H,"<"&$C$4)+SUM(SUMIFS(DEALS!$J:$J,DEALS!$A:$A,{"*REFUND*","*EXECUTED*"},DEALS!$G:$G,$B$2,DEALS!$E:$E,"<"&$C$4,DEALS!$K:$K,G$6,DEALS!$M:$M,$B8,DEALS!$N:$N,"<>*RECEIVED*",DEALS!$N:$N,"<>*EXECUTED*"))+SUM(SUMIFS(DEALS!$R:$R,DEALS!$A:$A,{"*REFUND*","*EXECUTED*"},DEALS!$O:$O,$B$2,DEALS!$E:$E,"<"&$C$4,DEALS!$S:$S,G$6,DEALS!$U:$U,$B8,DEALS!$V:$V,"<>*RECEIVED*",DEALS!$V:$V,"<>*EXECUTED*"))} -> 0 | H8: {=SUMIFS(BALANCES!$C:$C,BALANCES!$A:$A,$B$2,BALANCES!$B:$B,$B8,BALANCES!$D:$D,H$6)+SUMIFS(FLOWS!$C:$C,FLOWS!$A:$A,$B$2,FLOWS!$E:$E,$B8,FLOWS!$D:$D,H$6,FLOWS!$H:$H,"<"&$C$4)+SUM(SUMIFS(DEALS!$J:$J,DEALS!$A:$A,{"*REFUND*","*EXECUTED*"},DEALS!$G:$G,$B$2,DEALS!$E:$E,"<"&$C$4,DEALS!$K:$K,H$6,DEALS!$M:$M,$B8,DEALS!$N:$N,"<>*RECEIVED*",DEALS!$N:$N,"<>*EXECUTED*"))+SUM(SUMIFS(DEALS!$R:$R,DEALS!$A:$A,{"*REFUND*","*EXECUTED*"},DEALS!$O:$O,$B$2,DEALS!$E:$E,"<"&$C$4,DEALS!$S:$S,H$6,DEALS!$U:$U,$B8,DEALS!$V:$V,"<>*RECEIVED*",DEALS!$V:$V,"<>*EXECUTED*"))} -> 0 | I8: =C8*VLOOKUP(C$6,'FX RATES'!$E$1:$F$50,2,FALSE)+D8*VLOOKUP(D$6,'FX RATES'!$E$1:$F$50,2,FALSE)+E8*VLOOKUP(E$6,'FX RATES'!$E$1:$F$50,2,FALSE)+F8*VLOOKUP(F$6,'FX RATES'!$E$1:$F$50,2,FALSE)+G8*VLOOKUP(G$6,'FX RATES'!$E$1:$F$50,2,FALSE)+H8*VLOOKUP(H$6,'FX RATES'!$E$1:$F$50,2,FALSE) -> 525308.54 | K8: =B8 -> CBD | L8: {=SUMIFS(FLOWS!$C:$C,FLOWS!$A:$A,$B$2,FLOWS!$E:$E,$K8,FLOWS!$D:$D,L$6,FLOWS!$H:$H,">="&$C$4,FLOWS!$H:$H,"<="&$U$4)+SUM(SUMIFS(DEALS!$J:$J,DEALS!$A:$A,{"*REFUND*","*EXECUTED*"},DEALS!$G:$G,$B$2,DEALS!$E:$E,">="&$C$4,DEALS!$E:$E,"<="&$U$4,DEALS!$K:$K,L$6,DEALS!$M:$M,$K8,DEALS!$N:$N,"<>*RECEIVED*",DEALS!$N:$N,"<>*EXECUTED*"))+SUM(SUMIFS(DEALS!$R:$R,DEALS!$A:$A,{"*REFUND*","*EXECUTED*"},DEALS!$O:$O,$B$2,DEALS!$E:$E,">="&$C$4,DEALS!$E:$E,"<="&$U$4,DEALS!$S:$S,L$6,DEALS!$U:$U,$K8,DEALS!$V:$V,"<>*RECEIVED*",DEALS!$V:$V,"<>*EXECUTED*"))} -> 3012058.3 | M8: {=SUMIFS(FLOWS!$C:$C,FLOWS!$A:$A,$B$2,FLOWS!$E:$E,$K8,FLOWS!$D:$D,M$6,FLOWS!$H:$H,">="&$C$4,FLOWS!$H:$H,"<="&$U$4)+SUM(SUMIFS(DEALS!$J:$J,DEALS!$A:$A,{"*REFUND*","*EXECUTED*"},DEALS!$G:$G,$B$2,DEALS!$E:$E,">="&$C$4,DEALS!$E:$E,"<="&$U$4,DEALS!$K:$K,M$6,DEALS!$M:$M,$K8,DEALS!$N:$N,"<>*RECEIVED*",DEALS!$N:$N,"<>*EXECUTED*"))+SUM(SUMIFS(DEALS!$R:$R,DEALS!$A:$A,{"*REFUND*","*EXECUTED*"},DEALS!$O:$O,$B$2,DEALS!$E:$E,">="&$C$4,DEALS!$E:$E,"<="&$U$4,DEALS!$S:$S,M$6,DEALS!$U:$U,$K8,DEALS!$V:$V,"<>*RECEIVED*",DEALS!$V:$V,"<>*EXECUTED*"))} -> 0 | N8: {=SUMIFS(FLOWS!$C:$C,FLOWS!$A:$A,$B$2,FLOWS!$E:$E,$K8,FLOWS!$D:$D,N$6,FLOWS!$H:$H,">="&$C$4,FLOWS!$H:$H,"<="&$U$4)+SUM(SUMIFS(DEALS!$J:$J,DEALS!$A:$A,{"*REFUND*","*EXECUTED*"},DEALS!$G:$G,$B$2,DEALS!$E:$E,">="&$C$4,DEALS!$E:$E,"<="&$U$4,DEALS!$K:$K,N$6,DEALS!$M:$M,$K8,DEALS!$N:$N,"<>*RECEIVED*",DEALS!$N:$N,"<>*EXECUTED*"))+SUM(SUMIFS(DEALS!$R:$R,DEALS!$A:$A,{"*REFUND*","*EXECUTED*"},DEALS!$O:$O,$B$2,DEALS!$E:$E,">="&$C$4,DEALS!$E:$E,"<="&$U$4,DEALS!$S:$S,N$6,DEALS!$U:$U,$K8,DEALS!$V:$V,"<>*RECEIVED*",DEALS!$V:$V,"<>*EXECUTED*"))} -> 0 | O8: {=SUMIFS(FLOWS!$C:$C,FLOWS!$A:$A,$B$2,FLOWS!$E:$E,$K8,FLOWS!$D:$D,O$6,FLOWS!$H:$H,">="&$C$4,FLOWS!$H:$H,"<="&$U$4)+SUM(SUMIFS(DEALS!$J:$J,DEALS!$A:$A,{"*REFUND*","*EXECUTED*"},DEALS!$G:$G,$B$2,DEALS!$E:$E,">="&$C$4,DEALS!$E:$E,"<="&$U$4,DEALS!$K:$K,O$6,DEALS!$M:$M,$K8,DEALS!$N:$N,"<>*RECEIVED*",DEALS!$N:$N,"<>*EXECUTED*"))+SUM(SUMIFS(DEALS!$R:$R,DEALS!$A:$A,{"*REFUND*","*EXECUTED*"},DEALS!$O:$O,$B$2,DEALS!$E:$E,">="&$C$4,DEALS!$E:$E,"<="&$U$4,DEALS!$S:$S,O$6,DEALS!$U:$U,$K8,DEALS!$V:$V,"<>*RECEIVED*",DEALS!$V:$V,"<>*EXECUTED*"))} -> 0 | P8: {=SUMIFS(FLOWS!$C:$C,FLOWS!$A:$A,$B$2,FLOWS!$E:$E,$K8,FLOWS!$D:$D,P$6,FLOWS!$H:$H,">="&$C$4,FLOWS!$H:$H,"<="&$U$4)+SUM(SUMIFS(DEALS!$J:$J,DEALS!$A:$A,{"*REFUND*","*EXECUTED*"},DEALS!$G:$G,$B$2,DEALS!$E:$E,">="&$C$4,DEALS!$E:$E,"<="&$U$4,DEALS!$K:$K,P$6,DEALS!$M:$M,$K8,DEALS!$N:$N,"<>*RECEIVED*",DEALS!$N:$N,"<>*EXECUTED*"))+SUM(SUMIFS(DEALS!$R:$R,DEALS!$A:$A,{"*REFUND*","*EXECUTED*"},DEALS!$O:$O,$B$2,DEALS!$E:$E,">="&$C$4,DEALS!$E:$E,"<="&$U$4,DEALS!$S:$S,P$6,DEALS!$U:$U,$K8,DEALS!$V:$V,"<>*RECEIVED*",DEALS!$V:$V,"<>*EXECUTED*"))} -> 0 | Q8: {=SUMIFS(FLOWS!$C:$C,FLOWS!$A:$A,$B$2,FLOWS!$E:$E,$K8,FLOWS!$D:$D,Q$6,FLOWS!$H:$H,">="&$C$4,FLOWS!$H:$H,"<="&$U$4)+SUM(SUMIFS(DEALS!$J:$J,DEALS!$A:$A,{"*REFUND*","*EXECUTED*"},DEALS!$G:$G,$B$2,DEALS!$E:$E,">="&$C$4,DEALS!$E:$E,"<="&$U$4,DEALS!$K:$K,Q$6,DEALS!$M:$M,$K8,DEALS!$N:$N,"<>*RECEIVED*",DEALS!$N:$N,"<>*EXECUTED*"))+SUM(SUMIFS(DEALS!$R:$R,DEALS!$A:$A,{"*REFUND*","*EXECUTED*"},DEALS!$O:$O,$B$2,DEALS!$E:$E,">="&$C$4,DEALS!$E:$E,"<="&$U$4,DEALS!$S:$S,Q$6,DEALS!$U:$U,$K8,DEALS!$V:$V,"<>*RECEIVED*",DEALS!$V:$V,"<>*EXECUTED*"))} -> 0 | R8: =L8*VLOOKUP(L$6,'FX RATES'!$E$1:$F$50,2,FALSE)+M8*VLOOKUP(M$6,'FX RATES'!$E$1:$F$50,2,FALSE)+N8*VLOOKUP(N$6,'FX RATES'!$E$1:$F$50,2,FALSE)+O8*VLOOKUP(O$6,'FX RATES'!$E$1:$F$50,2,FALSE)+P8*VLOOKUP(P$6,'FX RATES'!$E$1:$F$50,2,FALSE)+Q8*VLOOKUP(Q$6,'FX RATES'!$E$1:$F$50,2,FALSE) -> 3012058.3 | T8: =B8 -> CBD | U8: {=SUMIFS(BALANCES!$C:$C,BALANCES!$A:$A,$B$2,BALANCES!$B:$B,$T8,BALANCES!$D:$D,U$6)+SUMIFS(FLOWS!$C:$C,FLOWS!$A:$A,$B$2,FLOWS!$E:$E,$T8,FLOWS!$D:$D,U$6,FLOWS!$H:$H,"<="&$U$4)+SUM(SUMIFS(DEALS!$J:$J,DEALS!$A:$A,{"*REFUND*","*EXECUTED*"},DEALS!$G:$G,$B$2,DEALS!$E:$E,"<="&$U$4,DEALS!$K:$K,U$6,DEALS!$M:$M,$T8,DEALS!$N:$N,"<>*RECEIVED*",DEALS!$N:$N,"<>*EXECUTED*"))+SUM(SUMIFS(DEALS!$R:$R,DEALS!$A:$A,{"*REFUND*","*EXECUTED*"},DEALS!$O:$O,$B$2,DEALS!$E:$E,"<="&$U$4,DEALS!$S:$S,U$6,DEALS!$U:$U,$T8,DEALS!$V:$V,"<>*RECEIVED*",DEALS!$V:$V,"<>*EXECUTED*"))} -> 3105846 | V8: {=SUMIFS(BALANCES!$C:$C,BALANCES!$A:$A,$B$2,BALANCES!$B:$B,$T8,BALANCES!$D:$D,V$6)+SUMIFS(FLOWS!$C:$C,FLOWS!$A:$A,$B$2,FLOWS!$E:$E,$T8,FLOWS!$D:$D,V$6,FLOWS!$H:$H,"<="&$U$4)+SUM(SUMIFS(DEALS!$J:$J,DEALS!$A:$A,{"*REFUND*","*EXECUTED*"},DEALS!$G:$G,$B$2,DEALS!$E:$E,"<="&$U$4,DEALS!$K:$K,V$6,DEALS!$M:$M,$T8,DEALS!$N:$N,"<>*RECEIVED*",DEALS!$N:$N,"<>*EXECUTED*"))+SUM(SUMIFS(DEALS!$R:$R,DEALS!$A:$A,{"*REFUND*","*EXECUTED*"},DEALS!$O:$O,$B$2,DEALS!$E:$E,"<="&$U$4,DEALS!$S:$S,V$6,DEALS!$U:$U,$T8,DEALS!$V:$V,"<>*RECEIVED*",DEALS!$V:$V,"<>*EXECUTED*"))} -> 893.77 | W8: {=SUMIFS(BALANCES!$C:$C,BALANCES!$A:$A,$B$2,BALANCES!$B:$B,$T8,BALANCES!$D:$D,W$6)+SUMIFS(FLOWS!$C:$C,FLOWS!$A:$A,$B$2,FLOWS!$E:$E,$T8,FLOWS!$D:$D,W$6,FLOWS!$H:$H,"<="&$U$4)+SUM(SUMIFS(DEALS!$J:$J,DEALS!$A:$A,{"*REFUND*","*EXECUTED*"},DEALS!$G:$G,$B$2,DEALS!$E:$E,"<="&$U$4,DEALS!$K:$K,W$6,DEALS!$M:$M,$T8,DEALS!$N:$N,"<>*RECEIVED*",DEALS!$N:$N,"<>*EXECUTED*"))+SUM(SUMIFS(DEALS!$R:$R,DEALS!$A:$A,{"*REFUND*","*EXECUTED*"},DEALS!$O:$O,$B$2,DEALS!$E:$E,"<="&$U$4,DEALS!$S:$S,W$6,DEALS!$U:$U,$T8,DEALS!$V:$V,"<>*RECEIVED*",DEALS!$V:$V,"<>*EXECUTED*"))} -> 6100.28 | X8: {=SUMIFS(BALANCES!$C:$C,BALANCES!$A:$A,$B$2,BALANCES!$B:$B,$T8,BALANCES!$D:$D,X$6)+SUMIFS(FLOWS!$C:$C,FLOWS!$A:$A,$B$2,FLOWS!$E:$E,$T8,FLOWS!$D:$D,X$6,FLOWS!$H:$H,"<="&$U$4)+SUM(SUMIFS(DEALS!$J:$J,DEALS!$A:$A,{"*REFUND*","*EXECUTED*"},DEALS!$G:$G,$B$2,DEALS!$E:$E,"<="&$U$4,DEALS!$K:$K,X$6,DEALS!$M:$M,$T8,DEALS!$N:$N,"<>*RECEIVED*",DEALS!$N:$N,"<>*EXECUTED*"))+SUM(SUMIFS(DEALS!$R:$R,DEALS!$A:$A,{"*REFUND*","*EXECUTED*"},DEALS!$O:$O,$B$2,DEALS!$E:$E,"<="&$U$4,DEALS!$S:$S,X$6,DEALS!$U:$U,$T8,DEALS!$V:$V,"<>*RECEIVED*",DEALS!$V:$V,"<>*EXECUTED*"))} -> 1577693.5 | Y8: {=SUMIFS(BALANCES!$C:$C,BALANCES!$A:$A,$B$2,BALANCES!$B:$B,$T8,BALANCES!$D:$D,Y$6)+SUMIFS(FLOWS!$C:$C,FLOWS!$A:$A,$B$2,FLOWS!$E:$E,$T8,FLOWS!$D:$D,Y$6,FLOWS!$H:$H,"<="&$U$4)+SUM(SUMIFS(DEALS!$J:$J,DEALS!$A:$A,{"*REFUND*","*EXECUTED*"},DEALS!$G:$G,$B$2,DEALS!$E:$E,"<="&$U$4,DEALS!$K:$K,Y$6,DEALS!$M:$M,$T8,DEALS!$N:$N,"<>*RECEIVED*",DEALS!$N:$N,"<>*EXECUTED*"))+SUM(SUMIFS(DEALS!$R:$R,DEALS!$A:$A,{"*REFUND*","*EXECUTED*"},DEALS!$O:$O,$B$2,DEALS!$E:$E,"<="&$U$4,DEALS!$S:$S,Y$6,DEALS!$U:$U,$T8,DEALS!$V:$V,"<>*RECEIVED*",DEALS!$V:$V,"<>*EXECUTED*"))} -> 0 | Z8: {=SUMIFS(BALANCES!$C:$C,BALANCES!$A:$A,$B$2,BALANCES!$B:$B,$T8,BALANCES!$D:$D,Z$6)+SUMIFS(FLOWS!$C:$C,FLOWS!$A:$A,$B$2,FLOWS!$E:$E,$T8,FLOWS!$D:$D,Z$6,FLOWS!$H:$H,"<="&$U$4)+SUM(SUMIFS(DEALS!$J:$J,DEALS!$A:$A,{"*REFUND*","*EXECUTED*"},DEALS!$G:$G,$B$2,DEALS!$E:$E,"<="&$U$4,DEALS!$K:$K,Z$6,DEALS!$M:$M,$T8,DEALS!$N:$N,"<>*RECEIVED*",DEALS!$N:$N,"<>*EXECUTED*"))+SUM(SUMIFS(DEALS!$R:$R,DEALS!$A:$A,{"*REFUND*","*EXECUTED*"},DEALS!$O:$O,$B$2,DEALS!$E:$E,"<="&$U$4,DEALS!$S:$S,Z$6,DEALS!$U:$U,$T8,DEALS!$V:$V,"<>*RECEIVED*",DEALS!$V:$V,"<>*EXECUTED*"))} -> 0 | AA8: =U8*VLOOKUP(U$6,'FX RATES'!$E$1:$F$50,2,FALSE)+V8*VLOOKUP(V$6,'FX RATES'!$E$1:$F$50,2,FALSE)+W8*VLOOKUP(W$6,'FX RATES'!$E$1:$F$50,2,FALSE)+X8*VLOOKUP(X$6,'FX RATES'!$E$1:$F$50,2,FALSE)+Y8*VLOOKUP(Y$6,'FX RATES'!$E$1:$F$50,2,FALSE)+Z8*VLOOKUP(Z$6,'FX RATES'!$E$1:$F$50,2,FALSE) -> 3537366.9 | AC8: =I8+R8-AA8 -> 0
B9: MISR | C9: {=SUMIFS(BALANCES!$C:$C,BALANCES!$A:$A,$B$2,BALANCES!$B:$B,$B9,BALANCES!$D:$D,C$6)+SUMIFS(FLOWS!$C:$C,FLOWS!$A:$A,$B$2,FLOWS!$E:$E,$B9,FLOWS!$D:$D,C$6,FLOWS!$H:$H,"<"&$C$4)+SUM(SUMIFS(DEALS!$J:$J,DEALS!$A:$A,{"*REFUND*","*EXECUTED*"},DEALS!$G:$G,$B$2,DEALS!$E:$E,"<"&$C$4,DEALS!$K:$K,C$6,DEALS!$M:$M,$B9,DEALS!$N:$N,"<>*RECEIVED*",DEALS!$N:$N,"<>*EXECUTED*"))+SUM(SUMIFS(DEALS!$R:$R,DEALS!$A:$A,{"*REFUND*","*EXECUTED*"},DEALS!$O:$O,$B$2,DEALS!$E:$E,"<"&$C$4,DEALS!$S:$S,C$6,DEALS!$U:$U,$B9,DEALS!$V:$V,"<>*RECEIVED*",DEALS!$V:$V,"<>*EXECUTED*"))} -> 2916.76 | D9: {=SUMIFS(BALANCES!$C:$C,BALANCES!$A:$A,$B$2,BALANCES!$B:$B,$B9,BALANCES!$D:$D,D$6)+SUMIFS(FLOWS!$C:$C,FLOWS!$A:$A,$B$2,FLOWS!$E:$E,$B9,FLOWS!$D:$D,D$6,FLOWS!$H:$H,"<"&$C$4)+SUM(SUMIFS(DEALS!$J:$J,DEALS!$A:$A,{"*REFUND*","*EXECUTED*"},DEALS!$G:$G,$B$2,DEALS!$E:$E,"<"&$C$4,DEALS!$K:$K,D$6,DEALS!$M:$M,$B9,DEALS!$N:$N,"<>*RECEIVED*",DEALS!$N:$N,"<>*EXECUTED*"))+SUM(SUMIFS(DEALS!$R:$R,DEALS!$A:$A,{"*REFUND*","*EXECUTED*"},DEALS!$O:$O,$B$2,DEALS!$E:$E,"<"&$C$4,DEALS!$S:$S,D$6,DEALS!$U:$U,$B9,DEALS!$V:$V,"<>*RECEIVED*",DEALS!$V:$V,"<>*EXECUTED*"))} -> 712.19 | E9: {=SUMIFS(BALANCES!$C:$C,BALANCES!$A:$A,$B$2,BALANCES!$B:$B,$B9,BALANCES!$D:$D,E$6)+SUMIFS(FLOWS!$C:$C,FLOWS!$A:$A,$B$2,FLOWS!$E:$E,$B9,FLOWS!$D:$D,E$6,FLOWS!$H:$H,"<"&$C$4)+SUM(SUMIFS(DEALS!$J:$J,DEALS!$A:$A,{"*REFUND*","*EXECUTED*"},DEALS!$G:$G,$B$2,DEALS!$E:$E,"<"&$C$4,DEALS!$K:$K,E$6,DEALS!$M:$M,$B9,DEALS!$N:$N,"<>*RECEIVED*",DEALS!$N:$N,"<>*EXECUTED*"))+SUM(SUMIFS(DEALS!$R:$R,DEALS!$A:$A,{"*REFUND*","*EXECUTED*"},DEALS!$O:$O,$B$2,DEALS!$E:$E,"<"&$C$4,DEALS!$S:$S,E$6,DEALS!$U:$U,$B9,DEALS!$V:$V,"<>*RECEIVED*",DEALS!$V:$V,"<>*EXECUTED*"))} -> 0 | F9: {=SUMIFS(BALANCES!$C:$C,BALANCES!$A:$A,$B$2,BALANCES!$B:$B,$B9,BALANCES!$D:$D,F$6)+SUMIFS(FLOWS!$C:$C,FLOWS!$A:$A,$B$2,FLOWS!$E:$E,$B9,FLOWS!$D:$D,F$6,FLOWS!$H:$H,"<"&$C$4)+SUM(SUMIFS(DEALS!$J:$J,DEALS!$A:$A,{"*REFUND*","*EXECUTED*"},DEALS!$G:$G,$B$2,DEALS!$E:$E,"<"&$C$4,DEALS!$K:$K,F$6,DEALS!$M:$M,$B9,DEALS!$N:$N,"<>*RECEIVED*",DEALS!$N:$N,"<>*EXECUTED*"))+SUM(SUMIFS(DEALS!$R:$R,DEALS!$A:$A,{"*REFUND*","*EXECUTED*"},DEALS!$O:$O,$B$2,DEALS!$E:$E,"<"&$C$4,DEALS!$S:$S,F$6,DEALS!$U:$U,$B9,DEALS!$V:$V,"<>*RECEIVED*",DEALS!$V:$V,"<>*EXECUTED*"))} -> 4430.61 | G9: {=SUMIFS(BALANCES!$C:$C,BALANCES!$A:$A,$B$2,BALANCES!$B:$B,$B9,BALANCES!$D:$D,G$6)+SUMIFS(FLOWS!$C:$C,FLOWS!$A:$A,$B$2,FLOWS!$E:$E,$B9,FLOWS!$D:$D,G$6,FLOWS!$H:$H,"<"&$C$4)+SUM(SUMIFS(DEALS!$J:$J,DEALS!$A:$A,{"*REFUND*","*EXECUTED*"},DEALS!$G:$G,$B$2,DEALS!$E:$E,"<"&$C$4,DEALS!$K:$K,G$6,DEALS!$M:$M,$B9,DEALS!$N:$N,"<>*RECEIVED*",DEALS!$N:$N,"<>*EXECUTED*"))+SUM(SUMIFS(DEALS!$R:$R,DEALS!$A:$A,{"*REFUND*","*EXECUTED*"},DEALS!$O:$O,$B$2,DEALS!$E:$E,"<"&$C$4,DEALS!$S:$S,G$6,DEALS!$U:$U,$B9,DEALS!$V:$V,"<>*RECEIVED*",DEALS!$V:$V,"<>*EXECUTED*"))} -> 0 | H9: {=SUMIFS(BALANCES!$C:$C,BALANCES!$A:$A,$B$2,BALANCES!$B:$B,$B9,BALANCES!$D:$D,H$6)+SUMIFS(FLOWS!$C:$C,FLOWS!$A:$A,$B$2,FLOWS!$E:$E,$B9,FLOWS!$D:$D,H$6,FLOWS!$H:$H,"<"&$C$4)+SUM(SUMIFS(DEALS!$J:$J,DEALS!$A:$A,{"*REFUND*","*EXECUTED*"},DEALS!$G:$G,$B$2,DEALS!$E:$E,"<"&$C$4,DEALS!$K:$K,H$6,DEALS!$M:$M,$B9,DEALS!$N:$N,"<>*RECEIVED*",DEALS!$N:$N,"<>*EXECUTED*"))+SUM(SUMIFS(DEALS!$R:$R,DEALS!$A:$A,{"*REFUND*","*EXECUTED*"},DEALS!$O:$O,$B$2,DEALS!$E:$E,"<"&$C$4,DEALS!$S:$S,H$6,DEALS!$U:$U,$B9,DEALS!$V:$V,"<>*RECEIVED*",DEALS!$V:$V,"<>*EXECUTED*"))} -> 0 | I9: =C9*VLOOKUP(C$6,'FX RATES'!$E$1:$F$50,2,FALSE)+D9*VLOOKUP(D$6,'FX RATES'!$E$1:$F$50,2,FALSE)+E9*VLOOKUP(E$6,'FX RATES'!$E$1:$F$50,2,FALSE)+F9*VLOOKUP(F$6,'FX RATES'!$E$1:$F$50,2,FALSE)+G9*VLOOKUP(G$6,'FX RATES'!$E$1:$F$50,2,FALSE)+H9*VLOOKUP(H$6,'FX RATES'!$E$1:$F$50,2,FALSE) -> 4962.1158 | K9: =B9 -> MISR | L9: {=SUMIFS(FLOWS!$C:$C,FLOWS!$A:$A,$B$2,FLOWS!$E:$E,$K9,FLOWS!$D:$D,L$6,FLOWS!$H:$H,">="&$C$4,FLOWS!$H:$H,"<="&$U$4)+SUM(SUMIFS(DEALS!$J:$J,DEALS!$A:$A,{"*REFUND*","*EXECUTED*"},DEALS!$G:$G,$B$2,DEALS!$E:$E,">="&$C$4,DEALS!$E:$E,"<="&$U$4,DEALS!$K:$K,L$6,DEALS!$M:$M,$K9,DEALS!$N:$N,"<>*RECEIVED*",DEALS!$N:$N,"<>*EXECUTED*"))+SUM(SUMIFS(DEALS!$R:$R,DEALS!$A:$A,{"*REFUND*","*EXECUTED*"},DEALS!$O:$O,$B$2,DEALS!$E:$E,">="&$C$4,DEALS!$E:$E,"<="&$U$4,DEALS!$S:$S,L$6,DEALS!$U:$U,$K9,DEALS!$V:$V,"<>*RECEIVED*",DEALS!$V:$V,"<>*EXECUTED*"))} -> 0 | M9: {=SUMIFS(FLOWS!$C:$C,FLOWS!$A:$A,$B$2,FLOWS!$E:$E,$K9,FLOWS!$D:$D,M$6,FLOWS!$H:$H,">="&$C$4,FLOWS!$H:$H,"<="&$U$4)+SUM(SUMIFS(DEALS!$J:$J,DEALS!$A:$A,{"*REFUND*","*EXECUTED*"},DEALS!$G:$G,$B$2,DEALS!$E:$E,">="&$C$4,DEALS!$E:$E,"<="&$U$4,DEALS!$K:$K,M$6,DEALS!$M:$M,$K9,DEALS!$N:$N,"<>*RECEIVED*",DEALS!$N:$N,"<>*EXECUTED*"))+SUM(SUMIFS(DEALS!$R:$R,DEALS!$A:$A,{"*REFUND*","*EXECUTED*"},DEALS!$O:$O,$B$2,DEALS!$E:$E,">="&$C$4,DEALS!$E:$E,"<="&$U$4,DEALS!$S:$S,M$6,DEALS!$U:$U,$K9,DEALS!$V:$V,"<>*RECEIVED*",DEALS!$V:$V,"<>*EXECUTED*"))} -> 0 | N9: {=SUMIFS(FLOWS!$C:$C,FLOWS!$A:$A,$B$2,FLOWS!$E:$E,$K9,FLOWS!$D:$D,N$6,FLOWS!$H:$H,">="&$C$4,FLOWS!$H:$H,"<="&$U$4)+SUM(SUMIFS(DEALS!$J:$J,DEALS!$A:$A,{"*REFUND*","*EXECUTED*"},DEALS!$G:$G,$B$2,DEALS!$E:$E,">="&$C$4,DEALS!$E:$E,"<="&$U$4,DEALS!$K:$K,N$6,DEALS!$M:$M,$K9,DEALS!$N:$N,"<>*RECEIVED*",DEALS!$N:$N,"<>*EXECUTED*"))+SUM(SUMIFS(DEALS!$R:$R,DEALS!$A:$A,{"*REFUND*","*EXECUTED*"},DEALS!$O:$O,$B$2,DEALS!$E:$E,">="&$C$4,DEALS!$E:$E,"<="&$U$4,DEALS!$S:$S,N$6,DEALS!$U:$U,$K9,DEALS!$V:$V,"<>*RECEIVED*",DEALS!$V:$V,"<>*EXECUTED*"))} -> 0 | O9: {=SUMIFS(FLOWS!$C:$C,FLOWS!$A:$A,$B$2,FLOWS!$E:$E,$K9,FLOWS!$D:$D,O$6,FLOWS!$H:$H,">="&$C$4,FLOWS!$H:$H,"<="&$U$4)+SUM(SUMIFS(DEALS!$J:$J,DEALS!$A:$A,{"*REFUND*","*EXECUTED*"},DEALS!$G:$G,$B$2,DEALS!$E:$E,">="&$C$4,DEALS!$E:$E,"<="&$U$4,DEALS!$K:$K,O$6,DEALS!$M:$M,$K9,DEALS!$N:$N,"<>*RECEIVED*",DEALS!$N:$N,"<>*EXECUTED*"))+SUM(SUMIFS(DEALS!$R:$R,DEALS!$A:$A,{"*REFUND*","*EXECUTED*"},DEALS!$O:$O,$B$2,DEALS!$E:$E,">="&$C$4,DEALS!$E:$E,"<="&$U$4,DEALS!$S:$S,O$6,DEALS!$U:$U,$K9,DEALS!$V:$V,"<>*RECEIVED*",DEALS!$V:$V,"<>*EXECUTED*"))} -> 0 | P9: {=SUMIFS(FLOWS!$C:$C,FLOWS!$A:$A,$B$2,FLOWS!$E:$E,$K9,FLOWS!$D:$D,P$6,FLOWS!$H:$H,">="&$C$4,FLOWS!$H:$H,"<="&$U$4)+SUM(SUMIFS(DEALS!$J:$J,DEALS!$A:$A,{"*REFUND*","*EXECUTED*"},DEALS!$G:$G,$B$2,DEALS!$E:$E,">="&$C$4,DEALS!$E:$E,"<="&$U$4,DEALS!$K:$K,P$6,DEALS!$M:$M,$K9,DEALS!$N:$N,"<>*RECEIVED*",DEALS!$N:$N,"<>*EXECUTED*"))+SUM(SUMIFS(DEALS!$R:$R,DEALS!$A:$A,{"*REFUND*","*EXECUTED*"},DEALS!$O:$O,$B$2,DEALS!$E:$E,">="&$C$4,DEALS!$E:$E,"<="&$U$4,DEALS!$S:$S,P$6,DEALS!$U:$U,$K9,DEALS!$V:$V,"<>*RECEIVED*",DEALS!$V:$V,"<>*EXECUTED*"))} -> 0 | Q9: {=SUMIFS(FLOWS!$C:$C,FLOWS!$A:$A,$B$2,FLOWS!$E:$E,$K9,FLOWS!$D:$D,Q$6,FLOWS!$H:$H,">="&$C$4,FLOWS!$H:$H,"<="&$U$4)+SUM(SUMIFS(DEALS!$J:$J,DEALS!$A:$A,{"*REFUND*","*EXECUTED*"},DEALS!$G:$G,$B$2,DEALS!$E:$E,">="&$C$4,DEALS!$E:$E,"<="&$U$4,DEALS!$K:$K,Q$6,DEALS!$M:$M,$K9,DEALS!$N:$N,"<>*RECEIVED*",DEALS!$N:$N,"<>*EXECUTED*"))+SUM(SUMIFS(DEALS!$R:$R,DEALS!$A:$A,{"*REFUND*","*EXECUTED*"},DEALS!$O:$O,$B$2,DEALS!$E:$E,">="&$C$4,DEALS!$E:$E,"<="&$U$4,DEALS!$S:$S,Q$6,DEALS!$U:$U,$K9,DEALS!$V:$V,"<>*RECEIVED*",DEALS!$V:$V,"<>*EXECUTED*"))} -> 0 | R9: =L9*VLOOKUP(L$6,'FX RATES'!$E$1:$F$50,2,FALSE)+M9*VLOOKUP(M$6,'FX RATES'!$E$1:$F$50,2,FALSE)+N9*VLOOKUP(N$6,'FX RATES'!$E$1:$F$50,2,FALSE)+O9*VLOOKUP(O$6,'FX RATES'!$E$1:$F$50,2,FALSE)+P9*VLOOKUP(P$6,'FX RATES'!$E$1:$F$50,2,FALSE)+Q9*VLOOKUP(Q$6,'FX RATES'!$E$1:$F$50,2,FALSE) -> 0 | T9: =B9 -> MISR | U9: {=SUMIFS(BALANCES!$C:$C,BALANCES!$A:$A,$B$2,BALANCES!$B:$B,$T9,BALANCES!$D:$D,U$6)+SUMIFS(FLOWS!$C:$C,FLOWS!$A:$A,$B$2,FLOWS!$E:$E,$T9,FLOWS!$D:$D,U$6,FLOWS!$H:$H,"<="&$U$4)+SUM(SUMIFS(DEALS!$J:$J,DEALS!$A:$A,{"*REFUND*","*EXECUTED*"},DEALS!$G:$G,$B$2,DEALS!$E:$E,"<="&$U$4,DEALS!$K:$K,U$6,DEALS!$M:$M,$T9,DEALS!$N:$N,"<>*RECEIVED*",DEALS!$N:$N,"<>*EXECUTED*"))+SUM(SUMIFS(DEALS!$R:$R,DEALS!$A:$A,{"*REFUND*","*EXECUTED*"},DEALS!$O:$O,$B$2,DEALS!$E:$E,"<="&$U$4,DEALS!$S:$S,U$6,DEALS!$U:$U,$T9,DEALS!$V:$V,"<>*RECEIVED*",DEALS!$V:$V,"<>*EXECUTED*"))} -> 2916.76 | V9: {=SUMIFS(BALANCES!$C:$C,BALANCES!$A:$A,$B$2,BALANCES!$B:$B,$T9,BALANCES!$D:$D,V$6)+SUMIFS(FLOWS!$C:$C,FLOWS!$A:$A,$B$2,FLOWS!$E:$E,$T9,FLOWS!$D:$D,V$6,FLOWS!$H:$H,"<="&$U$4)+SUM(SUMIFS(DEALS!$J:$J,DEALS!$A:$A,{"*REFUND*","*EXECUTED*"},DEALS!$G:$G,$B$2,DEALS!$E:$E,"<="&$U$4,DEALS!$K:$K,V$6,DEALS!$M:$M,$T9,DEALS!$N:$N,"<>*RECEIVED*",DEALS!$N:$N,"<>*EXECUTED*"))+SUM(SUMIFS(DEALS!$R:$R,DEALS!$A:$A,{"*REFUND*","*EXECUTED*"},DEALS!$O:$O,$B$2,DEALS!$E:$E,"<="&$U$4,DEALS!$S:$S,V$6,DEALS!$U:$U,$T9,DEALS!$V:$V,"<>*RECEIVED*",DEALS!$V:$V,"<>*EXECUTED*"))} -> 712.19 | W9: {=SUMIFS(BALANCES!$C:$C,BALANCES!$A:$A,$B$2,BALANCES!$B:$B,$T9,BALANCES!$D:$D,W$6)+SUMIFS(FLOWS!$C:$C,FLOWS!$A:$A,$B$2,FLOWS!$E:$E,$T9,FLOWS!$D:$D,W$6,FLOWS!$H:$H,"<="&$U$4)+SUM(SUMIFS(DEALS!$J:$J,DEALS!$A:$A,{"*REFUND*","*EXECUTED*"},DEALS!$G:$G,$B$2,DEALS!$E:$E,"<="&$U$4,DEALS!$K:$K,W$6,DEALS!$M:$M,$T9,DEALS!$N:$N,"<>*RECEIVED*",DEALS!$N:$N,"<>*EXECUTED*"))+SUM(SUMIFS(DEALS!$R:$R,DEALS!$A:$A,{"*REFUND*","*EXECUTED*"},DEALS!$O:$O,$B$2,DEALS!$E:$E,"<="&$U$4,DEALS!$S:$S,W$6,DEALS!$U:$U,$T9,DEALS!$V:$V,"<>*RECEIVED*",DEALS!$V:$V,"<>*EXECUTED*"))} -> 0 | X9: {=SUMIFS(BALANCES!$C:$C,BALANCES!$A:$A,$B$2,BALANCES!$B:$B,$T9,BALANCES!$D:$D,X$6)+SUMIFS(FLOWS!$C:$C,FLOWS!$A:$A,$B$2,FLOWS!$E:$E,$T9,FLOWS!$D:$D,X$6,FLOWS!$H:$H,"<="&$U$4)+SUM(SUMIFS(DEALS!$J:$J,DEALS!$A:$A,{"*REFUND*","*EXECUTED*"},DEALS!$G:$G,$B$2,DEALS!$E:$E,"<="&$U$4,DEALS!$K:$K,X$6,DEALS!$M:$M,$T9,DEALS!$N:$N,"<>*RECEIVED*",DEALS!$N:$N,"<>*EXECUTED*"))+SUM(SUMIFS(DEALS!$R:$R,DEALS!$A:$A,{"*REFUND*","*EXECUTED*"},DEALS!$O:$O,$B$2,DEALS!$E:$E,"<="&$U$4,DEALS!$S:$S,X$6,DEALS!$U:$U,$T9,DEALS!$V:$V,"<>*RECEIVED*",DEALS!$V:$V,"<>*EXECUTED*"))} -> 4430.61 | Y9: {=SUMIFS(BALANCES!$C:$C,BALANCES!$A:$A,$B$2,BALANCES!$B:$B,$T9,BALANCES!$D:$D,Y$6)+SUMIFS(FLOWS!$C:$C,FLOWS!$A:$A,$B$2,FLOWS!$E:$E,$T9,FLOWS!$D:$D,Y$6,FLOWS!$H:$H,"<="&$U$4)+SUM(SUMIFS(DEALS!$J:$J,DEALS!$A:$A,{"*REFUND*","*EXECUTED*"},DEALS!$G:$G,$B$2,DEALS!$E:$E,"<="&$U$4,DEALS!$K:$K,Y$6,DEALS!$M:$M,$T9,DEALS!$N:$N,"<>*RECEIVED*",DEALS!$N:$N,"<>*EXECUTED*"))+SUM(SUMIFS(DEALS!$R:$R,DEALS!$A:$A,{"*REFUND*","*EXECUTED*"},DEALS!$O:$O,$B$2,DEALS!$E:$E,"<="&$U$4,DEALS!$S:$S,Y$6,DEALS!$U:$U,$T9,DEALS!$V:$V,"<>*RECEIVED*",DEALS!$V:$V,"<>*EXECUTED*"))} -> 0 | Z9: {=SUMIFS(BALANCES!$C:$C,BALANCES!$A:$A,$B$2,BALANCES!$B:$B,$T9,BALANCES!$D:$D,Z$6)+SUMIFS(FLOWS!$C:$C,FLOWS!$A:$A,$B$2,FLOWS!$E:$E,$T9,FLOWS!$D:$D,Z$6,FLOWS!$H:$H,"<="&$U$4)+SUM(SUMIFS(DEALS!$J:$J,DEALS!$A:$A,{"*REFUND*","*EXECUTED*"},DEALS!$G:$G,$B$2,DEALS!$E:$E,"<="&$U$4,DEALS!$K:$K,Z$6,DEALS!$M:$M,$T9,DEALS!$N:$N,"<>*RECEIVED*",DEALS!$N:$N,"<>*EXECUTED*"))+SUM(SUMIFS(DEALS!$R:$R,DEALS!$A:$A,{"*REFUND*","*EXECUTED*"},DEALS!$O:$O,$B$2,DEALS!$E:$E,"<="&$U$4,DEALS!$S:$S,Z$6,DEALS!$U:$U,$T9,DEALS!$V:$V,"<>*RECEIVED*",DEALS!$V:$V,"<>*EXECUTED*"))} -> 0 | AA9: =U9*VLOOKUP(U$6,'FX RATES'!$E$1:$F$50,2,FALSE)+V9*VLOOKUP(V$6,'FX RATES'!$E$1:$F$50,2,FALSE)+W9*VLOOKUP(W$6,'FX RATES'!$E$1:$F$50,2,FALSE)+X9*VLOOKUP(X$6,'FX RATES'!$E$1:$F$50,2,FALSE)+Y9*VLOOKUP(Y$6,'FX RATES'!$E$1:$F$50,2,FALSE)+Z9*VLOOKUP(Z$6,'FX RATES'!$E$1:$F$50,2,FALSE) -> 4962.1158 | AC9: =I9+R9-AA9 -> 0
B10: ADIB | C10: {=SUMIFS(BALANCES!$C:$C,BALANCES!$A:$A,$B$2,BALANCES!$B:$B,$B10,BALANCES!$D:$D,C$6)+SUMIFS(FLOWS!$C:$C,FLOWS!$A:$A,$B$2,FLOWS!$E:$E,$B10,FLOWS!$D:$D,C$6,FLOWS!$H:$H,"<"&$C$4)+SUM(SUMIFS(DEALS!$J:$J,DEALS!$A:$A,{"*REFUND*","*EXECUTED*"},DEALS!$G:$G,$B$2,DEALS!$E:$E,"<"&$C$4,DEALS!$K:$K,C$6,DEALS!$M:$M,$B10,DEALS!$N:$N,"<>*RECEIVED*",DEALS!$N:$N,"<>*EXECUTED*"))+SUM(SUMIFS(DEALS!$R:$R,DEALS!$A:$A,{"*REFUND*","*EXECUTED*"},DEALS!$O:$O,$B$2,DEALS!$E:$E,"<"&$C$4,DEALS!$S:$S,C$6,DEALS!$U:$U,$B10,DEALS!$V:$V,"<>*RECEIVED*",DEALS!$V:$V,"<>*EXECUTED*"))} -> 1080.98 | D10: {=SUMIFS(BALANCES!$C:$C,BALANCES!$A:$A,$B$2,BALANCES!$B:$B,$B10,BALANCES!$D:$D,D$6)+SUMIFS(FLOWS!$C:$C,FLOWS!$A:$A,$B$2,FLOWS!$E:$E,$B10,FLOWS!$D:$D,D$6,FLOWS!$H:$H,"<"&$C$4)+SUM(SUMIFS(DEALS!$J:$J,DEALS!$A:$A,{"*REFUND*","*EXECUTED*"},DEALS!$G:$G,$B$2,DEALS!$E:$E,"<"&$C$4,DEALS!$K:$K,D$6,DEALS!$M:$M,$B10,DEALS!$N:$N,"<>*RECEIVED*",DEALS!$N:$N,"<>*EXECUTED*"))+SUM(SUMIFS(DEALS!$R:$R,DEALS!$A:$A,{"*REFUND*","*EXECUTED*"},DEALS!$O:$O,$B$2,DEALS!$E:$E,"<"&$C$4,DEALS!$S:$S,D$6,DEALS!$U:$U,$B10,DEALS!$V:$V,"<>*RECEIVED*",DEALS!$V:$V,"<>*EXECUTED*"))} -> 0 | E10: {=SUMIFS(BALANCES!$C:$C,BALANCES!$A:$A,$B$2,BALANCES!$B:$B,$B10,BALANCES!$D:$D,E$6)+SUMIFS(FLOWS!$C:$C,FLOWS!$A:$A,$B$2,FLOWS!$E:$E,$B10,FLOWS!$D:$D,E$6,FLOWS!$H:$H,"<"&$C$4)+SUM(SUMIFS(DEALS!$J:$J,DEALS!$A:$A,{"*REFUND*","*EXECUTED*"},DEALS!$G:$G,$B$2,DEALS!$E:$E,"<"&$C$4,DEALS!$K:$K,E$6,DEALS!$M:$M,$B10,DEALS!$N:$N,"<>*RECEIVED*",DEALS!$N:$N,"<>*EXECUTED*"))+SUM(SUMIFS(DEALS!$R:$R,DEALS!$A:$A,{"*REFUND*","*EXECUTED*"},DEALS!$O:$O,$B$2,DEALS!$E:$E,"<"&$C$4,DEALS!$S:$S,E$6,DEALS!$U:$U,$B10,DEALS!$V:$V,"<>*RECEIVED*",DEALS!$V:$V,"<>*EXECUTED*"))} -> 0 | F10: {=SUMIFS(BALANCES!$C:$C,BALANCES!$A:$A,$B$2,BALANCES!$B:$B,$B10,BALANCES!$D:$D,F$6)+SUMIFS(FLOWS!$C:$C,FLOWS!$A:$A,$B$2,FLOWS!$E:$E,$B10,FLOWS!$D:$D,F$6,FLOWS!$H:$H,"<"&$C$4)+SUM(SUMIFS(DEALS!$J:$J,DEALS!$A:$A,{"*REFUND*","*EXECUTED*"},DEALS!$G:$G,$B$2,DEALS!$E:$E,"<"&$C$4,DEALS!$K:$K,F$6,DEALS!$M:$M,$B10,DEALS!$N:$N,"<>*RECEIVED*",DEALS!$N:$N,"<>*EXECUTED*"))+SUM(SUMIFS(DEALS!$R:$R,DEALS!$A:$A,{"*REFUND*","*EXECUTED*"},DEALS!$O:$O,$B$2,DEALS!$E:$E,"<"&$C$4,DEALS!$S:$S,F$6,DEALS!$U:$U,$B10,DEALS!$V:$V,"<>*RECEIVED*",DEALS!$V:$V,"<>*EXECUTED*"))} -> 164092.25 | G10: {=SUMIFS(BALANCES!$C:$C,BALANCES!$A:$A,$B$2,BALANCES!$B:$B,$B10,BALANCES!$D:$D,G$6)+SUMIFS(FLOWS!$C:$C,FLOWS!$A:$A,$B$2,FLOWS!$E:$E,$B10,FLOWS!$D:$D,G$6,FLOWS!$H:$H,"<"&$C$4)+SUM(SUMIFS(DEALS!$J:$J,DEALS!$A:$A,{"*REFUND*","*EXECUTED*"},DEALS!$G:$G,$B$2,DEALS!$E:$E,"<"&$C$4,DEALS!$K:$K,G$6,DEALS!$M:$M,$B10,DEALS!$N:$N,"<>*RECEIVED*",DEALS!$N:$N,"<>*EXECUTED*"))+SUM(SUMIFS(DEALS!$R:$R,DEALS!$A:$A,{"*REFUND*","*EXECUTED*"},DEALS!$O:$O,$B$2,DEALS!$E:$E,"<"&$C$4,DEALS!$S:$S,G$6,DEALS!$U:$U,$B10,DEALS!$V:$V,"<>*RECEIVED*",DEALS!$V:$V,"<>*EXECUTED*"))} -> 0 | H10: {=SUMIFS(BALANCES!$C:$C,BALANCES!$A:$A,$B$2,BALANCES!$B:$B,$B10,BALANCES!$D:$D,H$6)+SUMIFS(FLOWS!$C:$C,FLOWS!$A:$A,$B$2,FLOWS!$E:$E,$B10,FLOWS!$D:$D,H$6,FLOWS!$H:$H,"<"&$C$4)+SUM(SUMIFS(DEALS!$J:$J,DEALS!$A:$A,{"*REFUND*","*EXECUTED*"},DEALS!$G:$G,$B$2,DEALS!$E:$E,"<"&$C$4,DEALS!$K:$K,H$6,DEALS!$M:$M,$B10,DEALS!$N:$N,"<>*RECEIVED*",DEALS!$N:$N,"<>*EXECUTED*"))+SUM(SUMIFS(DEALS!$R:$R,DEALS!$A:$A,{"*REFUND*","*EXECUTED*"},DEALS!$O:$O,$B$2,DEALS!$E:$E,"<"&$C$4,DEALS!$S:$S,H$6,DEALS!$U:$U,$B10,DEALS!$V:$V,"<>*RECEIVED*",DEALS!$V:$V,"<>*EXECUTED*"))} -> 0 | I10: =C10*VLOOKUP(C$6,'FX RATES'!$E$1:$F$50,2,FALSE)+D10*VLOOKUP(D$6,'FX RATES'!$E$1:$F$50,2,FALSE)+E10*VLOOKUP(E$6,'FX RATES'!$E$1:$F$50,2,FALSE)+F10*VLOOKUP(F$6,'FX RATES'!$E$1:$F$50,2,FALSE)+G10*VLOOKUP(G$6,'FX RATES'!$E$1:$F$50,2,FALSE)+H10*VLOOKUP(H$6,'FX RATES'!$E$1:$F$50,2,FALSE) -> 45761.111 | K10: =B10 -> ADIB | L10: {=SUMIFS(FLOWS!$C:$C,FLOWS!$A:$A,$B$2,FLOWS!$E:$E,$K10,FLOWS!$D:$D,L$6,FLOWS!$H:$H,">="&$C$4,FLOWS!$H:$H,"<="&$U$4)+SUM(SUMIFS(DEALS!$J:$J,DEALS!$A:$A,{"*REFUND*","*EXECUTED*"},DEALS!$G:$G,$B$2,DEALS!$E:$E,">="&$C$4,DEALS!$E:$E,"<="&$U$4,DEALS!$K:$K,L$6,DEALS!$M:$M,$K10,DEALS!$N:$N,"<>*RECEIVED*",DEALS!$N:$N,"<>*EXECUTED*"))+SUM(SUMIFS(DEALS!$R:$R,DEALS!$A:$A,{"*REFUND*","*EXECUTED*"},DEALS!$O:$O,$B$2,DEALS!$E:$E,">="&$C$4,DEALS!$E:$E,"<="&$U$4,DEALS!$S:$S,L$6,DEALS!$U:$U,$K10,DEALS!$V:$V,"<>*RECEIVED*",DEALS!$V:$V,"<>*EXECUTED*"))} -> 0 | M10: {=SUMIFS(FLOWS!$C:$C,FLOWS!$A:$A,$B$2,FLOWS!$E:$E,$K10,FLOWS!$D:$D,M$6,FLOWS!$H:$H,">="&$C$4,FLOWS!$H:$H,"<="&$U$4)+SUM(SUMIFS(DEALS!$J:$J,DEALS!$A:$A,{"*REFUND*","*EXECUTED*"},DEALS!$G:$G,$B$2,DEALS!$E:$E,">="&$C$4,DEALS!$E:$E,"<="&$U$4,DEALS!$K:$K,M$6,DEALS!$M:$M,$K10,DEALS!$N:$N,"<>*RECEIVED*",DEALS!$N:$N,"<>*EXECUTED*"))+SUM(SUMIFS(DEALS!$R:$R,DEALS!$A:$A,{"*REFUND*","*EXECUTED*"},DEALS!$O:$O,$B$2,DEALS!$E:$E,">="&$C$4,DEALS!$E:$E,"<="&$U$4,DEALS!$S:$S,M$6,DEALS!$U:$U,$K10,DEALS!$V:$V,"<>*RECEIVED*",DEALS!$V:$V,"<>*EXECUTED*"))} -> 0 | N10: {=SUMIFS(FLOWS!$C:$C,FLOWS!$A:$A,$B$2,FLOWS!$E:$E,$K10,FLOWS!$D:$D,N$6,FLOWS!$H:$H,">="&$C$4,FLOWS!$H:$H,"<="&$U$4)+SUM(SUMIFS(DEALS!$J:$J,DEALS!$A:$A,{"*REFUND*","*EXECUTED*"},DEALS!$G:$G,$B$2,DEALS!$E:$E,">="&$C$4,DEALS!$E:$E,"<="&$U$4,DEALS!$K:$K,N$6,DEALS!$M:$M,$K10,DEALS!$N:$N,"<>*RECEIVED*",DEALS!$N:$N,"<>*EXECUTED*"))+SUM(SUMIFS(DEALS!$R:$R,DEALS!$A:$A,{"*REFUND*","*EXECUTED*"},DEALS!$O:$O,$B$2,DEALS!$E:$E,">="&$C$4,DEALS!$E:$E,"<="&$U$4,DEALS!$S:$S,N$6,DEALS!$U:$U,$K10,DEALS!$V:$V,"<>*RECEIVED*",DEALS!$V:$V,"<>*EXECUTED*"))} -> 0 | O10: {=SUMIFS(FLOWS!$C:$C,FLOWS!$A:$A,$B$2,FLOWS!$E:$E,$K10,FLOWS!$D:$D,O$6,FLOWS!$H:$H,">="&$C$4,FLOWS!$H:$H,"<="&$U$4)+SUM(SUMIFS(DEALS!$J:$J,DEALS!$A:$A,{"*REFUND*","*EXECUTED*"},DEALS!$G:$G,$B$2,DEALS!$E:$E,">="&$C$4,DEALS!$E:$E,"<="&$U$4,DEALS!$K:$K,O$6,DEALS!$M:$M,$K10,DEALS!$N:$N,"<>*RECEIVED*",DEALS!$N:$N,"<>*EXECUTED*"))+SUM(SUMIFS(DEALS!$R:$R,DEALS!$A:$A,{"*REFUND*","*EXECUTED*"},DEALS!$O:$O,$B$2,DEALS!$E:$E,">="&$C$4,DEALS!$E:$E,"<="&$U$4,DEALS!$S:$S,O$6,DEALS!$U:$U,$K10,DEALS!$V:$V,"<>*RECEIVED*",DEALS!$V:$V,"<>*EXECUTED*"))} -> 0 | P10: {=SUMIFS(FLOWS!$C:$C,FLOWS!$A:$A,$B$2,FLOWS!$E:$E,$K10,FLOWS!$D:$D,P$6,FLOWS!$H:$H,">="&$C$4,FLOWS!$H:$H,"<="&$U$4)+SUM(SUMIFS(DEALS!$J:$J,DEALS!$A:$A,{"*REFUND*","*EXECUTED*"},DEALS!$G:$G,$B$2,DEALS!$E:$E,">="&$C$4,DEALS!$E:$E,"<="&$U$4,DEALS!$K:$K,P$6,DEALS!$M:$M,$K10,DEALS!$N:$N,"<>*RECEIVED*",DEALS!$N:$N,"<>*EXECUTED*"))+SUM(SUMIFS(DEALS!$R:$R,DEALS!$A:$A,{"*REFUND*","*EXECUTED*"},DEALS!$O:$O,$B$2,DEALS!$E:$E,">="&$C$4,DEALS!$E:$E,"<="&$U$4,DEALS!$S:$S,P$6,DEALS!$U:$U,$K10,DEALS!$V:$V,"<>*RECEIVED*",DEALS!$V:$V,"<>*EXECUTED*"))} -> 0 | Q10: {=SUMIFS(FLOWS!$C:$C,FLOWS!$A:$A,$B$2,FLOWS!$E:$E,$K10,FLOWS!$D:$D,Q$6,FLOWS!$H:$H,">="&$C$4,FLOWS!$H:$H,"<="&$U$4)+SUM(SUMIFS(DEALS!$J:$J,DEALS!$A:$A,{"*REFUND*","*EXECUTED*"},DEALS!$G:$G,$B$2,DEALS!$E:$E,">="&$C$4,DEALS!$E:$E,"<="&$U$4,DEALS!$K:$K,Q$6,DEALS!$M:$M,$K10,DEALS!$N:$N,"<>*RECEIVED*",DEALS!$N:$N,"<>*EXECUTED*"))+SUM(SUMIFS(DEALS!$R:$R,DEALS!$A:$A,{"*REFUND*","*EXECUTED*"},DEALS!$O:$O,$B$2,DEALS!$E:$E,">="&$C$4,DEALS!$E:$E,"<="&$U$4,DEALS!$S:$S,Q$6,DEALS!$U:$U,$K10,DEALS!$V:$V,"<>*RECEIVED*",DEALS!$V:$V,"<>*EXECUTED*"))} -> 0 | R10: =L10*VLOOKUP(L$6,'FX RATES'!$E$1:$F$50,2,FALSE)+M10*VLOOKUP(M$6,'FX RATES'!$E$1:$F$50,2,FALSE)+N10*VLOOKUP(N$6,'FX RATES'!$E$1:$F$50,2,FALSE)+O10*VLOOKUP(O$6,'FX RATES'!$E$1:$F$50,2,FALSE)+P10*VLOOKUP(P$6,'FX RATES'!$E$1:$F$50,2,FALSE)+Q10*VLOOKUP(Q$6,'FX RATES'!$E$1:$F$50,2,FALSE) -> 0 | T10: =B10 -> ADIB | U10: {=SUMIFS(BALANCES!$C:$C,BALANCES!$A:$A,$B$2,BALANCES!$B:$B,$T10,BALANCES!$D:$D,U$6)+SUMIFS(FLOWS!$C:$C,FLOWS!$A:$A,$B$2,FLOWS!$E:$E,$T10,FLOWS!$D:$D,U$6,FLOWS!$H:$H,"<="&$U$4)+SUM(SUMIFS(DEALS!$J:$J,DEALS!$A:$A,{"*REFUND*","*EXECUTED*"},DEALS!$G:$G,$B$2,DEALS!$E:$E,"<="&$U$4,DEALS!$K:$K,U$6,DEALS!$M:$M,$T10,DEALS!$N:$N,"<>*RECEIVED*",DEALS!$N:$N,"<>*EXECUTED*"))+SUM(SUMIFS(DEALS!$R:$R,DEALS!$A:$A,{"*REFUND*","*EXECUTED*"},DEALS!$O:$O,$B$2,DEALS!$E:$E,"<="&$U$4,DEALS!$S:$S,U$6,DEALS!$U:$U,$T10,DEALS!$V:$V,"<>*RECEIVED*",DEALS!$V:$V,"<>*EXECUTED*"))} -> 1080.98 | V10: {=SUMIFS(BALANCES!$C:$C,BALANCES!$A:$A,$B$2,BALANCES!$B:$B,$T10,BALANCES!$D:$D,V$6)+SUMIFS(FLOWS!$C:$C,FLOWS!$A:$A,$B$2,FLOWS!$E:$E,$T10,FLOWS!$D:$D,V$6,FLOWS!$H:$H,"<="&$U$4)+SUM(SUMIFS(DEALS!$J:$J,DEALS!$A:$A,{"*REFUND*","*EXECUTED*"},DEALS!$G:$G,$B$2,DEALS!$E:$E,"<="&$U$4,DEALS!$K:$K,V$6,DEALS!$M:$M,$T10,DEALS!$N:$N,"<>*RECEIVED*",DEALS!$N:$N,"<>*EXECUTED*"))+SUM(SUMIFS(DEALS!$R:$R,DEALS!$A:$A,{"*REFUND*","*EXECUTED*"},DEALS!$O:$O,$B$2,DEALS!$E:$E,"<="&$U$4,DEALS!$S:$S,V$6,DEALS!$U:$U,$T10,DEALS!$V:$V,"<>*RECEIVED*",DEALS!$V:$V,"<>*EXECUTED*"))} -> 0 | W10: {=SUMIFS(BALANCES!$C:$C,BALANCES!$A:$A,$B$2,BALANCES!$B:$B,$T10,BALANCES!$D:$D,W$6)+SUMIFS(FLOWS!$C:$C,FLOWS!$A:$A,$B$2,FLOWS!$E:$E,$T10,FLOWS!$D:$D,W$6,FLOWS!$H:$H,"<="&$U$4)+SUM(SUMIFS(DEALS!$J:$J,DEALS!$A:$A,{"*REFUND*","*EXECUTED*"},DEALS!$G:$G,$B$2,DEALS!$E:$E,"<="&$U$4,DEALS!$K:$K,W$6,DEALS!$M:$M,$T10,DEALS!$N:$N,"<>*RECEIVED*",DEALS!$N:$N,"<>*EXECUTED*"))+SUM(SUMIFS(DEALS!$R:$R,DEALS!$A:$A,{"*REFUND*","*EXECUTED*"},DEALS!$O:$O,$B$2,DEALS!$E:$E,"<="&$U$4,DEALS!$S:$S,W$6,DEALS!$U:$U,$T10,DEALS!$V:$V,"<>*RECEIVED*",DEALS!$V:$V,"<>*EXECUTED*"))} -> 0 | X10: {=SUMIFS(BALANCES!$C:$C,BALANCES!$A:$A,$B$2,BALANCES!$B:$B,$T10,BALANCES!$D:$D,X$6)+SUMIFS(FLOWS!$C:$C,FLOWS!$A:$A,$B$2,FLOWS!$E:$E,$T10,FLOWS!$D:$D,X$6,FLOWS!$H:$H,"<="&$U$4)+SUM(SUMIFS(DEALS!$J:$J,DEALS!$A:$A,{"*REFUND*","*EXECUTED*"},DEALS!$G:$G,$B$2,DEALS!$E:$E,"<="&$U$4,DEALS!$K:$K,X$6,DEALS!$M:$M,$T10,DEALS!$N:$N,"<>*RECEIVED*",DEALS!$N:$N,"<>*EXECUTED*"))+SUM(SUMIFS(DEALS!$R:$R,DEALS!$A:$A,{"*REFUND*","*EXECUTED*"},DEALS!$O:$O,$B$2,DEALS!$E:$E,"<="&$U$4,DEALS!$S:$S,X$6,DEALS!$U:$U,$T10,DEALS!$V:$V,"<>*RECEIVED*",DEALS!$V:$V,"<>*EXECUTED*"))} -> 164092.25 | Y10: {=SUMIFS(BALANCES!$C:$C,BALANCES!$A:$A,$B$2,BALANCES!$B:$B,$T10,BALANCES!$D:$D,Y$6)+SUMIFS(FLOWS!$C:$C,FLOWS!$A:$A,$B$2,FLOWS!$E:$E,$T10,FLOWS!$D:$D,Y$6,FLOWS!$H:$H,"<="&$U$4)+SUM(SUMIFS(DEALS!$J:$J,DEALS!$A:$A,{"*REFUND*","*EXECUTED*"},DEALS!$G:$G,$B$2,DEALS!$E:$E,"<="&$U$4,DEALS!$K:$K,Y$6,DEALS!$M:$M,$T10,DEALS!$N:$N,"<>*RECEIVED*",DEALS!$N:$N,"<>*EXECUTED*"))+SUM(SUMIFS(DEALS!$R:$R,DEALS!$A:$A,{"*REFUND*","*EXECUTED*"},DEALS!$O:$O,$B$2,DEALS!$E:$E,"<="&$U$4,DEALS!$S:$S,Y$6,DEALS!$U:$U,$T10,DEALS!$V:$V,"<>*RECEIVED*",DEALS!$V:$V,"<>*EXECUTED*"))} -> 0 | Z10: {=SUMIFS(BALANCES!$C:$C,BALANCES!$A:$A,$B$2,BALANCES!$B:$B,$T10,BALANCES!$D:$D,Z$6)+SUMIFS(FLOWS!$C:$C,FLOWS!$A:$A,$B$2,FLOWS!$E:$E,$T10,FLOWS!$D:$D,Z$6,FLOWS!$H:$H,"<="&$U$4)+SUM(SUMIFS(DEALS!$J:$J,DEALS!$A:$A,{"*REFUND*","*EXECUTED*"},DEALS!$G:$G,$B$2,DEALS!$E:$E,"<="&$U$4,DEALS!$K:$K,Z$6,DEALS!$M:$M,$T10,DEALS!$N:$N,"<>*RECEIVED*",DEALS!$N:$N,"<>*EXECUTED*"))+SUM(SUMIFS(DEALS!$R:$R,DEALS!$A:$A,{"*REFUND*","*EXECUTED*"},DEALS!$O:$O,$B$2,DEALS!$E:$E,"<="&$U$4,DEALS!$S:$S,Z$6,DEALS!$U:$U,$T10,DEALS!$V:$V,"<>*RECEIVED*",DEALS!$V:$V,"<>*EXECUTED*"))} -> 0 | AA10: =U10*VLOOKUP(U$6,'FX RATES'!$E$1:$F$50,2,FALSE)+V10*VLOOKUP(V$6,'FX RATES'!$E$1:$F$50,2,FALSE)+W10*VLOOKUP(W$6,'FX RATES'!$E$1:$F$50,2,FALSE)+X10*VLOOKUP(X$6,'FX RATES'!$E$1:$F$50,2,FALSE)+Y10*VLOOKUP(Y$6,'FX RATES'!$E$1:$F$50,2,FALSE)+Z10*VLOOKUP(Z$6,'FX RATES'!$E$1:$F$50,2,FALSE) -> 45761.111 | AC10: =I10+R10-AA10 -> 0
B11: UBL | C11: {=SUMIFS(BALANCES!$C:$C,BALANCES!$A:$A,$B$2,BALANCES!$B:$B,$B11,BALANCES!$D:$D,C$6)+SUMIFS(FLOWS!$C:$C,FLOWS!$A:$A,$B$2,FLOWS!$E:$E,$B11,FLOWS!$D:$D,C$6,FLOWS!$H:$H,"<"&$C$4)+SUM(SUMIFS(DEALS!$J:$J,DEALS!$A:$A,{"*REFUND*","*EXECUTED*"},DEALS!$G:$G,$B$2,DEALS!$E:$E,"<"&$C$4,DEALS!$K:$K,C$6,DEALS!$M:$M,$B11,DEALS!$N:$N,"<>*RECEIVED*",DEALS!$N:$N,"<>*EXECUTED*"))+SUM(SUMIFS(DEALS!$R:$R,DEALS!$A:$A,{"*REFUND*","*EXECUTED*"},DEALS!$O:$O,$B$2,DEALS!$E:$E,"<"&$C$4,DEALS!$S:$S,C$6,DEALS!$U:$U,$B11,DEALS!$V:$V,"<>*RECEIVED*",DEALS!$V:$V,"<>*EXECUTED*"))} -> 12811.26 | D11: {=SUMIFS(BALANCES!$C:$C,BALANCES!$A:$A,$B$2,BALANCES!$B:$B,$B11,BALANCES!$D:$D,D$6)+SUMIFS(FLOWS!$C:$C,FLOWS!$A:$A,$B$2,FLOWS!$E:$E,$B11,FLOWS!$D:$D,D$6,FLOWS!$H:$H,"<"&$C$4)+SUM(SUMIFS(DEALS!$J:$J,DEALS!$A:$A,{"*REFUND*","*EXECUTED*"},DEALS!$G:$G,$B$2,DEALS!$E:$E,"<"&$C$4,DEALS!$K:$K,D$6,DEALS!$M:$M,$B11,DEALS!$N:$N,"<>*RECEIVED*",DEALS!$N:$N,"<>*EXECUTED*"))+SUM(SUMIFS(DEALS!$R:$R,DEALS!$A:$A,{"*REFUND*","*EXECUTED*"},DEALS!$O:$O,$B$2,DEALS!$E:$E,"<"&$C$4,DEALS!$S:$S,D$6,DEALS!$U:$U,$B11,DEALS!$V:$V,"<>*RECEIVED*",DEALS!$V:$V,"<>*EXECUTED*"))} -> 2901.34 | E11: {=SUMIFS(BALANCES!$C:$C,BALANCES!$A:$A,$B$2,BALANCES!$B:$B,$B11,BALANCES!$D:$D,E$6)+SUMIFS(FLOWS!$C:$C,FLOWS!$A:$A,$B$2,FLOWS!$E:$E,$B11,FLOWS!$D:$D,E$6,FLOWS!$H:$H,"<"&$C$4)+SUM(SUMIFS(DEALS!$J:$J,DEALS!$A:$A,{"*REFUND*","*EXECUTED*"},DEALS!$G:$G,$B$2,DEALS!$E:$E,"<"&$C$4,DEALS!$K:$K,E$6,DEALS!$M:$M,$B11,DEALS!$N:$N,"<>*RECEIVED*",DEALS!$N:$N,"<>*EXECUTED*"))+SUM(SUMIFS(DEALS!$R:$R,DEALS!$A:$A,{"*REFUND*","*EXECUTED*"},DEALS!$O:$O,$B$2,DEALS!$E:$E,"<"&$C$4,DEALS!$S:$S,E$6,DEALS!$U:$U,$B11,DEALS!$V:$V,"<>*RECEIVED*",DEALS!$V:$V,"<>*EXECUTED*"))} -> 0 | F11: {=SUMIFS(BALANCES!$C:$C,BALANCES!$A:$A,$B$2,BALANCES!$B:$B,$B11,BALANCES!$D:$D,F$6)+SUMIFS(FLOWS!$C:$C,FLOWS!$A:$A,$B$2,FLOWS!$E:$E,$B11,FLOWS!$D:$D,F$6,FLOWS!$H:$H,"<"&$C$4)+SUM(SUMIFS(DEALS!$J:$J,DEALS!$A:$A,{"*REFUND*","*EXECUTED*"},DEALS!$G:$G,$B$2,DEALS!$E:$E,"<"&$C$4,DEALS!$K:$K,F$6,DEALS!$M:$M,$B11,DEALS!$N:$N,"<>*RECEIVED*",DEALS!$N:$N,"<>*EXECUTED*"))+SUM(SUMIFS(DEALS!$R:$R,DEALS!$A:$A,{"*REFUND*","*EXECUTED*"},DEALS!$O:$O,$B$2,DEALS!$E:$E,"<"&$C$4,DEALS!$S:$S,F$6,DEALS!$U:$U,$B11,DEALS!$V:$V,"<>*RECEIVED*",DEALS!$V:$V,"<>*EXECUTED*"))} -> -2827656.5 | G11: {=SUMIFS(BALANCES!$C:$C,BALANCES!$A:$A,$B$2,BALANCES!$B:$B,$B11,BALANCES!$D:$D,G$6)+SUMIFS(FLOWS!$C:$C,FLOWS!$A:$A,$B$2,FLOWS!$E:$E,$B11,FLOWS!$D:$D,G$6,FLOWS!$H:$H,"<"&$C$4)+SUM(SUMIFS(DEALS!$J:$J,DEALS!$A:$A,{"*REFUND*","*EXECUTED*"},DEALS!$G:$G,$B$2,DEALS!$E:$E,"<"&$C$4,DEALS!$K:$K,G$6,DEALS!$M:$M,$B11,DEALS!$N:$N,"<>*RECEIVED*",DEALS!$N:$N,"<>*EXECUTED*"))+SUM(SUMIFS(DEALS!$R:$R,DEALS!$A:$A,{"*REFUND*","*EXECUTED*"},DEALS!$O:$O,$B$2,DEALS!$E:$E,"<"&$C$4,DEALS!$S:$S,G$6,DEALS!$U:$U,$B11,DEALS!$V:$V,"<>*RECEIVED*",DEALS!$V:$V,"<>*EXECUTED*"))} -> 0 | H11: {=SUMIFS(BALANCES!$C:$C,BALANCES!$A:$A,$B$2,BALANCES!$B:$B,$B11,BALANCES!$D:$D,H$6)+SUMIFS(FLOWS!$C:$C,FLOWS!$A:$A,$B$2,FLOWS!$E:$E,$B11,FLOWS!$D:$D,H$6,FLOWS!$H:$H,"<"&$C$4)+SUM(SUMIFS(DEALS!$J:$J,DEALS!$A:$A,{"*REFUND*","*EXECUTED*"},DEALS!$G:$G,$B$2,DEALS!$E:$E,"<"&$C$4,DEALS!$K:$K,H$6,DEALS!$M:$M,$B11,DEALS!$N:$N,"<>*RECEIVED*",DEALS!$N:$N,"<>*EXECUTED*"))+SUM(SUMIFS(DEALS!$R:$R,DEALS!$A:$A,{"*REFUND*","*EXECUTED*"},DEALS!$O:$O,$B$2,DEALS!$E:$E,"<"&$C$4,DEALS!$S:$S,H$6,DEALS!$U:$U,$B11,DEALS!$V:$V,"<>*RECEIVED*",DEALS!$V:$V,"<>*EXECUTED*"))} -> 0 | I11: =C11*VLOOKUP(C$6,'FX RATES'!$E$1:$F$50,2,FALSE)+D11*VLOOKUP(D$6,'FX RATES'!$E$1:$F$50,2,FALSE)+E11*VLOOKUP(E$6,'FX RATES'!$E$1:$F$50,2,FALSE)+F11*VLOOKUP(F$6,'FX RATES'!$E$1:$F$50,2,FALSE)+G11*VLOOKUP(G$6,'FX RATES'!$E$1:$F$50,2,FALSE)+H11*VLOOKUP(H$6,'FX RATES'!$E$1:$F$50,2,FALSE) -> -753704.12 | K11: =B11 -> UBL | L11: {=SUMIFS(FLOWS!$C:$C,FLOWS!$A:$A,$B$2,FLOWS!$E:$E,$K11,FLOWS!$D:$D,L$6,FLOWS!$H:$H,">="&$C$4,FLOWS!$H:$H,"<="&$U$4)+SUM(SUMIFS(DEALS!$J:$J,DEALS!$A:$A,{"*REFUND*","*EXECUTED*"},DEALS!$G:$G,$B$2,DEALS!$E:$E,">="&$C$4,DEALS!$E:$E,"<="&$U$4,DEALS!$K:$K,L$6,DEALS!$M:$M,$K11,DEALS!$N:$N,"<>*RECEIVED*",DEALS!$N:$N,"<>*EXECUTED*"))+SUM(SUMIFS(DEALS!$R:$R,DEALS!$A:$A,{"*REFUND*","*EXECUTED*"},DEALS!$O:$O,$B$2,DEALS!$E:$E,">="&$C$4,DEALS!$E:$E,"<="&$U$4,DEALS!$S:$S,L$6,DEALS!$U:$U,$K11,DEALS!$V:$V,"<>*RECEIVED*",DEALS!$V:$V,"<>*EXECUTED*"))} -> 0 | M11: {=SUMIFS(FLOWS!$C:$C,FLOWS!$A:$A,$B$2,FLOWS!$E:$E,$K11,FLOWS!$D:$D,M$6,FLOWS!$H:$H,">="&$C$4,FLOWS!$H:$H,"<="&$U$4)+SUM(SUMIFS(DEALS!$J:$J,DEALS!$A:$A,{"*REFUND*","*EXECUTED*"},DEALS!$G:$G,$B$2,DEALS!$E:$E,">="&$C$4,DEALS!$E:$E,"<="&$U$4,DEALS!$K:$K,M$6,DEALS!$M:$M,$K11,DEALS!$N:$N,"<>*RECEIVED*",DEALS!$N:$N,"<>*EXECUTED*"))+SUM(SUMIFS(DEALS!$R:$R,DEALS!$A:$A,{"*REFUND*","*EXECUTED*"},DEALS!$O:$O,$B$2,DEALS!$E:$E,">="&$C$4,DEALS!$E:$E,"<="&$U$4,DEALS!$S:$S,M$6,DEALS!$U:$U,$K11,DEALS!$V:$V,"<>*RECEIVED*",DEALS!$V:$V,"<>*EXECUTED*"))} -> 0 | N11: {=SUMIFS(FLOWS!$C:$C,FLOWS!$A:$A,$B$2,FLOWS!$E:$E,$K11,FLOWS!$D:$D,N$6,FLOWS!$H:$H,">="&$C$4,FLOWS!$H:$H,"<="&$U$4)+SUM(SUMIFS(DEALS!$J:$J,DEALS!$A:$A,{"*REFUND*","*EXECUTED*"},DEALS!$G:$G,$B$2,DEALS!$E:$E,">="&$C$4,DEALS!$E:$E,"<="&$U$4,DEALS!$K:$K,N$6,DEALS!$M:$M,$K11,DEALS!$N:$N,"<>*RECEIVED*",DEALS!$N:$N,"<>*EXECUTED*"))+SUM(SUMIFS(DEALS!$R:$R,DEALS!$A:$A,{"*REFUND*","*EXECUTED*"},DEALS!$O:$O,$B$2,DEALS!$E:$E,">="&$C$4,DEALS!$E:$E,"<="&$U$4,DEALS!$S:$S,N$6,DEALS!$U:$U,$K11,DEALS!$V:$V,"<>*RECEIVED*",DEALS!$V:$V,"<>*EXECUTED*"))} -> 0 | O11: {=SUMIFS(FLOWS!$C:$C,FLOWS!$A:$A,$B$2,FLOWS!$E:$E,$K11,FLOWS!$D:$D,O$6,FLOWS!$H:$H,">="&$C$4,FLOWS!$H:$H,"<="&$U$4)+SUM(SUMIFS(DEALS!$J:$J,DEALS!$A:$A,{"*REFUND*","*EXECUTED*"},DEALS!$G:$G,$B$2,DEALS!$E:$E,">="&$C$4,DEALS!$E:$E,"<="&$U$4,DEALS!$K:$K,O$6,DEALS!$M:$M,$K11,DEALS!$N:$N,"<>*RECEIVED*",DEALS!$N:$N,"<>*EXECUTED*"))+SUM(SUMIFS(DEALS!$R:$R,DEALS!$A:$A,{"*REFUND*","*EXECUTED*"},DEALS!$O:$O,$B$2,DEALS!$E:$E,">="&$C$4,DEALS!$E:$E,"<="&$U$4,DEALS!$S:$S,O$6,DEALS!$U:$U,$K11,DEALS!$V:$V,"<>*RECEIVED*",DEALS!$V:$V,"<>*EXECUTED*"))} -> 0 | P11: {=SUMIFS(FLOWS!$C:$C,FLOWS!$A:$A,$B$2,FLOWS!$E:$E,$K11,FLOWS!$D:$D,P$6,FLOWS!$H:$H,">="&$C$4,FLOWS!$H:$H,"<="&$U$4)+SUM(SUMIFS(DEALS!$J:$J,DEALS!$A:$A,{"*REFUND*","*EXECUTED*"},DEALS!$G:$G,$B$2,DEALS!$E:$E,">="&$C$4,DEALS!$E:$E,"<="&$U$4,DEALS!$K:$K,P$6,DEALS!$M:$M,$K11,DEALS!$N:$N,"<>*RECEIVED*",DEALS!$N:$N,"<>*EXECUTED*"))+SUM(SUMIFS(DEALS!$R:$R,DEALS!$A:$A,{"*REFUND*","*EXECUTED*"},DEALS!$O:$O,$B$2,DEALS!$E:$E,">="&$C$4,DEALS!$E:$E,"<="&$U$4,DEALS!$S:$S,P$6,DEALS!$U:$U,$K11,DEALS!$V:$V,"<>*RECEIVED*",DEALS!$V:$V,"<>*EXECUTED*"))} -> 0 | Q11: {=SUMIFS(FLOWS!$C:$C,FLOWS!$A:$A,$B$2,FLOWS!$E:$E,$K11,FLOWS!$D:$D,Q$6,FLOWS!$H:$H,">="&$C$4,FLOWS!$H:$H,"<="&$U$4)+SUM(SUMIFS(DEALS!$J:$J,DEALS!$A:$A,{"*REFUND*","*EXECUTED*"},DEALS!$G:$G,$B$2,DEALS!$E:$E,">="&$C$4,DEALS!$E:$E,"<="&$U$4,DEALS!$K:$K,Q$6,DEALS!$M:$M,$K11,DEALS!$N:$N,"<>*RECEIVED*",DEALS!$N:$N,"<>*EXECUTED*"))+SUM(SUMIFS(DEALS!$R:$R,DEALS!$A:$A,{"*REFUND*","*EXECUTED*"},DEALS!$O:$O,$B$2,DEALS!$E:$E,">="&$C$4,DEALS!$E:$E,"<="&$U$4,DEALS!$S:$S,Q$6,DEALS!$U:$U,$K11,DEALS!$V:$V,"<>*RECEIVED*",DEALS!$V:$V,"<>*EXECUTED*"))} -> 0 | R11: =L11*VLOOKUP(L$6,'FX RATES'!$E$1:$F$50,2,FALSE)+M11*VLOOKUP(M$6,'FX RATES'!$E$1:$F$50,2,FALSE)+N11*VLOOKUP(N$6,'FX RATES'!$E$1:$F$50,2,FALSE)+O11*VLOOKUP(O$6,'FX RATES'!$E$1:$F$50,2,FALSE)+P11*VLOOKUP(P$6,'FX RATES'!$E$1:$F$50,2,FALSE)+Q11*VLOOKUP(Q$6,'FX RATES'!$E$1:$F$50,2,FALSE) -> 0 | T11: =B11 -> UBL | U11: {=SUMIFS(BALANCES!$C:$C,BALANCES!$A:$A,$B$2,BALANCES!$B:$B,$T11,BALANCES!$D:$D,U$6)+SUMIFS(FLOWS!$C:$C,FLOWS!$A:$A,$B$2,FLOWS!$E:$E,$T11,FLOWS!$D:$D,U$6,FLOWS!$H:$H,"<="&$U$4)+SUM(SUMIFS(DEALS!$J:$J,DEALS!$A:$A,{"*REFUND*","*EXECUTED*"},DEALS!$G:$G,$B$2,DEALS!$E:$E,"<="&$U$4,DEALS!$K:$K,U$6,DEALS!$M:$M,$T11,DEALS!$N:$N,"<>*RECEIVED*",DEALS!$N:$N,"<>*EXECUTED*"))+SUM(SUMIFS(DEALS!$R:$R,DEALS!$A:$A,{"*REFUND*","*EXECUTED*"},DEALS!$O:$O,$B$2,DEALS!$E:$E,"<="&$U$4,DEALS!$S:$S,U$6,DEALS!$U:$U,$T11,DEALS!$V:$V,"<>*RECEIVED*",DEALS!$V:$V,"<>*EXECUTED*"))} -> 12811.26 | V11: {=SUMIFS(BALANCES!$C:$C,BALANCES!$A:$A,$B$2,BALANCES!$B:$B,$T11,BALANCES!$D:$D,V$6)+SUMIFS(FLOWS!$C:$C,FLOWS!$A:$A,$B$2,FLOWS!$E:$E,$T11,FLOWS!$D:$D,V$6,FLOWS!$H:$H,"<="&$U$4)+SUM(SUMIFS(DEALS!$J:$J,DEALS!$A:$A,{"*REFUND*","*EXECUTED*"},DEALS!$G:$G,$B$2,DEALS!$E:$E,"<="&$U$4,DEALS!$K:$K,V$6,DEALS!$M:$M,$T11,DEALS!$N:$N,"<>*RECEIVED*",DEALS!$N:$N,"<>*EXECUTED*"))+SUM(SUMIFS(DEALS!$R:$R,DEALS!$A:$A,{"*REFUND*","*EXECUTED*"},DEALS!$O:$O,$B$2,DEALS!$E:$E,"<="&$U$4,DEALS!$S:$S,V$6,DEALS!$U:$U,$T11,DEALS!$V:$V,"<>*RECEIVED*",DEALS!$V:$V,"<>*EXECUTED*"))} -> 2901.34 | W11: {=SUMIFS(BALANCES!$C:$C,BALANCES!$A:$A,$B$2,BALANCES!$B:$B,$T11,BALANCES!$D:$D,W$6)+SUMIFS(FLOWS!$C:$C,FLOWS!$A:$A,$B$2,FLOWS!$E:$E,$T11,FLOWS!$D:$D,W$6,FLOWS!$H:$H,"<="&$U$4)+SUM(SUMIFS(DEALS!$J:$J,DEALS!$A:$A,{"*REFUND*","*EXECUTED*"},DEALS!$G:$G,$B$2,DEALS!$E:$E,"<="&$U$4,DEALS!$K:$K,W$6,DEALS!$M:$M,$T11,DEALS!$N:$N,"<>*RECEIVED*",DEALS!$N:$N,"<>*EXECUTED*"))+SUM(SUMIFS(DEALS!$R:$R,DEALS!$A:$A,{"*REFUND*","*EXECUTED*"},DEALS!$O:$O,$B$2,DEALS!$E:$E,"<="&$U$4,DEALS!$S:$S,W$6,DEALS!$U:$U,$T11,DEALS!$V:$V,"<>*RECEIVED*",DEALS!$V:$V,"<>*EXECUTED*"))} -> 0 | X11: {=SUMIFS(BALANCES!$C:$C,BALANCES!$A:$A,$B$2,BALANCES!$B:$B,$T11,BALANCES!$D:$D,X$6)+SUMIFS(FLOWS!$C:$C,FLOWS!$A:$A,$B$2,FLOWS!$E:$E,$T11,FLOWS!$D:$D,X$6,FLOWS!$H:$H,"<="&$U$4)+SUM(SUMIFS(DEALS!$J:$J,DEALS!$A:$A,{"*REFUND*","*EXECUTED*"},DEALS!$G:$G,$B$2,DEALS!$E:$E,"<="&$U$4,DEALS!$K:$K,X$6,DEALS!$M:$M,$T11,DEALS!$N:$N,"<>*RECEIVED*",DEALS!$N:$N,"<>*EXECUTED*"))+SUM(SUMIFS(DEALS!$R:$R,DEALS!$A:$A,{"*REFUND*","*EXECUTED*"},DEALS!$O:$O,$B$2,DEALS!$E:$E,"<="&$U$4,DEALS!$S:$S,X$6,DEALS!$U:$U,$T11,DEALS!$V:$V,"<>*RECEIVED*",DEALS!$V:$V,"<>*EXECUTED*"))} -> -2827656.5 | Y11: {=SUMIFS(BALANCES!$C:$C,BALANCES!$A:$A,$B$2,BALANCES!$B:$B,$T11,BALANCES!$D:$D,Y$6)+SUMIFS(FLOWS!$C:$C,FLOWS!$A:$A,$B$2,FLOWS!$E:$E,$T11,FLOWS!$D:$D,Y$6,FLOWS!$H:$H,"<="&$U$4)+SUM(SUMIFS(DEALS!$J:$J,DEALS!$A:$A,{"*REFUND*","*EXECUTED*"},DEALS!$G:$G,$B$2,DEALS!$E:$E,"<="&$U$4,DEALS!$K:$K,Y$6,DEALS!$M:$M,$T11,DEALS!$N:$N,"<>*RECEIVED*",DEALS!$N:$N,"<>*EXECUTED*"))+SUM(SUMIFS(DEALS!$R:$R,DEALS!$A:$A,{"*REFUND*","*EXECUTED*"},DEALS!$O:$O,$B$2,DEALS!$E:$E,"<="&$U$4,DEALS!$S:$S,Y$6,DEALS!$U:$U,$T11,DEALS!$V:$V,"<>*RECEIVED*",DEALS!$V:$V,"<>*EXECUTED*"))} -> 0 | Z11: {=SUMIFS(BALANCES!$C:$C,BALANCES!$A:$A,$B$2,BALANCES!$B:$B,$T11,BALANCES!$D:$D,Z$6)+SUMIFS(FLOWS!$C:$C,FLOWS!$A:$A,$B$2,FLOWS!$E:$E,$T11,FLOWS!$D:$D,Z$6,FLOWS!$H:$H,"<="&$U$4)+SUM(SUMIFS(DEALS!$J:$J,DEALS!$A:$A,{"*REFUND*","*EXECUTED*"},DEALS!$G:$G,$B$2,DEALS!$E:$E,"<="&$U$4,DEALS!$K:$K,Z$6,DEALS!$M:$M,$T11,DEALS!$N:$N,"<>*RECEIVED*",DEALS!$N:$N,"<>*EXECUTED*"))+SUM(SUMIFS(DEALS!$R:$R,DEALS!$A:$A,{"*REFUND*","*EXECUTED*"},DEALS!$O:$O,$B$2,DEALS!$E:$E,"<="&$U$4,DEALS!$S:$S,Z$6,DEALS!$U:$U,$T11,DEALS!$V:$V,"<>*RECEIVED*",DEALS!$V:$V,"<>*EXECUTED*"))} -> 0 | AA11: =U11*VLOOKUP(U$6,'FX RATES'!$E$1:$F$50,2,FALSE)+V11*VLOOKUP(V$6,'FX RATES'!$E$1:$F$50,2,FALSE)+W11*VLOOKUP(W$6,'FX RATES'!$E$1:$F$50,2,FALSE)+X11*VLOOKUP(X$6,'FX RATES'!$E$1:$F$50,2,FALSE)+Y11*VLOOKUP(Y$6,'FX RATES'!$E$1:$F$50,2,FALSE)+Z11*VLOOKUP(Z$6,'FX RATES'!$E$1:$F$50,2,FALSE) -> -753704.12 | AC11: =I11+R11-AA11 -> 0
B12: HDFC | C12: {=SUMIFS(BALANCES!$C:$C,BALANCES!$A:$A,$B$2,BALANCES!$B:$B,$B12,BALANCES!$D:$D,C$6)+SUMIFS(FLOWS!$C:$C,FLOWS!$A:$A,$B$2,FLOWS!$E:$E,$B12,FLOWS!$D:$D,C$6,FLOWS!$H:$H,"<"&$C$4)+SUM(SUMIFS(DEALS!$J:$J,DEALS!$A:$A,{"*REFUND*","*EXECUTED*"},DEALS!$G:$G,$B$2,DEALS!$E:$E,"<"&$C$4,DEALS!$K:$K,C$6,DEALS!$M:$M,$B12,DEALS!$N:$N,"<>*RECEIVED*",DEALS!$N:$N,"<>*EXECUTED*"))+SUM(SUMIFS(DEALS!$R:$R,DEALS!$A:$A,{"*REFUND*","*EXECUTED*"},DEALS!$O:$O,$B$2,DEALS!$E:$E,"<"&$C$4,DEALS!$S:$S,C$6,DEALS!$U:$U,$B12,DEALS!$V:$V,"<>*RECEIVED*",DEALS!$V:$V,"<>*EXECUTED*"))} -> 6486.39 | D12: {=SUMIFS(BALANCES!$C:$C,BALANCES!$A:$A,$B$2,BALANCES!$B:$B,$B12,BALANCES!$D:$D,D$6)+SUMIFS(FLOWS!$C:$C,FLOWS!$A:$A,$B$2,FLOWS!$E:$E,$B12,FLOWS!$D:$D,D$6,FLOWS!$H:$H,"<"&$C$4)+SUM(SUMIFS(DEALS!$J:$J,DEALS!$A:$A,{"*REFUND*","*EXECUTED*"},DEALS!$G:$G,$B$2,DEALS!$E:$E,"<"&$C$4,DEALS!$K:$K,D$6,DEALS!$M:$M,$B12,DEALS!$N:$N,"<>*RECEIVED*",DEALS!$N:$N,"<>*EXECUTED*"))+SUM(SUMIFS(DEALS!$R:$R,DEALS!$A:$A,{"*REFUND*","*EXECUTED*"},DEALS!$O:$O,$B$2,DEALS!$E:$E,"<"&$C$4,DEALS!$S:$S,D$6,DEALS!$U:$U,$B12,DEALS!$V:$V,"<>*RECEIVED*",DEALS!$V:$V,"<>*EXECUTED*"))} -> 0 | E12: {=SUMIFS(BALANCES!$C:$C,BALANCES!$A:$A,$B$2,BALANCES!$B:$B,$B12,BALANCES!$D:$D,E$6)+SUMIFS(FLOWS!$C:$C,FLOWS!$A:$A,$B$2,FLOWS!$E:$E,$B12,FLOWS!$D:$D,E$6,FLOWS!$H:$H,"<"&$C$4)+SUM(SUMIFS(DEALS!$J:$J,DEALS!$A:$A,{"*REFUND*","*EXECUTED*"},DEALS!$G:$G,$B$2,DEALS!$E:$E,"<"&$C$4,DEALS!$K:$K,E$6,DEALS!$M:$M,$B12,DEALS!$N:$N,"<>*RECEIVED*",DEALS!$N:$N,"<>*EXECUTED*"))+SUM(SUMIFS(DEALS!$R:$R,DEALS!$A:$A,{"*REFUND*","*EXECUTED*"},DEALS!$O:$O,$B$2,DEALS!$E:$E,"<"&$C$4,DEALS!$S:$S,E$6,DEALS!$U:$U,$B12,DEALS!$V:$V,"<>*RECEIVED*",DEALS!$V:$V,"<>*EXECUTED*"))} -> 0 | F12: {=SUMIFS(BALANCES!$C:$C,BALANCES!$A:$A,$B$2,BALANCES!$B:$B,$B12,BALANCES!$D:$D,F$6)+SUMIFS(FLOWS!$C:$C,FLOWS!$A:$A,$B$2,FLOWS!$E:$E,$B12,FLOWS!$D:$D,F$6,FLOWS!$H:$H,"<"&$C$4)+SUM(SUMIFS(DEALS!$J:$J,DEALS!$A:$A,{"*REFUND*","*EXECUTED*"},DEALS!$G:$G,$B$2,DEALS!$E:$E,"<"&$C$4,DEALS!$K:$K,F$6,DEALS!$M:$M,$B12,DEALS!$N:$N,"<>*RECEIVED*",DEALS!$N:$N,"<>*EXECUTED*"))+SUM(SUMIFS(DEALS!$R:$R,DEALS!$A:$A,{"*REFUND*","*EXECUTED*"},DEALS!$O:$O,$B$2,DEALS!$E:$E,"<"&$C$4,DEALS!$S:$S,F$6,DEALS!$U:$U,$B12,DEALS!$V:$V,"<>*RECEIVED*",DEALS!$V:$V,"<>*EXECUTED*"))} -> 2284.19 | G12: {=SUMIFS(BALANCES!$C:$C,BALANCES!$A:$A,$B$2,BALANCES!$B:$B,$B12,BALANCES!$D:$D,G$6)+SUMIFS(FLOWS!$C:$C,FLOWS!$A:$A,$B$2,FLOWS!$E:$E,$B12,FLOWS!$D:$D,G$6,FLOWS!$H:$H,"<"&$C$4)+SUM(SUMIFS(DEALS!$J:$J,DEALS!$A:$A,{"*REFUND*","*EXECUTED*"},DEALS!$G:$G,$B$2,DEALS!$E:$E,"<"&$C$4,DEALS!$K:$K,G$6,DEALS!$M:$M,$B12,DEALS!$N:$N,"<>*RECEIVED*",DEALS!$N:$N,"<>*EXECUTED*"))+SUM(SUMIFS(DEALS!$R:$R,DEALS!$A:$A,{"*REFUND*","*EXECUTED*"},DEALS!$O:$O,$B$2,DEALS!$E:$E,"<"&$C$4,DEALS!$S:$S,G$6,DEALS!$U:$U,$B12,DEALS!$V:$V,"<>*RECEIVED*",DEALS!$V:$V,"<>*EXECUTED*"))} -> 0 | H12: {=SUMIFS(BALANCES!$C:$C,BALANCES!$A:$A,$B$2,BALANCES!$B:$B,$B12,BALANCES!$D:$D,H$6)+SUMIFS(FLOWS!$C:$C,FLOWS!$A:$A,$B$2,FLOWS!$E:$E,$B12,FLOWS!$D:$D,H$6,FLOWS!$H:$H,"<"&$C$4)+SUM(SUMIFS(DEALS!$J:$J,DEALS!$A:$A,{"*REFUND*","*EXECUTED*"},DEALS!$G:$G,$B$2,DEALS!$E:$E,"<"&$C$4,DEALS!$K:$K,H$6,DEALS!$M:$M,$B12,DEALS!$N:$N,"<>*RECEIVED*",DEALS!$N:$N,"<>*EXECUTED*"))+SUM(SUMIFS(DEALS!$R:$R,DEALS!$A:$A,{"*REFUND*","*EXECUTED*"},DEALS!$O:$O,$B$2,DEALS!$E:$E,"<"&$C$4,DEALS!$S:$S,H$6,DEALS!$U:$U,$B12,DEALS!$V:$V,"<>*RECEIVED*",DEALS!$V:$V,"<>*EXECUTED*"))} -> 0 | I12: =C12*VLOOKUP(C$6,'FX RATES'!$E$1:$F$50,2,FALSE)+D12*VLOOKUP(D$6,'FX RATES'!$E$1:$F$50,2,FALSE)+E12*VLOOKUP(E$6,'FX RATES'!$E$1:$F$50,2,FALSE)+F12*VLOOKUP(F$6,'FX RATES'!$E$1:$F$50,2,FALSE)+G12*VLOOKUP(G$6,'FX RATES'!$E$1:$F$50,2,FALSE)+H12*VLOOKUP(H$6,'FX RATES'!$E$1:$F$50,2,FALSE) -> 7108.3445 | K12: =B12 -> HDFC | L12: {=SUMIFS(FLOWS!$C:$C,FLOWS!$A:$A,$B$2,FLOWS!$E:$E,$K12,FLOWS!$D:$D,L$6,FLOWS!$H:$H,">="&$C$4,FLOWS!$H:$H,"<="&$U$4)+SUM(SUMIFS(DEALS!$J:$J,DEALS!$A:$A,{"*REFUND*","*EXECUTED*"},DEALS!$G:$G,$B$2,DEALS!$E:$E,">="&$C$4,DEALS!$E:$E,"<="&$U$4,DEALS!$K:$K,L$6,DEALS!$M:$M,$K12,DEALS!$N:$N,"<>*RECEIVED*",DEALS!$N:$N,"<>*EXECUTED*"))+SUM(SUMIFS(DEALS!$R:$R,DEALS!$A:$A,{"*REFUND*","*EXECUTED*"},DEALS!$O:$O,$B$2,DEALS!$E:$E,">="&$C$4,DEALS!$E:$E,"<="&$U$4,DEALS!$S:$S,L$6,DEALS!$U:$U,$K12,DEALS!$V:$V,"<>*RECEIVED*",DEALS!$V:$V,"<>*EXECUTED*"))} -> 0 | M12: {=SUMIFS(FLOWS!$C:$C,FLOWS!$A:$A,$B$2,FLOWS!$E:$E,$K12,FLOWS!$D:$D,M$6,FLOWS!$H:$H,">="&$C$4,FLOWS!$H:$H,"<="&$U$4)+SUM(SUMIFS(DEALS!$J:$J,DEALS!$A:$A,{"*REFUND*","*EXECUTED*"},DEALS!$G:$G,$B$2,DEALS!$E:$E,">="&$C$4,DEALS!$E:$E,"<="&$U$4,DEALS!$K:$K,M$6,DEALS!$M:$M,$K12,DEALS!$N:$N,"<>*RECEIVED*",DEALS!$N:$N,"<>*EXECUTED*"))+SUM(SUMIFS(DEALS!$R:$R,DEALS!$A:$A,{"*REFUND*","*EXECUTED*"},DEALS!$O:$O,$B$2,DEALS!$E:$E,">="&$C$4,DEALS!$E:$E,"<="&$U$4,DEALS!$S:$S,M$6,DEALS!$U:$U,$K12,DEALS!$V:$V,"<>*RECEIVED*",DEALS!$V:$V,"<>*EXECUTED*"))} -> 0 | N12: {=SUMIFS(FLOWS!$C:$C,FLOWS!$A:$A,$B$2,FLOWS!$E:$E,$K12,FLOWS!$D:$D,N$6,FLOWS!$H:$H,">="&$C$4,FLOWS!$H:$H,"<="&$U$4)+SUM(SUMIFS(DEALS!$J:$J,DEALS!$A:$A,{"*REFUND*","*EXECUTED*"},DEALS!$G:$G,$B$2,DEALS!$E:$E,">="&$C$4,DEALS!$E:$E,"<="&$U$4,DEALS!$K:$K,N$6,DEALS!$M:$M,$K12,DEALS!$N:$N,"<>*RECEIVED*",DEALS!$N:$N,"<>*EXECUTED*"))+SUM(SUMIFS(DEALS!$R:$R,DEALS!$A:$A,{"*REFUND*","*EXECUTED*"},DEALS!$O:$O,$B$2,DEALS!$E:$E,">="&$C$4,DEALS!$E:$E,"<="&$U$4,DEALS!$S:$S,N$6,DEALS!$U:$U,$K12,DEALS!$V:$V,"<>*RECEIVED*",DEALS!$V:$V,"<>*EXECUTED*"))} -> 0 | O12: {=SUMIFS(FLOWS!$C:$C,FLOWS!$A:$A,$B$2,FLOWS!$E:$E,$K12,FLOWS!$D:$D,O$6,FLOWS!$H:$H,">="&$C$4,FLOWS!$H:$H,"<="&$U$4)+SUM(SUMIFS(DEALS!$J:$J,DEALS!$A:$A,{"*REFUND*","*EXECUTED*"},DEALS!$G:$G,$B$2,DEALS!$E:$E,">="&$C$4,DEALS!$E:$E,"<="&$U$4,DEALS!$K:$K,O$6,DEALS!$M:$M,$K12,DEALS!$N:$N,"<>*RECEIVED*",DEALS!$N:$N,"<>*EXECUTED*"))+SUM(SUMIFS(DEALS!$R:$R,DEALS!$A:$A,{"*REFUND*","*EXECUTED*"},DEALS!$O:$O,$B$2,DEALS!$E:$E,">="&$C$4,DEALS!$E:$E,"<="&$U$4,DEALS!$S:$S,O$6,DEALS!$U:$U,$K12,DEALS!$V:$V,"<>*RECEIVED*",DEALS!$V:$V,"<>*EXECUTED*"))} -> 0 | P12: {=SUMIFS(FLOWS!$C:$C,FLOWS!$A:$A,$B$2,FLOWS!$E:$E,$K12,FLOWS!$D:$D,P$6,FLOWS!$H:$H,">="&$C$4,FLOWS!$H:$H,"<="&$U$4)+SUM(SUMIFS(DEALS!$J:$J,DEALS!$A:$A,{"*REFUND*","*EXECUTED*"},DEALS!$G:$G,$B$2,DEALS!$E:$E,">="&$C$4,DEALS!$E:$E,"<="&$U$4,DEALS!$K:$K,P$6,DEALS!$M:$M,$K12,DEALS!$N:$N,"<>*RECEIVED*",DEALS!$N:$N,"<>*EXECUTED*"))+SUM(SUMIFS(DEALS!$R:$R,DEALS!$A:$A,{"*REFUND*","*EXECUTED*"},DEALS!$O:$O,$B$2,DEALS!$E:$E,">="&$C$4,DEALS!$E:$E,"<="&$U$4,DEALS!$S:$S,P$6,DEALS!$U:$U,$K12,DEALS!$V:$V,"<>*RECEIVED*",DEALS!$V:$V,"<>*EXECUTED*"))} -> 0 | Q12: {=SUMIFS(FLOWS!$C:$C,FLOWS!$A:$A,$B$2,FLOWS!$E:$E,$K12,FLOWS!$D:$D,Q$6,FLOWS!$H:$H,">="&$C$4,FLOWS!$H:$H,"<="&$U$4)+SUM(SUMIFS(DEALS!$J:$J,DEALS!$A:$A,{"*REFUND*","*EXECUTED*"},DEALS!$G:$G,$B$2,DEALS!$E:$E,">="&$C$4,DEALS!$E:$E,"<="&$U$4,DEALS!$K:$K,Q$6,DEALS!$M:$M,$K12,DEALS!$N:$N,"<>*RECEIVED*",DEALS!$N:$N,"<>*EXECUTED*"))+SUM(SUMIFS(DEALS!$R:$R,DEALS!$A:$A,{"*REFUND*","*EXECUTED*"},DEALS!$O:$O,$B$2,DEALS!$E:$E,">="&$C$4,DEALS!$E:$E,"<="&$U$4,DEALS!$S:$S,Q$6,DEALS!$U:$U,$K12,DEALS!$V:$V,"<>*RECEIVED*",DEALS!$V:$V,"<>*EXECUTED*"))} -> 0 | R12: =L12*VLOOKUP(L$6,'FX RATES'!$E$1:$F$50,2,FALSE)+M12*VLOOKUP(M$6,'FX RATES'!$E$1:$F$50,2,FALSE)+N12*VLOOKUP(N$6,'FX RATES'!$E$1:$F$50,2,FALSE)+O12*VLOOKUP(O$6,'FX RATES'!$E$1:$F$50,2,FALSE)+P12*VLOOKUP(P$6,'FX RATES'!$E$1:$F$50,2,FALSE)+Q12*VLOOKUP(Q$6,'FX RATES'!$E$1:$F$50,2,FALSE) -> 0 | T12: =B12 -> HDFC | U12: {=SUMIFS(BALANCES!$C:$C,BALANCES!$A:$A,$B$2,BALANCES!$B:$B,$T12,BALANCES!$D:$D,U$6)+SUMIFS(FLOWS!$C:$C,FLOWS!$A:$A,$B$2,FLOWS!$E:$E,$T12,FLOWS!$D:$D,U$6,FLOWS!$H:$H,"<="&$U$4)+SUM(SUMIFS(DEALS!$J:$J,DEALS!$A:$A,{"*REFUND*","*EXECUTED*"},DEALS!$G:$G,$B$2,DEALS!$E:$E,"<="&$U$4,DEALS!$K:$K,U$6,DEALS!$M:$M,$T12,DEALS!$N:$N,"<>*RECEIVED*",DEALS!$N:$N,"<>*EXECUTED*"))+SUM(SUMIFS(DEALS!$R:$R,DEALS!$A:$A,{"*REFUND*","*EXECUTED*"},DEALS!$O:$O,$B$2,DEALS!$E:$E,"<="&$U$4,DEALS!$S:$S,U$6,DEALS!$U:$U,$T12,DEALS!$V:$V,"<>*RECEIVED*",DEALS!$V:$V,"<>*EXECUTED*"))} -> 6486.39 | V12: {=SUMIFS(BALANCES!$C:$C,BALANCES!$A:$A,$B$2,BALANCES!$B:$B,$T12,BALANCES!$D:$D,V$6)+SUMIFS(FLOWS!$C:$C,FLOWS!$A:$A,$B$2,FLOWS!$E:$E,$T12,FLOWS!$D:$D,V$6,FLOWS!$H:$H,"<="&$U$4)+SUM(SUMIFS(DEALS!$J:$J,DEALS!$A:$A,{"*REFUND*","*EXECUTED*"},DEALS!$G:$G,$B$2,DEALS!$E:$E,"<="&$U$4,DEALS!$K:$K,V$6,DEALS!$M:$M,$T12,DEALS!$N:$N,"<>*RECEIVED*",DEALS!$N:$N,"<>*EXECUTED*"))+SUM(SUMIFS(DEALS!$R:$R,DEALS!$A:$A,{"*REFUND*","*EXECUTED*"},DEALS!$O:$O,$B$2,DEALS!$E:$E,"<="&$U$4,DEALS!$S:$S,V$6,DEALS!$U:$U,$T12,DEALS!$V:$V,"<>*RECEIVED*",DEALS!$V:$V,"<>*EXECUTED*"))} -> 0 | W12: {=SUMIFS(BALANCES!$C:$C,BALANCES!$A:$A,$B$2,BALANCES!$B:$B,$T12,BALANCES!$D:$D,W$6)+SUMIFS(FLOWS!$C:$C,FLOWS!$A:$A,$B$2,FLOWS!$E:$E,$T12,FLOWS!$D:$D,W$6,FLOWS!$H:$H,"<="&$U$4)+SUM(SUMIFS(DEALS!$J:$J,DEALS!$A:$A,{"*REFUND*","*EXECUTED*"},DEALS!$G:$G,$B$2,DEALS!$E:$E,"<="&$U$4,DEALS!$K:$K,W$6,DEALS!$M:$M,$T12,DEALS!$N:$N,"<>*RECEIVED*",DEALS!$N:$N,"<>*EXECUTED*"))+SUM(SUMIFS(DEALS!$R:$R,DEALS!$A:$A,{"*REFUND*","*EXECUTED*"},DEALS!$O:$O,$B$2,DEALS!$E:$E,"<="&$U$4,DEALS!$S:$S,W$6,DEALS!$U:$U,$T12,DEALS!$V:$V,"<>*RECEIVED*",DEALS!$V:$V,"<>*EXECUTED*"))} -> 0 | X12: {=SUMIFS(BALANCES!$C:$C,BALANCES!$A:$A,$B$2,BALANCES!$B:$B,$T12,BALANCES!$D:$D,X$6)+SUMIFS(FLOWS!$C:$C,FLOWS!$A:$A,$B$2,FLOWS!$E:$E,$T12,FLOWS!$D:$D,X$6,FLOWS!$H:$H,"<="&$U$4)+SUM(SUMIFS(DEALS!$J:$J,DEALS!$A:$A,{"*REFUND*","*EXECUTED*"},DEALS!$G:$G,$B$2,DEALS!$E:$E,"<="&$U$4,DEALS!$K:$K,X$6,DEALS!$M:$M,$T12,DEALS!$N:$N,"<>*RECEIVED*",DEALS!$N:$N,"<>*EXECUTED*"))+SUM(SUMIFS(DEALS!$R:$R,DEALS!$A:$A,{"*REFUND*","*EXECUTED*"},DEALS!$O:$O,$B$2,DEALS!$E:$E,"<="&$U$4,DEALS!$S:$S,X$6,DEALS!$U:$U,$T12,DEALS!$V:$V,"<>*RECEIVED*",DEALS!$V:$V,"<>*EXECUTED*"))} -> 2284.19 | Y12: {=SUMIFS(BALANCES!$C:$C,BALANCES!$A:$A,$B$2,BALANCES!$B:$B,$T12,BALANCES!$D:$D,Y$6)+SUMIFS(FLOWS!$C:$C,FLOWS!$A:$A,$B$2,FLOWS!$E:$E,$T12,FLOWS!$D:$D,Y$6,FLOWS!$H:$H,"<="&$U$4)+SUM(SUMIFS(DEALS!$J:$J,DEALS!$A:$A,{"*REFUND*","*EXECUTED*"},DEALS!$G:$G,$B$2,DEALS!$E:$E,"<="&$U$4,DEALS!$K:$K,Y$6,DEALS!$M:$M,$T12,DEALS!$N:$N,"<>*RECEIVED*",DEALS!$N:$N,"<>*EXECUTED*"))+SUM(SUMIFS(DEALS!$R:$R,DEALS!$A:$A,{"*REFUND*","*EXECUTED*"},DEALS!$O:$O,$B$2,DEALS!$E:$E,"<="&$U$4,DEALS!$S:$S,Y$6,DEALS!$U:$U,$T12,DEALS!$V:$V,"<>*RECEIVED*",DEALS!$V:$V,"<>*EXECUTED*"))} -> 0 | Z12: {=SUMIFS(BALANCES!$C:$C,BALANCES!$A:$A,$B$2,BALANCES!$B:$B,$T12,BALANCES!$D:$D,Z$6)+SUMIFS(FLOWS!$C:$C,FLOWS!$A:$A,$B$2,FLOWS!$E:$E,$T12,FLOWS!$D:$D,Z$6,FLOWS!$H:$H,"<="&$U$4)+SUM(SUMIFS(DEALS!$J:$J,DEALS!$A:$A,{"*REFUND*","*EXECUTED*"},DEALS!$G:$G,$B$2,DEALS!$E:$E,"<="&$U$4,DEALS!$K:$K,Z$6,DEALS!$M:$M,$T12,DEALS!$N:$N,"<>*RECEIVED*",DEALS!$N:$N,"<>*EXECUTED*"))+SUM(SUMIFS(DEALS!$R:$R,DEALS!$A:$A,{"*REFUND*","*EXECUTED*"},DEALS!$O:$O,$B$2,DEALS!$E:$E,"<="&$U$4,DEALS!$S:$S,Z$6,DEALS!$U:$U,$T12,DEALS!$V:$V,"<>*RECEIVED*",DEALS!$V:$V,"<>*EXECUTED*"))} -> 0 | AA12: =U12*VLOOKUP(U$6,'FX RATES'!$E$1:$F$50,2,FALSE)+V12*VLOOKUP(V$6,'FX RATES'!$E$1:$F$50,2,FALSE)+W12*VLOOKUP(W$6,'FX RATES'!$E$1:$F$50,2,FALSE)+X12*VLOOKUP(X$6,'FX RATES'!$E$1:$F$50,2,FALSE)+Y12*VLOOKUP(Y$6,'FX RATES'!$E$1:$F$50,2,FALSE)+Z12*VLOOKUP(Z$6,'FX RATES'!$E$1:$F$50,2,FALSE) -> 7108.3445 | AC12: =I12+R12-AA12 -> 0
B13: ALSAL | C13: {=SUMIFS(BALANCES!$C:$C,BALANCES!$A:$A,$B$2,BALANCES!$B:$B,$B13,BALANCES!$D:$D,C$6)+SUMIFS(FLOWS!$C:$C,FLOWS!$A:$A,$B$2,FLOWS!$E:$E,$B13,FLOWS!$D:$D,C$6,FLOWS!$H:$H,"<"&$C$4)+SUM(SUMIFS(DEALS!$J:$J,DEALS!$A:$A,{"*REFUND*","*EXECUTED*"},DEALS!$G:$G,$B$2,DEALS!$E:$E,"<"&$C$4,DEALS!$K:$K,C$6,DEALS!$M:$M,$B13,DEALS!$N:$N,"<>*RECEIVED*",DEALS!$N:$N,"<>*EXECUTED*"))+SUM(SUMIFS(DEALS!$R:$R,DEALS!$A:$A,{"*REFUND*","*EXECUTED*"},DEALS!$O:$O,$B$2,DEALS!$E:$E,"<"&$C$4,DEALS!$S:$S,C$6,DEALS!$U:$U,$B13,DEALS!$V:$V,"<>*RECEIVED*",DEALS!$V:$V,"<>*EXECUTED*"))} -> 33041.58 | D13: {=SUMIFS(BALANCES!$C:$C,BALANCES!$A:$A,$B$2,BALANCES!$B:$B,$B13,BALANCES!$D:$D,D$6)+SUMIFS(FLOWS!$C:$C,FLOWS!$A:$A,$B$2,FLOWS!$E:$E,$B13,FLOWS!$D:$D,D$6,FLOWS!$H:$H,"<"&$C$4)+SUM(SUMIFS(DEALS!$J:$J,DEALS!$A:$A,{"*REFUND*","*EXECUTED*"},DEALS!$G:$G,$B$2,DEALS!$E:$E,"<"&$C$4,DEALS!$K:$K,D$6,DEALS!$M:$M,$B13,DEALS!$N:$N,"<>*RECEIVED*",DEALS!$N:$N,"<>*EXECUTED*"))+SUM(SUMIFS(DEALS!$R:$R,DEALS!$A:$A,{"*REFUND*","*EXECUTED*"},DEALS!$O:$O,$B$2,DEALS!$E:$E,"<"&$C$4,DEALS!$S:$S,D$6,DEALS!$U:$U,$B13,DEALS!$V:$V,"<>*RECEIVED*",DEALS!$V:$V,"<>*EXECUTED*"))} -> 6449.57 | E13: {=SUMIFS(BALANCES!$C:$C,BALANCES!$A:$A,$B$2,BALANCES!$B:$B,$B13,BALANCES!$D:$D,E$6)+SUMIFS(FLOWS!$C:$C,FLOWS!$A:$A,$B$2,FLOWS!$E:$E,$B13,FLOWS!$D:$D,E$6,FLOWS!$H:$H,"<"&$C$4)+SUM(SUMIFS(DEALS!$J:$J,DEALS!$A:$A,{"*REFUND*","*EXECUTED*"},DEALS!$G:$G,$B$2,DEALS!$E:$E,"<"&$C$4,DEALS!$K:$K,E$6,DEALS!$M:$M,$B13,DEALS!$N:$N,"<>*RECEIVED*",DEALS!$N:$N,"<>*EXECUTED*"))+SUM(SUMIFS(DEALS!$R:$R,DEALS!$A:$A,{"*REFUND*","*EXECUTED*"},DEALS!$O:$O,$B$2,DEALS!$E:$E,"<"&$C$4,DEALS!$S:$S,E$6,DEALS!$U:$U,$B13,DEALS!$V:$V,"<>*RECEIVED*",DEALS!$V:$V,"<>*EXECUTED*"))} -> 0 | F13: {=SUMIFS(BALANCES!$C:$C,BALANCES!$A:$A,$B$2,BALANCES!$B:$B,$B13,BALANCES!$D:$D,F$6)+SUMIFS(FLOWS!$C:$C,FLOWS!$A:$A,$B$2,FLOWS!$E:$E,$B13,FLOWS!$D:$D,F$6,FLOWS!$H:$H,"<"&$C$4)+SUM(SUMIFS(DEALS!$J:$J,DEALS!$A:$A,{"*REFUND*","*EXECUTED*"},DEALS!$G:$G,$B$2,DEALS!$E:$E,"<"&$C$4,DEALS!$K:$K,F$6,DEALS!$M:$M,$B13,DEALS!$N:$N,"<>*RECEIVED*",DEALS!$N:$N,"<>*EXECUTED*"))+SUM(SUMIFS(DEALS!$R:$R,DEALS!$A:$A,{"*REFUND*","*EXECUTED*"},DEALS!$O:$O,$B$2,DEALS!$E:$E,"<"&$C$4,DEALS!$S:$S,F$6,DEALS!$U:$U,$B13,DEALS!$V:$V,"<>*RECEIVED*",DEALS!$V:$V,"<>*EXECUTED*"))} -> 0 | G13: {=SUMIFS(BALANCES!$C:$C,BALANCES!$A:$A,$B$2,BALANCES!$B:$B,$B13,BALANCES!$D:$D,G$6)+SUMIFS(FLOWS!$C:$C,FLOWS!$A:$A,$B$2,FLOWS!$E:$E,$B13,FLOWS!$D:$D,G$6,FLOWS!$H:$H,"<"&$C$4)+SUM(SUMIFS(DEALS!$J:$J,DEALS!$A:$A,{"*REFUND*","*EXECUTED*"},DEALS!$G:$G,$B$2,DEALS!$E:$E,"<"&$C$4,DEALS!$K:$K,G$6,DEALS!$M:$M,$B13,DEALS!$N:$N,"<>*RECEIVED*",DEALS!$N:$N,"<>*EXECUTED*"))+SUM(SUMIFS(DEALS!$R:$R,DEALS!$A:$A,{"*REFUND*","*EXECUTED*"},DEALS!$O:$O,$B$2,DEALS!$E:$E,"<"&$C$4,DEALS!$S:$S,G$6,DEALS!$U:$U,$B13,DEALS!$V:$V,"<>*RECEIVED*",DEALS!$V:$V,"<>*EXECUTED*"))} -> 0 | H13: {=SUMIFS(BALANCES!$C:$C,BALANCES!$A:$A,$B$2,BALANCES!$B:$B,$B13,BALANCES!$D:$D,H$6)+SUMIFS(FLOWS!$C:$C,FLOWS!$A:$A,$B$2,FLOWS!$E:$E,$B13,FLOWS!$D:$D,H$6,FLOWS!$H:$H,"<"&$C$4)+SUM(SUMIFS(DEALS!$J:$J,DEALS!$A:$A,{"*REFUND*","*EXECUTED*"},DEALS!$G:$G,$B$2,DEALS!$E:$E,"<"&$C$4,DEALS!$K:$K,H$6,DEALS!$M:$M,$B13,DEALS!$N:$N,"<>*RECEIVED*",DEALS!$N:$N,"<>*EXECUTED*"))+SUM(SUMIFS(DEALS!$R:$R,DEALS!$A:$A,{"*REFUND*","*EXECUTED*"},DEALS!$O:$O,$B$2,DEALS!$E:$E,"<"&$C$4,DEALS!$S:$S,H$6,DEALS!$U:$U,$B13,DEALS!$V:$V,"<>*RECEIVED*",DEALS!$V:$V,"<>*EXECUTED*"))} -> 0 | I13: =C13*VLOOKUP(C$6,'FX RATES'!$E$1:$F$50,2,FALSE)+D13*VLOOKUP(D$6,'FX RATES'!$E$1:$F$50,2,FALSE)+E13*VLOOKUP(E$6,'FX RATES'!$E$1:$F$50,2,FALSE)+F13*VLOOKUP(F$6,'FX RATES'!$E$1:$F$50,2,FALSE)+G13*VLOOKUP(G$6,'FX RATES'!$E$1:$F$50,2,FALSE)+H13*VLOOKUP(H$6,'FX RATES'!$E$1:$F$50,2,FALSE) -> 40639.173 | K13: =B13 -> ALSAL | L13: {=SUMIFS(FLOWS!$C:$C,FLOWS!$A:$A,$B$2,FLOWS!$E:$E,$K13,FLOWS!$D:$D,L$6,FLOWS!$H:$H,">="&$C$4,FLOWS!$H:$H,"<="&$U$4)+SUM(SUMIFS(DEALS!$J:$J,DEALS!$A:$A,{"*REFUND*","*EXECUTED*"},DEALS!$G:$G,$B$2,DEALS!$E:$E,">="&$C$4,DEALS!$E:$E,"<="&$U$4,DEALS!$K:$K,L$6,DEALS!$M:$M,$K13,DEALS!$N:$N,"<>*RECEIVED*",DEALS!$N:$N,"<>*EXECUTED*"))+SUM(SUMIFS(DEALS!$R:$R,DEALS!$A:$A,{"*REFUND*","*EXECUTED*"},DEALS!$O:$O,$B$2,DEALS!$E:$E,">="&$C$4,DEALS!$E:$E,"<="&$U$4,DEALS!$S:$S,L$6,DEALS!$U:$U,$K13,DEALS!$V:$V,"<>*RECEIVED*",DEALS!$V:$V,"<>*EXECUTED*"))} -> 0 | M13: {=SUMIFS(FLOWS!$C:$C,FLOWS!$A:$A,$B$2,FLOWS!$E:$E,$K13,FLOWS!$D:$D,M$6,FLOWS!$H:$H,">="&$C$4,FLOWS!$H:$H,"<="&$U$4)+SUM(SUMIFS(DEALS!$J:$J,DEALS!$A:$A,{"*REFUND*","*EXECUTED*"},DEALS!$G:$G,$B$2,DEALS!$E:$E,">="&$C$4,DEALS!$E:$E,"<="&$U$4,DEALS!$K:$K,M$6,DEALS!$M:$M,$K13,DEALS!$N:$N,"<>*RECEIVED*",DEALS!$N:$N,"<>*EXECUTED*"))+SUM(SUMIFS(DEALS!$R:$R,DEALS!$A:$A,{"*REFUND*","*EXECUTED*"},DEALS!$O:$O,$B$2,DEALS!$E:$E,">="&$C$4,DEALS!$E:$E,"<="&$U$4,DEALS!$S:$S,M$6,DEALS!$U:$U,$K13,DEALS!$V:$V,"<>*RECEIVED*",DEALS!$V:$V,"<>*EXECUTED*"))} -> 0 | N13: {=SUMIFS(FLOWS!$C:$C,FLOWS!$A:$A,$B$2,FLOWS!$E:$E,$K13,FLOWS!$D:$D,N$6,FLOWS!$H:$H,">="&$C$4,FLOWS!$H:$H,"<="&$U$4)+SUM(SUMIFS(DEALS!$J:$J,DEALS!$A:$A,{"*REFUND*","*EXECUTED*"},DEALS!$G:$G,$B$2,DEALS!$E:$E,">="&$C$4,DEALS!$E:$E,"<="&$U$4,DEALS!$K:$K,N$6,DEALS!$M:$M,$K13,DEALS!$N:$N,"<>*RECEIVED*",DEALS!$N:$N,"<>*EXECUTED*"))+SUM(SUMIFS(DEALS!$R:$R,DEALS!$A:$A,{"*REFUND*","*EXECUTED*"},DEALS!$O:$O,$B$2,DEALS!$E:$E,">="&$C$4,DEALS!$E:$E,"<="&$U$4,DEALS!$S:$S,N$6,DEALS!$U:$U,$K13,DEALS!$V:$V,"<>*RECEIVED*",DEALS!$V:$V,"<>*EXECUTED*"))} -> 0 | O13: {=SUMIFS(FLOWS!$C:$C,FLOWS!$A:$A,$B$2,FLOWS!$E:$E,$K13,FLOWS!$D:$D,O$6,FLOWS!$H:$H,">="&$C$4,FLOWS!$H:$H,"<="&$U$4)+SUM(SUMIFS(DEALS!$J:$J,DEALS!$A:$A,{"*REFUND*","*EXECUTED*"},DEALS!$G:$G,$B$2,DEALS!$E:$E,">="&$C$4,DEALS!$E:$E,"<="&$U$4,DEALS!$K:$K,O$6,DEALS!$M:$M,$K13,DEALS!$N:$N,"<>*RECEIVED*",DEALS!$N:$N,"<>*EXECUTED*"))+SUM(SUMIFS(DEALS!$R:$R,DEALS!$A:$A,{"*REFUND*","*EXECUTED*"},DEALS!$O:$O,$B$2,DEALS!$E:$E,">="&$C$4,DEALS!$E:$E,"<="&$U$4,DEALS!$S:$S,O$6,DEALS!$U:$U,$K13,DEALS!$V:$V,"<>*RECEIVED*",DEALS!$V:$V,"<>*EXECUTED*"))} -> 0 | P13: {=SUMIFS(FLOWS!$C:$C,FLOWS!$A:$A,$B$2,FLOWS!$E:$E,$K13,FLOWS!$D:$D,P$6,FLOWS!$H:$H,">="&$C$4,FLOWS!$H:$H,"<="&$U$4)+SUM(SUMIFS(DEALS!$J:$J,DEALS!$A:$A,{"*REFUND*","*EXECUTED*"},DEALS!$G:$G,$B$2,DEALS!$E:$E,">="&$C$4,DEALS!$E:$E,"<="&$U$4,DEALS!$K:$K,P$6,DEALS!$M:$M,$K13,DEALS!$N:$N,"<>*RECEIVED*",DEALS!$N:$N,"<>*EXECUTED*"))+SUM(SUMIFS(DEALS!$R:$R,DEALS!$A:$A,{"*REFUND*","*EXECUTED*"},DEALS!$O:$O,$B$2,DEALS!$E:$E,">="&$C$4,DEALS!$E:$E,"<="&$U$4,DEALS!$S:$S,P$6,DEALS!$U:$U,$K13,DEALS!$V:$V,"<>*RECEIVED*",DEALS!$V:$V,"<>*EXECUTED*"))} -> 0 | Q13: {=SUMIFS(FLOWS!$C:$C,FLOWS!$A:$A,$B$2,FLOWS!$E:$E,$K13,FLOWS!$D:$D,Q$6,FLOWS!$H:$H,">="&$C$4,FLOWS!$H:$H,"<="&$U$4)+SUM(SUMIFS(DEALS!$J:$J,DEALS!$A:$A,{"*REFUND*","*EXECUTED*"},DEALS!$G:$G,$B$2,DEALS!$E:$E,">="&$C$4,DEALS!$E:$E,"<="&$U$4,DEALS!$K:$K,Q$6,DEALS!$M:$M,$K13,DEALS!$N:$N,"<>*RECEIVED*",DEALS!$N:$N,"<>*EXECUTED*"))+SUM(SUMIFS(DEALS!$R:$R,DEALS!$A:$A,{"*REFUND*","*EXECUTED*"},DEALS!$O:$O,$B$2,DEALS!$E:$E,">="&$C$4,DEALS!$E:$E,"<="&$U$4,DEALS!$S:$S,Q$6,DEALS!$U:$U,$K13,DEALS!$V:$V,"<>*RECEIVED*",DEALS!$V:$V,"<>*EXECUTED*"))} -> 0 | R13: =L13*VLOOKUP(L$6,'FX RATES'!$E$1:$F$50,2,FALSE)+M13*VLOOKUP(M$6,'FX RATES'!$E$1:$F$50,2,FALSE)+N13*VLOOKUP(N$6,'FX RATES'!$E$1:$F$50,2,FALSE)+O13*VLOOKUP(O$6,'FX RATES'!$E$1:$F$50,2,FALSE)+P13*VLOOKUP(P$6,'FX RATES'!$E$1:$F$50,2,FALSE)+Q13*VLOOKUP(Q$6,'FX RATES'!$E$1:$F$50,2,FALSE) -> 0 | T13: =B13 -> ALSAL | U13: {=SUMIFS(BALANCES!$C:$C,BALANCES!$A:$A,$B$2,BALANCES!$B:$B,$T13,BALANCES!$D:$D,U$6)+SUMIFS(FLOWS!$C:$C,FLOWS!$A:$A,$B$2,FLOWS!$E:$E,$T13,FLOWS!$D:$D,U$6,FLOWS!$H:$H,"<="&$U$4)+SUM(SUMIFS(DEALS!$J:$J,DEALS!$A:$A,{"*REFUND*","*EXECUTED*"},DEALS!$G:$G,$B$2,DEALS!$E:$E,"<="&$U$4,DEALS!$K:$K,U$6,DEALS!$M:$M,$T13,DEALS!$N:$N,"<>*RECEIVED*",DEALS!$N:$N,"<>*EXECUTED*"))+SUM(SUMIFS(DEALS!$R:$R,DEALS!$A:$A,{"*REFUND*","*EXECUTED*"},DEALS!$O:$O,$B$2,DEALS!$E:$E,"<="&$U$4,DEALS!$S:$S,U$6,DEALS!$U:$U,$T13,DEALS!$V:$V,"<>*RECEIVED*",DEALS!$V:$V,"<>*EXECUTED*"))} -> 33041.58 | V13: {=SUMIFS(BALANCES!$C:$C,BALANCES!$A:$A,$B$2,BALANCES!$B:$B,$T13,BALANCES!$D:$D,V$6)+SUMIFS(FLOWS!$C:$C,FLOWS!$A:$A,$B$2,FLOWS!$E:$E,$T13,FLOWS!$D:$D,V$6,FLOWS!$H:$H,"<="&$U$4)+SUM(SUMIFS(DEALS!$J:$J,DEALS!$A:$A,{"*REFUND*","*EXECUTED*"},DEALS!$G:$G,$B$2,DEALS!$E:$E,"<="&$U$4,DEALS!$K:$K,V$6,DEALS!$M:$M,$T13,DEALS!$N:$N,"<>*RECEIVED*",DEALS!$N:$N,"<>*EXECUTED*"))+SUM(SUMIFS(DEALS!$R:$R,DEALS!$A:$A,{"*REFUND*","*EXECUTED*"},DEALS!$O:$O,$B$2,DEALS!$E:$E,"<="&$U$4,DEALS!$S:$S,V$6,DEALS!$U:$U,$T13,DEALS!$V:$V,"<>*RECEIVED*",DEALS!$V:$V,"<>*EXECUTED*"))} -> 6449.57 | W13: {=SUMIFS(BALANCES!$C:$C,BALANCES!$A:$A,$B$2,BALANCES!$B:$B,$T13,BALANCES!$D:$D,W$6)+SUMIFS(FLOWS!$C:$C,FLOWS!$A:$A,$B$2,FLOWS!$E:$E,$T13,FLOWS!$D:$D,W$6,FLOWS!$H:$H,"<="&$U$4)+SUM(SUMIFS(DEALS!$J:$J,DEALS!$A:$A,{"*REFUND*","*EXECUTED*"},DEALS!$G:$G,$B$2,DEALS!$E:$E,"<="&$U$4,DEALS!$K:$K,W$6,DEALS!$M:$M,$T13,DEALS!$N:$N,"<>*RECEIVED*",DEALS!$N:$N,"<>*EXECUTED*"))+SUM(SUMIFS(DEALS!$R:$R,DEALS!$A:$A,{"*REFUND*","*EXECUTED*"},DEALS!$O:$O,$B$2,DEALS!$E:$E,"<="&$U$4,DEALS!$S:$S,W$6,DEALS!$U:$U,$T13,DEALS!$V:$V,"<>*RECEIVED*",DEALS!$V:$V,"<>*EXECUTED*"))} -> 0 | X13: {=SUMIFS(BALANCES!$C:$C,BALANCES!$A:$A,$B$2,BALANCES!$B:$B,$T13,BALANCES!$D:$D,X$6)+SUMIFS(FLOWS!$C:$C,FLOWS!$A:$A,$B$2,FLOWS!$E:$E,$T13,FLOWS!$D:$D,X$6,FLOWS!$H:$H,"<="&$U$4)+SUM(SUMIFS(DEALS!$J:$J,DEALS!$A:$A,{"*REFUND*","*EXECUTED*"},DEALS!$G:$G,$B$2,DEALS!$E:$E,"<="&$U$4,DEALS!$K:$K,X$6,DEALS!$M:$M,$T13,DEALS!$N:$N,"<>*RECEIVED*",DEALS!$N:$N,"<>*EXECUTED*"))+SUM(SUMIFS(DEALS!$R:$R,DEALS!$A:$A,{"*REFUND*","*EXECUTED*"},DEALS!$O:$O,$B$2,DEALS!$E:$E,"<="&$U$4,DEALS!$S:$S,X$6,DEALS!$U:$U,$T13,DEALS!$V:$V,"<>*RECEIVED*",DEALS!$V:$V,"<>*EXECUTED*"))} -> 0 | Y13: {=SUMIFS(BALANCES!$C:$C,BALANCES!$A:$A,$B$2,BALANCES!$B:$B,$T13,BALANCES!$D:$D,Y$6)+SUMIFS(FLOWS!$C:$C,FLOWS!$A:$A,$B$2,FLOWS!$E:$E,$T13,FLOWS!$D:$D,Y$6,FLOWS!$H:$H,"<="&$U$4)+SUM(SUMIFS(DEALS!$J:$J,DEALS!$A:$A,{"*REFUND*","*EXECUTED*"},DEALS!$G:$G,$B$2,DEALS!$E:$E,"<="&$U$4,DEALS!$K:$K,Y$6,DEALS!$M:$M,$T13,DEALS!$N:$N,"<>*RECEIVED*",DEALS!$N:$N,"<>*EXECUTED*"))+SUM(SUMIFS(DEALS!$R:$R,DEALS!$A:$A,{"*REFUND*","*EXECUTED*"},DEALS!$O:$O,$B$2,DEALS!$E:$E,"<="&$U$4,DEALS!$S:$S,Y$6,DEALS!$U:$U,$T13,DEALS!$V:$V,"<>*RECEIVED*",DEALS!$V:$V,"<>*EXECUTED*"))} -> 0 | Z13: {=SUMIFS(BALANCES!$C:$C,BALANCES!$A:$A,$B$2,BALANCES!$B:$B,$T13,BALANCES!$D:$D,Z$6)+SUMIFS(FLOWS!$C:$C,FLOWS!$A:$A,$B$2,FLOWS!$E:$E,$T13,FLOWS!$D:$D,Z$6,FLOWS!$H:$H,"<="&$U$4)+SUM(SUMIFS(DEALS!$J:$J,DEALS!$A:$A,{"*REFUND*","*EXECUTED*"},DEALS!$G:$G,$B$2,DEALS!$E:$E,"<="&$U$4,DEALS!$K:$K,Z$6,DEALS!$M:$M,$T13,DEALS!$N:$N,"<>*RECEIVED*",DEALS!$N:$N,"<>*EXECUTED*"))+SUM(SUMIFS(DEALS!$R:$R,DEALS!$A:$A,{"*REFUND*","*EXECUTED*"},DEALS!$O:$O,$B$2,DEALS!$E:$E,"<="&$U$4,DEALS!$S:$S,Z$6,DEALS!$U:$U,$T13,DEALS!$V:$V,"<>*RECEIVED*",DEALS!$V:$V,"<>*EXECUTED*"))} -> 0 | AA13: =U13*VLOOKUP(U$6,'FX RATES'!$E$1:$F$50,2,FALSE)+V13*VLOOKUP(V$6,'FX RATES'!$E$1:$F$50,2,FALSE)+W13*VLOOKUP(W$6,'FX RATES'!$E$1:$F$50,2,FALSE)+X13*VLOOKUP(X$6,'FX RATES'!$E$1:$F$50,2,FALSE)+Y13*VLOOKUP(Y$6,'FX RATES'!$E$1:$F$50,2,FALSE)+Z13*VLOOKUP(Z$6,'FX RATES'!$E$1:$F$50,2,FALSE) -> 40639.173 | AC13: =I13+R13-AA13 -> 0
B14: UAB | C14: {=SUMIFS(BALANCES!$C:$C,BALANCES!$A:$A,$B$2,BALANCES!$B:$B,$B14,BALANCES!$D:$D,C$6)+SUMIFS(FLOWS!$C:$C,FLOWS!$A:$A,$B$2,FLOWS!$E:$E,$B14,FLOWS!$D:$D,C$6,FLOWS!$H:$H,"<"&$C$4)+SUM(SUMIFS(DEALS!$J:$J,DEALS!$A:$A,{"*REFUND*","*EXECUTED*"},DEALS!$G:$G,$B$2,DEALS!$E:$E,"<"&$C$4,DEALS!$K:$K,C$6,DEALS!$M:$M,$B14,DEALS!$N:$N,"<>*RECEIVED*",DEALS!$N:$N,"<>*EXECUTED*"))+SUM(SUMIFS(DEALS!$R:$R,DEALS!$A:$A,{"*REFUND*","*EXECUTED*"},DEALS!$O:$O,$B$2,DEALS!$E:$E,"<"&$C$4,DEALS!$S:$S,C$6,DEALS!$U:$U,$B14,DEALS!$V:$V,"<>*RECEIVED*",DEALS!$V:$V,"<>*EXECUTED*"))} -> 703.27 | D14: {=SUMIFS(BALANCES!$C:$C,BALANCES!$A:$A,$B$2,BALANCES!$B:$B,$B14,BALANCES!$D:$D,D$6)+SUMIFS(FLOWS!$C:$C,FLOWS!$A:$A,$B$2,FLOWS!$E:$E,$B14,FLOWS!$D:$D,D$6,FLOWS!$H:$H,"<"&$C$4)+SUM(SUMIFS(DEALS!$J:$J,DEALS!$A:$A,{"*REFUND*","*EXECUTED*"},DEALS!$G:$G,$B$2,DEALS!$E:$E,"<"&$C$4,DEALS!$K:$K,D$6,DEALS!$M:$M,$B14,DEALS!$N:$N,"<>*RECEIVED*",DEALS!$N:$N,"<>*EXECUTED*"))+SUM(SUMIFS(DEALS!$R:$R,DEALS!$A:$A,{"*REFUND*","*EXECUTED*"},DEALS!$O:$O,$B$2,DEALS!$E:$E,"<"&$C$4,DEALS!$S:$S,D$6,DEALS!$U:$U,$B14,DEALS!$V:$V,"<>*RECEIVED*",DEALS!$V:$V,"<>*EXECUTED*"))} -> 0 | E14: {=SUMIFS(BALANCES!$C:$C,BALANCES!$A:$A,$B$2,BALANCES!$B:$B,$B14,BALANCES!$D:$D,E$6)+SUMIFS(FLOWS!$C:$C,FLOWS!$A:$A,$B$2,FLOWS!$E:$E,$B14,FLOWS!$D:$D,E$6,FLOWS!$H:$H,"<"&$C$4)+SUM(SUMIFS(DEALS!$J:$J,DEALS!$A:$A,{"*REFUND*","*EXECUTED*"},DEALS!$G:$G,$B$2,DEALS!$E:$E,"<"&$C$4,DEALS!$K:$K,E$6,DEALS!$M:$M,$B14,DEALS!$N:$N,"<>*RECEIVED*",DEALS!$N:$N,"<>*EXECUTED*"))+SUM(SUMIFS(DEALS!$R:$R,DEALS!$A:$A,{"*REFUND*","*EXECUTED*"},DEALS!$O:$O,$B$2,DEALS!$E:$E,"<"&$C$4,DEALS!$S:$S,E$6,DEALS!$U:$U,$B14,DEALS!$V:$V,"<>*RECEIVED*",DEALS!$V:$V,"<>*EXECUTED*"))} -> 0.5 | F14: {=SUMIFS(BALANCES!$C:$C,BALANCES!$A:$A,$B$2,BALANCES!$B:$B,$B14,BALANCES!$D:$D,F$6)+SUMIFS(FLOWS!$C:$C,FLOWS!$A:$A,$B$2,FLOWS!$E:$E,$B14,FLOWS!$D:$D,F$6,FLOWS!$H:$H,"<"&$C$4)+SUM(SUMIFS(DEALS!$J:$J,DEALS!$A:$A,{"*REFUND*","*EXECUTED*"},DEALS!$G:$G,$B$2,DEALS!$E:$E,"<"&$C$4,DEALS!$K:$K,F$6,DEALS!$M:$M,$B14,DEALS!$N:$N,"<>*RECEIVED*",DEALS!$N:$N,"<>*EXECUTED*"))+SUM(SUMIFS(DEALS!$R:$R,DEALS!$A:$A,{"*REFUND*","*EXECUTED*"},DEALS!$O:$O,$B$2,DEALS!$E:$E,"<"&$C$4,DEALS!$S:$S,F$6,DEALS!$U:$U,$B14,DEALS!$V:$V,"<>*RECEIVED*",DEALS!$V:$V,"<>*EXECUTED*"))} -> 56383.25 | G14: {=SUMIFS(BALANCES!$C:$C,BALANCES!$A:$A,$B$2,BALANCES!$B:$B,$B14,BALANCES!$D:$D,G$6)+SUMIFS(FLOWS!$C:$C,FLOWS!$A:$A,$B$2,FLOWS!$E:$E,$B14,FLOWS!$D:$D,G$6,FLOWS!$H:$H,"<"&$C$4)+SUM(SUMIFS(DEALS!$J:$J,DEALS!$A:$A,{"*REFUND*","*EXECUTED*"},DEALS!$G:$G,$B$2,DEALS!$E:$E,"<"&$C$4,DEALS!$K:$K,G$6,DEALS!$M:$M,$B14,DEALS!$N:$N,"<>*RECEIVED*",DEALS!$N:$N,"<>*EXECUTED*"))+SUM(SUMIFS(DEALS!$R:$R,DEALS!$A:$A,{"*REFUND*","*EXECUTED*"},DEALS!$O:$O,$B$2,DEALS!$E:$E,"<"&$C$4,DEALS!$S:$S,G$6,DEALS!$U:$U,$B14,DEALS!$V:$V,"<>*RECEIVED*",DEALS!$V:$V,"<>*EXECUTED*"))} -> 0 | H14: {=SUMIFS(BALANCES!$C:$C,BALANCES!$A:$A,$B$2,BALANCES!$B:$B,$B14,BALANCES!$D:$D,H$6)+SUMIFS(FLOWS!$C:$C,FLOWS!$A:$A,$B$2,FLOWS!$E:$E,$B14,FLOWS!$D:$D,H$6,FLOWS!$H:$H,"<"&$C$4)+SUM(SUMIFS(DEALS!$J:$J,DEALS!$A:$A,{"*REFUND*","*EXECUTED*"},DEALS!$G:$G,$B$2,DEALS!$E:$E,"<"&$C$4,DEALS!$K:$K,H$6,DEALS!$M:$M,$B14,DEALS!$N:$N,"<>*RECEIVED*",DEALS!$N:$N,"<>*EXECUTED*"))+SUM(SUMIFS(DEALS!$R:$R,DEALS!$A:$A,{"*REFUND*","*EXECUTED*"},DEALS!$O:$O,$B$2,DEALS!$E:$E,"<"&$C$4,DEALS!$S:$S,H$6,DEALS!$U:$U,$B14,DEALS!$V:$V,"<>*RECEIVED*",DEALS!$V:$V,"<>*EXECUTED*"))} -> 0 | I14: =C14*VLOOKUP(C$6,'FX RATES'!$E$1:$F$50,2,FALSE)+D14*VLOOKUP(D$6,'FX RATES'!$E$1:$F$50,2,FALSE)+E14*VLOOKUP(E$6,'FX RATES'!$E$1:$F$50,2,FALSE)+F14*VLOOKUP(F$6,'FX RATES'!$E$1:$F$50,2,FALSE)+G14*VLOOKUP(G$6,'FX RATES'!$E$1:$F$50,2,FALSE)+H14*VLOOKUP(H$6,'FX RATES'!$E$1:$F$50,2,FALSE) -> 16055.749 | K14: =B14 -> UAB | L14: {=SUMIFS(FLOWS!$C:$C,FLOWS!$A:$A,$B$2,FLOWS!$E:$E,$K14,FLOWS!$D:$D,L$6,FLOWS!$H:$H,">="&$C$4,FLOWS!$H:$H,"<="&$U$4)+SUM(SUMIFS(DEALS!$J:$J,DEALS!$A:$A,{"*REFUND*","*EXECUTED*"},DEALS!$G:$G,$B$2,DEALS!$E:$E,">="&$C$4,DEALS!$E:$E,"<="&$U$4,DEALS!$K:$K,L$6,DEALS!$M:$M,$K14,DEALS!$N:$N,"<>*RECEIVED*",DEALS!$N:$N,"<>*EXECUTED*"))+SUM(SUMIFS(DEALS!$R:$R,DEALS!$A:$A,{"*REFUND*","*EXECUTED*"},DEALS!$O:$O,$B$2,DEALS!$E:$E,">="&$C$4,DEALS!$E:$E,"<="&$U$4,DEALS!$S:$S,L$6,DEALS!$U:$U,$K14,DEALS!$V:$V,"<>*RECEIVED*",DEALS!$V:$V,"<>*EXECUTED*"))} -> 0 | M14: {=SUMIFS(FLOWS!$C:$C,FLOWS!$A:$A,$B$2,FLOWS!$E:$E,$K14,FLOWS!$D:$D,M$6,FLOWS!$H:$H,">="&$C$4,FLOWS!$H:$H,"<="&$U$4)+SUM(SUMIFS(DEALS!$J:$J,DEALS!$A:$A,{"*REFUND*","*EXECUTED*"},DEALS!$G:$G,$B$2,DEALS!$E:$E,">="&$C$4,DEALS!$E:$E,"<="&$U$4,DEALS!$K:$K,M$6,DEALS!$M:$M,$K14,DEALS!$N:$N,"<>*RECEIVED*",DEALS!$N:$N,"<>*EXECUTED*"))+SUM(SUMIFS(DEALS!$R:$R,DEALS!$A:$A,{"*REFUND*","*EXECUTED*"},DEALS!$O:$O,$B$2,DEALS!$E:$E,">="&$C$4,DEALS!$E:$E,"<="&$U$4,DEALS!$S:$S,M$6,DEALS!$U:$U,$K14,DEALS!$V:$V,"<>*RECEIVED*",DEALS!$V:$V,"<>*EXECUTED*"))} -> 0 | N14: {=SUMIFS(FLOWS!$C:$C,FLOWS!$A:$A,$B$2,FLOWS!$E:$E,$K14,FLOWS!$D:$D,N$6,FLOWS!$H:$H,">="&$C$4,FLOWS!$H:$H,"<="&$U$4)+SUM(SUMIFS(DEALS!$J:$J,DEALS!$A:$A,{"*REFUND*","*EXECUTED*"},DEALS!$G:$G,$B$2,DEALS!$E:$E,">="&$C$4,DEALS!$E:$E,"<="&$U$4,DEALS!$K:$K,N$6,DEALS!$M:$M,$K14,DEALS!$N:$N,"<>*RECEIVED*",DEALS!$N:$N,"<>*EXECUTED*"))+SUM(SUMIFS(DEALS!$R:$R,DEALS!$A:$A,{"*REFUND*","*EXECUTED*"},DEALS!$O:$O,$B$2,DEALS!$E:$E,">="&$C$4,DEALS!$E:$E,"<="&$U$4,DEALS!$S:$S,N$6,DEALS!$U:$U,$K14,DEALS!$V:$V,"<>*RECEIVED*",DEALS!$V:$V,"<>*EXECUTED*"))} -> 0 | O14: {=SUMIFS(FLOWS!$C:$C,FLOWS!$A:$A,$B$2,FLOWS!$E:$E,$K14,FLOWS!$D:$D,O$6,FLOWS!$H:$H,">="&$C$4,FLOWS!$H:$H,"<="&$U$4)+SUM(SUMIFS(DEALS!$J:$J,DEALS!$A:$A,{"*REFUND*","*EXECUTED*"},DEALS!$G:$G,$B$2,DEALS!$E:$E,">="&$C$4,DEALS!$E:$E,"<="&$U$4,DEALS!$K:$K,O$6,DEALS!$M:$M,$K14,DEALS!$N:$N,"<>*RECEIVED*",DEALS!$N:$N,"<>*EXECUTED*"))+SUM(SUMIFS(DEALS!$R:$R,DEALS!$A:$A,{"*REFUND*","*EXECUTED*"},DEALS!$O:$O,$B$2,DEALS!$E:$E,">="&$C$4,DEALS!$E:$E,"<="&$U$4,DEALS!$S:$S,O$6,DEALS!$U:$U,$K14,DEALS!$V:$V,"<>*RECEIVED*",DEALS!$V:$V,"<>*EXECUTED*"))} -> 0 | P14: {=SUMIFS(FLOWS!$C:$C,FLOWS!$A:$A,$B$2,FLOWS!$E:$E,$K14,FLOWS!$D:$D,P$6,FLOWS!$H:$H,">="&$C$4,FLOWS!$H:$H,"<="&$U$4)+SUM(SUMIFS(DEALS!$J:$J,DEALS!$A:$A,{"*REFUND*","*EXECUTED*"},DEALS!$G:$G,$B$2,DEALS!$E:$E,">="&$C$4,DEALS!$E:$E,"<="&$U$4,DEALS!$K:$K,P$6,DEALS!$M:$M,$K14,DEALS!$N:$N,"<>*RECEIVED*",DEALS!$N:$N,"<>*EXECUTED*"))+SUM(SUMIFS(DEALS!$R:$R,DEALS!$A:$A,{"*REFUND*","*EXECUTED*"},DEALS!$O:$O,$B$2,DEALS!$E:$E,">="&$C$4,DEALS!$E:$E,"<="&$U$4,DEALS!$S:$S,P$6,DEALS!$U:$U,$K14,DEALS!$V:$V,"<>*RECEIVED*",DEALS!$V:$V,"<>*EXECUTED*"))} -> 0 | Q14: {=SUMIFS(FLOWS!$C:$C,FLOWS!$A:$A,$B$2,FLOWS!$E:$E,$K14,FLOWS!$D:$D,Q$6,FLOWS!$H:$H,">="&$C$4,FLOWS!$H:$H,"<="&$U$4)+SUM(SUMIFS(DEALS!$J:$J,DEALS!$A:$A,{"*REFUND*","*EXECUTED*"},DEALS!$G:$G,$B$2,DEALS!$E:$E,">="&$C$4,DEALS!$E:$E,"<="&$U$4,DEALS!$K:$K,Q$6,DEALS!$M:$M,$K14,DEALS!$N:$N,"<>*RECEIVED*",DEALS!$N:$N,"<>*EXECUTED*"))+SUM(SUMIFS(DEALS!$R:$R,DEALS!$A:$A,{"*REFUND*","*EXECUTED*"},DEALS!$O:$O,$B$2,DEALS!$E:$E,">="&$C$4,DEALS!$E:$E,"<="&$U$4,DEALS!$S:$S,Q$6,DEALS!$U:$U,$K14,DEALS!$V:$V,"<>*RECEIVED*",DEALS!$V:$V,"<>*EXECUTED*"))} -> 0 | R14: =L14*VLOOKUP(L$6,'FX RATES'!$E$1:$F$50,2,FALSE)+M14*VLOOKUP(M$6,'FX RATES'!$E$1:$F$50,2,FALSE)+N14*VLOOKUP(N$6,'FX RATES'!$E$1:$F$50,2,FALSE)+O14*VLOOKUP(O$6,'FX RATES'!$E$1:$F$50,2,FALSE)+P14*VLOOKUP(P$6,'FX RATES'!$E$1:$F$50,2,FALSE)+Q14*VLOOKUP(Q$6,'FX RATES'!$E$1:$F$50,2,FALSE) -> 0 | T14: =B14 -> UAB | U14: {=SUMIFS(BALANCES!$C:$C,BALANCES!$A:$A,$B$2,BALANCES!$B:$B,$T14,BALANCES!$D:$D,U$6)+SUMIFS(FLOWS!$C:$C,FLOWS!$A:$A,$B$2,FLOWS!$E:$E,$T14,FLOWS!$D:$D,U$6,FLOWS!$H:$H,"<="&$U$4)+SUM(SUMIFS(DEALS!$J:$J,DEALS!$A:$A,{"*REFUND*","*EXECUTED*"},DEALS!$G:$G,$B$2,DEALS!$E:$E,"<="&$U$4,DEALS!$K:$K,U$6,DEALS!$M:$M,$T14,DEALS!$N:$N,"<>*RECEIVED*",DEALS!$N:$N,"<>*EXECUTED*"))+SUM(SUMIFS(DEALS!$R:$R,DEALS!$A:$A,{"*REFUND*","*EXECUTED*"},DEALS!$O:$O,$B$2,DEALS!$E:$E,"<="&$U$4,DEALS!$S:$S,U$6,DEALS!$U:$U,$T14,DEALS!$V:$V,"<>*RECEIVED*",DEALS!$V:$V,"<>*EXECUTED*"))} -> 703.27 | V14: {=SUMIFS(BALANCES!$C:$C,BALANCES!$A:$A,$B$2,BALANCES!$B:$B,$T14,BALANCES!$D:$D,V$6)+SUMIFS(FLOWS!$C:$C,FLOWS!$A:$A,$B$2,FLOWS!$E:$E,$T14,FLOWS!$D:$D,V$6,FLOWS!$H:$H,"<="&$U$4)+SUM(SUMIFS(DEALS!$J:$J,DEALS!$A:$A,{"*REFUND*","*EXECUTED*"},DEALS!$G:$G,$B$2,DEALS!$E:$E,"<="&$U$4,DEALS!$K:$K,V$6,DEALS!$M:$M,$T14,DEALS!$N:$N,"<>*RECEIVED*",DEALS!$N:$N,"<>*EXECUTED*"))+SUM(SUMIFS(DEALS!$R:$R,DEALS!$A:$A,{"*REFUND*","*EXECUTED*"},DEALS!$O:$O,$B$2,DEALS!$E:$E,"<="&$U$4,DEALS!$S:$S,V$6,DEALS!$U:$U,$T14,DEALS!$V:$V,"<>*RECEIVED*",DEALS!$V:$V,"<>*EXECUTED*"))} -> 0 | W14: {=SUMIFS(BALANCES!$C:$C,BALANCES!$A:$A,$B$2,BALANCES!$B:$B,$T14,BALANCES!$D:$D,W$6)+SUMIFS(FLOWS!$C:$C,FLOWS!$A:$A,$B$2,FLOWS!$E:$E,$T14,FLOWS!$D:$D,W$6,FLOWS!$H:$H,"<="&$U$4)+SUM(SUMIFS(DEALS!$J:$J,DEALS!$A:$A,{"*REFUND*","*EXECUTED*"},DEALS!$G:$G,$B$2,DEALS!$E:$E,"<="&$U$4,DEALS!$K:$K,W$6,DEALS!$M:$M,$T14,DEALS!$N:$N,"<>*RECEIVED*",DEALS!$N:$N,"<>*EXECUTED*"))+SUM(SUMIFS(DEALS!$R:$R,DEALS!$A:$A,{"*REFUND*","*EXECUTED*"},DEALS!$O:$O,$B$2,DEALS!$E:$E,"<="&$U$4,DEALS!$S:$S,W$6,DEALS!$U:$U,$T14,DEALS!$V:$V,"<>*RECEIVED*",DEALS!$V:$V,"<>*EXECUTED*"))} -> 0.5 | X14: {=SUMIFS(BALANCES!$C:$C,BALANCES!$A:$A,$B$2,BALANCES!$B:$B,$T14,BALANCES!$D:$D,X$6)+SUMIFS(FLOWS!$C:$C,FLOWS!$A:$A,$B$2,FLOWS!$E:$E,$T14,FLOWS!$D:$D,X$6,FLOWS!$H:$H,"<="&$U$4)+SUM(SUMIFS(DEALS!$J:$J,DEALS!$A:$A,{"*REFUND*","*EXECUTED*"},DEALS!$G:$G,$B$2,DEALS!$E:$E,"<="&$U$4,DEALS!$K:$K,X$6,DEALS!$M:$M,$T14,DEALS!$N:$N,"<>*RECEIVED*",DEALS!$N:$N,"<>*EXECUTED*"))+SUM(SUMIFS(DEALS!$R:$R,DEALS!$A:$A,{"*REFUND*","*EXECUTED*"},DEALS!$O:$O,$B$2,DEALS!$E:$E,"<="&$U$4,DEALS!$S:$S,X$6,DEALS!$U:$U,$T14,DEALS!$V:$V,"<>*RECEIVED*",DEALS!$V:$V,"<>*EXECUTED*"))} -> 56383.25 | Y14: {=SUMIFS(BALANCES!$C:$C,BALANCES!$A:$A,$B$2,BALANCES!$B:$B,$T14,BALANCES!$D:$D,Y$6)+SUMIFS(FLOWS!$C:$C,FLOWS!$A:$A,$B$2,FLOWS!$E:$E,$T14,FLOWS!$D:$D,Y$6,FLOWS!$H:$H,"<="&$U$4)+SUM(SUMIFS(DEALS!$J:$J,DEALS!$A:$A,{"*REFUND*","*EXECUTED*"},DEALS!$G:$G,$B$2,DEALS!$E:$E,"<="&$U$4,DEALS!$K:$K,Y$6,DEALS!$M:$M,$T14,DEALS!$N:$N,"<>*RECEIVED*",DEALS!$N:$N,"<>*EXECUTED*"))+SUM(SUMIFS(DEALS!$R:$R,DEALS!$A:$A,{"*REFUND*","*EXECUTED*"},DEALS!$O:$O,$B$2,DEALS!$E:$E,"<="&$U$4,DEALS!$S:$S,Y$6,DEALS!$U:$U,$T14,DEALS!$V:$V,"<>*RECEIVED*",DEALS!$V:$V,"<>*EXECUTED*"))} -> 0 | Z14: {=SUMIFS(BALANCES!$C:$C,BALANCES!$A:$A,$B$2,BALANCES!$B:$B,$T14,BALANCES!$D:$D,Z$6)+SUMIFS(FLOWS!$C:$C,FLOWS!$A:$A,$B$2,FLOWS!$E:$E,$T14,FLOWS!$D:$D,Z$6,FLOWS!$H:$H,"<="&$U$4)+SUM(SUMIFS(DEALS!$J:$J,DEALS!$A:$A,{"*REFUND*","*EXECUTED*"},DEALS!$G:$G,$B$2,DEALS!$E:$E,"<="&$U$4,DEALS!$K:$K,Z$6,DEALS!$M:$M,$T14,DEALS!$N:$N,"<>*RECEIVED*",DEALS!$N:$N,"<>*EXECUTED*"))+SUM(SUMIFS(DEALS!$R:$R,DEALS!$A:$A,{"*REFUND*","*EXECUTED*"},DEALS!$O:$O,$B$2,DEALS!$E:$E,"<="&$U$4,DEALS!$S:$S,Z$6,DEALS!$U:$U,$T14,DEALS!$V:$V,"<>*RECEIVED*",DEALS!$V:$V,"<>*EXECUTED*"))} -> 0 | AA14: =U14*VLOOKUP(U$6,'FX RATES'!$E$1:$F$50,2,FALSE)+V14*VLOOKUP(V$6,'FX RATES'!$E$1:$F$50,2,FALSE)+W14*VLOOKUP(W$6,'FX RATES'!$E$1:$F$50,2,FALSE)+X14*VLOOKUP(X$6,'FX RATES'!$E$1:$F$50,2,FALSE)+Y14*VLOOKUP(Y$6,'FX RATES'!$E$1:$F$50,2,FALSE)+Z14*VLOOKUP(Z$6,'FX RATES'!$E$1:$F$50,2,FALSE) -> 16055.749 | AC14: =I14+R14-AA14 -> 0
B15: ICBC CM | C15: {=SUMIFS(BALANCES!$C:$C,BALANCES!$A:$A,$B$2,BALANCES!$B:$B,$B15,BALANCES!$D:$D,C$6)+SUMIFS(FLOWS!$C:$C,FLOWS!$A:$A,$B$2,FLOWS!$E:$E,$B15,FLOWS!$D:$D,C$6,FLOWS!$H:$H,"<"&$C$4)+SUM(SUMIFS(DEALS!$J:$J,DEALS!$A:$A,{"*REFUND*","*EXECUTED*"},DEALS!$G:$G,$B$2,DEALS!$E:$E,"<"&$C$4,DEALS!$K:$K,C$6,DEALS!$M:$M,$B15,DEALS!$N:$N,"<>*RECEIVED*",DEALS!$N:$N,"<>*EXECUTED*"))+SUM(SUMIFS(DEALS!$R:$R,DEALS!$A:$A,{"*REFUND*","*EXECUTED*"},DEALS!$O:$O,$B$2,DEALS!$E:$E,"<"&$C$4,DEALS!$S:$S,C$6,DEALS!$U:$U,$B15,DEALS!$V:$V,"<>*RECEIVED*",DEALS!$V:$V,"<>*EXECUTED*"))} -> 0.52 | D15: {=SUMIFS(BALANCES!$C:$C,BALANCES!$A:$A,$B$2,BALANCES!$B:$B,$B15,BALANCES!$D:$D,D$6)+SUMIFS(FLOWS!$C:$C,FLOWS!$A:$A,$B$2,FLOWS!$E:$E,$B15,FLOWS!$D:$D,D$6,FLOWS!$H:$H,"<"&$C$4)+SUM(SUMIFS(DEALS!$J:$J,DEALS!$A:$A,{"*REFUND*","*EXECUTED*"},DEALS!$G:$G,$B$2,DEALS!$E:$E,"<"&$C$4,DEALS!$K:$K,D$6,DEALS!$M:$M,$B15,DEALS!$N:$N,"<>*RECEIVED*",DEALS!$N:$N,"<>*EXECUTED*"))+SUM(SUMIFS(DEALS!$R:$R,DEALS!$A:$A,{"*REFUND*","*EXECUTED*"},DEALS!$O:$O,$B$2,DEALS!$E:$E,"<"&$C$4,DEALS!$S:$S,D$6,DEALS!$U:$U,$B15,DEALS!$V:$V,"<>*RECEIVED*",DEALS!$V:$V,"<>*EXECUTED*"))} -> 0 | E15: {=SUMIFS(BALANCES!$C:$C,BALANCES!$A:$A,$B$2,BALANCES!$B:$B,$B15,BALANCES!$D:$D,E$6)+SUMIFS(FLOWS!$C:$C,FLOWS!$A:$A,$B$2,FLOWS!$E:$E,$B15,FLOWS!$D:$D,E$6,FLOWS!$H:$H,"<"&$C$4)+SUM(SUMIFS(DEALS!$J:$J,DEALS!$A:$A,{"*REFUND*","*EXECUTED*"},DEALS!$G:$G,$B$2,DEALS!$E:$E,"<"&$C$4,DEALS!$K:$K,E$6,DEALS!$M:$M,$B15,DEALS!$N:$N,"<>*RECEIVED*",DEALS!$N:$N,"<>*EXECUTED*"))+SUM(SUMIFS(DEALS!$R:$R,DEALS!$A:$A,{"*REFUND*","*EXECUTED*"},DEALS!$O:$O,$B$2,DEALS!$E:$E,"<"&$C$4,DEALS!$S:$S,E$6,DEALS!$U:$U,$B15,DEALS!$V:$V,"<>*RECEIVED*",DEALS!$V:$V,"<>*EXECUTED*"))} -> 80965.19 | F15: {=SUMIFS(BALANCES!$C:$C,BALANCES!$A:$A,$B$2,BALANCES!$B:$B,$B15,BALANCES!$D:$D,F$6)+SUMIFS(FLOWS!$C:$C,FLOWS!$A:$A,$B$2,FLOWS!$E:$E,$B15,FLOWS!$D:$D,F$6,FLOWS!$H:$H,"<"&$C$4)+SUM(SUMIFS(DEALS!$J:$J,DEALS!$A:$A,{"*REFUND*","*EXECUTED*"},DEALS!$G:$G,$B$2,DEALS!$E:$E,"<"&$C$4,DEALS!$K:$K,F$6,DEALS!$M:$M,$B15,DEALS!$N:$N,"<>*RECEIVED*",DEALS!$N:$N,"<>*EXECUTED*"))+SUM(SUMIFS(DEALS!$R:$R,DEALS!$A:$A,{"*REFUND*","*EXECUTED*"},DEALS!$O:$O,$B$2,DEALS!$E:$E,"<"&$C$4,DEALS!$S:$S,F$6,DEALS!$U:$U,$B15,DEALS!$V:$V,"<>*RECEIVED*",DEALS!$V:$V,"<>*EXECUTED*"))} -> 0 | G15: {=SUMIFS(BALANCES!$C:$C,BALANCES!$A:$A,$B$2,BALANCES!$B:$B,$B15,BALANCES!$D:$D,G$6)+SUMIFS(FLOWS!$C:$C,FLOWS!$A:$A,$B$2,FLOWS!$E:$E,$B15,FLOWS!$D:$D,G$6,FLOWS!$H:$H,"<"&$C$4)+SUM(SUMIFS(DEALS!$J:$J,DEALS!$A:$A,{"*REFUND*","*EXECUTED*"},DEALS!$G:$G,$B$2,DEALS!$E:$E,"<"&$C$4,DEALS!$K:$K,G$6,DEALS!$M:$M,$B15,DEALS!$N:$N,"<>*RECEIVED*",DEALS!$N:$N,"<>*EXECUTED*"))+SUM(SUMIFS(DEALS!$R:$R,DEALS!$A:$A,{"*REFUND*","*EXECUTED*"},DEALS!$O:$O,$B$2,DEALS!$E:$E,"<"&$C$4,DEALS!$S:$S,G$6,DEALS!$U:$U,$B15,DEALS!$V:$V,"<>*RECEIVED*",DEALS!$V:$V,"<>*EXECUTED*"))} -> 0 | H15: {=SUMIFS(BALANCES!$C:$C,BALANCES!$A:$A,$B$2,BALANCES!$B:$B,$B15,BALANCES!$D:$D,H$6)+SUMIFS(FLOWS!$C:$C,FLOWS!$A:$A,$B$2,FLOWS!$E:$E,$B15,FLOWS!$D:$D,H$6,FLOWS!$H:$H,"<"&$C$4)+SUM(SUMIFS(DEALS!$J:$J,DEALS!$A:$A,{"*REFUND*","*EXECUTED*"},DEALS!$G:$G,$B$2,DEALS!$E:$E,"<"&$C$4,DEALS!$K:$K,H$6,DEALS!$M:$M,$B15,DEALS!$N:$N,"<>*RECEIVED*",DEALS!$N:$N,"<>*EXECUTED*"))+SUM(SUMIFS(DEALS!$R:$R,DEALS!$A:$A,{"*REFUND*","*EXECUTED*"},DEALS!$O:$O,$B$2,DEALS!$E:$E,"<"&$C$4,DEALS!$S:$S,H$6,DEALS!$U:$U,$B15,DEALS!$V:$V,"<>*RECEIVED*",DEALS!$V:$V,"<>*EXECUTED*"))} -> 0 | I15: =C15*VLOOKUP(C$6,'FX RATES'!$E$1:$F$50,2,FALSE)+D15*VLOOKUP(D$6,'FX RATES'!$E$1:$F$50,2,FALSE)+E15*VLOOKUP(E$6,'FX RATES'!$E$1:$F$50,2,FALSE)+F15*VLOOKUP(F$6,'FX RATES'!$E$1:$F$50,2,FALSE)+G15*VLOOKUP(G$6,'FX RATES'!$E$1:$F$50,2,FALSE)+H15*VLOOKUP(H$6,'FX RATES'!$E$1:$F$50,2,FALSE) -> 11721.017 | K15: =B15 -> ICBC CM | L15: {=SUMIFS(FLOWS!$C:$C,FLOWS!$A:$A,$B$2,FLOWS!$E:$E,$K15,FLOWS!$D:$D,L$6,FLOWS!$H:$H,">="&$C$4,FLOWS!$H:$H,"<="&$U$4)+SUM(SUMIFS(DEALS!$J:$J,DEALS!$A:$A,{"*REFUND*","*EXECUTED*"},DEALS!$G:$G,$B$2,DEALS!$E:$E,">="&$C$4,DEALS!$E:$E,"<="&$U$4,DEALS!$K:$K,L$6,DEALS!$M:$M,$K15,DEALS!$N:$N,"<>*RECEIVED*",DEALS!$N:$N,"<>*EXECUTED*"))+SUM(SUMIFS(DEALS!$R:$R,DEALS!$A:$A,{"*REFUND*","*EXECUTED*"},DEALS!$O:$O,$B$2,DEALS!$E:$E,">="&$C$4,DEALS!$E:$E,"<="&$U$4,DEALS!$S:$S,L$6,DEALS!$U:$U,$K15,DEALS!$V:$V,"<>*RECEIVED*",DEALS!$V:$V,"<>*EXECUTED*"))} -> 0 | M15: {=SUMIFS(FLOWS!$C:$C,FLOWS!$A:$A,$B$2,FLOWS!$E:$E,$K15,FLOWS!$D:$D,M$6,FLOWS!$H:$H,">="&$C$4,FLOWS!$H:$H,"<="&$U$4)+SUM(SUMIFS(DEALS!$J:$J,DEALS!$A:$A,{"*REFUND*","*EXECUTED*"},DEALS!$G:$G,$B$2,DEALS!$E:$E,">="&$C$4,DEALS!$E:$E,"<="&$U$4,DEALS!$K:$K,M$6,DEALS!$M:$M,$K15,DEALS!$N:$N,"<>*RECEIVED*",DEALS!$N:$N,"<>*EXECUTED*"))+SUM(SUMIFS(DEALS!$R:$R,DEALS!$A:$A,{"*REFUND*","*EXECUTED*"},DEALS!$O:$O,$B$2,DEALS!$E:$E,">="&$C$4,DEALS!$E:$E,"<="&$U$4,DEALS!$S:$S,M$6,DEALS!$U:$U,$K15,DEALS!$V:$V,"<>*RECEIVED*",DEALS!$V:$V,"<>*EXECUTED*"))} -> 0 | N15: {=SUMIFS(FLOWS!$C:$C,FLOWS!$A:$A,$B$2,FLOWS!$E:$E,$K15,FLOWS!$D:$D,N$6,FLOWS!$H:$H,">="&$C$4,FLOWS!$H:$H,"<="&$U$4)+SUM(SUMIFS(DEALS!$J:$J,DEALS!$A:$A,{"*REFUND*","*EXECUTED*"},DEALS!$G:$G,$B$2,DEALS!$E:$E,">="&$C$4,DEALS!$E:$E,"<="&$U$4,DEALS!$K:$K,N$6,DEALS!$M:$M,$K15,DEALS!$N:$N,"<>*RECEIVED*",DEALS!$N:$N,"<>*EXECUTED*"))+SUM(SUMIFS(DEALS!$R:$R,DEALS!$A:$A,{"*REFUND*","*EXECUTED*"},DEALS!$O:$O,$B$2,DEALS!$E:$E,">="&$C$4,DEALS!$E:$E,"<="&$U$4,DEALS!$S:$S,N$6,DEALS!$U:$U,$K15,DEALS!$V:$V,"<>*RECEIVED*",DEALS!$V:$V,"<>*EXECUTED*"))} -> 0 | O15: {=SUMIFS(FLOWS!$C:$C,FLOWS!$A:$A,$B$2,FLOWS!$E:$E,$K15,FLOWS!$D:$D,O$6,FLOWS!$H:$H,">="&$C$4,FLOWS!$H:$H,"<="&$U$4)+SUM(SUMIFS(DEALS!$J:$J,DEALS!$A:$A,{"*REFUND*","*EXECUTED*"},DEALS!$G:$G,$B$2,DEALS!$E:$E,">="&$C$4,DEALS!$E:$E,"<="&$U$4,DEALS!$K:$K,O$6,DEALS!$M:$M,$K15,DEALS!$N:$N,"<>*RECEIVED*",DEALS!$N:$N,"<>*EXECUTED*"))+SUM(SUMIFS(DEALS!$R:$R,DEALS!$A:$A,{"*REFUND*","*EXECUTED*"},DEALS!$O:$O,$B$2,DEALS!$E:$E,">="&$C$4,DEALS!$E:$E,"<="&$U$4,DEALS!$S:$S,O$6,DEALS!$U:$U,$K15,DEALS!$V:$V,"<>*RECEIVED*",DEALS!$V:$V,"<>*EXECUTED*"))} -> 0 | P15: {=SUMIFS(FLOWS!$C:$C,FLOWS!$A:$A,$B$2,FLOWS!$E:$E,$K15,FLOWS!$D:$D,P$6,FLOWS!$H:$H,">="&$C$4,FLOWS!$H:$H,"<="&$U$4)+SUM(SUMIFS(DEALS!$J:$J,DEALS!$A:$A,{"*REFUND*","*EXECUTED*"},DEALS!$G:$G,$B$2,DEALS!$E:$E,">="&$C$4,DEALS!$E:$E,"<="&$U$4,DEALS!$K:$K,P$6,DEALS!$M:$M,$K15,DEALS!$N:$N,"<>*RECEIVED*",DEALS!$N:$N,"<>*EXECUTED*"))+SUM(SUMIFS(DEALS!$R:$R,DEALS!$A:$A,{"*REFUND*","*EXECUTED*"},DEALS!$O:$O,$B$2,DEALS!$E:$E,">="&$C$4,DEALS!$E:$E,"<="&$U$4,DEALS!$S:$S,P$6,DEALS!$U:$U,$K15,DEALS!$V:$V,"<>*RECEIVED*",DEALS!$V:$V,"<>*EXECUTED*"))} -> 0 | Q15: {=SUMIFS(FLOWS!$C:$C,FLOWS!$A:$A,$B$2,FLOWS!$E:$E,$K15,FLOWS!$D:$D,Q$6,FLOWS!$H:$H,">="&$C$4,FLOWS!$H:$H,"<="&$U$4)+SUM(SUMIFS(DEALS!$J:$J,DEALS!$A:$A,{"*REFUND*","*EXECUTED*"},DEALS!$G:$G,$B$2,DEALS!$E:$E,">="&$C$4,DEALS!$E:$E,"<="&$U$4,DEALS!$K:$K,Q$6,DEALS!$M:$M,$K15,DEALS!$N:$N,"<>*RECEIVED*",DEALS!$N:$N,"<>*EXECUTED*"))+SUM(SUMIFS(DEALS!$R:$R,DEALS!$A:$A,{"*REFUND*","*EXECUTED*"},DEALS!$O:$O,$B$2,DEALS!$E:$E,">="&$C$4,DEALS!$E:$E,"<="&$U$4,DEALS!$S:$S,Q$6,DEALS!$U:$U,$K15,DEALS!$V:$V,"<>*RECEIVED*",DEALS!$V:$V,"<>*EXECUTED*"))} -> 0 | R15: =L15*VLOOKUP(L$6,'FX RATES'!$E$1:$F$50,2,FALSE)+M15*VLOOKUP(M$6,'FX RATES'!$E$1:$F$50,2,FALSE)+N15*VLOOKUP(N$6,'FX RATES'!$E$1:$F$50,2,FALSE)+O15*VLOOKUP(O$6,'FX RATES'!$E$1:$F$50,2,FALSE)+P15*VLOOKUP(P$6,'FX RATES'!$E$1:$F$50,2,FALSE)+Q15*VLOOKUP(Q$6,'FX RATES'!$E$1:$F$50,2,FALSE) -> 0 | T15: =B15 -> ICBC CM | U15: {=SUMIFS(BALANCES!$C:$C,BALANCES!$A:$A,$B$2,BALANCES!$B:$B,$T15,BALANCES!$D:$D,U$6)+SUMIFS(FLOWS!$C:$C,FLOWS!$A:$A,$B$2,FLOWS!$E:$E,$T15,FLOWS!$D:$D,U$6,FLOWS!$H:$H,"<="&$U$4)+SUM(SUMIFS(DEALS!$J:$J,DEALS!$A:$A,{"*REFUND*","*EXECUTED*"},DEALS!$G:$G,$B$2,DEALS!$E:$E,"<="&$U$4,DEALS!$K:$K,U$6,DEALS!$M:$M,$T15,DEALS!$N:$N,"<>*RECEIVED*",DEALS!$N:$N,"<>*EXECUTED*"))+SUM(SUMIFS(DEALS!$R:$R,DEALS!$A:$A,{"*REFUND*","*EXECUTED*"},DEALS!$O:$O,$B$2,DEALS!$E:$E,"<="&$U$4,DEALS!$S:$S,U$6,DEALS!$U:$U,$T15,DEALS!$V:$V,"<>*RECEIVED*",DEALS!$V:$V,"<>*EXECUTED*"))} -> 0.52 | V15: {=SUMIFS(BALANCES!$C:$C,BALANCES!$A:$A,$B$2,BALANCES!$B:$B,$T15,BALANCES!$D:$D,V$6)+SUMIFS(FLOWS!$C:$C,FLOWS!$A:$A,$B$2,FLOWS!$E:$E,$T15,FLOWS!$D:$D,V$6,FLOWS!$H:$H,"<="&$U$4)+SUM(SUMIFS(DEALS!$J:$J,DEALS!$A:$A,{"*REFUND*","*EXECUTED*"},DEALS!$G:$G,$B$2,DEALS!$E:$E,"<="&$U$4,DEALS!$K:$K,V$6,DEALS!$M:$M,$T15,DEALS!$N:$N,"<>*RECEIVED*",DEALS!$N:$N,"<>*EXECUTED*"))+SUM(SUMIFS(DEALS!$R:$R,DEALS!$A:$A,{"*REFUND*","*EXECUTED*"},DEALS!$O:$O,$B$2,DEALS!$E:$E,"<="&$U$4,DEALS!$S:$S,V$6,DEALS!$U:$U,$T15,DEALS!$V:$V,"<>*RECEIVED*",DEALS!$V:$V,"<>*EXECUTED*"))} -> 0 | W15: {=SUMIFS(BALANCES!$C:$C,BALANCES!$A:$A,$B$2,BALANCES!$B:$B,$T15,BALANCES!$D:$D,W$6)+SUMIFS(FLOWS!$C:$C,FLOWS!$A:$A,$B$2,FLOWS!$E:$E,$T15,FLOWS!$D:$D,W$6,FLOWS!$H:$H,"<="&$U$4)+SUM(SUMIFS(DEALS!$J:$J,DEALS!$A:$A,{"*REFUND*","*EXECUTED*"},DEALS!$G:$G,$B$2,DEALS!$E:$E,"<="&$U$4,DEALS!$K:$K,W$6,DEALS!$M:$M,$T15,DEALS!$N:$N,"<>*RECEIVED*",DEALS!$N:$N,"<>*EXECUTED*"))+SUM(SUMIFS(DEALS!$R:$R,DEALS!$A:$A,{"*REFUND*","*EXECUTED*"},DEALS!$O:$O,$B$2,DEALS!$E:$E,"<="&$U$4,DEALS!$S:$S,W$6,DEALS!$U:$U,$T15,DEALS!$V:$V,"<>*RECEIVED*",DEALS!$V:$V,"<>*EXECUTED*"))} -> 80965.19 | X15: {=SUMIFS(BALANCES!$C:$C,BALANCES!$A:$A,$B$2,BALANCES!$B:$B,$T15,BALANCES!$D:$D,X$6)+SUMIFS(FLOWS!$C:$C,FLOWS!$A:$A,$B$2,FLOWS!$E:$E,$T15,FLOWS!$D:$D,X$6,FLOWS!$H:$H,"<="&$U$4)+SUM(SUMIFS(DEALS!$J:$J,DEALS!$A:$A,{"*REFUND*","*EXECUTED*"},DEALS!$G:$G,$B$2,DEALS!$E:$E,"<="&$U$4,DEALS!$K:$K,X$6,DEALS!$M:$M,$T15,DEALS!$N:$N,"<>*RECEIVED*",DEALS!$N:$N,"<>*EXECUTED*"))+SUM(SUMIFS(DEALS!$R:$R,DEALS!$A:$A,{"*REFUND*","*EXECUTED*"},DEALS!$O:$O,$B$2,DEALS!$E:$E,"<="&$U$4,DEALS!$S:$S,X$6,DEALS!$U:$U,$T15,DEALS!$V:$V,"<>*RECEIVED*",DEALS!$V:$V,"<>*EXECUTED*"))} -> 0 | Y15: {=SUMIFS(BALANCES!$C:$C,BALANCES!$A:$A,$B$2,BALANCES!$B:$B,$T15,BALANCES!$D:$D,Y$6)+SUMIFS(FLOWS!$C:$C,FLOWS!$A:$A,$B$2,FLOWS!$E:$E,$T15,FLOWS!$D:$D,Y$6,FLOWS!$H:$H,"<="&$U$4)+SUM(SUMIFS(DEALS!$J:$J,DEALS!$A:$A,{"*REFUND*","*EXECUTED*"},DEALS!$G:$G,$B$2,DEALS!$E:$E,"<="&$U$4,DEALS!$K:$K,Y$6,DEALS!$M:$M,$T15,DEALS!$N:$N,"<>*RECEIVED*",DEALS!$N:$N,"<>*EXECUTED*"))+SUM(SUMIFS(DEALS!$R:$R,DEALS!$A:$A,{"*REFUND*","*EXECUTED*"},DEALS!$O:$O,$B$2,DEALS!$E:$E,"<="&$U$4,DEALS!$S:$S,Y$6,DEALS!$U:$U,$T15,DEALS!$V:$V,"<>*RECEIVED*",DEALS!$V:$V,"<>*EXECUTED*"))} -> 0 | Z15: {=SUMIFS(BALANCES!$C:$C,BALANCES!$A:$A,$B$2,BALANCES!$B:$B,$T15,BALANCES!$D:$D,Z$6)+SUMIFS(FLOWS!$C:$C,FLOWS!$A:$A,$B$2,FLOWS!$E:$E,$T15,FLOWS!$D:$D,Z$6,FLOWS!$H:$H,"<="&$U$4)+SUM(SUMIFS(DEALS!$J:$J,DEALS!$A:$A,{"*REFUND*","*EXECUTED*"},DEALS!$G:$G,$B$2,DEALS!$E:$E,"<="&$U$4,DEALS!$K:$K,Z$6,DEALS!$M:$M,$T15,DEALS!$N:$N,"<>*RECEIVED*",DEALS!$N:$N,"<>*EXECUTED*"))+SUM(SUMIFS(DEALS!$R:$R,DEALS!$A:$A,{"*REFUND*","*EXECUTED*"},DEALS!$O:$O,$B$2,DEALS!$E:$E,"<="&$U$4,DEALS!$S:$S,Z$6,DEALS!$U:$U,$T15,DEALS!$V:$V,"<>*RECEIVED*",DEALS!$V:$V,"<>*EXECUTED*"))} -> 0 | AA15: =U15*VLOOKUP(U$6,'FX RATES'!$E$1:$F$50,2,FALSE)+V15*VLOOKUP(V$6,'FX RATES'!$E$1:$F$50,2,FALSE)+W15*VLOOKUP(W$6,'FX RATES'!$E$1:$F$50,2,FALSE)+X15*VLOOKUP(X$6,'FX RATES'!$E$1:$F$50,2,FALSE)+Y15*VLOOKUP(Y$6,'FX RATES'!$E$1:$F$50,2,FALSE)+Z15*VLOOKUP(Z$6,'FX RATES'!$E$1:$F$50,2,FALSE) -> 11721.017 | AC15: =I15+R15-AA15 -> 0
B16: CHZH | C16: {=SUMIFS(BALANCES!$C:$C,BALANCES!$A:$A,$B$2,BALANCES!$B:$B,$B16,BALANCES!$D:$D,C$6)+SUMIFS(FLOWS!$C:$C,FLOWS!$A:$A,$B$2,FLOWS!$E:$E,$B16,FLOWS!$D:$D,C$6,FLOWS!$H:$H,"<"&$C$4)+SUM(SUMIFS(DEALS!$J:$J,DEALS!$A:$A,{"*REFUND*","*EXECUTED*"},DEALS!$G:$G,$B$2,DEALS!$E:$E,"<"&$C$4,DEALS!$K:$K,C$6,DEALS!$M:$M,$B16,DEALS!$N:$N,"<>*RECEIVED*",DEALS!$N:$N,"<>*EXECUTED*"))+SUM(SUMIFS(DEALS!$R:$R,DEALS!$A:$A,{"*REFUND*","*EXECUTED*"},DEALS!$O:$O,$B$2,DEALS!$E:$E,"<"&$C$4,DEALS!$S:$S,C$6,DEALS!$U:$U,$B16,DEALS!$V:$V,"<>*RECEIVED*",DEALS!$V:$V,"<>*EXECUTED*"))} -> 0 | D16: {=SUMIFS(BALANCES!$C:$C,BALANCES!$A:$A,$B$2,BALANCES!$B:$B,$B16,BALANCES!$D:$D,D$6)+SUMIFS(FLOWS!$C:$C,FLOWS!$A:$A,$B$2,FLOWS!$E:$E,$B16,FLOWS!$D:$D,D$6,FLOWS!$H:$H,"<"&$C$4)+SUM(SUMIFS(DEALS!$J:$J,DEALS!$A:$A,{"*REFUND*","*EXECUTED*"},DEALS!$G:$G,$B$2,DEALS!$E:$E,"<"&$C$4,DEALS!$K:$K,D$6,DEALS!$M:$M,$B16,DEALS!$N:$N,"<>*RECEIVED*",DEALS!$N:$N,"<>*EXECUTED*"))+SUM(SUMIFS(DEALS!$R:$R,DEALS!$A:$A,{"*REFUND*","*EXECUTED*"},DEALS!$O:$O,$B$2,DEALS!$E:$E,"<"&$C$4,DEALS!$S:$S,D$6,DEALS!$U:$U,$B16,DEALS!$V:$V,"<>*RECEIVED*",DEALS!$V:$V,"<>*EXECUTED*"))} -> 0 | E16: {=SUMIFS(BALANCES!$C:$C,BALANCES!$A:$A,$B$2,BALANCES!$B:$B,$B16,BALANCES!$D:$D,E$6)+SUMIFS(FLOWS!$C:$C,FLOWS!$A:$A,$B$2,FLOWS!$E:$E,$B16,FLOWS!$D:$D,E$6,FLOWS!$H:$H,"<"&$C$4)+SUM(SUMIFS(DEALS!$J:$J,DEALS!$A:$A,{"*REFUND*","*EXECUTED*"},DEALS!$G:$G,$B$2,DEALS!$E:$E,"<"&$C$4,DEALS!$K:$K,E$6,DEALS!$M:$M,$B16,DEALS!$N:$N,"<>*RECEIVED*",DEALS!$N:$N,"<>*EXECUTED*"))+SUM(SUMIFS(DEALS!$R:$R,DEALS!$A:$A,{"*REFUND*","*EXECUTED*"},DEALS!$O:$O,$B$2,DEALS!$E:$E,"<"&$C$4,DEALS!$S:$S,E$6,DEALS!$U:$U,$B16,DEALS!$V:$V,"<>*RECEIVED*",DEALS!$V:$V,"<>*EXECUTED*"))} -> 9899.35 | F16: {=SUMIFS(BALANCES!$C:$C,BALANCES!$A:$A,$B$2,BALANCES!$B:$B,$B16,BALANCES!$D:$D,F$6)+SUMIFS(FLOWS!$C:$C,FLOWS!$A:$A,$B$2,FLOWS!$E:$E,$B16,FLOWS!$D:$D,F$6,FLOWS!$H:$H,"<"&$C$4)+SUM(SUMIFS(DEALS!$J:$J,DEALS!$A:$A,{"*REFUND*","*EXECUTED*"},DEALS!$G:$G,$B$2,DEALS!$E:$E,"<"&$C$4,DEALS!$K:$K,F$6,DEALS!$M:$M,$B16,DEALS!$N:$N,"<>*RECEIVED*",DEALS!$N:$N,"<>*EXECUTED*"))+SUM(SUMIFS(DEALS!$R:$R,DEALS!$A:$A,{"*REFUND*","*EXECUTED*"},DEALS!$O:$O,$B$2,DEALS!$E:$E,"<"&$C$4,DEALS!$S:$S,F$6,DEALS!$U:$U,$B16,DEALS!$V:$V,"<>*RECEIVED*",DEALS!$V:$V,"<>*EXECUTED*"))} -> 0 | G16: {=SUMIFS(BALANCES!$C:$C,BALANCES!$A:$A,$B$2,BALANCES!$B:$B,$B16,BALANCES!$D:$D,G$6)+SUMIFS(FLOWS!$C:$C,FLOWS!$A:$A,$B$2,FLOWS!$E:$E,$B16,FLOWS!$D:$D,G$6,FLOWS!$H:$H,"<"&$C$4)+SUM(SUMIFS(DEALS!$J:$J,DEALS!$A:$A,{"*REFUND*","*EXECUTED*"},DEALS!$G:$G,$B$2,DEALS!$E:$E,"<"&$C$4,DEALS!$K:$K,G$6,DEALS!$M:$M,$B16,DEALS!$N:$N,"<>*RECEIVED*",DEALS!$N:$N,"<>*EXECUTED*"))+SUM(SUMIFS(DEALS!$R:$R,DEALS!$A:$A,{"*REFUND*","*EXECUTED*"},DEALS!$O:$O,$B$2,DEALS!$E:$E,"<"&$C$4,DEALS!$S:$S,G$6,DEALS!$U:$U,$B16,DEALS!$V:$V,"<>*RECEIVED*",DEALS!$V:$V,"<>*EXECUTED*"))} -> 0 | H16: {=SUMIFS(BALANCES!$C:$C,BALANCES!$A:$A,$B$2,BALANCES!$B:$B,$B16,BALANCES!$D:$D,H$6)+SUMIFS(FLOWS!$C:$C,FLOWS!$A:$A,$B$2,FLOWS!$E:$E,$B16,FLOWS!$D:$D,H$6,FLOWS!$H:$H,"<"&$C$4)+SUM(SUMIFS(DEALS!$J:$J,DEALS!$A:$A,{"*REFUND*","*EXECUTED*"},DEALS!$G:$G,$B$2,DEALS!$E:$E,"<"&$C$4,DEALS!$K:$K,H$6,DEALS!$M:$M,$B16,DEALS!$N:$N,"<>*RECEIVED*",DEALS!$N:$N,"<>*EXECUTED*"))+SUM(SUMIFS(DEALS!$R:$R,DEALS!$A:$A,{"*REFUND*","*EXECUTED*"},DEALS!$O:$O,$B$2,DEALS!$E:$E,"<"&$C$4,DEALS!$S:$S,H$6,DEALS!$U:$U,$B16,DEALS!$V:$V,"<>*RECEIVED*",DEALS!$V:$V,"<>*EXECUTED*"))} -> 0 | I16: =C16*VLOOKUP(C$6,'FX RATES'!$E$1:$F$50,2,FALSE)+D16*VLOOKUP(D$6,'FX RATES'!$E$1:$F$50,2,FALSE)+E16*VLOOKUP(E$6,'FX RATES'!$E$1:$F$50,2,FALSE)+F16*VLOOKUP(F$6,'FX RATES'!$E$1:$F$50,2,FALSE)+G16*VLOOKUP(G$6,'FX RATES'!$E$1:$F$50,2,FALSE)+H16*VLOOKUP(H$6,'FX RATES'!$E$1:$F$50,2,FALSE) -> 1433.0269 | K16: =B16 -> CHZH | L16: {=SUMIFS(FLOWS!$C:$C,FLOWS!$A:$A,$B$2,FLOWS!$E:$E,$K16,FLOWS!$D:$D,L$6,FLOWS!$H:$H,">="&$C$4,FLOWS!$H:$H,"<="&$U$4)+SUM(SUMIFS(DEALS!$J:$J,DEALS!$A:$A,{"*REFUND*","*EXECUTED*"},DEALS!$G:$G,$B$2,DEALS!$E:$E,">="&$C$4,DEALS!$E:$E,"<="&$U$4,DEALS!$K:$K,L$6,DEALS!$M:$M,$K16,DEALS!$N:$N,"<>*RECEIVED*",DEALS!$N:$N,"<>*EXECUTED*"))+SUM(SUMIFS(DEALS!$R:$R,DEALS!$A:$A,{"*REFUND*","*EXECUTED*"},DEALS!$O:$O,$B$2,DEALS!$E:$E,">="&$C$4,DEALS!$E:$E,"<="&$U$4,DEALS!$S:$S,L$6,DEALS!$U:$U,$K16,DEALS!$V:$V,"<>*RECEIVED*",DEALS!$V:$V,"<>*EXECUTED*"))} -> 0 | M16: {=SUMIFS(FLOWS!$C:$C,FLOWS!$A:$A,$B$2,FLOWS!$E:$E,$K16,FLOWS!$D:$D,M$6,FLOWS!$H:$H,">="&$C$4,FLOWS!$H:$H,"<="&$U$4)+SUM(SUMIFS(DEALS!$J:$J,DEALS!$A:$A,{"*REFUND*","*EXECUTED*"},DEALS!$G:$G,$B$2,DEALS!$E:$E,">="&$C$4,DEALS!$E:$E,"<="&$U$4,DEALS!$K:$K,M$6,DEALS!$M:$M,$K16,DEALS!$N:$N,"<>*RECEIVED*",DEALS!$N:$N,"<>*EXECUTED*"))+SUM(SUMIFS(DEALS!$R:$R,DEALS!$A:$A,{"*REFUND*","*EXECUTED*"},DEALS!$O:$O,$B$2,DEALS!$E:$E,">="&$C$4,DEALS!$E:$E,"<="&$U$4,DEALS!$S:$S,M$6,DEALS!$U:$U,$K16,DEALS!$V:$V,"<>*RECEIVED*",DEALS!$V:$V,"<>*EXECUTED*"))} -> 0 | N16: {=SUMIFS(FLOWS!$C:$C,FLOWS!$A:$A,$B$2,FLOWS!$E:$E,$K16,FLOWS!$D:$D,N$6,FLOWS!$H:$H,">="&$C$4,FLOWS!$H:$H,"<="&$U$4)+SUM(SUMIFS(DEALS!$J:$J,DEALS!$A:$A,{"*REFUND*","*EXECUTED*"},DEALS!$G:$G,$B$2,DEALS!$E:$E,">="&$C$4,DEALS!$E:$E,"<="&$U$4,DEALS!$K:$K,N$6,DEALS!$M:$M,$K16,DEALS!$N:$N,"<>*RECEIVED*",DEALS!$N:$N,"<>*EXECUTED*"))+SUM(SUMIFS(DEALS!$R:$R,DEALS!$A:$A,{"*REFUND*","*EXECUTED*"},DEALS!$O:$O,$B$2,DEALS!$E:$E,">="&$C$4,DEALS!$E:$E,"<="&$U$4,DEALS!$S:$S,N$6,DEALS!$U:$U,$K16,DEALS!$V:$V,"<>*RECEIVED*",DEALS!$V:$V,"<>*EXECUTED*"))} -> 0 | O16: {=SUMIFS(FLOWS!$C:$C,FLOWS!$A:$A,$B$2,FLOWS!$E:$E,$K16,FLOWS!$D:$D,O$6,FLOWS!$H:$H,">="&$C$4,FLOWS!$H:$H,"<="&$U$4)+SUM(SUMIFS(DEALS!$J:$J,DEALS!$A:$A,{"*REFUND*","*EXECUTED*"},DEALS!$G:$G,$B$2,DEALS!$E:$E,">="&$C$4,DEALS!$E:$E,"<="&$U$4,DEALS!$K:$K,O$6,DEALS!$M:$M,$K16,DEALS!$N:$N,"<>*RECEIVED*",DEALS!$N:$N,"<>*EXECUTED*"))+SUM(SUMIFS(DEALS!$R:$R,DEALS!$A:$A,{"*REFUND*","*EXECUTED*"},DEALS!$O:$O,$B$2,DEALS!$E:$E,">="&$C$4,DEALS!$E:$E,"<="&$U$4,DEALS!$S:$S,O$6,DEALS!$U:$U,$K16,DEALS!$V:$V,"<>*RECEIVED*",DEALS!$V:$V,"<>*EXECUTED*"))} -> 0 | P16: {=SUMIFS(FLOWS!$C:$C,FLOWS!$A:$A,$B$2,FLOWS!$E:$E,$K16,FLOWS!$D:$D,P$6,FLOWS!$H:$H,">="&$C$4,FLOWS!$H:$H,"<="&$U$4)+SUM(SUMIFS(DEALS!$J:$J,DEALS!$A:$A,{"*REFUND*","*EXECUTED*"},DEALS!$G:$G,$B$2,DEALS!$E:$E,">="&$C$4,DEALS!$E:$E,"<="&$U$4,DEALS!$K:$K,P$6,DEALS!$M:$M,$K16,DEALS!$N:$N,"<>*RECEIVED*",DEALS!$N:$N,"<>*EXECUTED*"))+SUM(SUMIFS(DEALS!$R:$R,DEALS!$A:$A,{"*REFUND*","*EXECUTED*"},DEALS!$O:$O,$B$2,DEALS!$E:$E,">="&$C$4,DEALS!$E:$E,"<="&$U$4,DEALS!$S:$S,P$6,DEALS!$U:$U,$K16,DEALS!$V:$V,"<>*RECEIVED*",DEALS!$V:$V,"<>*EXECUTED*"))} -> 0 | Q16: {=SUMIFS(FLOWS!$C:$C,FLOWS!$A:$A,$B$2,FLOWS!$E:$E,$K16,FLOWS!$D:$D,Q$6,FLOWS!$H:$H,">="&$C$4,FLOWS!$H:$H,"<="&$U$4)+SUM(SUMIFS(DEALS!$J:$J,DEALS!$A:$A,{"*REFUND*","*EXECUTED*"},DEALS!$G:$G,$B$2,DEALS!$E:$E,">="&$C$4,DEALS!$E:$E,"<="&$U$4,DEALS!$K:$K,Q$6,DEALS!$M:$M,$K16,DEALS!$N:$N,"<>*RECEIVED*",DEALS!$N:$N,"<>*EXECUTED*"))+SUM(SUMIFS(DEALS!$R:$R,DEALS!$A:$A,{"*REFUND*","*EXECUTED*"},DEALS!$O:$O,$B$2,DEALS!$E:$E,">="&$C$4,DEALS!$E:$E,"<="&$U$4,DEALS!$S:$S,Q$6,DEALS!$U:$U,$K16,DEALS!$V:$V,"<>*RECEIVED*",DEALS!$V:$V,"<>*EXECUTED*"))} -> 0 | R16: =L16*VLOOKUP(L$6,'FX RATES'!$E$1:$F$50,2,FALSE)+M16*VLOOKUP(M$6,'FX RATES'!$E$1:$F$50,2,FALSE)+N16*VLOOKUP(N$6,'FX RATES'!$E$1:$F$50,2,FALSE)+O16*VLOOKUP(O$6,'FX RATES'!$E$1:$F$50,2,FALSE)+P16*VLOOKUP(P$6,'FX RATES'!$E$1:$F$50,2,FALSE)+Q16*VLOOKUP(Q$6,'FX RATES'!$E$1:$F$50,2,FALSE) -> 0 | T16: =B16 -> CHZH | U16: {=SUMIFS(BALANCES!$C:$C,BALANCES!$A:$A,$B$2,BALANCES!$B:$B,$T16,BALANCES!$D:$D,U$6)+SUMIFS(FLOWS!$C:$C,FLOWS!$A:$A,$B$2,FLOWS!$E:$E,$T16,FLOWS!$D:$D,U$6,FLOWS!$H:$H,"<="&$U$4)+SUM(SUMIFS(DEALS!$J:$J,DEALS!$A:$A,{"*REFUND*","*EXECUTED*"},DEALS!$G:$G,$B$2,DEALS!$E:$E,"<="&$U$4,DEALS!$K:$K,U$6,DEALS!$M:$M,$T16,DEALS!$N:$N,"<>*RECEIVED*",DEALS!$N:$N,"<>*EXECUTED*"))+SUM(SUMIFS(DEALS!$R:$R,DEALS!$A:$A,{"*REFUND*","*EXECUTED*"},DEALS!$O:$O,$B$2,DEALS!$E:$E,"<="&$U$4,DEALS!$S:$S,U$6,DEALS!$U:$U,$T16,DEALS!$V:$V,"<>*RECEIVED*",DEALS!$V:$V,"<>*EXECUTED*"))} -> 0 | V16: {=SUMIFS(BALANCES!$C:$C,BALANCES!$A:$A,$B$2,BALANCES!$B:$B,$T16,BALANCES!$D:$D,V$6)+SUMIFS(FLOWS!$C:$C,FLOWS!$A:$A,$B$2,FLOWS!$E:$E,$T16,FLOWS!$D:$D,V$6,FLOWS!$H:$H,"<="&$U$4)+SUM(SUMIFS(DEALS!$J:$J,DEALS!$A:$A,{"*REFUND*","*EXECUTED*"},DEALS!$G:$G,$B$2,DEALS!$E:$E,"<="&$U$4,DEALS!$K:$K,V$6,DEALS!$M:$M,$T16,DEALS!$N:$N,"<>*RECEIVED*",DEALS!$N:$N,"<>*EXECUTED*"))+SUM(SUMIFS(DEALS!$R:$R,DEALS!$A:$A,{"*REFUND*","*EXECUTED*"},DEALS!$O:$O,$B$2,DEALS!$E:$E,"<="&$U$4,DEALS!$S:$S,V$6,DEALS!$U:$U,$T16,DEALS!$V:$V,"<>*RECEIVED*",DEALS!$V:$V,"<>*EXECUTED*"))} -> 0 | W16: {=SUMIFS(BALANCES!$C:$C,BALANCES!$A:$A,$B$2,BALANCES!$B:$B,$T16,BALANCES!$D:$D,W$6)+SUMIFS(FLOWS!$C:$C,FLOWS!$A:$A,$B$2,FLOWS!$E:$E,$T16,FLOWS!$D:$D,W$6,FLOWS!$H:$H,"<="&$U$4)+SUM(SUMIFS(DEALS!$J:$J,DEALS!$A:$A,{"*REFUND*","*EXECUTED*"},DEALS!$G:$G,$B$2,DEALS!$E:$E,"<="&$U$4,DEALS!$K:$K,W$6,DEALS!$M:$M,$T16,DEALS!$N:$N,"<>*RECEIVED*",DEALS!$N:$N,"<>*EXECUTED*"))+SUM(SUMIFS(DEALS!$R:$R,DEALS!$A:$A,{"*REFUND*","*EXECUTED*"},DEALS!$O:$O,$B$2,DEALS!$E:$E,"<="&$U$4,DEALS!$S:$S,W$6,DEALS!$U:$U,$T16,DEALS!$V:$V,"<>*RECEIVED*",DEALS!$V:$V,"<>*EXECUTED*"))} -> 9899.35 | X16: {=SUMIFS(BALANCES!$C:$C,BALANCES!$A:$A,$B$2,BALANCES!$B:$B,$T16,BALANCES!$D:$D,X$6)+SUMIFS(FLOWS!$C:$C,FLOWS!$A:$A,$B$2,FLOWS!$E:$E,$T16,FLOWS!$D:$D,X$6,FLOWS!$H:$H,"<="&$U$4)+SUM(SUMIFS(DEALS!$J:$J,DEALS!$A:$A,{"*REFUND*","*EXECUTED*"},DEALS!$G:$G,$B$2,DEALS!$E:$E,"<="&$U$4,DEALS!$K:$K,X$6,DEALS!$M:$M,$T16,DEALS!$N:$N,"<>*RECEIVED*",DEALS!$N:$N,"<>*EXECUTED*"))+SUM(SUMIFS(DEALS!$R:$R,DEALS!$A:$A,{"*REFUND*","*EXECUTED*"},DEALS!$O:$O,$B$2,DEALS!$E:$E,"<="&$U$4,DEALS!$S:$S,X$6,DEALS!$U:$U,$T16,DEALS!$V:$V,"<>*RECEIVED*",DEALS!$V:$V,"<>*EXECUTED*"))} -> 0 | Y16: {=SUMIFS(BALANCES!$C:$C,BALANCES!$A:$A,$B$2,BALANCES!$B:$B,$T16,BALANCES!$D:$D,Y$6)+SUMIFS(FLOWS!$C:$C,FLOWS!$A:$A,$B$2,FLOWS!$E:$E,$T16,FLOWS!$D:$D,Y$6,FLOWS!$H:$H,"<="&$U$4)+SUM(SUMIFS(DEALS!$J:$J,DEALS!$A:$A,{"*REFUND*","*EXECUTED*"},DEALS!$G:$G,$B$2,DEALS!$E:$E,"<="&$U$4,DEALS!$K:$K,Y$6,DEALS!$M:$M,$T16,DEALS!$N:$N,"<>*RECEIVED*",DEALS!$N:$N,"<>*EXECUTED*"))+SUM(SUMIFS(DEALS!$R:$R,DEALS!$A:$A,{"*REFUND*","*EXECUTED*"},DEALS!$O:$O,$B$2,DEALS!$E:$E,"<="&$U$4,DEALS!$S:$S,Y$6,DEALS!$U:$U,$T16,DEALS!$V:$V,"<>*RECEIVED*",DEALS!$V:$V,"<>*EXECUTED*"))} -> 0 | Z16: {=SUMIFS(BALANCES!$C:$C,BALANCES!$A:$A,$B$2,BALANCES!$B:$B,$T16,BALANCES!$D:$D,Z$6)+SUMIFS(FLOWS!$C:$C,FLOWS!$A:$A,$B$2,FLOWS!$E:$E,$T16,FLOWS!$D:$D,Z$6,FLOWS!$H:$H,"<="&$U$4)+SUM(SUMIFS(DEALS!$J:$J,DEALS!$A:$A,{"*REFUND*","*EXECUTED*"},DEALS!$G:$G,$B$2,DEALS!$E:$E,"<="&$U$4,DEALS!$K:$K,Z$6,DEALS!$M:$M,$T16,DEALS!$N:$N,"<>*RECEIVED*",DEALS!$N:$N,"<>*EXECUTED*"))+SUM(SUMIFS(DEALS!$R:$R,DEALS!$A:$A,{"*REFUND*","*EXECUTED*"},DEALS!$O:$O,$B$2,DEALS!$E:$E,"<="&$U$4,DEALS!$S:$S,Z$6,DEALS!$U:$U,$T16,DEALS!$V:$V,"<>*RECEIVED*",DEALS!$V:$V,"<>*EXECUTED*"))} -> 0 | AA16: =U16*VLOOKUP(U$6,'FX RATES'!$E$1:$F$50,2,FALSE)+V16*VLOOKUP(V$6,'FX RATES'!$E$1:$F$50,2,FALSE)+W16*VLOOKUP(W$6,'FX RATES'!$E$1:$F$50,2,FALSE)+X16*VLOOKUP(X$6,'FX RATES'!$E$1:$F$50,2,FALSE)+Y16*VLOOKUP(Y$6,'FX RATES'!$E$1:$F$50,2,FALSE)+Z16*VLOOKUP(Z$6,'FX RATES'!$E$1:$F$50,2,FALSE) -> 1433.0269 | AC16: =I16+R16-AA16 -> 0
B17: AGORA | C17: {=SUMIFS(BALANCES!$C:$C,BALANCES!$A:$A,$B$2,BALANCES!$B:$B,$B17,BALANCES!$D:$D,C$6)+SUMIFS(FLOWS!$C:$C,FLOWS!$A:$A,$B$2,FLOWS!$E:$E,$B17,FLOWS!$D:$D,C$6,FLOWS!$H:$H,"<"&$C$4)+SUM(SUMIFS(DEALS!$J:$J,DEALS!$A:$A,{"*REFUND*","*EXECUTED*"},DEALS!$G:$G,$B$2,DEALS!$E:$E,"<"&$C$4,DEALS!$K:$K,C$6,DEALS!$M:$M,$B17,DEALS!$N:$N,"<>*RECEIVED*",DEALS!$N:$N,"<>*EXECUTED*"))+SUM(SUMIFS(DEALS!$R:$R,DEALS!$A:$A,{"*REFUND*","*EXECUTED*"},DEALS!$O:$O,$B$2,DEALS!$E:$E,"<"&$C$4,DEALS!$S:$S,C$6,DEALS!$U:$U,$B17,DEALS!$V:$V,"<>*RECEIVED*",DEALS!$V:$V,"<>*EXECUTED*"))} -> 0 | D17: {=SUMIFS(BALANCES!$C:$C,BALANCES!$A:$A,$B$2,BALANCES!$B:$B,$B17,BALANCES!$D:$D,D$6)+SUMIFS(FLOWS!$C:$C,FLOWS!$A:$A,$B$2,FLOWS!$E:$E,$B17,FLOWS!$D:$D,D$6,FLOWS!$H:$H,"<"&$C$4)+SUM(SUMIFS(DEALS!$J:$J,DEALS!$A:$A,{"*REFUND*","*EXECUTED*"},DEALS!$G:$G,$B$2,DEALS!$E:$E,"<"&$C$4,DEALS!$K:$K,D$6,DEALS!$M:$M,$B17,DEALS!$N:$N,"<>*RECEIVED*",DEALS!$N:$N,"<>*EXECUTED*"))+SUM(SUMIFS(DEALS!$R:$R,DEALS!$A:$A,{"*REFUND*","*EXECUTED*"},DEALS!$O:$O,$B$2,DEALS!$E:$E,"<"&$C$4,DEALS!$S:$S,D$6,DEALS!$U:$U,$B17,DEALS!$V:$V,"<>*RECEIVED*",DEALS!$V:$V,"<>*EXECUTED*"))} -> 0 | E17: {=SUMIFS(BALANCES!$C:$C,BALANCES!$A:$A,$B$2,BALANCES!$B:$B,$B17,BALANCES!$D:$D,E$6)+SUMIFS(FLOWS!$C:$C,FLOWS!$A:$A,$B$2,FLOWS!$E:$E,$B17,FLOWS!$D:$D,E$6,FLOWS!$H:$H,"<"&$C$4)+SUM(SUMIFS(DEALS!$J:$J,DEALS!$A:$A,{"*REFUND*","*EXECUTED*"},DEALS!$G:$G,$B$2,DEALS!$E:$E,"<"&$C$4,DEALS!$K:$K,E$6,DEALS!$M:$M,$B17,DEALS!$N:$N,"<>*RECEIVED*",DEALS!$N:$N,"<>*EXECUTED*"))+SUM(SUMIFS(DEALS!$R:$R,DEALS!$A:$A,{"*REFUND*","*EXECUTED*"},DEALS!$O:$O,$B$2,DEALS!$E:$E,"<"&$C$4,DEALS!$S:$S,E$6,DEALS!$U:$U,$B17,DEALS!$V:$V,"<>*RECEIVED*",DEALS!$V:$V,"<>*EXECUTED*"))} -> 0 | F17: {=SUMIFS(BALANCES!$C:$C,BALANCES!$A:$A,$B$2,BALANCES!$B:$B,$B17,BALANCES!$D:$D,F$6)+SUMIFS(FLOWS!$C:$C,FLOWS!$A:$A,$B$2,FLOWS!$E:$E,$B17,FLOWS!$D:$D,F$6,FLOWS!$H:$H,"<"&$C$4)+SUM(SUMIFS(DEALS!$J:$J,DEALS!$A:$A,{"*REFUND*","*EXECUTED*"},DEALS!$G:$G,$B$2,DEALS!$E:$E,"<"&$C$4,DEALS!$K:$K,F$6,DEALS!$M:$M,$B17,DEALS!$N:$N,"<>*RECEIVED*",DEALS!$N:$N,"<>*EXECUTED*"))+SUM(SUMIFS(DEALS!$R:$R,DEALS!$A:$A,{"*REFUND*","*EXECUTED*"},DEALS!$O:$O,$B$2,DEALS!$E:$E,"<"&$C$4,DEALS!$S:$S,F$6,DEALS!$U:$U,$B17,DEALS!$V:$V,"<>*RECEIVED*",DEALS!$V:$V,"<>*EXECUTED*"))} -> 0 | G17: {=SUMIFS(BALANCES!$C:$C,BALANCES!$A:$A,$B$2,BALANCES!$B:$B,$B17,BALANCES!$D:$D,G$6)+SUMIFS(FLOWS!$C:$C,FLOWS!$A:$A,$B$2,FLOWS!$E:$E,$B17,FLOWS!$D:$D,G$6,FLOWS!$H:$H,"<"&$C$4)+SUM(SUMIFS(DEALS!$J:$J,DEALS!$A:$A,{"*REFUND*","*EXECUTED*"},DEALS!$G:$G,$B$2,DEALS!$E:$E,"<"&$C$4,DEALS!$K:$K,G$6,DEALS!$M:$M,$B17,DEALS!$N:$N,"<>*RECEIVED*",DEALS!$N:$N,"<>*EXECUTED*"))+SUM(SUMIFS(DEALS!$R:$R,DEALS!$A:$A,{"*REFUND*","*EXECUTED*"},DEALS!$O:$O,$B$2,DEALS!$E:$E,"<"&$C$4,DEALS!$S:$S,G$6,DEALS!$U:$U,$B17,DEALS!$V:$V,"<>*RECEIVED*",DEALS!$V:$V,"<>*EXECUTED*"))} -> 638946.37 | H17: {=SUMIFS(BALANCES!$C:$C,BALANCES!$A:$A,$B$2,BALANCES!$B:$B,$B17,BALANCES!$D:$D,H$6)+SUMIFS(FLOWS!$C:$C,FLOWS!$A:$A,$B$2,FLOWS!$E:$E,$B17,FLOWS!$D:$D,H$6,FLOWS!$H:$H,"<"&$C$4)+SUM(SUMIFS(DEALS!$J:$J,DEALS!$A:$A,{"*REFUND*","*EXECUTED*"},DEALS!$G:$G,$B$2,DEALS!$E:$E,"<"&$C$4,DEALS!$K:$K,H$6,DEALS!$M:$M,$B17,DEALS!$N:$N,"<>*RECEIVED*",DEALS!$N:$N,"<>*EXECUTED*"))+SUM(SUMIFS(DEALS!$R:$R,DEALS!$A:$A,{"*REFUND*","*EXECUTED*"},DEALS!$O:$O,$B$2,DEALS!$E:$E,"<"&$C$4,DEALS!$S:$S,H$6,DEALS!$U:$U,$B17,DEALS!$V:$V,"<>*RECEIVED*",DEALS!$V:$V,"<>*EXECUTED*"))} -> 0 | I17: =C17*VLOOKUP(C$6,'FX RATES'!$E$1:$F$50,2,FALSE)+D17*VLOOKUP(D$6,'FX RATES'!$E$1:$F$50,2,FALSE)+E17*VLOOKUP(E$6,'FX RATES'!$E$1:$F$50,2,FALSE)+F17*VLOOKUP(F$6,'FX RATES'!$E$1:$F$50,2,FALSE)+G17*VLOOKUP(G$6,'FX RATES'!$E$1:$F$50,2,FALSE)+H17*VLOOKUP(H$6,'FX RATES'!$E$1:$F$50,2,FALSE) -> 8328.2352 | K17: =B17 -> AGORA | L17: {=SUMIFS(FLOWS!$C:$C,FLOWS!$A:$A,$B$2,FLOWS!$E:$E,$K17,FLOWS!$D:$D,L$6,FLOWS!$H:$H,">="&$C$4,FLOWS!$H:$H,"<="&$U$4)+SUM(SUMIFS(DEALS!$J:$J,DEALS!$A:$A,{"*REFUND*","*EXECUTED*"},DEALS!$G:$G,$B$2,DEALS!$E:$E,">="&$C$4,DEALS!$E:$E,"<="&$U$4,DEALS!$K:$K,L$6,DEALS!$M:$M,$K17,DEALS!$N:$N,"<>*RECEIVED*",DEALS!$N:$N,"<>*EXECUTED*"))+SUM(SUMIFS(DEALS!$R:$R,DEALS!$A:$A,{"*REFUND*","*EXECUTED*"},DEALS!$O:$O,$B$2,DEALS!$E:$E,">="&$C$4,DEALS!$E:$E,"<="&$U$4,DEALS!$S:$S,L$6,DEALS!$U:$U,$K17,DEALS!$V:$V,"<>*RECEIVED*",DEALS!$V:$V,"<>*EXECUTED*"))} -> 0 | M17: {=SUMIFS(FLOWS!$C:$C,FLOWS!$A:$A,$B$2,FLOWS!$E:$E,$K17,FLOWS!$D:$D,M$6,FLOWS!$H:$H,">="&$C$4,FLOWS!$H:$H,"<="&$U$4)+SUM(SUMIFS(DEALS!$J:$J,DEALS!$A:$A,{"*REFUND*","*EXECUTED*"},DEALS!$G:$G,$B$2,DEALS!$E:$E,">="&$C$4,DEALS!$E:$E,"<="&$U$4,DEALS!$K:$K,M$6,DEALS!$M:$M,$K17,DEALS!$N:$N,"<>*RECEIVED*",DEALS!$N:$N,"<>*EXECUTED*"))+SUM(SUMIFS(DEALS!$R:$R,DEALS!$A:$A,{"*REFUND*","*EXECUTED*"},DEALS!$O:$O,$B$2,DEALS!$E:$E,">="&$C$4,DEALS!$E:$E,"<="&$U$4,DEALS!$S:$S,M$6,DEALS!$U:$U,$K17,DEALS!$V:$V,"<>*RECEIVED*",DEALS!$V:$V,"<>*EXECUTED*"))} -> 0 | N17: {=SUMIFS(FLOWS!$C:$C,FLOWS!$A:$A,$B$2,FLOWS!$E:$E,$K17,FLOWS!$D:$D,N$6,FLOWS!$H:$H,">="&$C$4,FLOWS!$H:$H,"<="&$U$4)+SUM(SUMIFS(DEALS!$J:$J,DEALS!$A:$A,{"*REFUND*","*EXECUTED*"},DEALS!$G:$G,$B$2,DEALS!$E:$E,">="&$C$4,DEALS!$E:$E,"<="&$U$4,DEALS!$K:$K,N$6,DEALS!$M:$M,$K17,DEALS!$N:$N,"<>*RECEIVED*",DEALS!$N:$N,"<>*EXECUTED*"))+SUM(SUMIFS(DEALS!$R:$R,DEALS!$A:$A,{"*REFUND*","*EXECUTED*"},DEALS!$O:$O,$B$2,DEALS!$E:$E,">="&$C$4,DEALS!$E:$E,"<="&$U$4,DEALS!$S:$S,N$6,DEALS!$U:$U,$K17,DEALS!$V:$V,"<>*RECEIVED*",DEALS!$V:$V,"<>*EXECUTED*"))} -> 0 | O17: {=SUMIFS(FLOWS!$C:$C,FLOWS!$A:$A,$B$2,FLOWS!$E:$E,$K17,FLOWS!$D:$D,O$6,FLOWS!$H:$H,">="&$C$4,FLOWS!$H:$H,"<="&$U$4)+SUM(SUMIFS(DEALS!$J:$J,DEALS!$A:$A,{"*REFUND*","*EXECUTED*"},DEALS!$G:$G,$B$2,DEALS!$E:$E,">="&$C$4,DEALS!$E:$E,"<="&$U$4,DEALS!$K:$K,O$6,DEALS!$M:$M,$K17,DEALS!$N:$N,"<>*RECEIVED*",DEALS!$N:$N,"<>*EXECUTED*"))+SUM(SUMIFS(DEALS!$R:$R,DEALS!$A:$A,{"*REFUND*","*EXECUTED*"},DEALS!$O:$O,$B$2,DEALS!$E:$E,">="&$C$4,DEALS!$E:$E,"<="&$U$4,DEALS!$S:$S,O$6,DEALS!$U:$U,$K17,DEALS!$V:$V,"<>*RECEIVED*",DEALS!$V:$V,"<>*EXECUTED*"))} -> 0 | P17: {=SUMIFS(FLOWS!$C:$C,FLOWS!$A:$A,$B$2,FLOWS!$E:$E,$K17,FLOWS!$D:$D,P$6,FLOWS!$H:$H,">="&$C$4,FLOWS!$H:$H,"<="&$U$4)+SUM(SUMIFS(DEALS!$J:$J,DEALS!$A:$A,{"*REFUND*","*EXECUTED*"},DEALS!$G:$G,$B$2,DEALS!$E:$E,">="&$C$4,DEALS!$E:$E,"<="&$U$4,DEALS!$K:$K,P$6,DEALS!$M:$M,$K17,DEALS!$N:$N,"<>*RECEIVED*",DEALS!$N:$N,"<>*EXECUTED*"))+SUM(SUMIFS(DEALS!$R:$R,DEALS!$A:$A,{"*REFUND*","*EXECUTED*"},DEALS!$O:$O,$B$2,DEALS!$E:$E,">="&$C$4,DEALS!$E:$E,"<="&$U$4,DEALS!$S:$S,P$6,DEALS!$U:$U,$K17,DEALS!$V:$V,"<>*RECEIVED*",DEALS!$V:$V,"<>*EXECUTED*"))} -> 0 | Q17: {=SUMIFS(FLOWS!$C:$C,FLOWS!$A:$A,$B$2,FLOWS!$E:$E,$K17,FLOWS!$D:$D,Q$6,FLOWS!$H:$H,">="&$C$4,FLOWS!$H:$H,"<="&$U$4)+SUM(SUMIFS(DEALS!$J:$J,DEALS!$A:$A,{"*REFUND*","*EXECUTED*"},DEALS!$G:$G,$B$2,DEALS!$E:$E,">="&$C$4,DEALS!$E:$E,"<="&$U$4,DEALS!$K:$K,Q$6,DEALS!$M:$M,$K17,DEALS!$N:$N,"<>*RECEIVED*",DEALS!$N:$N,"<>*EXECUTED*"))+SUM(SUMIFS(DEALS!$R:$R,DEALS!$A:$A,{"*REFUND*","*EXECUTED*"},DEALS!$O:$O,$B$2,DEALS!$E:$E,">="&$C$4,DEALS!$E:$E,"<="&$U$4,DEALS!$S:$S,Q$6,DEALS!$U:$U,$K17,DEALS!$V:$V,"<>*RECEIVED*",DEALS!$V:$V,"<>*EXECUTED*"))} -> 0 | R17: =L17*VLOOKUP(L$6,'FX RATES'!$E$1:$F$50,2,FALSE)+M17*VLOOKUP(M$6,'FX RATES'!$E$1:$F$50,2,FALSE)+N17*VLOOKUP(N$6,'FX RATES'!$E$1:$F$50,2,FALSE)+O17*VLOOKUP(O$6,'FX RATES'!$E$1:$F$50,2,FALSE)+P17*VLOOKUP(P$6,'FX RATES'!$E$1:$F$50,2,FALSE)+Q17*VLOOKUP(Q$6,'FX RATES'!$E$1:$F$50,2,FALSE) -> 0 | T17: =B17 -> AGORA | U17: {=SUMIFS(BALANCES!$C:$C,BALANCES!$A:$A,$B$2,BALANCES!$B:$B,$T17,BALANCES!$D:$D,U$6)+SUMIFS(FLOWS!$C:$C,FLOWS!$A:$A,$B$2,FLOWS!$E:$E,$T17,FLOWS!$D:$D,U$6,FLOWS!$H:$H,"<="&$U$4)+SUM(SUMIFS(DEALS!$J:$J,DEALS!$A:$A,{"*REFUND*","*EXECUTED*"},DEALS!$G:$G,$B$2,DEALS!$E:$E,"<="&$U$4,DEALS!$K:$K,U$6,DEALS!$M:$M,$T17,DEALS!$N:$N,"<>*RECEIVED*",DEALS!$N:$N,"<>*EXECUTED*"))+SUM(SUMIFS(DEALS!$R:$R,DEALS!$A:$A,{"*REFUND*","*EXECUTED*"},DEALS!$O:$O,$B$2,DEALS!$E:$E,"<="&$U$4,DEALS!$S:$S,U$6,DEALS!$U:$U,$T17,DEALS!$V:$V,"<>*RECEIVED*",DEALS!$V:$V,"<>*EXECUTED*"))} -> 0 | V17: {=SUMIFS(BALANCES!$C:$C,BALANCES!$A:$A,$B$2,BALANCES!$B:$B,$T17,BALANCES!$D:$D,V$6)+SUMIFS(FLOWS!$C:$C,FLOWS!$A:$A,$B$2,FLOWS!$E:$E,$T17,FLOWS!$D:$D,V$6,FLOWS!$H:$H,"<="&$U$4)+SUM(SUMIFS(DEALS!$J:$J,DEALS!$A:$A,{"*REFUND*","*EXECUTED*"},DEALS!$G:$G,$B$2,DEALS!$E:$E,"<="&$U$4,DEALS!$K:$K,V$6,DEALS!$M:$M,$T17,DEALS!$N:$N,"<>*RECEIVED*",DEALS!$N:$N,"<>*EXECUTED*"))+SUM(SUMIFS(DEALS!$R:$R,DEALS!$A:$A,{"*REFUND*","*EXECUTED*"},DEALS!$O:$O,$B$2,DEALS!$E:$E,"<="&$U$4,DEALS!$S:$S,V$6,DEALS!$U:$U,$T17,DEALS!$V:$V,"<>*RECEIVED*",DEALS!$V:$V,"<>*EXECUTED*"))} -> 0 | W17: {=SUMIFS(BALANCES!$C:$C,BALANCES!$A:$A,$B$2,BALANCES!$B:$B,$T17,BALANCES!$D:$D,W$6)+SUMIFS(FLOWS!$C:$C,FLOWS!$A:$A,$B$2,FLOWS!$E:$E,$T17,FLOWS!$D:$D,W$6,FLOWS!$H:$H,"<="&$U$4)+SUM(SUMIFS(DEALS!$J:$J,DEALS!$A:$A,{"*REFUND*","*EXECUTED*"},DEALS!$G:$G,$B$2,DEALS!$E:$E,"<="&$U$4,DEALS!$K:$K,W$6,DEALS!$M:$M,$T17,DEALS!$N:$N,"<>*RECEIVED*",DEALS!$N:$N,"<>*EXECUTED*"))+SUM(SUMIFS(DEALS!$R:$R,DEALS!$A:$A,{"*REFUND*","*EXECUTED*"},DEALS!$O:$O,$B$2,DEALS!$E:$E,"<="&$U$4,DEALS!$S:$S,W$6,DEALS!$U:$U,$T17,DEALS!$V:$V,"<>*RECEIVED*",DEALS!$V:$V,"<>*EXECUTED*"))} -> 0 | X17: {=SUMIFS(BALANCES!$C:$C,BALANCES!$A:$A,$B$2,BALANCES!$B:$B,$T17,BALANCES!$D:$D,X$6)+SUMIFS(FLOWS!$C:$C,FLOWS!$A:$A,$B$2,FLOWS!$E:$E,$T17,FLOWS!$D:$D,X$6,FLOWS!$H:$H,"<="&$U$4)+SUM(SUMIFS(DEALS!$J:$J,DEALS!$A:$A,{"*REFUND*","*EXECUTED*"},DEALS!$G:$G,$B$2,DEALS!$E:$E,"<="&$U$4,DEALS!$K:$K,X$6,DEALS!$M:$M,$T17,DEALS!$N:$N,"<>*RECEIVED*",DEALS!$N:$N,"<>*EXECUTED*"))+SUM(SUMIFS(DEALS!$R:$R,DEALS!$A:$A,{"*REFUND*","*EXECUTED*"},DEALS!$O:$O,$B$2,DEALS!$E:$E,"<="&$U$4,DEALS!$S:$S,X$6,DEALS!$U:$U,$T17,DEALS!$V:$V,"<>*RECEIVED*",DEALS!$V:$V,"<>*EXECUTED*"))} -> 0 | Y17: {=SUMIFS(BALANCES!$C:$C,BALANCES!$A:$A,$B$2,BALANCES!$B:$B,$T17,BALANCES!$D:$D,Y$6)+SUMIFS(FLOWS!$C:$C,FLOWS!$A:$A,$B$2,FLOWS!$E:$E,$T17,FLOWS!$D:$D,Y$6,FLOWS!$H:$H,"<="&$U$4)+SUM(SUMIFS(DEALS!$J:$J,DEALS!$A:$A,{"*REFUND*","*EXECUTED*"},DEALS!$G:$G,$B$2,DEALS!$E:$E,"<="&$U$4,DEALS!$K:$K,Y$6,DEALS!$M:$M,$T17,DEALS!$N:$N,"<>*RECEIVED*",DEALS!$N:$N,"<>*EXECUTED*"))+SUM(SUMIFS(DEALS!$R:$R,DEALS!$A:$A,{"*REFUND*","*EXECUTED*"},DEALS!$O:$O,$B$2,DEALS!$E:$E,"<="&$U$4,DEALS!$S:$S,Y$6,DEALS!$U:$U,$T17,DEALS!$V:$V,"<>*RECEIVED*",DEALS!$V:$V,"<>*EXECUTED*"))} -> 638946.37 | Z17: {=SUMIFS(BALANCES!$C:$C,BALANCES!$A:$A,$B$2,BALANCES!$B:$B,$T17,BALANCES!$D:$D,Z$6)+SUMIFS(FLOWS!$C:$C,FLOWS!$A:$A,$B$2,FLOWS!$E:$E,$T17,FLOWS!$D:$D,Z$6,FLOWS!$H:$H,"<="&$U$4)+SUM(SUMIFS(DEALS!$J:$J,DEALS!$A:$A,{"*REFUND*","*EXECUTED*"},DEALS!$G:$G,$B$2,DEALS!$E:$E,"<="&$U$4,DEALS!$K:$K,Z$6,DEALS!$M:$M,$T17,DEALS!$N:$N,"<>*RECEIVED*",DEALS!$N:$N,"<>*EXECUTED*"))+SUM(SUMIFS(DEALS!$R:$R,DEALS!$A:$A,{"*REFUND*","*EXECUTED*"},DEALS!$O:$O,$B$2,DEALS!$E:$E,"<="&$U$4,DEALS!$S:$S,Z$6,DEALS!$U:$U,$T17,DEALS!$V:$V,"<>*RECEIVED*",DEALS!$V:$V,"<>*EXECUTED*"))} -> 0 | AA17: =U17*VLOOKUP(U$6,'FX RATES'!$E$1:$F$50,2,FALSE)+V17*VLOOKUP(V$6,'FX RATES'!$E$1:$F$50,2,FALSE)+W17*VLOOKUP(W$6,'FX RATES'!$E$1:$F$50,2,FALSE)+X17*VLOOKUP(X$6,'FX RATES'!$E$1:$F$50,2,FALSE)+Y17*VLOOKUP(Y$6,'FX RATES'!$E$1:$F$50,2,FALSE)+Z17*VLOOKUP(Z$6,'FX RATES'!$E$1:$F$50,2,FALSE) -> 8328.2352 | AC17: =I17+R17-AA17 -> 0
B18: BK | C18: {=SUMIFS(BALANCES!$C:$C,BALANCES!$A:$A,$B$2,BALANCES!$B:$B,$B18,BALANCES!$D:$D,C$6)+SUMIFS(FLOWS!$C:$C,FLOWS!$A:$A,$B$2,FLOWS!$E:$E,$B18,FLOWS!$D:$D,C$6,FLOWS!$H:$H,"<"&$C$4)+SUM(SUMIFS(DEALS!$J:$J,DEALS!$A:$A,{"*REFUND*","*EXECUTED*"},DEALS!$G:$G,$B$2,DEALS!$E:$E,"<"&$C$4,DEALS!$K:$K,C$6,DEALS!$M:$M,$B18,DEALS!$N:$N,"<>*RECEIVED*",DEALS!$N:$N,"<>*EXECUTED*"))+SUM(SUMIFS(DEALS!$R:$R,DEALS!$A:$A,{"*REFUND*","*EXECUTED*"},DEALS!$O:$O,$B$2,DEALS!$E:$E,"<"&$C$4,DEALS!$S:$S,C$6,DEALS!$U:$U,$B18,DEALS!$V:$V,"<>*RECEIVED*",DEALS!$V:$V,"<>*EXECUTED*"))} -> 0 | D18: {=SUMIFS(BALANCES!$C:$C,BALANCES!$A:$A,$B$2,BALANCES!$B:$B,$B18,BALANCES!$D:$D,D$6)+SUMIFS(FLOWS!$C:$C,FLOWS!$A:$A,$B$2,FLOWS!$E:$E,$B18,FLOWS!$D:$D,D$6,FLOWS!$H:$H,"<"&$C$4)+SUM(SUMIFS(DEALS!$J:$J,DEALS!$A:$A,{"*REFUND*","*EXECUTED*"},DEALS!$G:$G,$B$2,DEALS!$E:$E,"<"&$C$4,DEALS!$K:$K,D$6,DEALS!$M:$M,$B18,DEALS!$N:$N,"<>*RECEIVED*",DEALS!$N:$N,"<>*EXECUTED*"))+SUM(SUMIFS(DEALS!$R:$R,DEALS!$A:$A,{"*REFUND*","*EXECUTED*"},DEALS!$O:$O,$B$2,DEALS!$E:$E,"<"&$C$4,DEALS!$S:$S,D$6,DEALS!$U:$U,$B18,DEALS!$V:$V,"<>*RECEIVED*",DEALS!$V:$V,"<>*EXECUTED*"))} -> 0 | E18: {=SUMIFS(BALANCES!$C:$C,BALANCES!$A:$A,$B$2,BALANCES!$B:$B,$B18,BALANCES!$D:$D,E$6)+SUMIFS(FLOWS!$C:$C,FLOWS!$A:$A,$B$2,FLOWS!$E:$E,$B18,FLOWS!$D:$D,E$6,FLOWS!$H:$H,"<"&$C$4)+SUM(SUMIFS(DEALS!$J:$J,DEALS!$A:$A,{"*REFUND*","*EXECUTED*"},DEALS!$G:$G,$B$2,DEALS!$E:$E,"<"&$C$4,DEALS!$K:$K,E$6,DEALS!$M:$M,$B18,DEALS!$N:$N,"<>*RECEIVED*",DEALS!$N:$N,"<>*EXECUTED*"))+SUM(SUMIFS(DEALS!$R:$R,DEALS!$A:$A,{"*REFUND*","*EXECUTED*"},DEALS!$O:$O,$B$2,DEALS!$E:$E,"<"&$C$4,DEALS!$S:$S,E$6,DEALS!$U:$U,$B18,DEALS!$V:$V,"<>*RECEIVED*",DEALS!$V:$V,"<>*EXECUTED*"))} -> 0 | F18: {=SUMIFS(BALANCES!$C:$C,BALANCES!$A:$A,$B$2,BALANCES!$B:$B,$B18,BALANCES!$D:$D,F$6)+SUMIFS(FLOWS!$C:$C,FLOWS!$A:$A,$B$2,FLOWS!$E:$E,$B18,FLOWS!$D:$D,F$6,FLOWS!$H:$H,"<"&$C$4)+SUM(SUMIFS(DEALS!$J:$J,DEALS!$A:$A,{"*REFUND*","*EXECUTED*"},DEALS!$G:$G,$B$2,DEALS!$E:$E,"<"&$C$4,DEALS!$K:$K,F$6,DEALS!$M:$M,$B18,DEALS!$N:$N,"<>*RECEIVED*",DEALS!$N:$N,"<>*EXECUTED*"))+SUM(SUMIFS(DEALS!$R:$R,DEALS!$A:$A,{"*REFUND*","*EXECUTED*"},DEALS!$O:$O,$B$2,DEALS!$E:$E,"<"&$C$4,DEALS!$S:$S,F$6,DEALS!$U:$U,$B18,DEALS!$V:$V,"<>*RECEIVED*",DEALS!$V:$V,"<>*EXECUTED*"))} -> 0 | G18: {=SUMIFS(BALANCES!$C:$C,BALANCES!$A:$A,$B$2,BALANCES!$B:$B,$B18,BALANCES!$D:$D,G$6)+SUMIFS(FLOWS!$C:$C,FLOWS!$A:$A,$B$2,FLOWS!$E:$E,$B18,FLOWS!$D:$D,G$6,FLOWS!$H:$H,"<"&$C$4)+SUM(SUMIFS(DEALS!$J:$J,DEALS!$A:$A,{"*REFUND*","*EXECUTED*"},DEALS!$G:$G,$B$2,DEALS!$E:$E,"<"&$C$4,DEALS!$K:$K,G$6,DEALS!$M:$M,$B18,DEALS!$N:$N,"<>*RECEIVED*",DEALS!$N:$N,"<>*EXECUTED*"))+SUM(SUMIFS(DEALS!$R:$R,DEALS!$A:$A,{"*REFUND*","*EXECUTED*"},DEALS!$O:$O,$B$2,DEALS!$E:$E,"<"&$C$4,DEALS!$S:$S,G$6,DEALS!$U:$U,$B18,DEALS!$V:$V,"<>*RECEIVED*",DEALS!$V:$V,"<>*EXECUTED*"))} -> 6499.37 | H18: {=SUMIFS(BALANCES!$C:$C,BALANCES!$A:$A,$B$2,BALANCES!$B:$B,$B18,BALANCES!$D:$D,H$6)+SUMIFS(FLOWS!$C:$C,FLOWS!$A:$A,$B$2,FLOWS!$E:$E,$B18,FLOWS!$D:$D,H$6,FLOWS!$H:$H,"<"&$C$4)+SUM(SUMIFS(DEALS!$J:$J,DEALS!$A:$A,{"*REFUND*","*EXECUTED*"},DEALS!$G:$G,$B$2,DEALS!$E:$E,"<"&$C$4,DEALS!$K:$K,H$6,DEALS!$M:$M,$B18,DEALS!$N:$N,"<>*RECEIVED*",DEALS!$N:$N,"<>*EXECUTED*"))+SUM(SUMIFS(DEALS!$R:$R,DEALS!$A:$A,{"*REFUND*","*EXECUTED*"},DEALS!$O:$O,$B$2,DEALS!$E:$E,"<"&$C$4,DEALS!$S:$S,H$6,DEALS!$U:$U,$B18,DEALS!$V:$V,"<>*RECEIVED*",DEALS!$V:$V,"<>*EXECUTED*"))} -> 0 | I18: =C18*VLOOKUP(C$6,'FX RATES'!$E$1:$F$50,2,FALSE)+D18*VLOOKUP(D$6,'FX RATES'!$E$1:$F$50,2,FALSE)+E18*VLOOKUP(E$6,'FX RATES'!$E$1:$F$50,2,FALSE)+F18*VLOOKUP(F$6,'FX RATES'!$E$1:$F$50,2,FALSE)+G18*VLOOKUP(G$6,'FX RATES'!$E$1:$F$50,2,FALSE)+H18*VLOOKUP(H$6,'FX RATES'!$E$1:$F$50,2,FALSE) -> 84.714907 | K18: =B18 -> BK | L18: {=SUMIFS(FLOWS!$C:$C,FLOWS!$A:$A,$B$2,FLOWS!$E:$E,$K18,FLOWS!$D:$D,L$6,FLOWS!$H:$H,">="&$C$4,FLOWS!$H:$H,"<="&$U$4)+SUM(SUMIFS(DEALS!$J:$J,DEALS!$A:$A,{"*REFUND*","*EXECUTED*"},DEALS!$G:$G,$B$2,DEALS!$E:$E,">="&$C$4,DEALS!$E:$E,"<="&$U$4,DEALS!$K:$K,L$6,DEALS!$M:$M,$K18,DEALS!$N:$N,"<>*RECEIVED*",DEALS!$N:$N,"<>*EXECUTED*"))+SUM(SUMIFS(DEALS!$R:$R,DEALS!$A:$A,{"*REFUND*","*EXECUTED*"},DEALS!$O:$O,$B$2,DEALS!$E:$E,">="&$C$4,DEALS!$E:$E,"<="&$U$4,DEALS!$S:$S,L$6,DEALS!$U:$U,$K18,DEALS!$V:$V,"<>*RECEIVED*",DEALS!$V:$V,"<>*EXECUTED*"))} -> 0 | M18: {=SUMIFS(FLOWS!$C:$C,FLOWS!$A:$A,$B$2,FLOWS!$E:$E,$K18,FLOWS!$D:$D,M$6,FLOWS!$H:$H,">="&$C$4,FLOWS!$H:$H,"<="&$U$4)+SUM(SUMIFS(DEALS!$J:$J,DEALS!$A:$A,{"*REFUND*","*EXECUTED*"},DEALS!$G:$G,$B$2,DEALS!$E:$E,">="&$C$4,DEALS!$E:$E,"<="&$U$4,DEALS!$K:$K,M$6,DEALS!$M:$M,$K18,DEALS!$N:$N,"<>*RECEIVED*",DEALS!$N:$N,"<>*EXECUTED*"))+SUM(SUMIFS(DEALS!$R:$R,DEALS!$A:$A,{"*REFUND*","*EXECUTED*"},DEALS!$O:$O,$B$2,DEALS!$E:$E,">="&$C$4,DEALS!$E:$E,"<="&$U$4,DEALS!$S:$S,M$6,DEALS!$U:$U,$K18,DEALS!$V:$V,"<>*RECEIVED*",DEALS!$V:$V,"<>*EXECUTED*"))} -> 0 | N18: {=SUMIFS(FLOWS!$C:$C,FLOWS!$A:$A,$B$2,FLOWS!$E:$E,$K18,FLOWS!$D:$D,N$6,FLOWS!$H:$H,">="&$C$4,FLOWS!$H:$H,"<="&$U$4)+SUM(SUMIFS(DEALS!$J:$J,DEALS!$A:$A,{"*REFUND*","*EXECUTED*"},DEALS!$G:$G,$B$2,DEALS!$E:$E,">="&$C$4,DEALS!$E:$E,"<="&$U$4,DEALS!$K:$K,N$6,DEALS!$M:$M,$K18,DEALS!$N:$N,"<>*RECEIVED*",DEALS!$N:$N,"<>*EXECUTED*"))+SUM(SUMIFS(DEALS!$R:$R,DEALS!$A:$A,{"*REFUND*","*EXECUTED*"},DEALS!$O:$O,$B$2,DEALS!$E:$E,">="&$C$4,DEALS!$E:$E,"<="&$U$4,DEALS!$S:$S,N$6,DEALS!$U:$U,$K18,DEALS!$V:$V,"<>*RECEIVED*",DEALS!$V:$V,"<>*EXECUTED*"))} -> 0 | O18: {=SUMIFS(FLOWS!$C:$C,FLOWS!$A:$A,$B$2,FLOWS!$E:$E,$K18,FLOWS!$D:$D,O$6,FLOWS!$H:$H,">="&$C$4,FLOWS!$H:$H,"<="&$U$4)+SUM(SUMIFS(DEALS!$J:$J,DEALS!$A:$A,{"*REFUND*","*EXECUTED*"},DEALS!$G:$G,$B$2,DEALS!$E:$E,">="&$C$4,DEALS!$E:$E,"<="&$U$4,DEALS!$K:$K,O$6,DEALS!$M:$M,$K18,DEALS!$N:$N,"<>*RECEIVED*",DEALS!$N:$N,"<>*EXECUTED*"))+SUM(SUMIFS(DEALS!$R:$R,DEALS!$A:$A,{"*REFUND*","*EXECUTED*"},DEALS!$O:$O,$B$2,DEALS!$E:$E,">="&$C$4,DEALS!$E:$E,"<="&$U$4,DEALS!$S:$S,O$6,DEALS!$U:$U,$K18,DEALS!$V:$V,"<>*RECEIVED*",DEALS!$V:$V,"<>*EXECUTED*"))} -> 0 | P18: {=SUMIFS(FLOWS!$C:$C,FLOWS!$A:$A,$B$2,FLOWS!$E:$E,$K18,FLOWS!$D:$D,P$6,FLOWS!$H:$H,">="&$C$4,FLOWS!$H:$H,"<="&$U$4)+SUM(SUMIFS(DEALS!$J:$J,DEALS!$A:$A,{"*REFUND*","*EXECUTED*"},DEALS!$G:$G,$B$2,DEALS!$E:$E,">="&$C$4,DEALS!$E:$E,"<="&$U$4,DEALS!$K:$K,P$6,DEALS!$M:$M,$K18,DEALS!$N:$N,"<>*RECEIVED*",DEALS!$N:$N,"<>*EXECUTED*"))+SUM(SUMIFS(DEALS!$R:$R,DEALS!$A:$A,{"*REFUND*","*EXECUTED*"},DEALS!$O:$O,$B$2,DEALS!$E:$E,">="&$C$4,DEALS!$E:$E,"<="&$U$4,DEALS!$S:$S,P$6,DEALS!$U:$U,$K18,DEALS!$V:$V,"<>*RECEIVED*",DEALS!$V:$V,"<>*EXECUTED*"))} -> 0 | Q18: {=SUMIFS(FLOWS!$C:$C,FLOWS!$A:$A,$B$2,FLOWS!$E:$E,$K18,FLOWS!$D:$D,Q$6,FLOWS!$H:$H,">="&$C$4,FLOWS!$H:$H,"<="&$U$4)+SUM(SUMIFS(DEALS!$J:$J,DEALS!$A:$A,{"*REFUND*","*EXECUTED*"},DEALS!$G:$G,$B$2,DEALS!$E:$E,">="&$C$4,DEALS!$E:$E,"<="&$U$4,DEALS!$K:$K,Q$6,DEALS!$M:$M,$K18,DEALS!$N:$N,"<>*RECEIVED*",DEALS!$N:$N,"<>*EXECUTED*"))+SUM(SUMIFS(DEALS!$R:$R,DEALS!$A:$A,{"*REFUND*","*EXECUTED*"},DEALS!$O:$O,$B$2,DEALS!$E:$E,">="&$C$4,DEALS!$E:$E,"<="&$U$4,DEALS!$S:$S,Q$6,DEALS!$U:$U,$K18,DEALS!$V:$V,"<>*RECEIVED*",DEALS!$V:$V,"<>*EXECUTED*"))} -> 0 | R18: =L18*VLOOKUP(L$6,'FX RATES'!$E$1:$F$50,2,FALSE)+M18*VLOOKUP(M$6,'FX RATES'!$E$1:$F$50,2,FALSE)+N18*VLOOKUP(N$6,'FX RATES'!$E$1:$F$50,2,FALSE)+O18*VLOOKUP(O$6,'FX RATES'!$E$1:$F$50,2,FALSE)+P18*VLOOKUP(P$6,'FX RATES'!$E$1:$F$50,2,FALSE)+Q18*VLOOKUP(Q$6,'FX RATES'!$E$1:$F$50,2,FALSE) -> 0 | T18: =B18 -> BK | U18: {=SUMIFS(BALANCES!$C:$C,BALANCES!$A:$A,$B$2,BALANCES!$B:$B,$T18,BALANCES!$D:$D,U$6)+SUMIFS(FLOWS!$C:$C,FLOWS!$A:$A,$B$2,FLOWS!$E:$E,$T18,FLOWS!$D:$D,U$6,FLOWS!$H:$H,"<="&$U$4)+SUM(SUMIFS(DEALS!$J:$J,DEALS!$A:$A,{"*REFUND*","*EXECUTED*"},DEALS!$G:$G,$B$2,DEALS!$E:$E,"<="&$U$4,DEALS!$K:$K,U$6,DEALS!$M:$M,$T18,DEALS!$N:$N,"<>*RECEIVED*",DEALS!$N:$N,"<>*EXECUTED*"))+SUM(SUMIFS(DEALS!$R:$R,DEALS!$A:$A,{"*REFUND*","*EXECUTED*"},DEALS!$O:$O,$B$2,DEALS!$E:$E,"<="&$U$4,DEALS!$S:$S,U$6,DEALS!$U:$U,$T18,DEALS!$V:$V,"<>*RECEIVED*",DEALS!$V:$V,"<>*EXECUTED*"))} -> 0 | V18: {=SUMIFS(BALANCES!$C:$C,BALANCES!$A:$A,$B$2,BALANCES!$B:$B,$T18,BALANCES!$D:$D,V$6)+SUMIFS(FLOWS!$C:$C,FLOWS!$A:$A,$B$2,FLOWS!$E:$E,$T18,FLOWS!$D:$D,V$6,FLOWS!$H:$H,"<="&$U$4)+SUM(SUMIFS(DEALS!$J:$J,DEALS!$A:$A,{"*REFUND*","*EXECUTED*"},DEALS!$G:$G,$B$2,DEALS!$E:$E,"<="&$U$4,DEALS!$K:$K,V$6,DEALS!$M:$M,$T18,DEALS!$N:$N,"<>*RECEIVED*",DEALS!$N:$N,"<>*EXECUTED*"))+SUM(SUMIFS(DEALS!$R:$R,DEALS!$A:$A,{"*REFUND*","*EXECUTED*"},DEALS!$O:$O,$B$2,DEALS!$E:$E,"<="&$U$4,DEALS!$S:$S,V$6,DEALS!$U:$U,$T18,DEALS!$V:$V,"<>*RECEIVED*",DEALS!$V:$V,"<>*EXECUTED*"))} -> 0 | W18: {=SUMIFS(BALANCES!$C:$C,BALANCES!$A:$A,$B$2,BALANCES!$B:$B,$T18,BALANCES!$D:$D,W$6)+SUMIFS(FLOWS!$C:$C,FLOWS!$A:$A,$B$2,FLOWS!$E:$E,$T18,FLOWS!$D:$D,W$6,FLOWS!$H:$H,"<="&$U$4)+SUM(SUMIFS(DEALS!$J:$J,DEALS!$A:$A,{"*REFUND*","*EXECUTED*"},DEALS!$G:$G,$B$2,DEALS!$E:$E,"<="&$U$4,DEALS!$K:$K,W$6,DEALS!$M:$M,$T18,DEALS!$N:$N,"<>*RECEIVED*",DEALS!$N:$N,"<>*EXECUTED*"))+SUM(SUMIFS(DEALS!$R:$R,DEALS!$A:$A,{"*REFUND*","*EXECUTED*"},DEALS!$O:$O,$B$2,DEALS!$E:$E,"<="&$U$4,DEALS!$S:$S,W$6,DEALS!$U:$U,$T18,DEALS!$V:$V,"<>*RECEIVED*",DEALS!$V:$V,"<>*EXECUTED*"))} -> 0 | X18: {=SUMIFS(BALANCES!$C:$C,BALANCES!$A:$A,$B$2,BALANCES!$B:$B,$T18,BALANCES!$D:$D,X$6)+SUMIFS(FLOWS!$C:$C,FLOWS!$A:$A,$B$2,FLOWS!$E:$E,$T18,FLOWS!$D:$D,X$6,FLOWS!$H:$H,"<="&$U$4)+SUM(SUMIFS(DEALS!$J:$J,DEALS!$A:$A,{"*REFUND*","*EXECUTED*"},DEALS!$G:$G,$B$2,DEALS!$E:$E,"<="&$U$4,DEALS!$K:$K,X$6,DEALS!$M:$M,$T18,DEALS!$N:$N,"<>*RECEIVED*",DEALS!$N:$N,"<>*EXECUTED*"))+SUM(SUMIFS(DEALS!$R:$R,DEALS!$A:$A,{"*REFUND*","*EXECUTED*"},DEALS!$O:$O,$B$2,DEALS!$E:$E,"<="&$U$4,DEALS!$S:$S,X$6,DEALS!$U:$U,$T18,DEALS!$V:$V,"<>*RECEIVED*",DEALS!$V:$V,"<>*EXECUTED*"))} -> 0 | Y18: {=SUMIFS(BALANCES!$C:$C,BALANCES!$A:$A,$B$2,BALANCES!$B:$B,$T18,BALANCES!$D:$D,Y$6)+SUMIFS(FLOWS!$C:$C,FLOWS!$A:$A,$B$2,FLOWS!$E:$E,$T18,FLOWS!$D:$D,Y$6,FLOWS!$H:$H,"<="&$U$4)+SUM(SUMIFS(DEALS!$J:$J,DEALS!$A:$A,{"*REFUND*","*EXECUTED*"},DEALS!$G:$G,$B$2,DEALS!$E:$E,"<="&$U$4,DEALS!$K:$K,Y$6,DEALS!$M:$M,$T18,DEALS!$N:$N,"<>*RECEIVED*",DEALS!$N:$N,"<>*EXECUTED*"))+SUM(SUMIFS(DEALS!$R:$R,DEALS!$A:$A,{"*REFUND*","*EXECUTED*"},DEALS!$O:$O,$B$2,DEALS!$E:$E,"<="&$U$4,DEALS!$S:$S,Y$6,DEALS!$U:$U,$T18,DEALS!$V:$V,"<>*RECEIVED*",DEALS!$V:$V,"<>*EXECUTED*"))} -> 6499.37 | Z18: {=SUMIFS(BALANCES!$C:$C,BALANCES!$A:$A,$B$2,BALANCES!$B:$B,$T18,BALANCES!$D:$D,Z$6)+SUMIFS(FLOWS!$C:$C,FLOWS!$A:$A,$B$2,FLOWS!$E:$E,$T18,FLOWS!$D:$D,Z$6,FLOWS!$H:$H,"<="&$U$4)+SUM(SUMIFS(DEALS!$J:$J,DEALS!$A:$A,{"*REFUND*","*EXECUTED*"},DEALS!$G:$G,$B$2,DEALS!$E:$E,"<="&$U$4,DEALS!$K:$K,Z$6,DEALS!$M:$M,$T18,DEALS!$N:$N,"<>*RECEIVED*",DEALS!$N:$N,"<>*EXECUTED*"))+SUM(SUMIFS(DEALS!$R:$R,DEALS!$A:$A,{"*REFUND*","*EXECUTED*"},DEALS!$O:$O,$B$2,DEALS!$E:$E,"<="&$U$4,DEALS!$S:$S,Z$6,DEALS!$U:$U,$T18,DEALS!$V:$V,"<>*RECEIVED*",DEALS!$V:$V,"<>*EXECUTED*"))} -> 0 | AA18: =U18*VLOOKUP(U$6,'FX RATES'!$E$1:$F$50,2,FALSE)+V18*VLOOKUP(V$6,'FX RATES'!$E$1:$F$50,2,FALSE)+W18*VLOOKUP(W$6,'FX RATES'!$E$1:$F$50,2,FALSE)+X18*VLOOKUP(X$6,'FX RATES'!$E$1:$F$50,2,FALSE)+Y18*VLOOKUP(Y$6,'FX RATES'!$E$1:$F$50,2,FALSE)+Z18*VLOOKUP(Z$6,'FX RATES'!$E$1:$F$50,2,FALSE) -> 84.714907 | AC18: =I18+R18-AA18 -> 0
B19: CEB | C19: {=SUMIFS(BALANCES!$C:$C,BALANCES!$A:$A,$B$2,BALANCES!$B:$B,$B19,BALANCES!$D:$D,C$6)+SUMIFS(FLOWS!$C:$C,FLOWS!$A:$A,$B$2,FLOWS!$E:$E,$B19,FLOWS!$D:$D,C$6,FLOWS!$H:$H,"<"&$C$4)+SUM(SUMIFS(DEALS!$J:$J,DEALS!$A:$A,{"*REFUND*","*EXECUTED*"},DEALS!$G:$G,$B$2,DEALS!$E:$E,"<"&$C$4,DEALS!$K:$K,C$6,DEALS!$M:$M,$B19,DEALS!$N:$N,"<>*RECEIVED*",DEALS!$N:$N,"<>*EXECUTED*"))+SUM(SUMIFS(DEALS!$R:$R,DEALS!$A:$A,{"*REFUND*","*EXECUTED*"},DEALS!$O:$O,$B$2,DEALS!$E:$E,"<"&$C$4,DEALS!$S:$S,C$6,DEALS!$U:$U,$B19,DEALS!$V:$V,"<>*RECEIVED*",DEALS!$V:$V,"<>*EXECUTED*"))} -> 0 | D19: {=SUMIFS(BALANCES!$C:$C,BALANCES!$A:$A,$B$2,BALANCES!$B:$B,$B19,BALANCES!$D:$D,D$6)+SUMIFS(FLOWS!$C:$C,FLOWS!$A:$A,$B$2,FLOWS!$E:$E,$B19,FLOWS!$D:$D,D$6,FLOWS!$H:$H,"<"&$C$4)+SUM(SUMIFS(DEALS!$J:$J,DEALS!$A:$A,{"*REFUND*","*EXECUTED*"},DEALS!$G:$G,$B$2,DEALS!$E:$E,"<"&$C$4,DEALS!$K:$K,D$6,DEALS!$M:$M,$B19,DEALS!$N:$N,"<>*RECEIVED*",DEALS!$N:$N,"<>*EXECUTED*"))+SUM(SUMIFS(DEALS!$R:$R,DEALS!$A:$A,{"*REFUND*","*EXECUTED*"},DEALS!$O:$O,$B$2,DEALS!$E:$E,"<"&$C$4,DEALS!$S:$S,D$6,DEALS!$U:$U,$B19,DEALS!$V:$V,"<>*RECEIVED*",DEALS!$V:$V,"<>*EXECUTED*"))} -> 0 | E19: {=SUMIFS(BALANCES!$C:$C,BALANCES!$A:$A,$B$2,BALANCES!$B:$B,$B19,BALANCES!$D:$D,E$6)+SUMIFS(FLOWS!$C:$C,FLOWS!$A:$A,$B$2,FLOWS!$E:$E,$B19,FLOWS!$D:$D,E$6,FLOWS!$H:$H,"<"&$C$4)+SUM(SUMIFS(DEALS!$J:$J,DEALS!$A:$A,{"*REFUND*","*EXECUTED*"},DEALS!$G:$G,$B$2,DEALS!$E:$E,"<"&$C$4,DEALS!$K:$K,E$6,DEALS!$M:$M,$B19,DEALS!$N:$N,"<>*RECEIVED*",DEALS!$N:$N,"<>*EXECUTED*"))+SUM(SUMIFS(DEALS!$R:$R,DEALS!$A:$A,{"*REFUND*","*EXECUTED*"},DEALS!$O:$O,$B$2,DEALS!$E:$E,"<"&$C$4,DEALS!$S:$S,E$6,DEALS!$U:$U,$B19,DEALS!$V:$V,"<>*RECEIVED*",DEALS!$V:$V,"<>*EXECUTED*"))} -> 1.01 | F19: {=SUMIFS(BALANCES!$C:$C,BALANCES!$A:$A,$B$2,BALANCES!$B:$B,$B19,BALANCES!$D:$D,F$6)+SUMIFS(FLOWS!$C:$C,FLOWS!$A:$A,$B$2,FLOWS!$E:$E,$B19,FLOWS!$D:$D,F$6,FLOWS!$H:$H,"<"&$C$4)+SUM(SUMIFS(DEALS!$J:$J,DEALS!$A:$A,{"*REFUND*","*EXECUTED*"},DEALS!$G:$G,$B$2,DEALS!$E:$E,"<"&$C$4,DEALS!$K:$K,F$6,DEALS!$M:$M,$B19,DEALS!$N:$N,"<>*RECEIVED*",DEALS!$N:$N,"<>*EXECUTED*"))+SUM(SUMIFS(DEALS!$R:$R,DEALS!$A:$A,{"*REFUND*","*EXECUTED*"},DEALS!$O:$O,$B$2,DEALS!$E:$E,"<"&$C$4,DEALS!$S:$S,F$6,DEALS!$U:$U,$B19,DEALS!$V:$V,"<>*RECEIVED*",DEALS!$V:$V,"<>*EXECUTED*"))} -> 0 | G19: {=SUMIFS(BALANCES!$C:$C,BALANCES!$A:$A,$B$2,BALANCES!$B:$B,$B19,BALANCES!$D:$D,G$6)+SUMIFS(FLOWS!$C:$C,FLOWS!$A:$A,$B$2,FLOWS!$E:$E,$B19,FLOWS!$D:$D,G$6,FLOWS!$H:$H,"<"&$C$4)+SUM(SUMIFS(DEALS!$J:$J,DEALS!$A:$A,{"*REFUND*","*EXECUTED*"},DEALS!$G:$G,$B$2,DEALS!$E:$E,"<"&$C$4,DEALS!$K:$K,G$6,DEALS!$M:$M,$B19,DEALS!$N:$N,"<>*RECEIVED*",DEALS!$N:$N,"<>*EXECUTED*"))+SUM(SUMIFS(DEALS!$R:$R,DEALS!$A:$A,{"*REFUND*","*EXECUTED*"},DEALS!$O:$O,$B$2,DEALS!$E:$E,"<"&$C$4,DEALS!$S:$S,G$6,DEALS!$U:$U,$B19,DEALS!$V:$V,"<>*RECEIVED*",DEALS!$V:$V,"<>*EXECUTED*"))} -> 329009.57 | H19: {=SUMIFS(BALANCES!$C:$C,BALANCES!$A:$A,$B$2,BALANCES!$B:$B,$B19,BALANCES!$D:$D,H$6)+SUMIFS(FLOWS!$C:$C,FLOWS!$A:$A,$B$2,FLOWS!$E:$E,$B19,FLOWS!$D:$D,H$6,FLOWS!$H:$H,"<"&$C$4)+SUM(SUMIFS(DEALS!$J:$J,DEALS!$A:$A,{"*REFUND*","*EXECUTED*"},DEALS!$G:$G,$B$2,DEALS!$E:$E,"<"&$C$4,DEALS!$K:$K,H$6,DEALS!$M:$M,$B19,DEALS!$N:$N,"<>*RECEIVED*",DEALS!$N:$N,"<>*EXECUTED*"))+SUM(SUMIFS(DEALS!$R:$R,DEALS!$A:$A,{"*REFUND*","*EXECUTED*"},DEALS!$O:$O,$B$2,DEALS!$E:$E,"<"&$C$4,DEALS!$S:$S,H$6,DEALS!$U:$U,$B19,DEALS!$V:$V,"<>*RECEIVED*",DEALS!$V:$V,"<>*EXECUTED*"))} -> 0 | I19: =C19*VLOOKUP(C$6,'FX RATES'!$E$1:$F$50,2,FALSE)+D19*VLOOKUP(D$6,'FX RATES'!$E$1:$F$50,2,FALSE)+E19*VLOOKUP(E$6,'FX RATES'!$E$1:$F$50,2,FALSE)+F19*VLOOKUP(F$6,'FX RATES'!$E$1:$F$50,2,FALSE)+G19*VLOOKUP(G$6,'FX RATES'!$E$1:$F$50,2,FALSE)+H19*VLOOKUP(H$6,'FX RATES'!$E$1:$F$50,2,FALSE) -> 4288.5642 | K19: =B19 -> CEB | L19: {=SUMIFS(FLOWS!$C:$C,FLOWS!$A:$A,$B$2,FLOWS!$E:$E,$K19,FLOWS!$D:$D,L$6,FLOWS!$H:$H,">="&$C$4,FLOWS!$H:$H,"<="&$U$4)+SUM(SUMIFS(DEALS!$J:$J,DEALS!$A:$A,{"*REFUND*","*EXECUTED*"},DEALS!$G:$G,$B$2,DEALS!$E:$E,">="&$C$4,DEALS!$E:$E,"<="&$U$4,DEALS!$K:$K,L$6,DEALS!$M:$M,$K19,DEALS!$N:$N,"<>*RECEIVED*",DEALS!$N:$N,"<>*EXECUTED*"))+SUM(SUMIFS(DEALS!$R:$R,DEALS!$A:$A,{"*REFUND*","*EXECUTED*"},DEALS!$O:$O,$B$2,DEALS!$E:$E,">="&$C$4,DEALS!$E:$E,"<="&$U$4,DEALS!$S:$S,L$6,DEALS!$U:$U,$K19,DEALS!$V:$V,"<>*RECEIVED*",DEALS!$V:$V,"<>*EXECUTED*"))} -> 0 | M19: {=SUMIFS(FLOWS!$C:$C,FLOWS!$A:$A,$B$2,FLOWS!$E:$E,$K19,FLOWS!$D:$D,M$6,FLOWS!$H:$H,">="&$C$4,FLOWS!$H:$H,"<="&$U$4)+SUM(SUMIFS(DEALS!$J:$J,DEALS!$A:$A,{"*REFUND*","*EXECUTED*"},DEALS!$G:$G,$B$2,DEALS!$E:$E,">="&$C$4,DEALS!$E:$E,"<="&$U$4,DEALS!$K:$K,M$6,DEALS!$M:$M,$K19,DEALS!$N:$N,"<>*RECEIVED*",DEALS!$N:$N,"<>*EXECUTED*"))+SUM(SUMIFS(DEALS!$R:$R,DEALS!$A:$A,{"*REFUND*","*EXECUTED*"},DEALS!$O:$O,$B$2,DEALS!$E:$E,">="&$C$4,DEALS!$E:$E,"<="&$U$4,DEALS!$S:$S,M$6,DEALS!$U:$U,$K19,DEALS!$V:$V,"<>*RECEIVED*",DEALS!$V:$V,"<>*EXECUTED*"))} -> 0 | N19: {=SUMIFS(FLOWS!$C:$C,FLOWS!$A:$A,$B$2,FLOWS!$E:$E,$K19,FLOWS!$D:$D,N$6,FLOWS!$H:$H,">="&$C$4,FLOWS!$H:$H,"<="&$U$4)+SUM(SUMIFS(DEALS!$J:$J,DEALS!$A:$A,{"*REFUND*","*EXECUTED*"},DEALS!$G:$G,$B$2,DEALS!$E:$E,">="&$C$4,DEALS!$E:$E,"<="&$U$4,DEALS!$K:$K,N$6,DEALS!$M:$M,$K19,DEALS!$N:$N,"<>*RECEIVED*",DEALS!$N:$N,"<>*EXECUTED*"))+SUM(SUMIFS(DEALS!$R:$R,DEALS!$A:$A,{"*REFUND*","*EXECUTED*"},DEALS!$O:$O,$B$2,DEALS!$E:$E,">="&$C$4,DEALS!$E:$E,"<="&$U$4,DEALS!$S:$S,N$6,DEALS!$U:$U,$K19,DEALS!$V:$V,"<>*RECEIVED*",DEALS!$V:$V,"<>*EXECUTED*"))} -> 0 | O19: {=SUMIFS(FLOWS!$C:$C,FLOWS!$A:$A,$B$2,FLOWS!$E:$E,$K19,FLOWS!$D:$D,O$6,FLOWS!$H:$H,">="&$C$4,FLOWS!$H:$H,"<="&$U$4)+SUM(SUMIFS(DEALS!$J:$J,DEALS!$A:$A,{"*REFUND*","*EXECUTED*"},DEALS!$G:$G,$B$2,DEALS!$E:$E,">="&$C$4,DEALS!$E:$E,"<="&$U$4,DEALS!$K:$K,O$6,DEALS!$M:$M,$K19,DEALS!$N:$N,"<>*RECEIVED*",DEALS!$N:$N,"<>*EXECUTED*"))+SUM(SUMIFS(DEALS!$R:$R,DEALS!$A:$A,{"*REFUND*","*EXECUTED*"},DEALS!$O:$O,$B$2,DEALS!$E:$E,">="&$C$4,DEALS!$E:$E,"<="&$U$4,DEALS!$S:$S,O$6,DEALS!$U:$U,$K19,DEALS!$V:$V,"<>*RECEIVED*",DEALS!$V:$V,"<>*EXECUTED*"))} -> 0 | P19: {=SUMIFS(FLOWS!$C:$C,FLOWS!$A:$A,$B$2,FLOWS!$E:$E,$K19,FLOWS!$D:$D,P$6,FLOWS!$H:$H,">="&$C$4,FLOWS!$H:$H,"<="&$U$4)+SUM(SUMIFS(DEALS!$J:$J,DEALS!$A:$A,{"*REFUND*","*EXECUTED*"},DEALS!$G:$G,$B$2,DEALS!$E:$E,">="&$C$4,DEALS!$E:$E,"<="&$U$4,DEALS!$K:$K,P$6,DEALS!$M:$M,$K19,DEALS!$N:$N,"<>*RECEIVED*",DEALS!$N:$N,"<>*EXECUTED*"))+SUM(SUMIFS(DEALS!$R:$R,DEALS!$A:$A,{"*REFUND*","*EXECUTED*"},DEALS!$O:$O,$B$2,DEALS!$E:$E,">="&$C$4,DEALS!$E:$E,"<="&$U$4,DEALS!$S:$S,P$6,DEALS!$U:$U,$K19,DEALS!$V:$V,"<>*RECEIVED*",DEALS!$V:$V,"<>*EXECUTED*"))} -> 0 | Q19: {=SUMIFS(FLOWS!$C:$C,FLOWS!$A:$A,$B$2,FLOWS!$E:$E,$K19,FLOWS!$D:$D,Q$6,FLOWS!$H:$H,">="&$C$4,FLOWS!$H:$H,"<="&$U$4)+SUM(SUMIFS(DEALS!$J:$J,DEALS!$A:$A,{"*REFUND*","*EXECUTED*"},DEALS!$G:$G,$B$2,DEALS!$E:$E,">="&$C$4,DEALS!$E:$E,"<="&$U$4,DEALS!$K:$K,Q$6,DEALS!$M:$M,$K19,DEALS!$N:$N,"<>*RECEIVED*",DEALS!$N:$N,"<>*EXECUTED*"))+SUM(SUMIFS(DEALS!$R:$R,DEALS!$A:$A,{"*REFUND*","*EXECUTED*"},DEALS!$O:$O,$B$2,DEALS!$E:$E,">="&$C$4,DEALS!$E:$E,"<="&$U$4,DEALS!$S:$S,Q$6,DEALS!$U:$U,$K19,DEALS!$V:$V,"<>*RECEIVED*",DEALS!$V:$V,"<>*EXECUTED*"))} -> 0 | R19: =L19*VLOOKUP(L$6,'FX RATES'!$E$1:$F$50,2,FALSE)+M19*VLOOKUP(M$6,'FX RATES'!$E$1:$F$50,2,FALSE)+N19*VLOOKUP(N$6,'FX RATES'!$E$1:$F$50,2,FALSE)+O19*VLOOKUP(O$6,'FX RATES'!$E$1:$F$50,2,FALSE)+P19*VLOOKUP(P$6,'FX RATES'!$E$1:$F$50,2,FALSE)+Q19*VLOOKUP(Q$6,'FX RATES'!$E$1:$F$50,2,FALSE) -> 0 | T19: =B19 -> CEB | U19: {=SUMIFS(BALANCES!$C:$C,BALANCES!$A:$A,$B$2,BALANCES!$B:$B,$T19,BALANCES!$D:$D,U$6)+SUMIFS(FLOWS!$C:$C,FLOWS!$A:$A,$B$2,FLOWS!$E:$E,$T19,FLOWS!$D:$D,U$6,FLOWS!$H:$H,"<="&$U$4)+SUM(SUMIFS(DEALS!$J:$J,DEALS!$A:$A,{"*REFUND*","*EXECUTED*"},DEALS!$G:$G,$B$2,DEALS!$E:$E,"<="&$U$4,DEALS!$K:$K,U$6,DEALS!$M:$M,$T19,DEALS!$N:$N,"<>*RECEIVED*",DEALS!$N:$N,"<>*EXECUTED*"))+SUM(SUMIFS(DEALS!$R:$R,DEALS!$A:$A,{"*REFUND*","*EXECUTED*"},DEALS!$O:$O,$B$2,DEALS!$E:$E,"<="&$U$4,DEALS!$S:$S,U$6,DEALS!$U:$U,$T19,DEALS!$V:$V,"<>*RECEIVED*",DEALS!$V:$V,"<>*EXECUTED*"))} -> 0 | V19: {=SUMIFS(BALANCES!$C:$C,BALANCES!$A:$A,$B$2,BALANCES!$B:$B,$T19,BALANCES!$D:$D,V$6)+SUMIFS(FLOWS!$C:$C,FLOWS!$A:$A,$B$2,FLOWS!$E:$E,$T19,FLOWS!$D:$D,V$6,FLOWS!$H:$H,"<="&$U$4)+SUM(SUMIFS(DEALS!$J:$J,DEALS!$A:$A,{"*REFUND*","*EXECUTED*"},DEALS!$G:$G,$B$2,DEALS!$E:$E,"<="&$U$4,DEALS!$K:$K,V$6,DEALS!$M:$M,$T19,DEALS!$N:$N,"<>*RECEIVED*",DEALS!$N:$N,"<>*EXECUTED*"))+SUM(SUMIFS(DEALS!$R:$R,DEALS!$A:$A,{"*REFUND*","*EXECUTED*"},DEALS!$O:$O,$B$2,DEALS!$E:$E,"<="&$U$4,DEALS!$S:$S,V$6,DEALS!$U:$U,$T19,DEALS!$V:$V,"<>*RECEIVED*",DEALS!$V:$V,"<>*EXECUTED*"))} -> 0 | W19: {=SUMIFS(BALANCES!$C:$C,BALANCES!$A:$A,$B$2,BALANCES!$B:$B,$T19,BALANCES!$D:$D,W$6)+SUMIFS(FLOWS!$C:$C,FLOWS!$A:$A,$B$2,FLOWS!$E:$E,$T19,FLOWS!$D:$D,W$6,FLOWS!$H:$H,"<="&$U$4)+SUM(SUMIFS(DEALS!$J:$J,DEALS!$A:$A,{"*REFUND*","*EXECUTED*"},DEALS!$G:$G,$B$2,DEALS!$E:$E,"<="&$U$4,DEALS!$K:$K,W$6,DEALS!$M:$M,$T19,DEALS!$N:$N,"<>*RECEIVED*",DEALS!$N:$N,"<>*EXECUTED*"))+SUM(SUMIFS(DEALS!$R:$R,DEALS!$A:$A,{"*REFUND*","*EXECUTED*"},DEALS!$O:$O,$B$2,DEALS!$E:$E,"<="&$U$4,DEALS!$S:$S,W$6,DEALS!$U:$U,$T19,DEALS!$V:$V,"<>*RECEIVED*",DEALS!$V:$V,"<>*EXECUTED*"))} -> 1.01 | X19: {=SUMIFS(BALANCES!$C:$C,BALANCES!$A:$A,$B$2,BALANCES!$B:$B,$T19,BALANCES!$D:$D,X$6)+SUMIFS(FLOWS!$C:$C,FLOWS!$A:$A,$B$2,FLOWS!$E:$E,$T19,FLOWS!$D:$D,X$6,FLOWS!$H:$H,"<="&$U$4)+SUM(SUMIFS(DEALS!$J:$J,DEALS!$A:$A,{"*REFUND*","*EXECUTED*"},DEALS!$G:$G,$B$2,DEALS!$E:$E,"<="&$U$4,DEALS!$K:$K,X$6,DEALS!$M:$M,$T19,DEALS!$N:$N,"<>*RECEIVED*",DEALS!$N:$N,"<>*EXECUTED*"))+SUM(SUMIFS(DEALS!$R:$R,DEALS!$A:$A,{"*REFUND*","*EXECUTED*"},DEALS!$O:$O,$B$2,DEALS!$E:$E,"<="&$U$4,DEALS!$S:$S,X$6,DEALS!$U:$U,$T19,DEALS!$V:$V,"<>*RECEIVED*",DEALS!$V:$V,"<>*EXECUTED*"))} -> 0 | Y19: {=SUMIFS(BALANCES!$C:$C,BALANCES!$A:$A,$B$2,BALANCES!$B:$B,$T19,BALANCES!$D:$D,Y$6)+SUMIFS(FLOWS!$C:$C,FLOWS!$A:$A,$B$2,FLOWS!$E:$E,$T19,FLOWS!$D:$D,Y$6,FLOWS!$H:$H,"<="&$U$4)+SUM(SUMIFS(DEALS!$J:$J,DEALS!$A:$A,{"*REFUND*","*EXECUTED*"},DEALS!$G:$G,$B$2,DEALS!$E:$E,"<="&$U$4,DEALS!$K:$K,Y$6,DEALS!$M:$M,$T19,DEALS!$N:$N,"<>*RECEIVED*",DEALS!$N:$N,"<>*EXECUTED*"))+SUM(SUMIFS(DEALS!$R:$R,DEALS!$A:$A,{"*REFUND*","*EXECUTED*"},DEALS!$O:$O,$B$2,DEALS!$E:$E,"<="&$U$4,DEALS!$S:$S,Y$6,DEALS!$U:$U,$T19,DEALS!$V:$V,"<>*RECEIVED*",DEALS!$V:$V,"<>*EXECUTED*"))} -> 329009.57 | Z19: {=SUMIFS(BALANCES!$C:$C,BALANCES!$A:$A,$B$2,BALANCES!$B:$B,$T19,BALANCES!$D:$D,Z$6)+SUMIFS(FLOWS!$C:$C,FLOWS!$A:$A,$B$2,FLOWS!$E:$E,$T19,FLOWS!$D:$D,Z$6,FLOWS!$H:$H,"<="&$U$4)+SUM(SUMIFS(DEALS!$J:$J,DEALS!$A:$A,{"*REFUND*","*EXECUTED*"},DEALS!$G:$G,$B$2,DEALS!$E:$E,"<="&$U$4,DEALS!$K:$K,Z$6,DEALS!$M:$M,$T19,DEALS!$N:$N,"<>*RECEIVED*",DEALS!$N:$N,"<>*EXECUTED*"))+SUM(SUMIFS(DEALS!$R:$R,DEALS!$A:$A,{"*REFUND*","*EXECUTED*"},DEALS!$O:$O,$B$2,DEALS!$E:$E,"<="&$U$4,DEALS!$S:$S,Z$6,DEALS!$U:$U,$T19,DEALS!$V:$V,"<>*RECEIVED*",DEALS!$V:$V,"<>*EXECUTED*"))} -> 0 | AA19: =U19*VLOOKUP(U$6,'FX RATES'!$E$1:$F$50,2,FALSE)+V19*VLOOKUP(V$6,'FX RATES'!$E$1:$F$50,2,FALSE)+W19*VLOOKUP(W$6,'FX RATES'!$E$1:$F$50,2,FALSE)+X19*VLOOKUP(X$6,'FX RATES'!$E$1:$F$50,2,FALSE)+Y19*VLOOKUP(Y$6,'FX RATES'!$E$1:$F$50,2,FALSE)+Z19*VLOOKUP(Z$6,'FX RATES'!$E$1:$F$50,2,FALSE) -> 4288.5642 | AC19: =I19+R19-AA19 -> 0
C20: {=SUMIFS(BALANCES!$C:$C,BALANCES!$A:$A,$B$2,BALANCES!$B:$B,$B20,BALANCES!$D:$D,C$6)+SUMIFS(FLOWS!$C:$C,FLOWS!$A:$A,$B$2,FLOWS!$E:$E,$B20,FLOWS!$D:$D,C$6,FLOWS!$H:$H,"<"&$C$4)+SUM(SUMIFS(DEALS!$J:$J,DEALS!$A:$A,{"*REFUND*","*EXECUTED*"},DEALS!$G:$G,$B$2,DEALS!$E:$E,"<"&$C$4,DEALS!$K:$K,C$6,DEALS!$M:$M,$B20,DEALS!$N:$N,"<>*RECEIVED*",DEALS!$N:$N,"<>*EXECUTED*"))+SUM(SUMIFS(DEALS!$R:$R,DEALS!$A:$A,{"*REFUND*","*EXECUTED*"},DEALS!$O:$O,$B$2,DEALS!$E:$E,"<"&$C$4,DEALS!$S:$S,C$6,DEALS!$U:$U,$B20,DEALS!$V:$V,"<>*RECEIVED*",DEALS!$V:$V,"<>*EXECUTED*"))} -> 0 | D20: {=SUMIFS(BALANCES!$C:$C,BALANCES!$A:$A,$B$2,BALANCES!$B:$B,$B20,BALANCES!$D:$D,D$6)+SUMIFS(FLOWS!$C:$C,FLOWS!$A:$A,$B$2,FLOWS!$E:$E,$B20,FLOWS!$D:$D,D$6,FLOWS!$H:$H,"<"&$C$4)+SUM(SUMIFS(DEALS!$J:$J,DEALS!$A:$A,{"*REFUND*","*EXECUTED*"},DEALS!$G:$G,$B$2,DEALS!$E:$E,"<"&$C$4,DEALS!$K:$K,D$6,DEALS!$M:$M,$B20,DEALS!$N:$N,"<>*RECEIVED*",DEALS!$N:$N,"<>*EXECUTED*"))+SUM(SUMIFS(DEALS!$R:$R,DEALS!$A:$A,{"*REFUND*","*EXECUTED*"},DEALS!$O:$O,$B$2,DEALS!$E:$E,"<"&$C$4,DEALS!$S:$S,D$6,DEALS!$U:$U,$B20,DEALS!$V:$V,"<>*RECEIVED*",DEALS!$V:$V,"<>*EXECUTED*"))} -> 0 | E20: {=SUMIFS(BALANCES!$C:$C,BALANCES!$A:$A,$B$2,BALANCES!$B:$B,$B20,BALANCES!$D:$D,E$6)+SUMIFS(FLOWS!$C:$C,FLOWS!$A:$A,$B$2,FLOWS!$E:$E,$B20,FLOWS!$D:$D,E$6,FLOWS!$H:$H,"<"&$C$4)+SUM(SUMIFS(DEALS!$J:$J,DEALS!$A:$A,{"*REFUND*","*EXECUTED*"},DEALS!$G:$G,$B$2,DEALS!$E:$E,"<"&$C$4,DEALS!$K:$K,E$6,DEALS!$M:$M,$B20,DEALS!$N:$N,"<>*RECEIVED*",DEALS!$N:$N,"<>*EXECUTED*"))+SUM(SUMIFS(DEALS!$R:$R,DEALS!$A:$A,{"*REFUND*","*EXECUTED*"},DEALS!$O:$O,$B$2,DEALS!$E:$E,"<"&$C$4,DEALS!$S:$S,E$6,DEALS!$U:$U,$B20,DEALS!$V:$V,"<>*RECEIVED*",DEALS!$V:$V,"<>*EXECUTED*"))} -> 0 | F20: {=SUMIFS(BALANCES!$C:$C,BALANCES!$A:$A,$B$2,BALANCES!$B:$B,$B20,BALANCES!$D:$D,F$6)+SUMIFS(FLOWS!$C:$C,FLOWS!$A:$A,$B$2,FLOWS!$E:$E,$B20,FLOWS!$D:$D,F$6,FLOWS!$H:$H,"<"&$C$4)+SUM(SUMIFS(DEALS!$J:$J,DEALS!$A:$A,{"*REFUND*","*EXECUTED*"},DEALS!$G:$G,$B$2,DEALS!$E:$E,"<"&$C$4,DEALS!$K:$K,F$6,DEALS!$M:$M,$B20,DEALS!$N:$N,"<>*RECEIVED*",DEALS!$N:$N,"<>*EXECUTED*"))+SUM(SUMIFS(DEALS!$R:$R,DEALS!$A:$A,{"*REFUND*","*EXECUTED*"},DEALS!$O:$O,$B$2,DEALS!$E:$E,"<"&$C$4,DEALS!$S:$S,F$6,DEALS!$U:$U,$B20,DEALS!$V:$V,"<>*RECEIVED*",DEALS!$V:$V,"<>*EXECUTED*"))} -> 0 | G20: {=SUMIFS(BALANCES!$C:$C,BALANCES!$A:$A,$B$2,BALANCES!$B:$B,$B20,BALANCES!$D:$D,G$6)+SUMIFS(FLOWS!$C:$C,FLOWS!$A:$A,$B$2,FLOWS!$E:$E,$B20,FLOWS!$D:$D,G$6,FLOWS!$H:$H,"<"&$C$4)+SUM(SUMIFS(DEALS!$J:$J,DEALS!$A:$A,{"*REFUND*","*EXECUTED*"},DEALS!$G:$G,$B$2,DEALS!$E:$E,"<"&$C$4,DEALS!$K:$K,G$6,DEALS!$M:$M,$B20,DEALS!$N:$N,"<>*RECEIVED*",DEALS!$N:$N,"<>*EXECUTED*"))+SUM(SUMIFS(DEALS!$R:$R,DEALS!$A:$A,{"*REFUND*","*EXECUTED*"},DEALS!$O:$O,$B$2,DEALS!$E:$E,"<"&$C$4,DEALS!$S:$S,G$6,DEALS!$U:$U,$B20,DEALS!$V:$V,"<>*RECEIVED*",DEALS!$V:$V,"<>*EXECUTED*"))} -> 0 | H20: {=SUMIFS(BALANCES!$C:$C,BALANCES!$A:$A,$B$2,BALANCES!$B:$B,$B20,BALANCES!$D:$D,H$6)+SUMIFS(FLOWS!$C:$C,FLOWS!$A:$A,$B$2,FLOWS!$E:$E,$B20,FLOWS!$D:$D,H$6,FLOWS!$H:$H,"<"&$C$4)+SUM(SUMIFS(DEALS!$J:$J,DEALS!$A:$A,{"*REFUND*","*EXECUTED*"},DEALS!$G:$G,$B$2,DEALS!$E:$E,"<"&$C$4,DEALS!$K:$K,H$6,DEALS!$M:$M,$B20,DEALS!$N:$N,"<>*RECEIVED*",DEALS!$N:$N,"<>*EXECUTED*"))+SUM(SUMIFS(DEALS!$R:$R,DEALS!$A:$A,{"*REFUND*","*EXECUTED*"},DEALS!$O:$O,$B$2,DEALS!$E:$E,"<"&$C$4,DEALS!$S:$S,H$6,DEALS!$U:$U,$B20,DEALS!$V:$V,"<>*RECEIVED*",DEALS!$V:$V,"<>*EXECUTED*"))} -> 0 | I20: =C20*VLOOKUP(C$6,'FX RATES'!$E$1:$F$50,2,FALSE)+D20*VLOOKUP(D$6,'FX RATES'!$E$1:$F$50,2,FALSE)+E20*VLOOKUP(E$6,'FX RATES'!$E$1:$F$50,2,FALSE)+F20*VLOOKUP(F$6,'FX RATES'!$E$1:$F$50,2,FALSE)+G20*VLOOKUP(G$6,'FX RATES'!$E$1:$F$50,2,FALSE)+H20*VLOOKUP(H$6,'FX RATES'!$E$1:$F$50,2,FALSE) -> 0 | K20: =B20 -> 0 | L20: {=SUMIFS(FLOWS!$C:$C,FLOWS!$A:$A,$B$2,FLOWS!$E:$E,$K20,FLOWS!$D:$D,L$6,FLOWS!$H:$H,">="&$C$4,FLOWS!$H:$H,"<="&$U$4)+SUM(SUMIFS(DEALS!$J:$J,DEALS!$A:$A,{"*REFUND*","*EXECUTED*"},DEALS!$G:$G,$B$2,DEALS!$E:$E,">="&$C$4,DEALS!$E:$E,"<="&$U$4,DEALS!$K:$K,L$6,DEALS!$M:$M,$K20,DEALS!$N:$N,"<>*RECEIVED*",DEALS!$N:$N,"<>*EXECUTED*"))+SUM(SUMIFS(DEALS!$R:$R,DEALS!$A:$A,{"*REFUND*","*EXECUTED*"},DEALS!$O:$O,$B$2,DEALS!$E:$E,">="&$C$4,DEALS!$E:$E,"<="&$U$4,DEALS!$S:$S,L$6,DEALS!$U:$U,$K20,DEALS!$V:$V,"<>*RECEIVED*",DEALS!$V:$V,"<>*EXECUTED*"))} -> 0 | M20: {=SUMIFS(FLOWS!$C:$C,FLOWS!$A:$A,$B$2,FLOWS!$E:$E,$K20,FLOWS!$D:$D,M$6,FLOWS!$H:$H,">="&$C$4,FLOWS!$H:$H,"<="&$U$4)+SUM(SUMIFS(DEALS!$J:$J,DEALS!$A:$A,{"*REFUND*","*EXECUTED*"},DEALS!$G:$G,$B$2,DEALS!$E:$E,">="&$C$4,DEALS!$E:$E,"<="&$U$4,DEALS!$K:$K,M$6,DEALS!$M:$M,$K20,DEALS!$N:$N,"<>*RECEIVED*",DEALS!$N:$N,"<>*EXECUTED*"))+SUM(SUMIFS(DEALS!$R:$R,DEALS!$A:$A,{"*REFUND*","*EXECUTED*"},DEALS!$O:$O,$B$2,DEALS!$E:$E,">="&$C$4,DEALS!$E:$E,"<="&$U$4,DEALS!$S:$S,M$6,DEALS!$U:$U,$K20,DEALS!$V:$V,"<>*RECEIVED*",DEALS!$V:$V,"<>*EXECUTED*"))} -> 0 | N20: {=SUMIFS(FLOWS!$C:$C,FLOWS!$A:$A,$B$2,FLOWS!$E:$E,$K20,FLOWS!$D:$D,N$6,FLOWS!$H:$H,">="&$C$4,FLOWS!$H:$H,"<="&$U$4)+SUM(SUMIFS(DEALS!$J:$J,DEALS!$A:$A,{"*REFUND*","*EXECUTED*"},DEALS!$G:$G,$B$2,DEALS!$E:$E,">="&$C$4,DEALS!$E:$E,"<="&$U$4,DEALS!$K:$K,N$6,DEALS!$M:$M,$K20,DEALS!$N:$N,"<>*RECEIVED*",DEALS!$N:$N,"<>*EXECUTED*"))+SUM(SUMIFS(DEALS!$R:$R,DEALS!$A:$A,{"*REFUND*","*EXECUTED*"},DEALS!$O:$O,$B$2,DEALS!$E:$E,">="&$C$4,DEALS!$E:$E,"<="&$U$4,DEALS!$S:$S,N$6,DEALS!$U:$U,$K20,DEALS!$V:$V,"<>*RECEIVED*",DEALS!$V:$V,"<>*EXECUTED*"))} -> 0 | O20: {=SUMIFS(FLOWS!$C:$C,FLOWS!$A:$A,$B$2,FLOWS!$E:$E,$K20,FLOWS!$D:$D,O$6,FLOWS!$H:$H,">="&$C$4,FLOWS!$H:$H,"<="&$U$4)+SUM(SUMIFS(DEALS!$J:$J,DEALS!$A:$A,{"*REFUND*","*EXECUTED*"},DEALS!$G:$G,$B$2,DEALS!$E:$E,">="&$C$4,DEALS!$E:$E,"<="&$U$4,DEALS!$K:$K,O$6,DEALS!$M:$M,$K20,DEALS!$N:$N,"<>*RECEIVED*",DEALS!$N:$N,"<>*EXECUTED*"))+SUM(SUMIFS(DEALS!$R:$R,DEALS!$A:$A,{"*REFUND*","*EXECUTED*"},DEALS!$O:$O,$B$2,DEALS!$E:$E,">="&$C$4,DEALS!$E:$E,"<="&$U$4,DEALS!$S:$S,O$6,DEALS!$U:$U,$K20,DEALS!$V:$V,"<>*RECEIVED*",DEALS!$V:$V,"<>*EXECUTED*"))} -> 0 | P20: {=SUMIFS(FLOWS!$C:$C,FLOWS!$A:$A,$B$2,FLOWS!$E:$E,$K20,FLOWS!$D:$D,P$6,FLOWS!$H:$H,">="&$C$4,FLOWS!$H:$H,"<="&$U$4)+SUM(SUMIFS(DEALS!$J:$J,DEALS!$A:$A,{"*REFUND*","*EXECUTED*"},DEALS!$G:$G,$B$2,DEALS!$E:$E,">="&$C$4,DEALS!$E:$E,"<="&$U$4,DEALS!$K:$K,P$6,DEALS!$M:$M,$K20,DEALS!$N:$N,"<>*RECEIVED*",DEALS!$N:$N,"<>*EXECUTED*"))+SUM(SUMIFS(DEALS!$R:$R,DEALS!$A:$A,{"*REFUND*","*EXECUTED*"},DEALS!$O:$O,$B$2,DEALS!$E:$E,">="&$C$4,DEALS!$E:$E,"<="&$U$4,DEALS!$S:$S,P$6,DEALS!$U:$U,$K20,DEALS!$V:$V,"<>*RECEIVED*",DEALS!$V:$V,"<>*EXECUTED*"))} -> 0 | Q20: {=SUMIFS(FLOWS!$C:$C,FLOWS!$A:$A,$B$2,FLOWS!$E:$E,$K20,FLOWS!$D:$D,Q$6,FLOWS!$H:$H,">="&$C$4,FLOWS!$H:$H,"<="&$U$4)+SUM(SUMIFS(DEALS!$J:$J,DEALS!$A:$A,{"*REFUND*","*EXECUTED*"},DEALS!$G:$G,$B$2,DEALS!$E:$E,">="&$C$4,DEALS!$E:$E,"<="&$U$4,DEALS!$K:$K,Q$6,DEALS!$M:$M,$K20,DEALS!$N:$N,"<>*RECEIVED*",DEALS!$N:$N,"<>*EXECUTED*"))+SUM(SUMIFS(DEALS!$R:$R,DEALS!$A:$A,{"*REFUND*","*EXECUTED*"},DEALS!$O:$O,$B$2,DEALS!$E:$E,">="&$C$4,DEALS!$E:$E,"<="&$U$4,DEALS!$S:$S,Q$6,DEALS!$U:$U,$K20,DEALS!$V:$V,"<>*RECEIVED*",DEALS!$V:$V,"<>*EXECUTED*"))} -> 0 | R20: =L20*VLOOKUP(L$6,'FX RATES'!$E$1:$F$50,2,FALSE)+M20*VLOOKUP(M$6,'FX RATES'!$E$1:$F$50,2,FALSE)+N20*VLOOKUP(N$6,'FX RATES'!$E$1:$F$50,2,FALSE)+O20*VLOOKUP(O$6,'FX RATES'!$E$1:$F$50,2,FALSE)+P20*VLOOKUP(P$6,'FX RATES'!$E$1:$F$50,2,FALSE)+Q20*VLOOKUP(Q$6,'FX RATES'!$E$1:$F$50,2,FALSE) -> 0 | T20: =B20 -> 0 | U20: {=SUMIFS(BALANCES!$C:$C,BALANCES!$A:$A,$B$2,BALANCES!$B:$B,$T20,BALANCES!$D:$D,U$6)+SUMIFS(FLOWS!$C:$C,FLOWS!$A:$A,$B$2,FLOWS!$E:$E,$T20,FLOWS!$D:$D,U$6,FLOWS!$H:$H,"<="&$U$4)+SUM(SUMIFS(DEALS!$J:$J,DEALS!$A:$A,{"*REFUND*","*EXECUTED*"},DEALS!$G:$G,$B$2,DEALS!$E:$E,"<="&$U$4,DEALS!$K:$K,U$6,DEALS!$M:$M,$T20,DEALS!$N:$N,"<>*RECEIVED*",DEALS!$N:$N,"<>*EXECUTED*"))+SUM(SUMIFS(DEALS!$R:$R,DEALS!$A:$A,{"*REFUND*","*EXECUTED*"},DEALS!$O:$O,$B$2,DEALS!$E:$E,"<="&$U$4,DEALS!$S:$S,U$6,DEALS!$U:$U,$T20,DEALS!$V:$V,"<>*RECEIVED*",DEALS!$V:$V,"<>*EXECUTED*"))} -> 0 | V20: {=SUMIFS(BALANCES!$C:$C,BALANCES!$A:$A,$B$2,BALANCES!$B:$B,$T20,BALANCES!$D:$D,V$6)+SUMIFS(FLOWS!$C:$C,FLOWS!$A:$A,$B$2,FLOWS!$E:$E,$T20,FLOWS!$D:$D,V$6,FLOWS!$H:$H,"<="&$U$4)+SUM(SUMIFS(DEALS!$J:$J,DEALS!$A:$A,{"*REFUND*","*EXECUTED*"},DEALS!$G:$G,$B$2,DEALS!$E:$E,"<="&$U$4,DEALS!$K:$K,V$6,DEALS!$M:$M,$T20,DEALS!$N:$N,"<>*RECEIVED*",DEALS!$N:$N,"<>*EXECUTED*"))+SUM(SUMIFS(DEALS!$R:$R,DEALS!$A:$A,{"*REFUND*","*EXECUTED*"},DEALS!$O:$O,$B$2,DEALS!$E:$E,"<="&$U$4,DEALS!$S:$S,V$6,DEALS!$U:$U,$T20,DEALS!$V:$V,"<>*RECEIVED*",DEALS!$V:$V,"<>*EXECUTED*"))} -> 0 | W20: {=SUMIFS(BALANCES!$C:$C,BALANCES!$A:$A,$B$2,BALANCES!$B:$B,$T20,BALANCES!$D:$D,W$6)+SUMIFS(FLOWS!$C:$C,FLOWS!$A:$A,$B$2,FLOWS!$E:$E,$T20,FLOWS!$D:$D,W$6,FLOWS!$H:$H,"<="&$U$4)+SUM(SUMIFS(DEALS!$J:$J,DEALS!$A:$A,{"*REFUND*","*EXECUTED*"},DEALS!$G:$G,$B$2,DEALS!$E:$E,"<="&$U$4,DEALS!$K:$K,W$6,DEALS!$M:$M,$T20,DEALS!$N:$N,"<>*RECEIVED*",DEALS!$N:$N,"<>*EXECUTED*"))+SUM(SUMIFS(DEALS!$R:$R,DEALS!$A:$A,{"*REFUND*","*EXECUTED*"},DEALS!$O:$O,$B$2,DEALS!$E:$E,"<="&$U$4,DEALS!$S:$S,W$6,DEALS!$U:$U,$T20,DEALS!$V:$V,"<>*RECEIVED*",DEALS!$V:$V,"<>*EXECUTED*"))} -> 0 | X20: {=SUMIFS(BALANCES!$C:$C,BALANCES!$A:$A,$B$2,BALANCES!$B:$B,$T20,BALANCES!$D:$D,X$6)+SUMIFS(FLOWS!$C:$C,FLOWS!$A:$A,$B$2,FLOWS!$E:$E,$T20,FLOWS!$D:$D,X$6,FLOWS!$H:$H,"<="&$U$4)+SUM(SUMIFS(DEALS!$J:$J,DEALS!$A:$A,{"*REFUND*","*EXECUTED*"},DEALS!$G:$G,$B$2,DEALS!$E:$E,"<="&$U$4,DEALS!$K:$K,X$6,DEALS!$M:$M,$T20,DEALS!$N:$N,"<>*RECEIVED*",DEALS!$N:$N,"<>*EXECUTED*"))+SUM(SUMIFS(DEALS!$R:$R,DEALS!$A:$A,{"*REFUND*","*EXECUTED*"},DEALS!$O:$O,$B$2,DEALS!$E:$E,"<="&$U$4,DEALS!$S:$S,X$6,DEALS!$U:$U,$T20,DEALS!$V:$V,"<>*RECEIVED*",DEALS!$V:$V,"<>*EXECUTED*"))} -> 0 | Y20: {=SUMIFS(BALANCES!$C:$C,BALANCES!$A:$A,$B$2,BALANCES!$B:$B,$T20,BALANCES!$D:$D,Y$6)+SUMIFS(FLOWS!$C:$C,FLOWS!$A:$A,$B$2,FLOWS!$E:$E,$T20,FLOWS!$D:$D,Y$6,FLOWS!$H:$H,"<="&$U$4)+SUM(SUMIFS(DEALS!$J:$J,DEALS!$A:$A,{"*REFUND*","*EXECUTED*"},DEALS!$G:$G,$B$2,DEALS!$E:$E,"<="&$U$4,DEALS!$K:$K,Y$6,DEALS!$M:$M,$T20,DEALS!$N:$N,"<>*RECEIVED*",DEALS!$N:$N,"<>*EXECUTED*"))+SUM(SUMIFS(DEALS!$R:$R,DEALS!$A:$A,{"*REFUND*","*EXECUTED*"},DEALS!$O:$O,$B$2,DEALS!$E:$E,"<="&$U$4,DEALS!$S:$S,Y$6,DEALS!$U:$U,$T20,DEALS!$V:$V,"<>*RECEIVED*",DEALS!$V:$V,"<>*EXECUTED*"))} -> 0 | Z20: {=SUMIFS(BALANCES!$C:$C,BALANCES!$A:$A,$B$2,BALANCES!$B:$B,$T20,BALANCES!$D:$D,Z$6)+SUMIFS(FLOWS!$C:$C,FLOWS!$A:$A,$B$2,FLOWS!$E:$E,$T20,FLOWS!$D:$D,Z$6,FLOWS!$H:$H,"<="&$U$4)+SUM(SUMIFS(DEALS!$J:$J,DEALS!$A:$A,{"*REFUND*","*EXECUTED*"},DEALS!$G:$G,$B$2,DEALS!$E:$E,"<="&$U$4,DEALS!$K:$K,Z$6,DEALS!$M:$M,$T20,DEALS!$N:$N,"<>*RECEIVED*",DEALS!$N:$N,"<>*EXECUTED*"))+SUM(SUMIFS(DEALS!$R:$R,DEALS!$A:$A,{"*REFUND*","*EXECUTED*"},DEALS!$O:$O,$B$2,DEALS!$E:$E,"<="&$U$4,DEALS!$S:$S,Z$6,DEALS!$U:$U,$T20,DEALS!$V:$V,"<>*RECEIVED*",DEALS!$V:$V,"<>*EXECUTED*"))} -> 0 | AA20: =U20*VLOOKUP(U$6,'FX RATES'!$E$1:$F$50,2,FALSE)+V20*VLOOKUP(V$6,'FX RATES'!$E$1:$F$50,2,FALSE)+W20*VLOOKUP(W$6,'FX RATES'!$E$1:$F$50,2,FALSE)+X20*VLOOKUP(X$6,'FX RATES'!$E$1:$F$50,2,FALSE)+Y20*VLOOKUP(Y$6,'FX RATES'!$E$1:$F$50,2,FALSE)+Z20*VLOOKUP(Z$6,'FX RATES'!$E$1:$F$50,2,FALSE) -> 0 | AC20: =I20+R20-AA20 -> 0
C21: {=SUMIFS(BALANCES!$C:$C,BALANCES!$A:$A,$B$2,BALANCES!$B:$B,$B21,BALANCES!$D:$D,C$6)+SUMIFS(FLOWS!$C:$C,FLOWS!$A:$A,$B$2,FLOWS!$E:$E,$B21,FLOWS!$D:$D,C$6,FLOWS!$H:$H,"<"&$C$4)+SUM(SUMIFS(DEALS!$J:$J,DEALS!$A:$A,{"*REFUND*","*EXECUTED*"},DEALS!$G:$G,$B$2,DEALS!$E:$E,"<"&$C$4,DEALS!$K:$K,C$6,DEALS!$M:$M,$B21,DEALS!$N:$N,"<>*RECEIVED*",DEALS!$N:$N,"<>*EXECUTED*"))+SUM(SUMIFS(DEALS!$R:$R,DEALS!$A:$A,{"*REFUND*","*EXECUTED*"},DEALS!$O:$O,$B$2,DEALS!$E:$E,"<"&$C$4,DEALS!$S:$S,C$6,DEALS!$U:$U,$B21,DEALS!$V:$V,"<>*RECEIVED*",DEALS!$V:$V,"<>*EXECUTED*"))} -> 0 | D21: {=SUMIFS(BALANCES!$C:$C,BALANCES!$A:$A,$B$2,BALANCES!$B:$B,$B21,BALANCES!$D:$D,D$6)+SUMIFS(FLOWS!$C:$C,FLOWS!$A:$A,$B$2,FLOWS!$E:$E,$B21,FLOWS!$D:$D,D$6,FLOWS!$H:$H,"<"&$C$4)+SUM(SUMIFS(DEALS!$J:$J,DEALS!$A:$A,{"*REFUND*","*EXECUTED*"},DEALS!$G:$G,$B$2,DEALS!$E:$E,"<"&$C$4,DEALS!$K:$K,D$6,DEALS!$M:$M,$B21,DEALS!$N:$N,"<>*RECEIVED*",DEALS!$N:$N,"<>*EXECUTED*"))+SUM(SUMIFS(DEALS!$R:$R,DEALS!$A:$A,{"*REFUND*","*EXECUTED*"},DEALS!$O:$O,$B$2,DEALS!$E:$E,"<"&$C$4,DEALS!$S:$S,D$6,DEALS!$U:$U,$B21,DEALS!$V:$V,"<>*RECEIVED*",DEALS!$V:$V,"<>*EXECUTED*"))} -> 0 | E21: {=SUMIFS(BALANCES!$C:$C,BALANCES!$A:$A,$B$2,BALANCES!$B:$B,$B21,BALANCES!$D:$D,E$6)+SUMIFS(FLOWS!$C:$C,FLOWS!$A:$A,$B$2,FLOWS!$E:$E,$B21,FLOWS!$D:$D,E$6,FLOWS!$H:$H,"<"&$C$4)+SUM(SUMIFS(DEALS!$J:$J,DEALS!$A:$A,{"*REFUND*","*EXECUTED*"},DEALS!$G:$G,$B$2,DEALS!$E:$E,"<"&$C$4,DEALS!$K:$K,E$6,DEALS!$M:$M,$B21,DEALS!$N:$N,"<>*RECEIVED*",DEALS!$N:$N,"<>*EXECUTED*"))+SUM(SUMIFS(DEALS!$R:$R,DEALS!$A:$A,{"*REFUND*","*EXECUTED*"},DEALS!$O:$O,$B$2,DEALS!$E:$E,"<"&$C$4,DEALS!$S:$S,E$6,DEALS!$U:$U,$B21,DEALS!$V:$V,"<>*RECEIVED*",DEALS!$V:$V,"<>*EXECUTED*"))} -> 0 | F21: {=SUMIFS(BALANCES!$C:$C,BALANCES!$A:$A,$B$2,BALANCES!$B:$B,$B21,BALANCES!$D:$D,F$6)+SUMIFS(FLOWS!$C:$C,FLOWS!$A:$A,$B$2,FLOWS!$E:$E,$B21,FLOWS!$D:$D,F$6,FLOWS!$H:$H,"<"&$C$4)+SUM(SUMIFS(DEALS!$J:$J,DEALS!$A:$A,{"*REFUND*","*EXECUTED*"},DEALS!$G:$G,$B$2,DEALS!$E:$E,"<"&$C$4,DEALS!$K:$K,F$6,DEALS!$M:$M,$B21,DEALS!$N:$N,"<>*RECEIVED*",DEALS!$N:$N,"<>*EXECUTED*"))+SUM(SUMIFS(DEALS!$R:$R,DEALS!$A:$A,{"*REFUND*","*EXECUTED*"},DEALS!$O:$O,$B$2,DEALS!$E:$E,"<"&$C$4,DEALS!$S:$S,F$6,DEALS!$U:$U,$B21,DEALS!$V:$V,"<>*RECEIVED*",DEALS!$V:$V,"<>*EXECUTED*"))} -> 0 | G21: {=SUMIFS(BALANCES!$C:$C,BALANCES!$A:$A,$B$2,BALANCES!$B:$B,$B21,BALANCES!$D:$D,G$6)+SUMIFS(FLOWS!$C:$C,FLOWS!$A:$A,$B$2,FLOWS!$E:$E,$B21,FLOWS!$D:$D,G$6,FLOWS!$H:$H,"<"&$C$4)+SUM(SUMIFS(DEALS!$J:$J,DEALS!$A:$A,{"*REFUND*","*EXECUTED*"},DEALS!$G:$G,$B$2,DEALS!$E:$E,"<"&$C$4,DEALS!$K:$K,G$6,DEALS!$M:$M,$B21,DEALS!$N:$N,"<>*RECEIVED*",DEALS!$N:$N,"<>*EXECUTED*"))+SUM(SUMIFS(DEALS!$R:$R,DEALS!$A:$A,{"*REFUND*","*EXECUTED*"},DEALS!$O:$O,$B$2,DEALS!$E:$E,"<"&$C$4,DEALS!$S:$S,G$6,DEALS!$U:$U,$B21,DEALS!$V:$V,"<>*RECEIVED*",DEALS!$V:$V,"<>*EXECUTED*"))} -> 0 | H21: {=SUMIFS(BALANCES!$C:$C,BALANCES!$A:$A,$B$2,BALANCES!$B:$B,$B21,BALANCES!$D:$D,H$6)+SUMIFS(FLOWS!$C:$C,FLOWS!$A:$A,$B$2,FLOWS!$E:$E,$B21,FLOWS!$D:$D,H$6,FLOWS!$H:$H,"<"&$C$4)+SUM(SUMIFS(DEALS!$J:$J,DEALS!$A:$A,{"*REFUND*","*EXECUTED*"},DEALS!$G:$G,$B$2,DEALS!$E:$E,"<"&$C$4,DEALS!$K:$K,H$6,DEALS!$M:$M,$B21,DEALS!$N:$N,"<>*RECEIVED*",DEALS!$N:$N,"<>*EXECUTED*"))+SUM(SUMIFS(DEALS!$R:$R,DEALS!$A:$A,{"*REFUND*","*EXECUTED*"},DEALS!$O:$O,$B$2,DEALS!$E:$E,"<"&$C$4,DEALS!$S:$S,H$6,DEALS!$U:$U,$B21,DEALS!$V:$V,"<>*RECEIVED*",DEALS!$V:$V,"<>*EXECUTED*"))} -> 0 | I21: =C21*VLOOKUP(C$6,'FX RATES'!$E$1:$F$50,2,FALSE)+D21*VLOOKUP(D$6,'FX RATES'!$E$1:$F$50,2,FALSE)+E21*VLOOKUP(E$6,'FX RATES'!$E$1:$F$50,2,FALSE)+F21*VLOOKUP(F$6,'FX RATES'!$E$1:$F$50,2,FALSE)+G21*VLOOKUP(G$6,'FX RATES'!$E$1:$F$50,2,FALSE)+H21*VLOOKUP(H$6,'FX RATES'!$E$1:$F$50,2,FALSE) -> 0 | K21: =B21 -> 0 | L21: {=SUMIFS(FLOWS!$C:$C,FLOWS!$A:$A,$B$2,FLOWS!$E:$E,$K21,FLOWS!$D:$D,L$6,FLOWS!$H:$H,">="&$C$4,FLOWS!$H:$H,"<="&$U$4)+SUM(SUMIFS(DEALS!$J:$J,DEALS!$A:$A,{"*REFUND*","*EXECUTED*"},DEALS!$G:$G,$B$2,DEALS!$E:$E,">="&$C$4,DEALS!$E:$E,"<="&$U$4,DEALS!$K:$K,L$6,DEALS!$M:$M,$K21,DEALS!$N:$N,"<>*RECEIVED*",DEALS!$N:$N,"<>*EXECUTED*"))+SUM(SUMIFS(DEALS!$R:$R,DEALS!$A:$A,{"*REFUND*","*EXECUTED*"},DEALS!$O:$O,$B$2,DEALS!$E:$E,">="&$C$4,DEALS!$E:$E,"<="&$U$4,DEALS!$S:$S,L$6,DEALS!$U:$U,$K21,DEALS!$V:$V,"<>*RECEIVED*",DEALS!$V:$V,"<>*EXECUTED*"))} -> 0 | M21: {=SUMIFS(FLOWS!$C:$C,FLOWS!$A:$A,$B$2,FLOWS!$E:$E,$K21,FLOWS!$D:$D,M$6,FLOWS!$H:$H,">="&$C$4,FLOWS!$H:$H,"<="&$U$4)+SUM(SUMIFS(DEALS!$J:$J,DEALS!$A:$A,{"*REFUND*","*EXECUTED*"},DEALS!$G:$G,$B$2,DEALS!$E:$E,">="&$C$4,DEALS!$E:$E,"<="&$U$4,DEALS!$K:$K,M$6,DEALS!$M:$M,$K21,DEALS!$N:$N,"<>*RECEIVED*",DEALS!$N:$N,"<>*EXECUTED*"))+SUM(SUMIFS(DEALS!$R:$R,DEALS!$A:$A,{"*REFUND*","*EXECUTED*"},DEALS!$O:$O,$B$2,DEALS!$E:$E,">="&$C$4,DEALS!$E:$E,"<="&$U$4,DEALS!$S:$S,M$6,DEALS!$U:$U,$K21,DEALS!$V:$V,"<>*RECEIVED*",DEALS!$V:$V,"<>*EXECUTED*"))} -> 0 | N21: {=SUMIFS(FLOWS!$C:$C,FLOWS!$A:$A,$B$2,FLOWS!$E:$E,$K21,FLOWS!$D:$D,N$6,FLOWS!$H:$H,">="&$C$4,FLOWS!$H:$H,"<="&$U$4)+SUM(SUMIFS(DEALS!$J:$J,DEALS!$A:$A,{"*REFUND*","*EXECUTED*"},DEALS!$G:$G,$B$2,DEALS!$E:$E,">="&$C$4,DEALS!$E:$E,"<="&$U$4,DEALS!$K:$K,N$6,DEALS!$M:$M,$K21,DEALS!$N:$N,"<>*RECEIVED*",DEALS!$N:$N,"<>*EXECUTED*"))+SUM(SUMIFS(DEALS!$R:$R,DEALS!$A:$A,{"*REFUND*","*EXECUTED*"},DEALS!$O:$O,$B$2,DEALS!$E:$E,">="&$C$4,DEALS!$E:$E,"<="&$U$4,DEALS!$S:$S,N$6,DEALS!$U:$U,$K21,DEALS!$V:$V,"<>*RECEIVED*",DEALS!$V:$V,"<>*EXECUTED*"))} -> 0 | O21: {=SUMIFS(FLOWS!$C:$C,FLOWS!$A:$A,$B$2,FLOWS!$E:$E,$K21,FLOWS!$D:$D,O$6,FLOWS!$H:$H,">="&$C$4,FLOWS!$H:$H,"<="&$U$4)+SUM(SUMIFS(DEALS!$J:$J,DEALS!$A:$A,{"*REFUND*","*EXECUTED*"},DEALS!$G:$G,$B$2,DEALS!$E:$E,">="&$C$4,DEALS!$E:$E,"<="&$U$4,DEALS!$K:$K,O$6,DEALS!$M:$M,$K21,DEALS!$N:$N,"<>*RECEIVED*",DEALS!$N:$N,"<>*EXECUTED*"))+SUM(SUMIFS(DEALS!$R:$R,DEALS!$A:$A,{"*REFUND*","*EXECUTED*"},DEALS!$O:$O,$B$2,DEALS!$E:$E,">="&$C$4,DEALS!$E:$E,"<="&$U$4,DEALS!$S:$S,O$6,DEALS!$U:$U,$K21,DEALS!$V:$V,"<>*RECEIVED*",DEALS!$V:$V,"<>*EXECUTED*"))} -> 0 | P21: {=SUMIFS(FLOWS!$C:$C,FLOWS!$A:$A,$B$2,FLOWS!$E:$E,$K21,FLOWS!$D:$D,P$6,FLOWS!$H:$H,">="&$C$4,FLOWS!$H:$H,"<="&$U$4)+SUM(SUMIFS(DEALS!$J:$J,DEALS!$A:$A,{"*REFUND*","*EXECUTED*"},DEALS!$G:$G,$B$2,DEALS!$E:$E,">="&$C$4,DEALS!$E:$E,"<="&$U$4,DEALS!$K:$K,P$6,DEALS!$M:$M,$K21,DEALS!$N:$N,"<>*RECEIVED*",DEALS!$N:$N,"<>*EXECUTED*"))+SUM(SUMIFS(DEALS!$R:$R,DEALS!$A:$A,{"*REFUND*","*EXECUTED*"},DEALS!$O:$O,$B$2,DEALS!$E:$E,">="&$C$4,DEALS!$E:$E,"<="&$U$4,DEALS!$S:$S,P$6,DEALS!$U:$U,$K21,DEALS!$V:$V,"<>*RECEIVED*",DEALS!$V:$V,"<>*EXECUTED*"))} -> 0 | Q21: {=SUMIFS(FLOWS!$C:$C,FLOWS!$A:$A,$B$2,FLOWS!$E:$E,$K21,FLOWS!$D:$D,Q$6,FLOWS!$H:$H,">="&$C$4,FLOWS!$H:$H,"<="&$U$4)+SUM(SUMIFS(DEALS!$J:$J,DEALS!$A:$A,{"*REFUND*","*EXECUTED*"},DEALS!$G:$G,$B$2,DEALS!$E:$E,">="&$C$4,DEALS!$E:$E,"<="&$U$4,DEALS!$K:$K,Q$6,DEALS!$M:$M,$K21,DEALS!$N:$N,"<>*RECEIVED*",DEALS!$N:$N,"<>*EXECUTED*"))+SUM(SUMIFS(DEALS!$R:$R,DEALS!$A:$A,{"*REFUND*","*EXECUTED*"},DEALS!$O:$O,$B$2,DEALS!$E:$E,">="&$C$4,DEALS!$E:$E,"<="&$U$4,DEALS!$S:$S,Q$6,DEALS!$U:$U,$K21,DEALS!$V:$V,"<>*RECEIVED*",DEALS!$V:$V,"<>*EXECUTED*"))} -> 0 | R21: =L21*VLOOKUP(L$6,'FX RATES'!$E$1:$F$50,2,FALSE)+M21*VLOOKUP(M$6,'FX RATES'!$E$1:$F$50,2,FALSE)+N21*VLOOKUP(N$6,'FX RATES'!$E$1:$F$50,2,FALSE)+O21*VLOOKUP(O$6,'FX RATES'!$E$1:$F$50,2,FALSE)+P21*VLOOKUP(P$6,'FX RATES'!$E$1:$F$50,2,FALSE)+Q21*VLOOKUP(Q$6,'FX RATES'!$E$1:$F$50,2,FALSE) -> 0 | T21: =B21 -> 0 | U21: {=SUMIFS(BALANCES!$C:$C,BALANCES!$A:$A,$B$2,BALANCES!$B:$B,$T21,BALANCES!$D:$D,U$6)+SUMIFS(FLOWS!$C:$C,FLOWS!$A:$A,$B$2,FLOWS!$E:$E,$T21,FLOWS!$D:$D,U$6,FLOWS!$H:$H,"<="&$U$4)+SUM(SUMIFS(DEALS!$J:$J,DEALS!$A:$A,{"*REFUND*","*EXECUTED*"},DEALS!$G:$G,$B$2,DEALS!$E:$E,"<="&$U$4,DEALS!$K:$K,U$6,DEALS!$M:$M,$T21,DEALS!$N:$N,"<>*RECEIVED*",DEALS!$N:$N,"<>*EXECUTED*"))+SUM(SUMIFS(DEALS!$R:$R,DEALS!$A:$A,{"*REFUND*","*EXECUTED*"},DEALS!$O:$O,$B$2,DEALS!$E:$E,"<="&$U$4,DEALS!$S:$S,U$6,DEALS!$U:$U,$T21,DEALS!$V:$V,"<>*RECEIVED*",DEALS!$V:$V,"<>*EXECUTED*"))} -> 0 | V21: {=SUMIFS(BALANCES!$C:$C,BALANCES!$A:$A,$B$2,BALANCES!$B:$B,$T21,BALANCES!$D:$D,V$6)+SUMIFS(FLOWS!$C:$C,FLOWS!$A:$A,$B$2,FLOWS!$E:$E,$T21,FLOWS!$D:$D,V$6,FLOWS!$H:$H,"<="&$U$4)+SUM(SUMIFS(DEALS!$J:$J,DEALS!$A:$A,{"*REFUND*","*EXECUTED*"},DEALS!$G:$G,$B$2,DEALS!$E:$E,"<="&$U$4,DEALS!$K:$K,V$6,DEALS!$M:$M,$T21,DEALS!$N:$N,"<>*RECEIVED*",DEALS!$N:$N,"<>*EXECUTED*"))+SUM(SUMIFS(DEALS!$R:$R,DEALS!$A:$A,{"*REFUND*","*EXECUTED*"},DEALS!$O:$O,$B$2,DEALS!$E:$E,"<="&$U$4,DEALS!$S:$S,V$6,DEALS!$U:$U,$T21,DEALS!$V:$V,"<>*RECEIVED*",DEALS!$V:$V,"<>*EXECUTED*"))} -> 0 | W21: {=SUMIFS(BALANCES!$C:$C,BALANCES!$A:$A,$B$2,BALANCES!$B:$B,$T21,BALANCES!$D:$D,W$6)+SUMIFS(FLOWS!$C:$C,FLOWS!$A:$A,$B$2,FLOWS!$E:$E,$T21,FLOWS!$D:$D,W$6,FLOWS!$H:$H,"<="&$U$4)+SUM(SUMIFS(DEALS!$J:$J,DEALS!$A:$A,{"*REFUND*","*EXECUTED*"},DEALS!$G:$G,$B$2,DEALS!$E:$E,"<="&$U$4,DEALS!$K:$K,W$6,DEALS!$M:$M,$T21,DEALS!$N:$N,"<>*RECEIVED*",DEALS!$N:$N,"<>*EXECUTED*"))+SUM(SUMIFS(DEALS!$R:$R,DEALS!$A:$A,{"*REFUND*","*EXECUTED*"},DEALS!$O:$O,$B$2,DEALS!$E:$E,"<="&$U$4,DEALS!$S:$S,W$6,DEALS!$U:$U,$T21,DEALS!$V:$V,"<>*RECEIVED*",DEALS!$V:$V,"<>*EXECUTED*"))} -> 0 | X21: {=SUMIFS(BALANCES!$C:$C,BALANCES!$A:$A,$B$2,BALANCES!$B:$B,$T21,BALANCES!$D:$D,X$6)+SUMIFS(FLOWS!$C:$C,FLOWS!$A:$A,$B$2,FLOWS!$E:$E,$T21,FLOWS!$D:$D,X$6,FLOWS!$H:$H,"<="&$U$4)+SUM(SUMIFS(DEALS!$J:$J,DEALS!$A:$A,{"*REFUND*","*EXECUTED*"},DEALS!$G:$G,$B$2,DEALS!$E:$E,"<="&$U$4,DEALS!$K:$K,X$6,DEALS!$M:$M,$T21,DEALS!$N:$N,"<>*RECEIVED*",DEALS!$N:$N,"<>*EXECUTED*"))+SUM(SUMIFS(DEALS!$R:$R,DEALS!$A:$A,{"*REFUND*","*EXECUTED*"},DEALS!$O:$O,$B$2,DEALS!$E:$E,"<="&$U$4,DEALS!$S:$S,X$6,DEALS!$U:$U,$T21,DEALS!$V:$V,"<>*RECEIVED*",DEALS!$V:$V,"<>*EXECUTED*"))} -> 0 | Y21: {=SUMIFS(BALANCES!$C:$C,BALANCES!$A:$A,$B$2,BALANCES!$B:$B,$T21,BALANCES!$D:$D,Y$6)+SUMIFS(FLOWS!$C:$C,FLOWS!$A:$A,$B$2,FLOWS!$E:$E,$T21,FLOWS!$D:$D,Y$6,FLOWS!$H:$H,"<="&$U$4)+SUM(SUMIFS(DEALS!$J:$J,DEALS!$A:$A,{"*REFUND*","*EXECUTED*"},DEALS!$G:$G,$B$2,DEALS!$E:$E,"<="&$U$4,DEALS!$K:$K,Y$6,DEALS!$M:$M,$T21,DEALS!$N:$N,"<>*RECEIVED*",DEALS!$N:$N,"<>*EXECUTED*"))+SUM(SUMIFS(DEALS!$R:$R,DEALS!$A:$A,{"*REFUND*","*EXECUTED*"},DEALS!$O:$O,$B$2,DEALS!$E:$E,"<="&$U$4,DEALS!$S:$S,Y$6,DEALS!$U:$U,$T21,DEALS!$V:$V,"<>*RECEIVED*",DEALS!$V:$V,"<>*EXECUTED*"))} -> 0 | Z21: {=SUMIFS(BALANCES!$C:$C,BALANCES!$A:$A,$B$2,BALANCES!$B:$B,$T21,BALANCES!$D:$D,Z$6)+SUMIFS(FLOWS!$C:$C,FLOWS!$A:$A,$B$2,FLOWS!$E:$E,$T21,FLOWS!$D:$D,Z$6,FLOWS!$H:$H,"<="&$U$4)+SUM(SUMIFS(DEALS!$J:$J,DEALS!$A:$A,{"*REFUND*","*EXECUTED*"},DEALS!$G:$G,$B$2,DEALS!$E:$E,"<="&$U$4,DEALS!$K:$K,Z$6,DEALS!$M:$M,$T21,DEALS!$N:$N,"<>*RECEIVED*",DEALS!$N:$N,"<>*EXECUTED*"))+SUM(SUMIFS(DEALS!$R:$R,DEALS!$A:$A,{"*REFUND*","*EXECUTED*"},DEALS!$O:$O,$B$2,DEALS!$E:$E,"<="&$U$4,DEALS!$S:$S,Z$6,DEALS!$U:$U,$T21,DEALS!$V:$V,"<>*RECEIVED*",DEALS!$V:$V,"<>*EXECUTED*"))} -> 0 | AA21: =U21*VLOOKUP(U$6,'FX RATES'!$E$1:$F$50,2,FALSE)+V21*VLOOKUP(V$6,'FX RATES'!$E$1:$F$50,2,FALSE)+W21*VLOOKUP(W$6,'FX RATES'!$E$1:$F$50,2,FALSE)+X21*VLOOKUP(X$6,'FX RATES'!$E$1:$F$50,2,FALSE)+Y21*VLOOKUP(Y$6,'FX RATES'!$E$1:$F$50,2,FALSE)+Z21*VLOOKUP(Z$6,'FX RATES'!$E$1:$F$50,2,FALSE) -> 0 | AC21: =I21+R21-AA21 -> 0
C22: {=SUMIFS(BALANCES!$C:$C,BALANCES!$A:$A,$B$2,BALANCES!$B:$B,$B22,BALANCES!$D:$D,C$6)+SUMIFS(FLOWS!$C:$C,FLOWS!$A:$A,$B$2,FLOWS!$E:$E,$B22,FLOWS!$D:$D,C$6,FLOWS!$H:$H,"<"&$C$4)+SUM(SUMIFS(DEALS!$J:$J,DEALS!$A:$A,{"*REFUND*","*EXECUTED*"},DEALS!$G:$G,$B$2,DEALS!$E:$E,"<"&$C$4,DEALS!$K:$K,C$6,DEALS!$M:$M,$B22,DEALS!$N:$N,"<>*RECEIVED*",DEALS!$N:$N,"<>*EXECUTED*"))+SUM(SUMIFS(DEALS!$R:$R,DEALS!$A:$A,{"*REFUND*","*EXECUTED*"},DEALS!$O:$O,$B$2,DEALS!$E:$E,"<"&$C$4,DEALS!$S:$S,C$6,DEALS!$U:$U,$B22,DEALS!$V:$V,"<>*RECEIVED*",DEALS!$V:$V,"<>*EXECUTED*"))} -> 0 | D22: {=SUMIFS(BALANCES!$C:$C,BALANCES!$A:$A,$B$2,BALANCES!$B:$B,$B22,BALANCES!$D:$D,D$6)+SUMIFS(FLOWS!$C:$C,FLOWS!$A:$A,$B$2,FLOWS!$E:$E,$B22,FLOWS!$D:$D,D$6,FLOWS!$H:$H,"<"&$C$4)+SUM(SUMIFS(DEALS!$J:$J,DEALS!$A:$A,{"*REFUND*","*EXECUTED*"},DEALS!$G:$G,$B$2,DEALS!$E:$E,"<"&$C$4,DEALS!$K:$K,D$6,DEALS!$M:$M,$B22,DEALS!$N:$N,"<>*RECEIVED*",DEALS!$N:$N,"<>*EXECUTED*"))+SUM(SUMIFS(DEALS!$R:$R,DEALS!$A:$A,{"*REFUND*","*EXECUTED*"},DEALS!$O:$O,$B$2,DEALS!$E:$E,"<"&$C$4,DEALS!$S:$S,D$6,DEALS!$U:$U,$B22,DEALS!$V:$V,"<>*RECEIVED*",DEALS!$V:$V,"<>*EXECUTED*"))} -> 0 | E22: {=SUMIFS(BALANCES!$C:$C,BALANCES!$A:$A,$B$2,BALANCES!$B:$B,$B22,BALANCES!$D:$D,E$6)+SUMIFS(FLOWS!$C:$C,FLOWS!$A:$A,$B$2,FLOWS!$E:$E,$B22,FLOWS!$D:$D,E$6,FLOWS!$H:$H,"<"&$C$4)+SUM(SUMIFS(DEALS!$J:$J,DEALS!$A:$A,{"*REFUND*","*EXECUTED*"},DEALS!$G:$G,$B$2,DEALS!$E:$E,"<"&$C$4,DEALS!$K:$K,E$6,DEALS!$M:$M,$B22,DEALS!$N:$N,"<>*RECEIVED*",DEALS!$N:$N,"<>*EXECUTED*"))+SUM(SUMIFS(DEALS!$R:$R,DEALS!$A:$A,{"*REFUND*","*EXECUTED*"},DEALS!$O:$O,$B$2,DEALS!$E:$E,"<"&$C$4,DEALS!$S:$S,E$6,DEALS!$U:$U,$B22,DEALS!$V:$V,"<>*RECEIVED*",DEALS!$V:$V,"<>*EXECUTED*"))} -> 0 | F22: {=SUMIFS(BALANCES!$C:$C,BALANCES!$A:$A,$B$2,BALANCES!$B:$B,$B22,BALANCES!$D:$D,F$6)+SUMIFS(FLOWS!$C:$C,FLOWS!$A:$A,$B$2,FLOWS!$E:$E,$B22,FLOWS!$D:$D,F$6,FLOWS!$H:$H,"<"&$C$4)+SUM(SUMIFS(DEALS!$J:$J,DEALS!$A:$A,{"*REFUND*","*EXECUTED*"},DEALS!$G:$G,$B$2,DEALS!$E:$E,"<"&$C$4,DEALS!$K:$K,F$6,DEALS!$M:$M,$B22,DEALS!$N:$N,"<>*RECEIVED*",DEALS!$N:$N,"<>*EXECUTED*"))+SUM(SUMIFS(DEALS!$R:$R,DEALS!$A:$A,{"*REFUND*","*EXECUTED*"},DEALS!$O:$O,$B$2,DEALS!$E:$E,"<"&$C$4,DEALS!$S:$S,F$6,DEALS!$U:$U,$B22,DEALS!$V:$V,"<>*RECEIVED*",DEALS!$V:$V,"<>*EXECUTED*"))} -> 0 | G22: {=SUMIFS(BALANCES!$C:$C,BALANCES!$A:$A,$B$2,BALANCES!$B:$B,$B22,BALANCES!$D:$D,G$6)+SUMIFS(FLOWS!$C:$C,FLOWS!$A:$A,$B$2,FLOWS!$E:$E,$B22,FLOWS!$D:$D,G$6,FLOWS!$H:$H,"<"&$C$4)+SUM(SUMIFS(DEALS!$J:$J,DEALS!$A:$A,{"*REFUND*","*EXECUTED*"},DEALS!$G:$G,$B$2,DEALS!$E:$E,"<"&$C$4,DEALS!$K:$K,G$6,DEALS!$M:$M,$B22,DEALS!$N:$N,"<>*RECEIVED*",DEALS!$N:$N,"<>*EXECUTED*"))+SUM(SUMIFS(DEALS!$R:$R,DEALS!$A:$A,{"*REFUND*","*EXECUTED*"},DEALS!$O:$O,$B$2,DEALS!$E:$E,"<"&$C$4,DEALS!$S:$S,G$6,DEALS!$U:$U,$B22,DEALS!$V:$V,"<>*RECEIVED*",DEALS!$V:$V,"<>*EXECUTED*"))} -> 0 | H22: {=SUMIFS(BALANCES!$C:$C,BALANCES!$A:$A,$B$2,BALANCES!$B:$B,$B22,BALANCES!$D:$D,H$6)+SUMIFS(FLOWS!$C:$C,FLOWS!$A:$A,$B$2,FLOWS!$E:$E,$B22,FLOWS!$D:$D,H$6,FLOWS!$H:$H,"<"&$C$4)+SUM(SUMIFS(DEALS!$J:$J,DEALS!$A:$A,{"*REFUND*","*EXECUTED*"},DEALS!$G:$G,$B$2,DEALS!$E:$E,"<"&$C$4,DEALS!$K:$K,H$6,DEALS!$M:$M,$B22,DEALS!$N:$N,"<>*RECEIVED*",DEALS!$N:$N,"<>*EXECUTED*"))+SUM(SUMIFS(DEALS!$R:$R,DEALS!$A:$A,{"*REFUND*","*EXECUTED*"},DEALS!$O:$O,$B$2,DEALS!$E:$E,"<"&$C$4,DEALS!$S:$S,H$6,DEALS!$U:$U,$B22,DEALS!$V:$V,"<>*RECEIVED*",DEALS!$V:$V,"<>*EXECUTED*"))} -> 0 | I22: =C22*VLOOKUP(C$6,'FX RATES'!$E$1:$F$50,2,FALSE)+D22*VLOOKUP(D$6,'FX RATES'!$E$1:$F$50,2,FALSE)+E22*VLOOKUP(E$6,'FX RATES'!$E$1:$F$50,2,FALSE)+F22*VLOOKUP(F$6,'FX RATES'!$E$1:$F$50,2,FALSE)+G22*VLOOKUP(G$6,'FX RATES'!$E$1:$F$50,2,FALSE)+H22*VLOOKUP(H$6,'FX RATES'!$E$1:$F$50,2,FALSE) -> 0 | K22: =B22 -> 0 | L22: {=SUMIFS(FLOWS!$C:$C,FLOWS!$A:$A,$B$2,FLOWS!$E:$E,$K22,FLOWS!$D:$D,L$6,FLOWS!$H:$H,">="&$C$4,FLOWS!$H:$H,"<="&$U$4)+SUM(SUMIFS(DEALS!$J:$J,DEALS!$A:$A,{"*REFUND*","*EXECUTED*"},DEALS!$G:$G,$B$2,DEALS!$E:$E,">="&$C$4,DEALS!$E:$E,"<="&$U$4,DEALS!$K:$K,L$6,DEALS!$M:$M,$K22,DEALS!$N:$N,"<>*RECEIVED*",DEALS!$N:$N,"<>*EXECUTED*"))+SUM(SUMIFS(DEALS!$R:$R,DEALS!$A:$A,{"*REFUND*","*EXECUTED*"},DEALS!$O:$O,$B$2,DEALS!$E:$E,">="&$C$4,DEALS!$E:$E,"<="&$U$4,DEALS!$S:$S,L$6,DEALS!$U:$U,$K22,DEALS!$V:$V,"<>*RECEIVED*",DEALS!$V:$V,"<>*EXECUTED*"))} -> 0 | M22: {=SUMIFS(FLOWS!$C:$C,FLOWS!$A:$A,$B$2,FLOWS!$E:$E,$K22,FLOWS!$D:$D,M$6,FLOWS!$H:$H,">="&$C$4,FLOWS!$H:$H,"<="&$U$4)+SUM(SUMIFS(DEALS!$J:$J,DEALS!$A:$A,{"*REFUND*","*EXECUTED*"},DEALS!$G:$G,$B$2,DEALS!$E:$E,">="&$C$4,DEALS!$E:$E,"<="&$U$4,DEALS!$K:$K,M$6,DEALS!$M:$M,$K22,DEALS!$N:$N,"<>*RECEIVED*",DEALS!$N:$N,"<>*EXECUTED*"))+SUM(SUMIFS(DEALS!$R:$R,DEALS!$A:$A,{"*REFUND*","*EXECUTED*"},DEALS!$O:$O,$B$2,DEALS!$E:$E,">="&$C$4,DEALS!$E:$E,"<="&$U$4,DEALS!$S:$S,M$6,DEALS!$U:$U,$K22,DEALS!$V:$V,"<>*RECEIVED*",DEALS!$V:$V,"<>*EXECUTED*"))} -> 0 | N22: {=SUMIFS(FLOWS!$C:$C,FLOWS!$A:$A,$B$2,FLOWS!$E:$E,$K22,FLOWS!$D:$D,N$6,FLOWS!$H:$H,">="&$C$4,FLOWS!$H:$H,"<="&$U$4)+SUM(SUMIFS(DEALS!$J:$J,DEALS!$A:$A,{"*REFUND*","*EXECUTED*"},DEALS!$G:$G,$B$2,DEALS!$E:$E,">="&$C$4,DEALS!$E:$E,"<="&$U$4,DEALS!$K:$K,N$6,DEALS!$M:$M,$K22,DEALS!$N:$N,"<>*RECEIVED*",DEALS!$N:$N,"<>*EXECUTED*"))+SUM(SUMIFS(DEALS!$R:$R,DEALS!$A:$A,{"*REFUND*","*EXECUTED*"},DEALS!$O:$O,$B$2,DEALS!$E:$E,">="&$C$4,DEALS!$E:$E,"<="&$U$4,DEALS!$S:$S,N$6,DEALS!$U:$U,$K22,DEALS!$V:$V,"<>*RECEIVED*",DEALS!$V:$V,"<>*EXECUTED*"))} -> 0 | O22: {=SUMIFS(FLOWS!$C:$C,FLOWS!$A:$A,$B$2,FLOWS!$E:$E,$K22,FLOWS!$D:$D,O$6,FLOWS!$H:$H,">="&$C$4,FLOWS!$H:$H,"<="&$U$4)+SUM(SUMIFS(DEALS!$J:$J,DEALS!$A:$A,{"*REFUND*","*EXECUTED*"},DEALS!$G:$G,$B$2,DEALS!$E:$E,">="&$C$4,DEALS!$E:$E,"<="&$U$4,DEALS!$K:$K,O$6,DEALS!$M:$M,$K22,DEALS!$N:$N,"<>*RECEIVED*",DEALS!$N:$N,"<>*EXECUTED*"))+SUM(SUMIFS(DEALS!$R:$R,DEALS!$A:$A,{"*REFUND*","*EXECUTED*"},DEALS!$O:$O,$B$2,DEALS!$E:$E,">="&$C$4,DEALS!$E:$E,"<="&$U$4,DEALS!$S:$S,O$6,DEALS!$U:$U,$K22,DEALS!$V:$V,"<>*RECEIVED*",DEALS!$V:$V,"<>*EXECUTED*"))} -> 0 | P22: {=SUMIFS(FLOWS!$C:$C,FLOWS!$A:$A,$B$2,FLOWS!$E:$E,$K22,FLOWS!$D:$D,P$6,FLOWS!$H:$H,">="&$C$4,FLOWS!$H:$H,"<="&$U$4)+SUM(SUMIFS(DEALS!$J:$J,DEALS!$A:$A,{"*REFUND*","*EXECUTED*"},DEALS!$G:$G,$B$2,DEALS!$E:$E,">="&$C$4,DEALS!$E:$E,"<="&$U$4,DEALS!$K:$K,P$6,DEALS!$M:$M,$K22,DEALS!$N:$N,"<>*RECEIVED*",DEALS!$N:$N,"<>*EXECUTED*"))+SUM(SUMIFS(DEALS!$R:$R,DEALS!$A:$A,{"*REFUND*","*EXECUTED*"},DEALS!$O:$O,$B$2,DEALS!$E:$E,">="&$C$4,DEALS!$E:$E,"<="&$U$4,DEALS!$S:$S,P$6,DEALS!$U:$U,$K22,DEALS!$V:$V,"<>*RECEIVED*",DEALS!$V:$V,"<>*EXECUTED*"))} -> 0 | Q22: {=SUMIFS(FLOWS!$C:$C,FLOWS!$A:$A,$B$2,FLOWS!$E:$E,$K22,FLOWS!$D:$D,Q$6,FLOWS!$H:$H,">="&$C$4,FLOWS!$H:$H,"<="&$U$4)+SUM(SUMIFS(DEALS!$J:$J,DEALS!$A:$A,{"*REFUND*","*EXECUTED*"},DEALS!$G:$G,$B$2,DEALS!$E:$E,">="&$C$4,DEALS!$E:$E,"<="&$U$4,DEALS!$K:$K,Q$6,DEALS!$M:$M,$K22,DEALS!$N:$N,"<>*RECEIVED*",DEALS!$N:$N,"<>*EXECUTED*"))+SUM(SUMIFS(DEALS!$R:$R,DEALS!$A:$A,{"*REFUND*","*EXECUTED*"},DEALS!$O:$O,$B$2,DEALS!$E:$E,">="&$C$4,DEALS!$E:$E,"<="&$U$4,DEALS!$S:$S,Q$6,DEALS!$U:$U,$K22,DEALS!$V:$V,"<>*RECEIVED*",DEALS!$V:$V,"<>*EXECUTED*"))} -> 0 | R22: =L22*VLOOKUP(L$6,'FX RATES'!$E$1:$F$50,2,FALSE)+M22*VLOOKUP(M$6,'FX RATES'!$E$1:$F$50,2,FALSE)+N22*VLOOKUP(N$6,'FX RATES'!$E$1:$F$50,2,FALSE)+O22*VLOOKUP(O$6,'FX RATES'!$E$1:$F$50,2,FALSE)+P22*VLOOKUP(P$6,'FX RATES'!$E$1:$F$50,2,FALSE)+Q22*VLOOKUP(Q$6,'FX RATES'!$E$1:$F$50,2,FALSE) -> 0 | T22: =B22 -> 0 | U22: {=SUMIFS(BALANCES!$C:$C,BALANCES!$A:$A,$B$2,BALANCES!$B:$B,$T22,BALANCES!$D:$D,U$6)+SUMIFS(FLOWS!$C:$C,FLOWS!$A:$A,$B$2,FLOWS!$E:$E,$T22,FLOWS!$D:$D,U$6,FLOWS!$H:$H,"<="&$U$4)+SUM(SUMIFS(DEALS!$J:$J,DEALS!$A:$A,{"*REFUND*","*EXECUTED*"},DEALS!$G:$G,$B$2,DEALS!$E:$E,"<="&$U$4,DEALS!$K:$K,U$6,DEALS!$M:$M,$T22,DEALS!$N:$N,"<>*RECEIVED*",DEALS!$N:$N,"<>*EXECUTED*"))+SUM(SUMIFS(DEALS!$R:$R,DEALS!$A:$A,{"*REFUND*","*EXECUTED*"},DEALS!$O:$O,$B$2,DEALS!$E:$E,"<="&$U$4,DEALS!$S:$S,U$6,DEALS!$U:$U,$T22,DEALS!$V:$V,"<>*RECEIVED*",DEALS!$V:$V,"<>*EXECUTED*"))} -> 0 | V22: {=SUMIFS(BALANCES!$C:$C,BALANCES!$A:$A,$B$2,BALANCES!$B:$B,$T22,BALANCES!$D:$D,V$6)+SUMIFS(FLOWS!$C:$C,FLOWS!$A:$A,$B$2,FLOWS!$E:$E,$T22,FLOWS!$D:$D,V$6,FLOWS!$H:$H,"<="&$U$4)+SUM(SUMIFS(DEALS!$J:$J,DEALS!$A:$A,{"*REFUND*","*EXECUTED*"},DEALS!$G:$G,$B$2,DEALS!$E:$E,"<="&$U$4,DEALS!$K:$K,V$6,DEALS!$M:$M,$T22,DEALS!$N:$N,"<>*RECEIVED*",DEALS!$N:$N,"<>*EXECUTED*"))+SUM(SUMIFS(DEALS!$R:$R,DEALS!$A:$A,{"*REFUND*","*EXECUTED*"},DEALS!$O:$O,$B$2,DEALS!$E:$E,"<="&$U$4,DEALS!$S:$S,V$6,DEALS!$U:$U,$T22,DEALS!$V:$V,"<>*RECEIVED*",DEALS!$V:$V,"<>*EXECUTED*"))} -> 0 | W22: {=SUMIFS(BALANCES!$C:$C,BALANCES!$A:$A,$B$2,BALANCES!$B:$B,$T22,BALANCES!$D:$D,W$6)+SUMIFS(FLOWS!$C:$C,FLOWS!$A:$A,$B$2,FLOWS!$E:$E,$T22,FLOWS!$D:$D,W$6,FLOWS!$H:$H,"<="&$U$4)+SUM(SUMIFS(DEALS!$J:$J,DEALS!$A:$A,{"*REFUND*","*EXECUTED*"},DEALS!$G:$G,$B$2,DEALS!$E:$E,"<="&$U$4,DEALS!$K:$K,W$6,DEALS!$M:$M,$T22,DEALS!$N:$N,"<>*RECEIVED*",DEALS!$N:$N,"<>*EXECUTED*"))+SUM(SUMIFS(DEALS!$R:$R,DEALS!$A:$A,{"*REFUND*","*EXECUTED*"},DEALS!$O:$O,$B$2,DEALS!$E:$E,"<="&$U$4,DEALS!$S:$S,W$6,DEALS!$U:$U,$T22,DEALS!$V:$V,"<>*RECEIVED*",DEALS!$V:$V,"<>*EXECUTED*"))} -> 0 | X22: {=SUMIFS(BALANCES!$C:$C,BALANCES!$A:$A,$B$2,BALANCES!$B:$B,$T22,BALANCES!$D:$D,X$6)+SUMIFS(FLOWS!$C:$C,FLOWS!$A:$A,$B$2,FLOWS!$E:$E,$T22,FLOWS!$D:$D,X$6,FLOWS!$H:$H,"<="&$U$4)+SUM(SUMIFS(DEALS!$J:$J,DEALS!$A:$A,{"*REFUND*","*EXECUTED*"},DEALS!$G:$G,$B$2,DEALS!$E:$E,"<="&$U$4,DEALS!$K:$K,X$6,DEALS!$M:$M,$T22,DEALS!$N:$N,"<>*RECEIVED*",DEALS!$N:$N,"<>*EXECUTED*"))+SUM(SUMIFS(DEALS!$R:$R,DEALS!$A:$A,{"*REFUND*","*EXECUTED*"},DEALS!$O:$O,$B$2,DEALS!$E:$E,"<="&$U$4,DEALS!$S:$S,X$6,DEALS!$U:$U,$T22,DEALS!$V:$V,"<>*RECEIVED*",DEALS!$V:$V,"<>*EXECUTED*"))} -> 0 | Y22: {=SUMIFS(BALANCES!$C:$C,BALANCES!$A:$A,$B$2,BALANCES!$B:$B,$T22,BALANCES!$D:$D,Y$6)+SUMIFS(FLOWS!$C:$C,FLOWS!$A:$A,$B$2,FLOWS!$E:$E,$T22,FLOWS!$D:$D,Y$6,FLOWS!$H:$H,"<="&$U$4)+SUM(SUMIFS(DEALS!$J:$J,DEALS!$A:$A,{"*REFUND*","*EXECUTED*"},DEALS!$G:$G,$B$2,DEALS!$E:$E,"<="&$U$4,DEALS!$K:$K,Y$6,DEALS!$M:$M,$T22,DEALS!$N:$N,"<>*RECEIVED*",DEALS!$N:$N,"<>*EXECUTED*"))+SUM(SUMIFS(DEALS!$R:$R,DEALS!$A:$A,{"*REFUND*","*EXECUTED*"},DEALS!$O:$O,$B$2,DEALS!$E:$E,"<="&$U$4,DEALS!$S:$S,Y$6,DEALS!$U:$U,$T22,DEALS!$V:$V,"<>*RECEIVED*",DEALS!$V:$V,"<>*EXECUTED*"))} -> 0 | Z22: {=SUMIFS(BALANCES!$C:$C,BALANCES!$A:$A,$B$2,BALANCES!$B:$B,$T22,BALANCES!$D:$D,Z$6)+SUMIFS(FLOWS!$C:$C,FLOWS!$A:$A,$B$2,FLOWS!$E:$E,$T22,FLOWS!$D:$D,Z$6,FLOWS!$H:$H,"<="&$U$4)+SUM(SUMIFS(DEALS!$J:$J,DEALS!$A:$A,{"*REFUND*","*EXECUTED*"},DEALS!$G:$G,$B$2,DEALS!$E:$E,"<="&$U$4,DEALS!$K:$K,Z$6,DEALS!$M:$M,$T22,DEALS!$N:$N,"<>*RECEIVED*",DEALS!$N:$N,"<>*EXECUTED*"))+SUM(SUMIFS(DEALS!$R:$R,DEALS!$A:$A,{"*REFUND*","*EXECUTED*"},DEALS!$O:$O,$B$2,DEALS!$E:$E,"<="&$U$4,DEALS!$S:$S,Z$6,DEALS!$U:$U,$T22,DEALS!$V:$V,"<>*RECEIVED*",DEALS!$V:$V,"<>*EXECUTED*"))} -> 0 | AA22: =U22*VLOOKUP(U$6,'FX RATES'!$E$1:$F$50,2,FALSE)+V22*VLOOKUP(V$6,'FX RATES'!$E$1:$F$50,2,FALSE)+W22*VLOOKUP(W$6,'FX RATES'!$E$1:$F$50,2,FALSE)+X22*VLOOKUP(X$6,'FX RATES'!$E$1:$F$50,2,FALSE)+Y22*VLOOKUP(Y$6,'FX RATES'!$E$1:$F$50,2,FALSE)+Z22*VLOOKUP(Z$6,'FX RATES'!$E$1:$F$50,2,FALSE) -> 0 | AC22: =I22+R22-AA22 -> 0
C23: {=SUMIFS(BALANCES!$C:$C,BALANCES!$A:$A,$B$2,BALANCES!$B:$B,$B23,BALANCES!$D:$D,C$6)+SUMIFS(FLOWS!$C:$C,FLOWS!$A:$A,$B$2,FLOWS!$E:$E,$B23,FLOWS!$D:$D,C$6,FLOWS!$H:$H,"<"&$C$4)+SUM(SUMIFS(DEALS!$J:$J,DEALS!$A:$A,{"*REFUND*","*EXECUTED*"},DEALS!$G:$G,$B$2,DEALS!$E:$E,"<"&$C$4,DEALS!$K:$K,C$6,DEALS!$M:$M,$B23,DEALS!$N:$N,"<>*RECEIVED*",DEALS!$N:$N,"<>*EXECUTED*"))+SUM(SUMIFS(DEALS!$R:$R,DEALS!$A:$A,{"*REFUND*","*EXECUTED*"},DEALS!$O:$O,$B$2,DEALS!$E:$E,"<"&$C$4,DEALS!$S:$S,C$6,DEALS!$U:$U,$B23,DEALS!$V:$V,"<>*RECEIVED*",DEALS!$V:$V,"<>*EXECUTED*"))} -> 0 | D23: {=SUMIFS(BALANCES!$C:$C,BALANCES!$A:$A,$B$2,BALANCES!$B:$B,$B23,BALANCES!$D:$D,D$6)+SUMIFS(FLOWS!$C:$C,FLOWS!$A:$A,$B$2,FLOWS!$E:$E,$B23,FLOWS!$D:$D,D$6,FLOWS!$H:$H,"<"&$C$4)+SUM(SUMIFS(DEALS!$J:$J,DEALS!$A:$A,{"*REFUND*","*EXECUTED*"},DEALS!$G:$G,$B$2,DEALS!$E:$E,"<"&$C$4,DEALS!$K:$K,D$6,DEALS!$M:$M,$B23,DEALS!$N:$N,"<>*RECEIVED*",DEALS!$N:$N,"<>*EXECUTED*"))+SUM(SUMIFS(DEALS!$R:$R,DEALS!$A:$A,{"*REFUND*","*EXECUTED*"},DEALS!$O:$O,$B$2,DEALS!$E:$E,"<"&$C$4,DEALS!$S:$S,D$6,DEALS!$U:$U,$B23,DEALS!$V:$V,"<>*RECEIVED*",DEALS!$V:$V,"<>*EXECUTED*"))} -> 0 | E23: {=SUMIFS(BALANCES!$C:$C,BALANCES!$A:$A,$B$2,BALANCES!$B:$B,$B23,BALANCES!$D:$D,E$6)+SUMIFS(FLOWS!$C:$C,FLOWS!$A:$A,$B$2,FLOWS!$E:$E,$B23,FLOWS!$D:$D,E$6,FLOWS!$H:$H,"<"&$C$4)+SUM(SUMIFS(DEALS!$J:$J,DEALS!$A:$A,{"*REFUND*","*EXECUTED*"},DEALS!$G:$G,$B$2,DEALS!$E:$E,"<"&$C$4,DEALS!$K:$K,E$6,DEALS!$M:$M,$B23,DEALS!$N:$N,"<>*RECEIVED*",DEALS!$N:$N,"<>*EXECUTED*"))+SUM(SUMIFS(DEALS!$R:$R,DEALS!$A:$A,{"*REFUND*","*EXECUTED*"},DEALS!$O:$O,$B$2,DEALS!$E:$E,"<"&$C$4,DEALS!$S:$S,E$6,DEALS!$U:$U,$B23,DEALS!$V:$V,"<>*RECEIVED*",DEALS!$V:$V,"<>*EXECUTED*"))} -> 0 | F23: {=SUMIFS(BALANCES!$C:$C,BALANCES!$A:$A,$B$2,BALANCES!$B:$B,$B23,BALANCES!$D:$D,F$6)+SUMIFS(FLOWS!$C:$C,FLOWS!$A:$A,$B$2,FLOWS!$E:$E,$B23,FLOWS!$D:$D,F$6,FLOWS!$H:$H,"<"&$C$4)+SUM(SUMIFS(DEALS!$J:$J,DEALS!$A:$A,{"*REFUND*","*EXECUTED*"},DEALS!$G:$G,$B$2,DEALS!$E:$E,"<"&$C$4,DEALS!$K:$K,F$6,DEALS!$M:$M,$B23,DEALS!$N:$N,"<>*RECEIVED*",DEALS!$N:$N,"<>*EXECUTED*"))+SUM(SUMIFS(DEALS!$R:$R,DEALS!$A:$A,{"*REFUND*","*EXECUTED*"},DEALS!$O:$O,$B$2,DEALS!$E:$E,"<"&$C$4,DEALS!$S:$S,F$6,DEALS!$U:$U,$B23,DEALS!$V:$V,"<>*RECEIVED*",DEALS!$V:$V,"<>*EXECUTED*"))} -> 0 | G23: {=SUMIFS(BALANCES!$C:$C,BALANCES!$A:$A,$B$2,BALANCES!$B:$B,$B23,BALANCES!$D:$D,G$6)+SUMIFS(FLOWS!$C:$C,FLOWS!$A:$A,$B$2,FLOWS!$E:$E,$B23,FLOWS!$D:$D,G$6,FLOWS!$H:$H,"<"&$C$4)+SUM(SUMIFS(DEALS!$J:$J,DEALS!$A:$A,{"*REFUND*","*EXECUTED*"},DEALS!$G:$G,$B$2,DEALS!$E:$E,"<"&$C$4,DEALS!$K:$K,G$6,DEALS!$M:$M,$B23,DEALS!$N:$N,"<>*RECEIVED*",DEALS!$N:$N,"<>*EXECUTED*"))+SUM(SUMIFS(DEALS!$R:$R,DEALS!$A:$A,{"*REFUND*","*EXECUTED*"},DEALS!$O:$O,$B$2,DEALS!$E:$E,"<"&$C$4,DEALS!$S:$S,G$6,DEALS!$U:$U,$B23,DEALS!$V:$V,"<>*RECEIVED*",DEALS!$V:$V,"<>*EXECUTED*"))} -> 0 | H23: {=SUMIFS(BALANCES!$C:$C,BALANCES!$A:$A,$B$2,BALANCES!$B:$B,$B23,BALANCES!$D:$D,H$6)+SUMIFS(FLOWS!$C:$C,FLOWS!$A:$A,$B$2,FLOWS!$E:$E,$B23,FLOWS!$D:$D,H$6,FLOWS!$H:$H,"<"&$C$4)+SUM(SUMIFS(DEALS!$J:$J,DEALS!$A:$A,{"*REFUND*","*EXECUTED*"},DEALS!$G:$G,$B$2,DEALS!$E:$E,"<"&$C$4,DEALS!$K:$K,H$6,DEALS!$M:$M,$B23,DEALS!$N:$N,"<>*RECEIVED*",DEALS!$N:$N,"<>*EXECUTED*"))+SUM(SUMIFS(DEALS!$R:$R,DEALS!$A:$A,{"*REFUND*","*EXECUTED*"},DEALS!$O:$O,$B$2,DEALS!$E:$E,"<"&$C$4,DEALS!$S:$S,H$6,DEALS!$U:$U,$B23,DEALS!$V:$V,"<>*RECEIVED*",DEALS!$V:$V,"<>*EXECUTED*"))} -> 0 | I23: =C23*VLOOKUP(C$6,'FX RATES'!$E$1:$F$50,2,FALSE)+D23*VLOOKUP(D$6,'FX RATES'!$E$1:$F$50,2,FALSE)+E23*VLOOKUP(E$6,'FX RATES'!$E$1:$F$50,2,FALSE)+F23*VLOOKUP(F$6,'FX RATES'!$E$1:$F$50,2,FALSE)+G23*VLOOKUP(G$6,'FX RATES'!$E$1:$F$50,2,FALSE)+H23*VLOOKUP(H$6,'FX RATES'!$E$1:$F$50,2,FALSE) -> 0 | K23: =B23 -> 0 | L23: {=SUMIFS(FLOWS!$C:$C,FLOWS!$A:$A,$B$2,FLOWS!$E:$E,$K23,FLOWS!$D:$D,L$6,FLOWS!$H:$H,">="&$C$4,FLOWS!$H:$H,"<="&$U$4)+SUM(SUMIFS(DEALS!$J:$J,DEALS!$A:$A,{"*REFUND*","*EXECUTED*"},DEALS!$G:$G,$B$2,DEALS!$E:$E,">="&$C$4,DEALS!$E:$E,"<="&$U$4,DEALS!$K:$K,L$6,DEALS!$M:$M,$K23,DEALS!$N:$N,"<>*RECEIVED*",DEALS!$N:$N,"<>*EXECUTED*"))+SUM(SUMIFS(DEALS!$R:$R,DEALS!$A:$A,{"*REFUND*","*EXECUTED*"},DEALS!$O:$O,$B$2,DEALS!$E:$E,">="&$C$4,DEALS!$E:$E,"<="&$U$4,DEALS!$S:$S,L$6,DEALS!$U:$U,$K23,DEALS!$V:$V,"<>*RECEIVED*",DEALS!$V:$V,"<>*EXECUTED*"))} -> 0 | M23: {=SUMIFS(FLOWS!$C:$C,FLOWS!$A:$A,$B$2,FLOWS!$E:$E,$K23,FLOWS!$D:$D,M$6,FLOWS!$H:$H,">="&$C$4,FLOWS!$H:$H,"<="&$U$4)+SUM(SUMIFS(DEALS!$J:$J,DEALS!$A:$A,{"*REFUND*","*EXECUTED*"},DEALS!$G:$G,$B$2,DEALS!$E:$E,">="&$C$4,DEALS!$E:$E,"<="&$U$4,DEALS!$K:$K,M$6,DEALS!$M:$M,$K23,DEALS!$N:$N,"<>*RECEIVED*",DEALS!$N:$N,"<>*EXECUTED*"))+SUM(SUMIFS(DEALS!$R:$R,DEALS!$A:$A,{"*REFUND*","*EXECUTED*"},DEALS!$O:$O,$B$2,DEALS!$E:$E,">="&$C$4,DEALS!$E:$E,"<="&$U$4,DEALS!$S:$S,M$6,DEALS!$U:$U,$K23,DEALS!$V:$V,"<>*RECEIVED*",DEALS!$V:$V,"<>*EXECUTED*"))} -> 0 | N23: {=SUMIFS(FLOWS!$C:$C,FLOWS!$A:$A,$B$2,FLOWS!$E:$E,$K23,FLOWS!$D:$D,N$6,FLOWS!$H:$H,">="&$C$4,FLOWS!$H:$H,"<="&$U$4)+SUM(SUMIFS(DEALS!$J:$J,DEALS!$A:$A,{"*REFUND*","*EXECUTED*"},DEALS!$G:$G,$B$2,DEALS!$E:$E,">="&$C$4,DEALS!$E:$E,"<="&$U$4,DEALS!$K:$K,N$6,DEALS!$M:$M,$K23,DEALS!$N:$N,"<>*RECEIVED*",DEALS!$N:$N,"<>*EXECUTED*"))+SUM(SUMIFS(DEALS!$R:$R,DEALS!$A:$A,{"*REFUND*","*EXECUTED*"},DEALS!$O:$O,$B$2,DEALS!$E:$E,">="&$C$4,DEALS!$E:$E,"<="&$U$4,DEALS!$S:$S,N$6,DEALS!$U:$U,$K23,DEALS!$V:$V,"<>*RECEIVED*",DEALS!$V:$V,"<>*EXECUTED*"))} -> 0 | O23: {=SUMIFS(FLOWS!$C:$C,FLOWS!$A:$A,$B$2,FLOWS!$E:$E,$K23,FLOWS!$D:$D,O$6,FLOWS!$H:$H,">="&$C$4,FLOWS!$H:$H,"<="&$U$4)+SUM(SUMIFS(DEALS!$J:$J,DEALS!$A:$A,{"*REFUND*","*EXECUTED*"},DEALS!$G:$G,$B$2,DEALS!$E:$E,">="&$C$4,DEALS!$E:$E,"<="&$U$4,DEALS!$K:$K,O$6,DEALS!$M:$M,$K23,DEALS!$N:$N,"<>*RECEIVED*",DEALS!$N:$N,"<>*EXECUTED*"))+SUM(SUMIFS(DEALS!$R:$R,DEALS!$A:$A,{"*REFUND*","*EXECUTED*"},DEALS!$O:$O,$B$2,DEALS!$E:$E,">="&$C$4,DEALS!$E:$E,"<="&$U$4,DEALS!$S:$S,O$6,DEALS!$U:$U,$K23,DEALS!$V:$V,"<>*RECEIVED*",DEALS!$V:$V,"<>*EXECUTED*"))} -> 0 | P23: {=SUMIFS(FLOWS!$C:$C,FLOWS!$A:$A,$B$2,FLOWS!$E:$E,$K23,FLOWS!$D:$D,P$6,FLOWS!$H:$H,">="&$C$4,FLOWS!$H:$H,"<="&$U$4)+SUM(SUMIFS(DEALS!$J:$J,DEALS!$A:$A,{"*REFUND*","*EXECUTED*"},DEALS!$G:$G,$B$2,DEALS!$E:$E,">="&$C$4,DEALS!$E:$E,"<="&$U$4,DEALS!$K:$K,P$6,DEALS!$M:$M,$K23,DEALS!$N:$N,"<>*RECEIVED*",DEALS!$N:$N,"<>*EXECUTED*"))+SUM(SUMIFS(DEALS!$R:$R,DEALS!$A:$A,{"*REFUND*","*EXECUTED*"},DEALS!$O:$O,$B$2,DEALS!$E:$E,">="&$C$4,DEALS!$E:$E,"<="&$U$4,DEALS!$S:$S,P$6,DEALS!$U:$U,$K23,DEALS!$V:$V,"<>*RECEIVED*",DEALS!$V:$V,"<>*EXECUTED*"))} -> 0 | Q23: {=SUMIFS(FLOWS!$C:$C,FLOWS!$A:$A,$B$2,FLOWS!$E:$E,$K23,FLOWS!$D:$D,Q$6,FLOWS!$H:$H,">="&$C$4,FLOWS!$H:$H,"<="&$U$4)+SUM(SUMIFS(DEALS!$J:$J,DEALS!$A:$A,{"*REFUND*","*EXECUTED*"},DEALS!$G:$G,$B$2,DEALS!$E:$E,">="&$C$4,DEALS!$E:$E,"<="&$U$4,DEALS!$K:$K,Q$6,DEALS!$M:$M,$K23,DEALS!$N:$N,"<>*RECEIVED*",DEALS!$N:$N,"<>*EXECUTED*"))+SUM(SUMIFS(DEALS!$R:$R,DEALS!$A:$A,{"*REFUND*","*EXECUTED*"},DEALS!$O:$O,$B$2,DEALS!$E:$E,">="&$C$4,DEALS!$E:$E,"<="&$U$4,DEALS!$S:$S,Q$6,DEALS!$U:$U,$K23,DEALS!$V:$V,"<>*RECEIVED*",DEALS!$V:$V,"<>*EXECUTED*"))} -> 0 | R23: =L23*VLOOKUP(L$6,'FX RATES'!$E$1:$F$50,2,FALSE)+M23*VLOOKUP(M$6,'FX RATES'!$E$1:$F$50,2,FALSE)+N23*VLOOKUP(N$6,'FX RATES'!$E$1:$F$50,2,FALSE)+O23*VLOOKUP(O$6,'FX RATES'!$E$1:$F$50,2,FALSE)+P23*VLOOKUP(P$6,'FX RATES'!$E$1:$F$50,2,FALSE)+Q23*VLOOKUP(Q$6,'FX RATES'!$E$1:$F$50,2,FALSE) -> 0 | T23: =B23 -> 0 | U23: {=SUMIFS(BALANCES!$C:$C,BALANCES!$A:$A,$B$2,BALANCES!$B:$B,$T23,BALANCES!$D:$D,U$6)+SUMIFS(FLOWS!$C:$C,FLOWS!$A:$A,$B$2,FLOWS!$E:$E,$T23,FLOWS!$D:$D,U$6,FLOWS!$H:$H,"<="&$U$4)+SUM(SUMIFS(DEALS!$J:$J,DEALS!$A:$A,{"*REFUND*","*EXECUTED*"},DEALS!$G:$G,$B$2,DEALS!$E:$E,"<="&$U$4,DEALS!$K:$K,U$6,DEALS!$M:$M,$T23,DEALS!$N:$N,"<>*RECEIVED*",DEALS!$N:$N,"<>*EXECUTED*"))+SUM(SUMIFS(DEALS!$R:$R,DEALS!$A:$A,{"*REFUND*","*EXECUTED*"},DEALS!$O:$O,$B$2,DEALS!$E:$E,"<="&$U$4,DEALS!$S:$S,U$6,DEALS!$U:$U,$T23,DEALS!$V:$V,"<>*RECEIVED*",DEALS!$V:$V,"<>*EXECUTED*"))} -> 0 | V23: {=SUMIFS(BALANCES!$C:$C,BALANCES!$A:$A,$B$2,BALANCES!$B:$B,$T23,BALANCES!$D:$D,V$6)+SUMIFS(FLOWS!$C:$C,FLOWS!$A:$A,$B$2,FLOWS!$E:$E,$T23,FLOWS!$D:$D,V$6,FLOWS!$H:$H,"<="&$U$4)+SUM(SUMIFS(DEALS!$J:$J,DEALS!$A:$A,{"*REFUND*","*EXECUTED*"},DEALS!$G:$G,$B$2,DEALS!$E:$E,"<="&$U$4,DEALS!$K:$K,V$6,DEALS!$M:$M,$T23,DEALS!$N:$N,"<>*RECEIVED*",DEALS!$N:$N,"<>*EXECUTED*"))+SUM(SUMIFS(DEALS!$R:$R,DEALS!$A:$A,{"*REFUND*","*EXECUTED*"},DEALS!$O:$O,$B$2,DEALS!$E:$E,"<="&$U$4,DEALS!$S:$S,V$6,DEALS!$U:$U,$T23,DEALS!$V:$V,"<>*RECEIVED*",DEALS!$V:$V,"<>*EXECUTED*"))} -> 0 | W23: {=SUMIFS(BALANCES!$C:$C,BALANCES!$A:$A,$B$2,BALANCES!$B:$B,$T23,BALANCES!$D:$D,W$6)+SUMIFS(FLOWS!$C:$C,FLOWS!$A:$A,$B$2,FLOWS!$E:$E,$T23,FLOWS!$D:$D,W$6,FLOWS!$H:$H,"<="&$U$4)+SUM(SUMIFS(DEALS!$J:$J,DEALS!$A:$A,{"*REFUND*","*EXECUTED*"},DEALS!$G:$G,$B$2,DEALS!$E:$E,"<="&$U$4,DEALS!$K:$K,W$6,DEALS!$M:$M,$T23,DEALS!$N:$N,"<>*RECEIVED*",DEALS!$N:$N,"<>*EXECUTED*"))+SUM(SUMIFS(DEALS!$R:$R,DEALS!$A:$A,{"*REFUND*","*EXECUTED*"},DEALS!$O:$O,$B$2,DEALS!$E:$E,"<="&$U$4,DEALS!$S:$S,W$6,DEALS!$U:$U,$T23,DEALS!$V:$V,"<>*RECEIVED*",DEALS!$V:$V,"<>*EXECUTED*"))} -> 0 | X23: {=SUMIFS(BALANCES!$C:$C,BALANCES!$A:$A,$B$2,BALANCES!$B:$B,$T23,BALANCES!$D:$D,X$6)+SUMIFS(FLOWS!$C:$C,FLOWS!$A:$A,$B$2,FLOWS!$E:$E,$T23,FLOWS!$D:$D,X$6,FLOWS!$H:$H,"<="&$U$4)+SUM(SUMIFS(DEALS!$J:$J,DEALS!$A:$A,{"*REFUND*","*EXECUTED*"},DEALS!$G:$G,$B$2,DEALS!$E:$E,"<="&$U$4,DEALS!$K:$K,X$6,DEALS!$M:$M,$T23,DEALS!$N:$N,"<>*RECEIVED*",DEALS!$N:$N,"<>*EXECUTED*"))+SUM(SUMIFS(DEALS!$R:$R,DEALS!$A:$A,{"*REFUND*","*EXECUTED*"},DEALS!$O:$O,$B$2,DEALS!$E:$E,"<="&$U$4,DEALS!$S:$S,X$6,DEALS!$U:$U,$T23,DEALS!$V:$V,"<>*RECEIVED*",DEALS!$V:$V,"<>*EXECUTED*"))} -> 0 | Y23: {=SUMIFS(BALANCES!$C:$C,BALANCES!$A:$A,$B$2,BALANCES!$B:$B,$T23,BALANCES!$D:$D,Y$6)+SUMIFS(FLOWS!$C:$C,FLOWS!$A:$A,$B$2,FLOWS!$E:$E,$T23,FLOWS!$D:$D,Y$6,FLOWS!$H:$H,"<="&$U$4)+SUM(SUMIFS(DEALS!$J:$J,DEALS!$A:$A,{"*REFUND*","*EXECUTED*"},DEALS!$G:$G,$B$2,DEALS!$E:$E,"<="&$U$4,DEALS!$K:$K,Y$6,DEALS!$M:$M,$T23,DEALS!$N:$N,"<>*RECEIVED*",DEALS!$N:$N,"<>*EXECUTED*"))+SUM(SUMIFS(DEALS!$R:$R,DEALS!$A:$A,{"*REFUND*","*EXECUTED*"},DEALS!$O:$O,$B$2,DEALS!$E:$E,"<="&$U$4,DEALS!$S:$S,Y$6,DEALS!$U:$U,$T23,DEALS!$V:$V,"<>*RECEIVED*",DEALS!$V:$V,"<>*EXECUTED*"))} -> 0 | Z23: {=SUMIFS(BALANCES!$C:$C,BALANCES!$A:$A,$B$2,BALANCES!$B:$B,$T23,BALANCES!$D:$D,Z$6)+SUMIFS(FLOWS!$C:$C,FLOWS!$A:$A,$B$2,FLOWS!$E:$E,$T23,FLOWS!$D:$D,Z$6,FLOWS!$H:$H,"<="&$U$4)+SUM(SUMIFS(DEALS!$J:$J,DEALS!$A:$A,{"*REFUND*","*EXECUTED*"},DEALS!$G:$G,$B$2,DEALS!$E:$E,"<="&$U$4,DEALS!$K:$K,Z$6,DEALS!$M:$M,$T23,DEALS!$N:$N,"<>*RECEIVED*",DEALS!$N:$N,"<>*EXECUTED*"))+SUM(SUMIFS(DEALS!$R:$R,DEALS!$A:$A,{"*REFUND*","*EXECUTED*"},DEALS!$O:$O,$B$2,DEALS!$E:$E,"<="&$U$4,DEALS!$S:$S,Z$6,DEALS!$U:$U,$T23,DEALS!$V:$V,"<>*RECEIVED*",DEALS!$V:$V,"<>*EXECUTED*"))} -> 0 | AA23: =U23*VLOOKUP(U$6,'FX RATES'!$E$1:$F$50,2,FALSE)+V23*VLOOKUP(V$6,'FX RATES'!$E$1:$F$50,2,FALSE)+W23*VLOOKUP(W$6,'FX RATES'!$E$1:$F$50,2,FALSE)+X23*VLOOKUP(X$6,'FX RATES'!$E$1:$F$50,2,FALSE)+Y23*VLOOKUP(Y$6,'FX RATES'!$E$1:$F$50,2,FALSE)+Z23*VLOOKUP(Z$6,'FX RATES'!$E$1:$F$50,2,FALSE) -> 0 | AC23: =I23+R23-AA23 -> 0
C24: {=SUMIFS(BALANCES!$C:$C,BALANCES!$A:$A,$B$2,BALANCES!$B:$B,$B24,BALANCES!$D:$D,C$6)+SUMIFS(FLOWS!$C:$C,FLOWS!$A:$A,$B$2,FLOWS!$E:$E,$B24,FLOWS!$D:$D,C$6,FLOWS!$H:$H,"<"&$C$4)+SUM(SUMIFS(DEALS!$J:$J,DEALS!$A:$A,{"*REFUND*","*EXECUTED*"},DEALS!$G:$G,$B$2,DEALS!$E:$E,"<"&$C$4,DEALS!$K:$K,C$6,DEALS!$M:$M,$B24,DEALS!$N:$N,"<>*RECEIVED*",DEALS!$N:$N,"<>*EXECUTED*"))+SUM(SUMIFS(DEALS!$R:$R,DEALS!$A:$A,{"*REFUND*","*EXECUTED*"},DEALS!$O:$O,$B$2,DEALS!$E:$E,"<"&$C$4,DEALS!$S:$S,C$6,DEALS!$U:$U,$B24,DEALS!$V:$V,"<>*RECEIVED*",DEALS!$V:$V,"<>*EXECUTED*"))} -> 0 | D24: {=SUMIFS(BALANCES!$C:$C,BALANCES!$A:$A,$B$2,BALANCES!$B:$B,$B24,BALANCES!$D:$D,D$6)+SUMIFS(FLOWS!$C:$C,FLOWS!$A:$A,$B$2,FLOWS!$E:$E,$B24,FLOWS!$D:$D,D$6,FLOWS!$H:$H,"<"&$C$4)+SUM(SUMIFS(DEALS!$J:$J,DEALS!$A:$A,{"*REFUND*","*EXECUTED*"},DEALS!$G:$G,$B$2,DEALS!$E:$E,"<"&$C$4,DEALS!$K:$K,D$6,DEALS!$M:$M,$B24,DEALS!$N:$N,"<>*RECEIVED*",DEALS!$N:$N,"<>*EXECUTED*"))+SUM(SUMIFS(DEALS!$R:$R,DEALS!$A:$A,{"*REFUND*","*EXECUTED*"},DEALS!$O:$O,$B$2,DEALS!$E:$E,"<"&$C$4,DEALS!$S:$S,D$6,DEALS!$U:$U,$B24,DEALS!$V:$V,"<>*RECEIVED*",DEALS!$V:$V,"<>*EXECUTED*"))} -> 0 | E24: {=SUMIFS(BALANCES!$C:$C,BALANCES!$A:$A,$B$2,BALANCES!$B:$B,$B24,BALANCES!$D:$D,E$6)+SUMIFS(FLOWS!$C:$C,FLOWS!$A:$A,$B$2,FLOWS!$E:$E,$B24,FLOWS!$D:$D,E$6,FLOWS!$H:$H,"<"&$C$4)+SUM(SUMIFS(DEALS!$J:$J,DEALS!$A:$A,{"*REFUND*","*EXECUTED*"},DEALS!$G:$G,$B$2,DEALS!$E:$E,"<"&$C$4,DEALS!$K:$K,E$6,DEALS!$M:$M,$B24,DEALS!$N:$N,"<>*RECEIVED*",DEALS!$N:$N,"<>*EXECUTED*"))+SUM(SUMIFS(DEALS!$R:$R,DEALS!$A:$A,{"*REFUND*","*EXECUTED*"},DEALS!$O:$O,$B$2,DEALS!$E:$E,"<"&$C$4,DEALS!$S:$S,E$6,DEALS!$U:$U,$B24,DEALS!$V:$V,"<>*RECEIVED*",DEALS!$V:$V,"<>*EXECUTED*"))} -> 0 | F24: {=SUMIFS(BALANCES!$C:$C,BALANCES!$A:$A,$B$2,BALANCES!$B:$B,$B24,BALANCES!$D:$D,F$6)+SUMIFS(FLOWS!$C:$C,FLOWS!$A:$A,$B$2,FLOWS!$E:$E,$B24,FLOWS!$D:$D,F$6,FLOWS!$H:$H,"<"&$C$4)+SUM(SUMIFS(DEALS!$J:$J,DEALS!$A:$A,{"*REFUND*","*EXECUTED*"},DEALS!$G:$G,$B$2,DEALS!$E:$E,"<"&$C$4,DEALS!$K:$K,F$6,DEALS!$M:$M,$B24,DEALS!$N:$N,"<>*RECEIVED*",DEALS!$N:$N,"<>*EXECUTED*"))+SUM(SUMIFS(DEALS!$R:$R,DEALS!$A:$A,{"*REFUND*","*EXECUTED*"},DEALS!$O:$O,$B$2,DEALS!$E:$E,"<"&$C$4,DEALS!$S:$S,F$6,DEALS!$U:$U,$B24,DEALS!$V:$V,"<>*RECEIVED*",DEALS!$V:$V,"<>*EXECUTED*"))} -> 0 | G24: {=SUMIFS(BALANCES!$C:$C,BALANCES!$A:$A,$B$2,BALANCES!$B:$B,$B24,BALANCES!$D:$D,G$6)+SUMIFS(FLOWS!$C:$C,FLOWS!$A:$A,$B$2,FLOWS!$E:$E,$B24,FLOWS!$D:$D,G$6,FLOWS!$H:$H,"<"&$C$4)+SUM(SUMIFS(DEALS!$J:$J,DEALS!$A:$A,{"*REFUND*","*EXECUTED*"},DEALS!$G:$G,$B$2,DEALS!$E:$E,"<"&$C$4,DEALS!$K:$K,G$6,DEALS!$M:$M,$B24,DEALS!$N:$N,"<>*RECEIVED*",DEALS!$N:$N,"<>*EXECUTED*"))+SUM(SUMIFS(DEALS!$R:$R,DEALS!$A:$A,{"*REFUND*","*EXECUTED*"},DEALS!$O:$O,$B$2,DEALS!$E:$E,"<"&$C$4,DEALS!$S:$S,G$6,DEALS!$U:$U,$B24,DEALS!$V:$V,"<>*RECEIVED*",DEALS!$V:$V,"<>*EXECUTED*"))} -> 0 | H24: {=SUMIFS(BALANCES!$C:$C,BALANCES!$A:$A,$B$2,BALANCES!$B:$B,$B24,BALANCES!$D:$D,H$6)+SUMIFS(FLOWS!$C:$C,FLOWS!$A:$A,$B$2,FLOWS!$E:$E,$B24,FLOWS!$D:$D,H$6,FLOWS!$H:$H,"<"&$C$4)+SUM(SUMIFS(DEALS!$J:$J,DEALS!$A:$A,{"*REFUND*","*EXECUTED*"},DEALS!$G:$G,$B$2,DEALS!$E:$E,"<"&$C$4,DEALS!$K:$K,H$6,DEALS!$M:$M,$B24,DEALS!$N:$N,"<>*RECEIVED*",DEALS!$N:$N,"<>*EXECUTED*"))+SUM(SUMIFS(DEALS!$R:$R,DEALS!$A:$A,{"*REFUND*","*EXECUTED*"},DEALS!$O:$O,$B$2,DEALS!$E:$E,"<"&$C$4,DEALS!$S:$S,H$6,DEALS!$U:$U,$B24,DEALS!$V:$V,"<>*RECEIVED*",DEALS!$V:$V,"<>*EXECUTED*"))} -> 0 | I24: =C24*VLOOKUP(C$6,'FX RATES'!$E$1:$F$50,2,FALSE)+D24*VLOOKUP(D$6,'FX RATES'!$E$1:$F$50,2,FALSE)+E24*VLOOKUP(E$6,'FX RATES'!$E$1:$F$50,2,FALSE)+F24*VLOOKUP(F$6,'FX RATES'!$E$1:$F$50,2,FALSE)+G24*VLOOKUP(G$6,'FX RATES'!$E$1:$F$50,2,FALSE)+H24*VLOOKUP(H$6,'FX RATES'!$E$1:$F$50,2,FALSE) -> 0 | K24: =B24 -> 0 | L24: {=SUMIFS(FLOWS!$C:$C,FLOWS!$A:$A,$B$2,FLOWS!$E:$E,$K24,FLOWS!$D:$D,L$6,FLOWS!$H:$H,">="&$C$4,FLOWS!$H:$H,"<="&$U$4)+SUM(SUMIFS(DEALS!$J:$J,DEALS!$A:$A,{"*REFUND*","*EXECUTED*"},DEALS!$G:$G,$B$2,DEALS!$E:$E,">="&$C$4,DEALS!$E:$E,"<="&$U$4,DEALS!$K:$K,L$6,DEALS!$M:$M,$K24,DEALS!$N:$N,"<>*RECEIVED*",DEALS!$N:$N,"<>*EXECUTED*"))+SUM(SUMIFS(DEALS!$R:$R,DEALS!$A:$A,{"*REFUND*","*EXECUTED*"},DEALS!$O:$O,$B$2,DEALS!$E:$E,">="&$C$4,DEALS!$E:$E,"<="&$U$4,DEALS!$S:$S,L$6,DEALS!$U:$U,$K24,DEALS!$V:$V,"<>*RECEIVED*",DEALS!$V:$V,"<>*EXECUTED*"))} -> 0 | M24: {=SUMIFS(FLOWS!$C:$C,FLOWS!$A:$A,$B$2,FLOWS!$E:$E,$K24,FLOWS!$D:$D,M$6,FLOWS!$H:$H,">="&$C$4,FLOWS!$H:$H,"<="&$U$4)+SUM(SUMIFS(DEALS!$J:$J,DEALS!$A:$A,{"*REFUND*","*EXECUTED*"},DEALS!$G:$G,$B$2,DEALS!$E:$E,">="&$C$4,DEALS!$E:$E,"<="&$U$4,DEALS!$K:$K,M$6,DEALS!$M:$M,$K24,DEALS!$N:$N,"<>*RECEIVED*",DEALS!$N:$N,"<>*EXECUTED*"))+SUM(SUMIFS(DEALS!$R:$R,DEALS!$A:$A,{"*REFUND*","*EXECUTED*"},DEALS!$O:$O,$B$2,DEALS!$E:$E,">="&$C$4,DEALS!$E:$E,"<="&$U$4,DEALS!$S:$S,M$6,DEALS!$U:$U,$K24,DEALS!$V:$V,"<>*RECEIVED*",DEALS!$V:$V,"<>*EXECUTED*"))} -> 0 | N24: {=SUMIFS(FLOWS!$C:$C,FLOWS!$A:$A,$B$2,FLOWS!$E:$E,$K24,FLOWS!$D:$D,N$6,FLOWS!$H:$H,">="&$C$4,FLOWS!$H:$H,"<="&$U$4)+SUM(SUMIFS(DEALS!$J:$J,DEALS!$A:$A,{"*REFUND*","*EXECUTED*"},DEALS!$G:$G,$B$2,DEALS!$E:$E,">="&$C$4,DEALS!$E:$E,"<="&$U$4,DEALS!$K:$K,N$6,DEALS!$M:$M,$K24,DEALS!$N:$N,"<>*RECEIVED*",DEALS!$N:$N,"<>*EXECUTED*"))+SUM(SUMIFS(DEALS!$R:$R,DEALS!$A:$A,{"*REFUND*","*EXECUTED*"},DEALS!$O:$O,$B$2,DEALS!$E:$E,">="&$C$4,DEALS!$E:$E,"<="&$U$4,DEALS!$S:$S,N$6,DEALS!$U:$U,$K24,DEALS!$V:$V,"<>*RECEIVED*",DEALS!$V:$V,"<>*EXECUTED*"))} -> 0 | O24: {=SUMIFS(FLOWS!$C:$C,FLOWS!$A:$A,$B$2,FLOWS!$E:$E,$K24,FLOWS!$D:$D,O$6,FLOWS!$H:$H,">="&$C$4,FLOWS!$H:$H,"<="&$U$4)+SUM(SUMIFS(DEALS!$J:$J,DEALS!$A:$A,{"*REFUND*","*EXECUTED*"},DEALS!$G:$G,$B$2,DEALS!$E:$E,">="&$C$4,DEALS!$E:$E,"<="&$U$4,DEALS!$K:$K,O$6,DEALS!$M:$M,$K24,DEALS!$N:$N,"<>*RECEIVED*",DEALS!$N:$N,"<>*EXECUTED*"))+SUM(SUMIFS(DEALS!$R:$R,DEALS!$A:$A,{"*REFUND*","*EXECUTED*"},DEALS!$O:$O,$B$2,DEALS!$E:$E,">="&$C$4,DEALS!$E:$E,"<="&$U$4,DEALS!$S:$S,O$6,DEALS!$U:$U,$K24,DEALS!$V:$V,"<>*RECEIVED*",DEALS!$V:$V,"<>*EXECUTED*"))} -> 0 | P24: {=SUMIFS(FLOWS!$C:$C,FLOWS!$A:$A,$B$2,FLOWS!$E:$E,$K24,FLOWS!$D:$D,P$6,FLOWS!$H:$H,">="&$C$4,FLOWS!$H:$H,"<="&$U$4)+SUM(SUMIFS(DEALS!$J:$J,DEALS!$A:$A,{"*REFUND*","*EXECUTED*"},DEALS!$G:$G,$B$2,DEALS!$E:$E,">="&$C$4,DEALS!$E:$E,"<="&$U$4,DEALS!$K:$K,P$6,DEALS!$M:$M,$K24,DEALS!$N:$N,"<>*RECEIVED*",DEALS!$N:$N,"<>*EXECUTED*"))+SUM(SUMIFS(DEALS!$R:$R,DEALS!$A:$A,{"*REFUND*","*EXECUTED*"},DEALS!$O:$O,$B$2,DEALS!$E:$E,">="&$C$4,DEALS!$E:$E,"<="&$U$4,DEALS!$S:$S,P$6,DEALS!$U:$U,$K24,DEALS!$V:$V,"<>*RECEIVED*",DEALS!$V:$V,"<>*EXECUTED*"))} -> 0 | Q24: {=SUMIFS(FLOWS!$C:$C,FLOWS!$A:$A,$B$2,FLOWS!$E:$E,$K24,FLOWS!$D:$D,Q$6,FLOWS!$H:$H,">="&$C$4,FLOWS!$H:$H,"<="&$U$4)+SUM(SUMIFS(DEALS!$J:$J,DEALS!$A:$A,{"*REFUND*","*EXECUTED*"},DEALS!$G:$G,$B$2,DEALS!$E:$E,">="&$C$4,DEALS!$E:$E,"<="&$U$4,DEALS!$K:$K,Q$6,DEALS!$M:$M,$K24,DEALS!$N:$N,"<>*RECEIVED*",DEALS!$N:$N,"<>*EXECUTED*"))+SUM(SUMIFS(DEALS!$R:$R,DEALS!$A:$A,{"*REFUND*","*EXECUTED*"},DEALS!$O:$O,$B$2,DEALS!$E:$E,">="&$C$4,DEALS!$E:$E,"<="&$U$4,DEALS!$S:$S,Q$6,DEALS!$U:$U,$K24,DEALS!$V:$V,"<>*RECEIVED*",DEALS!$V:$V,"<>*EXECUTED*"))} -> 0 | R24: =L24*VLOOKUP(L$6,'FX RATES'!$E$1:$F$50,2,FALSE)+M24*VLOOKUP(M$6,'FX RATES'!$E$1:$F$50,2,FALSE)+N24*VLOOKUP(N$6,'FX RATES'!$E$1:$F$50,2,FALSE)+O24*VLOOKUP(O$6,'FX RATES'!$E$1:$F$50,2,FALSE)+P24*VLOOKUP(P$6,'FX RATES'!$E$1:$F$50,2,FALSE)+Q24*VLOOKUP(Q$6,'FX RATES'!$E$1:$F$50,2,FALSE) -> 0 | T24: =B24 -> 0 | U24: {=SUMIFS(BALANCES!$C:$C,BALANCES!$A:$A,$B$2,BALANCES!$B:$B,$T24,BALANCES!$D:$D,U$6)+SUMIFS(FLOWS!$C:$C,FLOWS!$A:$A,$B$2,FLOWS!$E:$E,$T24,FLOWS!$D:$D,U$6,FLOWS!$H:$H,"<="&$U$4)+SUM(SUMIFS(DEALS!$J:$J,DEALS!$A:$A,{"*REFUND*","*EXECUTED*"},DEALS!$G:$G,$B$2,DEALS!$E:$E,"<="&$U$4,DEALS!$K:$K,U$6,DEALS!$M:$M,$T24,DEALS!$N:$N,"<>*RECEIVED*",DEALS!$N:$N,"<>*EXECUTED*"))+SUM(SUMIFS(DEALS!$R:$R,DEALS!$A:$A,{"*REFUND*","*EXECUTED*"},DEALS!$O:$O,$B$2,DEALS!$E:$E,"<="&$U$4,DEALS!$S:$S,U$6,DEALS!$U:$U,$T24,DEALS!$V:$V,"<>*RECEIVED*",DEALS!$V:$V,"<>*EXECUTED*"))} -> 0 | V24: {=SUMIFS(BALANCES!$C:$C,BALANCES!$A:$A,$B$2,BALANCES!$B:$B,$T24,BALANCES!$D:$D,V$6)+SUMIFS(FLOWS!$C:$C,FLOWS!$A:$A,$B$2,FLOWS!$E:$E,$T24,FLOWS!$D:$D,V$6,FLOWS!$H:$H,"<="&$U$4)+SUM(SUMIFS(DEALS!$J:$J,DEALS!$A:$A,{"*REFUND*","*EXECUTED*"},DEALS!$G:$G,$B$2,DEALS!$E:$E,"<="&$U$4,DEALS!$K:$K,V$6,DEALS!$M:$M,$T24,DEALS!$N:$N,"<>*RECEIVED*",DEALS!$N:$N,"<>*EXECUTED*"))+SUM(SUMIFS(DEALS!$R:$R,DEALS!$A:$A,{"*REFUND*","*EXECUTED*"},DEALS!$O:$O,$B$2,DEALS!$E:$E,"<="&$U$4,DEALS!$S:$S,V$6,DEALS!$U:$U,$T24,DEALS!$V:$V,"<>*RECEIVED*",DEALS!$V:$V,"<>*EXECUTED*"))} -> 0 | W24: {=SUMIFS(BALANCES!$C:$C,BALANCES!$A:$A,$B$2,BALANCES!$B:$B,$T24,BALANCES!$D:$D,W$6)+SUMIFS(FLOWS!$C:$C,FLOWS!$A:$A,$B$2,FLOWS!$E:$E,$T24,FLOWS!$D:$D,W$6,FLOWS!$H:$H,"<="&$U$4)+SUM(SUMIFS(DEALS!$J:$J,DEALS!$A:$A,{"*REFUND*","*EXECUTED*"},DEALS!$G:$G,$B$2,DEALS!$E:$E,"<="&$U$4,DEALS!$K:$K,W$6,DEALS!$M:$M,$T24,DEALS!$N:$N,"<>*RECEIVED*",DEALS!$N:$N,"<>*EXECUTED*"))+SUM(SUMIFS(DEALS!$R:$R,DEALS!$A:$A,{"*REFUND*","*EXECUTED*"},DEALS!$O:$O,$B$2,DEALS!$E:$E,"<="&$U$4,DEALS!$S:$S,W$6,DEALS!$U:$U,$T24,DEALS!$V:$V,"<>*RECEIVED*",DEALS!$V:$V,"<>*EXECUTED*"))} -> 0 | X24: {=SUMIFS(BALANCES!$C:$C,BALANCES!$A:$A,$B$2,BALANCES!$B:$B,$T24,BALANCES!$D:$D,X$6)+SUMIFS(FLOWS!$C:$C,FLOWS!$A:$A,$B$2,FLOWS!$E:$E,$T24,FLOWS!$D:$D,X$6,FLOWS!$H:$H,"<="&$U$4)+SUM(SUMIFS(DEALS!$J:$J,DEALS!$A:$A,{"*REFUND*","*EXECUTED*"},DEALS!$G:$G,$B$2,DEALS!$E:$E,"<="&$U$4,DEALS!$K:$K,X$6,DEALS!$M:$M,$T24,DEALS!$N:$N,"<>*RECEIVED*",DEALS!$N:$N,"<>*EXECUTED*"))+SUM(SUMIFS(DEALS!$R:$R,DEALS!$A:$A,{"*REFUND*","*EXECUTED*"},DEALS!$O:$O,$B$2,DEALS!$E:$E,"<="&$U$4,DEALS!$S:$S,X$6,DEALS!$U:$U,$T24,DEALS!$V:$V,"<>*RECEIVED*",DEALS!$V:$V,"<>*EXECUTED*"))} -> 0 | Y24: {=SUMIFS(BALANCES!$C:$C,BALANCES!$A:$A,$B$2,BALANCES!$B:$B,$T24,BALANCES!$D:$D,Y$6)+SUMIFS(FLOWS!$C:$C,FLOWS!$A:$A,$B$2,FLOWS!$E:$E,$T24,FLOWS!$D:$D,Y$6,FLOWS!$H:$H,"<="&$U$4)+SUM(SUMIFS(DEALS!$J:$J,DEALS!$A:$A,{"*REFUND*","*EXECUTED*"},DEALS!$G:$G,$B$2,DEALS!$E:$E,"<="&$U$4,DEALS!$K:$K,Y$6,DEALS!$M:$M,$T24,DEALS!$N:$N,"<>*RECEIVED*",DEALS!$N:$N,"<>*EXECUTED*"))+SUM(SUMIFS(DEALS!$R:$R,DEALS!$A:$A,{"*REFUND*","*EXECUTED*"},DEALS!$O:$O,$B$2,DEALS!$E:$E,"<="&$U$4,DEALS!$S:$S,Y$6,DEALS!$U:$U,$T24,DEALS!$V:$V,"<>*RECEIVED*",DEALS!$V:$V,"<>*EXECUTED*"))} -> 0 | Z24: {=SUMIFS(BALANCES!$C:$C,BALANCES!$A:$A,$B$2,BALANCES!$B:$B,$T24,BALANCES!$D:$D,Z$6)+SUMIFS(FLOWS!$C:$C,FLOWS!$A:$A,$B$2,FLOWS!$E:$E,$T24,FLOWS!$D:$D,Z$6,FLOWS!$H:$H,"<="&$U$4)+SUM(SUMIFS(DEALS!$J:$J,DEALS!$A:$A,{"*REFUND*","*EXECUTED*"},DEALS!$G:$G,$B$2,DEALS!$E:$E,"<="&$U$4,DEALS!$K:$K,Z$6,DEALS!$M:$M,$T24,DEALS!$N:$N,"<>*RECEIVED*",DEALS!$N:$N,"<>*EXECUTED*"))+SUM(SUMIFS(DEALS!$R:$R,DEALS!$A:$A,{"*REFUND*","*EXECUTED*"},DEALS!$O:$O,$B$2,DEALS!$E:$E,"<="&$U$4,DEALS!$S:$S,Z$6,DEALS!$U:$U,$T24,DEALS!$V:$V,"<>*RECEIVED*",DEALS!$V:$V,"<>*EXECUTED*"))} -> 0 | AA24: =U24*VLOOKUP(U$6,'FX RATES'!$E$1:$F$50,2,FALSE)+V24*VLOOKUP(V$6,'FX RATES'!$E$1:$F$50,2,FALSE)+W24*VLOOKUP(W$6,'FX RATES'!$E$1:$F$50,2,FALSE)+X24*VLOOKUP(X$6,'FX RATES'!$E$1:$F$50,2,FALSE)+Y24*VLOOKUP(Y$6,'FX RATES'!$E$1:$F$50,2,FALSE)+Z24*VLOOKUP(Z$6,'FX RATES'!$E$1:$F$50,2,FALSE) -> 0 | AC24: =I24+R24-AA24 -> 0
